Workbook

Sheet EN PROCESO (Alfa)
A1: Asignado a | B1: # REQ | C1: Requerimiento | D1: Detalle del requerimiento | E1: Proceso | F1: ESTADO | G1: % | H1: Dias estimados desarrollo | I1: F.Asignado | J1: Fecha inicio | K1: Fecha estimada de entrega | L1: Finalizado | M1: Dias total desarrollo | N1: Fecha compromiso cliente | O1: TEST | P1: PRODUCCION | Q1: OBSERVACIONES | R1: Visible | S1: OBSERVACIONES ALFA
A2: MAURICIO | B2: PRV_2025_001_1 | C2: REVISIÓN DE LIQUIDACIÓN PARA PAGO, | E2: Previsional | F2: FINALIZADO | G2: 100 | H2: =IF(OR(J2="",K2="",K2<J2),0,NETWORKDAYS(J2,K2,fESTIVOS!$A$2:$A$53)) -> 90 | J2: 45691 | K2: 45821 | L2: 45824 | M2: =IF(OR(J2="",AND(L2="",TODAY()<J2),AND(L2<>"",L2<J2)),0, IF(L2="", NETWORKDAYS(J2,TODAY(),fESTIVOS!$A$2:$A$53), NETWORKDAYS(J2,L2,fESTIVOS!$A$2:$A$53) ) ) -> 91 | P2: 45843 | Q2: Se notifica por par parte del jefe de unidad inconsistencias en Vistas de las fuentes de información entregadas. Carecen de data necesaria, 09/06/2025 :El requerimirneo fue pausado 12 mayo de 2025 10/06/2025: Hoy se definira si se contunua con el desarrollo o continua pausado. 11/06/2025: Ya se cuenta con los permisos y el query para la vista. Se sincronizan las reclamaciones de Cifren, pero falta integrar las de Plus (montadas en AWS) y ajustar la identificación del origen de cada reclamación. Se estima que este requerimiento adicional tomará un día de trabajo Iniciando el 12 de Junio 13/06/2025: Se obtuvo respuesta positiva sobre permisos para acceder a la vista de Plus. Sin embargo, falta que la vista tenga datos reales para completar la sincronización. 16/06/2025 : Se completó la primera fase de validación y hoy se trabaja en la parte de gestión de pagos, cliente realizara pruebas hoy 17/06/2025: Se realizan en ajustes en la mañana de hallasgoz reportados por el cliente tras las pruebas, y se entregaran al cliente para sus pruebas. 18/06/2025: Se adaptó el grid y los reportes a los distintos roles/permisos. También se incorporaron nuevos campos a solicitud del cliente; pendiente Pruebas por el cliente. 19/06/2025; supero pruebas del cliente y se aprueba paso a produccion para el dia sabado 21 de Junio.. 24/06/2025; Alfa aplazó el paso a produccion para el 5 de julio, debido a que tenían actualizaciones pendientes. Además, dependemos de la disponibilidad de ciertas vistas en el ambiente de producción para continuar con el proceso. 07/07/2025: Se realiza paso a produccion el 5 de julio. | R2: TRUE
A3: MAURICIO | B3: PRV_2025_001_2 | C3: VALIDACIÓN DE LOTE PARA PAGO, NOTIFICACIÓN DE PAGO | E3: Previsional | F3: FINALIZADO | G3: 100 | H3: =IF(OR(J3="",K3="",K3<J3),0,NETWORKDAYS(J3,K3,fESTIVOS!$A$2:$A$53)) -> 3 | I3: 45824 | J3: 45824 | K3: 45826 | L3: 45827 | M3: =IF(OR(J3="",AND(L3="",TODAY()<J3),AND(L3<>"",L3<J3)),0, IF(L3="", NETWORKDAYS(J3,TODAY(),fESTIVOS!$A$2:$A$53), NETWORKDAYS(J3,L3,fESTIVOS!$A$2:$A$53) ) ) -> 4 | P3: 45843 | Q3: El 16 de junio se inicia desarrollo confecha estimada de finalizacion 18 de junio. 18/06/2025: El 17 de junio se desarrollan dos informes adicionales: tesorería y porvenir, con definición de estructura en curso. 19/06/2025: Entrega al cliente para pruebas 19 de junio, Cliente solicita ajuste de vistas y campos necesarios para el proceso. 24/06/2025; Alfa aplazó el paso a produccion para el 5 de julio, debido a que tenían actualizaciones pendientes 07/07/2025: Se realiza paso a produccion el 5 de julio. | R3: TRUE
A4: MAURICIO | B4: PRV_2025_004 | C4: AUXILIOS FUNERARIOS PAGO AUX. FUNERARIOS | E4: Previsional | F4: FINALIZADO | G4: 100 | H4: =IF(OR(J4="",K4="",K4<J4),0,NETWORKDAYS(J4,K4,fESTIVOS!$A$2:$A$53)) -> 4 | J4: 45827 | K4: 45833 | L4: 45841 | M4: =IF(OR(J4="",AND(L4="",TODAY()<J4),AND(L4<>"",L4<J4)),0, IF(L4="", NETWORKDAYS(J4,TODAY(),fESTIVOS!$A$2:$A$53), NETWORKDAYS(J4,L4,fESTIVOS!$A$2:$A$53) ) ) -> 9 | P4: 45843 | Q4: Cargue de formatos de formalización y consolidado 100% Opción de edición y opción de histórico del flujo 100% Se notifica por par parte del jefe de unidad inconsistencias en Vistas de las fuentes de información entregadas. Carecen de data necesaria 09/06/2025 :El requerimirneo fue pausado el 6 de junio de 2025. 16/06/2025: Se comenzarán el jueves 19 de junio. Ya se están creando las vistas necesarias para ese flujo 19/06/2025: Inicio del desarrollo. 20/06/2025:No se pudo avanzar ayer 19 de junio por ajustes requeridos por el cliente para PRV_2025_001 VALIDACIÓN DE LOTE PARA PAGO,NOTIFICACIÓN DE PAGO, Se retomara desarrollo 24 de junio. 24/06/2025; Se encuentra sincronizando data, se estiman 2 dias para finalizar. 25/06/2025:Se ajustó la lógica del requerimiento tras diferenciarlo claramente del flujo de pagos. Se avanzó en la creación de vistas y en la sincronización inicial de datos. Se espera tener el desarrollo listo para pruebas el jueves 26. Se planea agregar botones para sincronización (Pago,auxilio y exportar) diferenciada según permisos,crear tabla de auxilios x año, ajustar campos (encabezados)de la vista de gestion y ajustar modulo de consulta. 26/06/2025: Se avanzó satisfactoriamente en la creación de la tabla de auxilios por año, el ajuste de encabezados en la vista de gestión y la incorporación de los botones de sincronización según permisos. PENDIENTE, Está pendiente la solución del error en la sincronización masiva, lo cual impide avanzar con la exportación y cargue de información. También sigue sin ajustes el módulo de consulta para auxilios. 27/06/2025: pendiente: 1. asignar opcion de pendientes 2. Ver consolidado pagos. (se envia masivamente y aprueba por el flujo para pasar a pagos). 3. Generar informe radicacion pagos plus. Se estima toda la entrega para hoy 01/07/2025: Se ha avanzado en un 75% del desarrollo, incluyendo funcionalidades principales. El cierre del tema está previsto para hoy, Faltan por implementar la generación de informes, la edición de fecha de siniestro y valor, así como la opción de marcar como pendiente. 02/07/2025:El desarrollo del módulo de auxilios funerarios presenta un avance estimado del 90%. Ya se encuentra implementada la funcionalidad principal, incluyendo la creación de vistas, funciones de sincronización y flujo de radicación hasta aprobación. Se están finalizando los ajustes a los reportes en Excel, Se programó una sesión de revisión hoy a las 2:00 p.m. para validación funcional y ajuste de pendientes. 04/07/2025: Se resolvió un error en la validación de pagos, el módulo ya está funcional. Se finalizó el desarrollo y se ajustaron validaciones necesarias para la gestión masiva y manual. Solo queda pendiente la validación del cliente, ya que la sesión programada fue cancelada. 07/07/2025: Se Pasado a producción el 5 de julio sin habilitar el menú. Faltan validaciones finales por el cliiente. 16/07/2025: Las pruebas no se han culminado por un error en el sistema del cliente al cargar unos registros. Sin estos registros no puedo ver la data que necesitamos en Imagine. 29/07/2025: Se proyecta acompañar al àrea para realizar pruebas con los recursos existentes para ya dejar cerrado el requerimiento 01/08/2025: Hoy se retoma el módulo con el cliente, para validar que se tiene hasta el momento, funcionalidad y posibles desviaciones, para dar gestion y cierre del requerimiento 04/08/2025: Se continùa validaciones y ajustes correspondientes para proyectar paso a producciòn el viernes 08 de agosto 12/08/2025: Debido a incidencia presentada en la conexión Plus + UAT , no fue posible el paso a producciòn el viernes 08 de agosto, por tanto se proyecta el despliegue para el viernes 15 de agosto 20/08/2025: Despliegue a produccion realizado en 15 de Agosto. | R4: TRUE | S4: 15/07/2025 Ya se encuenra en produccion
A5: MAURICIO | B5: PRV_2025_009 | C5: DESARROLLO PREVISIONALES INCAPACIDADES | E5: Previsional | F5: FINALIZADO | G5: 100 | H5: =IF(OR(J5="",K5="",K5<J5),0,NETWORKDAYS(J5,K5,fESTIVOS!$A$2:$A$53)) -> 3 | I5: 45817 | J5: 45817 | K5: 45819 | L5: 45820 | M5: =IF(OR(J5="",AND(L5="",TODAY()<J5),AND(L5<>"",L5<J5)),0, IF(L5="", NETWORKDAYS(J5,TODAY(),fESTIVOS!$A$2:$A$53), NETWORKDAYS(J5,L5,fESTIVOS!$A$2:$A$53) ) ) -> 4 | P5: 45843 | Q5: 09/06/2025: El Objetivo Automatizar el cálculo de incapacidades en el sistema Imagine, replicando el proceso manual actual utilizado por los liquidadores y presentando los resultados en un formato claro y compatible con Excel.\niniciara con el desarrollo. 11/06/2025: Mauricio completó la función de cálculo y está terminando el formulario de consulta. Planea entregar el requerimiento completo hoy para subir a pruebas el jueves. 13/06/2025: Ya fue entregado en ambiente de pruebas para validación del cliente. Está funcionando correctamente y aplicando los cálculos según lo solicitado. 9/06/2025: Paso a produccion para el 21 de junio. 24/06/2025: Fala aplazó el paso a produccion para el 5 de julio, debido a que tenían actualizaciones pendientes. 07/07/2025: Igual que Auxilios se paso a producciòn el 5 de julio sin habilitar el menu. Se requiere validación del cliente para habilitar. 16/07/2025: Requerimiento funcional en produccion con el menu habiitado. | R5: TRUE | S5: 15/07/2025 Ya se encuenra en produccion
A6: MAURICIO | B6: PRV_2025_007 | C6: CALCULO IBL | E6: Previsional | F6: FINALIZADO | G6: 100 | H6: =IF(OR(J6="",K6="",K6<J6),0,NETWORKDAYS(J6,K6,fESTIVOS!$A$2:$A$53)) -> 2 | I6: 45817 | J6: 45841 | K6: 45842 | L6: 45842 | M6: =IF(OR(J6="",AND(L6="",TODAY()<J6),AND(L6<>"",L6<J6)),0, IF(L6="", NETWORKDAYS(J6,TODAY(),fESTIVOS!$A$2:$A$53), NETWORKDAYS(J6,L6,fESTIVOS!$A$2:$A$53) ) ) -> 2 | P6: 45852 | Q6: 11/06/2025: Continuara con el desarrollo tras finalizar req PRV_2025_001 REVISIÓN DE LIQUIDACIÓN PARA PAGO 13/06/2025:Se programó su inicio para hoy. Mauricio confirmara la estimación del tiempo de desarrollo. 16/06/2025: Se requiere una sesion con Carlos, Jenry, Mauricio y Fabio para entender el detalle de validaciones. Aún no se tiene fecha ni estimación. 04/07/2015:Se inicia desarrollo con un avance del 20%. Se ajustaron funciones en Postgres para cálculos correctos según las vistas generadas. El siguiente paso es crear la funcionalidad de consulta por cédula o siniestro y desplegar cálculos de acuerdo a la fecha indicada. Se estima finalizar req hoy para realizar paso a produccion el 5 de julio. 07/07/2025: Se realizo paso a producciòn el 5 de Julio sin habiitar el menu, Faltan pruebas formales del cliente para habilitación final. 11/07/2025: El 10 de julio se realizó un ajuste para excluir los casos con auxilios funerarios. Ahora, el sistema valida que el origen del caso sea únicamente incapacidad o supervivencia; en caso contrario, se lanza una alerta. 16/07/2025: Se realiza paso a producción el 14 de julio en la noche. | R6: TRUE | S6: 10/07/2025 Posterior a pruebas se solicito ajuste a Mauricio para que no mostrara informacion diferentes a cod_origen 1,2 15/07/2025 Ya se encuenra en produccion
A7: MAURICIO | B7: PRV_2025_005 | C7: HISTORIA LABORAL | E7: Rentas | F7: FINALIZADO | G7: 100 | H7: =IF(OR(J7="",K7="",K7<J7),0,NETWORKDAYS(J7,K7,fESTIVOS!$A$2:$A$53)) -> 0 | I7: 45817 | J7: 45845 | L7: 45847 | M7: =IF(OR(J7="",AND(L7="",TODAY()<J7),AND(L7<>"",L7<J7)),0, IF(L7="", NETWORKDAYS(J7,TODAY(),fESTIVOS!$A$2:$A$53), NETWORKDAYS(J7,L7,fESTIVOS!$A$2:$A$53) ) ) -> 3 | P7: 45852 | Q7: 11/06/2025: Continuara con el desarrollo tras finalizar req PRV_2025_007 CALCULO IBL 07/07/2025: Inicia desarrollo 08/07/2025: Se reporta un avance del 50 % entre analisis y desarrollo del requerimeinto. 09/07/2025: Se Finaliza desarrollo y se entrega al cliente para pruebas. 14/07/2025: El 10 de julio se ajustó el reporte para incluir los períodos que existen en Multifondos pero no en Alfa. Adicionalmente, se incorporó una nueva columna que muestra el salario mensualizado proveniente de Porvenir. Los cambios ya fueron implementados y se encuentran listos para validación. 16/07/2025: Se realiza paso a producción el 14 de julio en la noche. | R7: TRUE | S7: 10/07/2025 Posterior a pruebas se solicito a Mauricio ajustes para visualizar los periodos a los cuales no se realizo analisis y tambien columna adicional para periodos falsos con calculo de el valor del los dias (Valor salario MF * 30) / Dias cotizados 11/07/2025: El 10 de julio se ajustó el reporte para incluir periodos que existan en multifondos pero no en Alfa. Se agregó una columna adicional para mostrar el salario mensualizado proveniente de Porvenir. Cambios ya implementados y listos para validación. 15/07/2025 Ya se encuenra en produccion
A8: MAURICIO | B8: AJUST_REN_2025_001_1 | C8: INCLUIR VALIDACION DOCUMENTAL PARA NUEVO ORIGEN SUSTITUCION PENSIONAL I | E8: Rentas | F8: FINALIZADO | G8: 100 | H8: =IF(OR(J8="",K8="",K8<J8),0,NETWORKDAYS(J8,K8,fESTIVOS!$A$2:$A$53)) -> 0 | I8: 45834 | J8: 45848 | L8: 45822 | M8: =IF(OR(J8="",AND(L8="",TODAY()<J8),AND(L8<>"",L8<J8)),0, IF(L8="", NETWORKDAYS(J8,TODAY(),fESTIVOS!$A$2:$A$53), NETWORKDAYS(J8,L8,fESTIVOS!$A$2:$A$53) ) ) -> 0 | P8: 45852 | Q8: 11/07/2025: Dado que ya se crearon las tablas de referencia, se finalizó este proceso el día 10 de julio. Queda pendiente validar el impacto que estas puedan tener en los diferentes módulos y consultas del sistema para que el cliente realice las pruebas. 14/07/2025: El viernes 11 se valida en ambiente de pruebas los ajustes realizados, confirmando funcionamiento correcto en: cargue de cotización y contratación, gestión telefónica desde call center, exportación del informe de Presidencia y descarga de documentos. Quedan pendientes por validar: envío de correos del portafolio de servicios, envío de comprobantes de nómina y validación de consultas.\n Hoy se trabajará en los informes que deben reflejar esta nueva parametrización y se verificará si afecta portafolios o comprobantes de nómina. 15/07/2025: El lunes 14 de julio se finalizó el desarrollo del ajuste, se realizaron las pruebas correspondientes con resultados exitosos y se procedió con el paso a producción. | R8: TRUE | S8: 26/06/2025 Se incluyen requerimientos de acuerdo a sesiones con el cliente. Corresponde a ajustes a plataforma ya en produccion 10/07/2025 ya que crearon las tablas de referencia. pendiente validar el impacto en los diferetnes modulos y consutas. 11/07/2025 Se valida ajustes realizados por mauricio en pruebas posterior a la incluision de nuevo ORIGEN. Para esto se confirma que esta correcto: 1. Cargue cotizacion y contratacion 2. Gestion telefonica call center 3. Exportar informe Presidencia 4. Descarga de documentos con nuevo Origen.) PENDIENTES: 5. Envio correos Portafolio de servicio 6. Envio Comprobantes de nomina 7. Valdacion de consultas. 15/07/2025 Ya se encuenra en produccion
A9: MAURICIO | B9: AJUST_REN_2025_001_2 | C9: INFORME DE PRESIDENCIA (Validación Documental Rentas) | E9: Rentas | F9: FINALIZADO | G9: 100 | H9: =IF(OR(J9="",K9="",K9<J9),0,NETWORKDAYS(J9,K9,fESTIVOS!$A$2:$A$53)) -> 0 | I9: 45834 | J9: 45848 | L9: 45848 | M9: =IF(OR(J9="",AND(L9="",TODAY()<J9),AND(L9<>"",L9<J9)),0, IF(L9="", NETWORKDAYS(J9,TODAY(),fESTIVOS!$A$2:$A$53), NETWORKDAYS(J9,L9,fESTIVOS!$A$2:$A$53) ) ) -> 1 | Q9: 10/07/2025: Se realizaron los ajustes solicitados por el área y estos ya fueron entregados en el ambiente de producción. El cliente efectuó las pruebas correspondientes y confirmó que el ajuste fue aplicado correctamente. | R9: TRUE | S9: 26/06/2025 Se incluyen requerimientos de acuerdo a sesiones con el cliente. Corresponde a ajustes a plataforma ya en produccion 10/07/2025 Se realizan ajustes solicitados por el area. Y ya se entregaron en produccion. El cliente realizo pruebas y confirmo ajuste.
A10: MAURICIO | B10: AJUST_REN_2025_001_3 | C10: CAMBIO DE ESTADO DE IMÁGENES PARA RENTAS NO CONTRATADAS | E10: Rentas | F10: FINALIZADO | G10: 100 | H10: =IF(OR(J10="",K10="",K10<J10),0,NETWORKDAYS(J10,K10,fESTIVOS!$A$2:$A$53)) -> 0 | I10: 45834 | J10: 45854 | L10: 45855 | M10: =IF(OR(J10="",AND(L10="",TODAY()<J10),AND(L10<>"",L10<J10)),0, IF(L10="", NETWORKDAYS(J10,TODAY(),fESTIVOS!$A$2:$A$53), NETWORKDAYS(J10,L10,fESTIVOS!$A$2:$A$53) ) ) -> 2 | P10: 45855 | Q10: 15/07/2025: Se inician ajustes solicitados 18/07/2025 Se culminaron los ajustes requeridos por el área, se realiza paso a produccion el 17 de julio. | R10: TRUE | S10: 15/07/2025 Se inicia ajustes requeridos 17/07/2025 Requerimiento probado y en produccion. Se realizo paso a produccion el dia 17/07/2025
A11: MAURICIO | B11: AJUST_REN_2025_001_4 | C11: VALIDAR INCONSISTENCIA INFORME RENTAS RCMA – DDEP | E11: Rentas | F11: FINALIZADO | G11: 100 | H11: =IF(OR(J11="",K11="",K11<J11),0,NETWORKDAYS(J11,K11,fESTIVOS!$A$2:$A$53)) -> 0 | I11: 45834 | J11: 45848 | L11: 45818 | M11: =IF(OR(J11="",AND(L11="",TODAY()<J11),AND(L11<>"",L11<J11)),0, IF(L11="", NETWORKDAYS(J11,TODAY(),fESTIVOS!$A$2:$A$53), NETWORKDAYS(J11,L11,fESTIVOS!$A$2:$A$53) ) ) -> 0 | P11: 45852 | Q11: 11/07/2025: EL 10 de julio Se realizaron pruebas por parte de Carlos Rodríguez. Actualmente, el cambio se encuentra pendiente de ser implementado en el ambiente de producción. 15/07/2025:Se realizó el paso a producción el día 14 de julio. | R11: TRUE | S11: 26/06/2025 Se incluyen requerimientos de acuerdo a sesiones con el cliente. Corresponde a ajustes a plataforma ya en produccion 10/07/2025 Se realizaron pruebas por parte de Carlos Rodriguez. Pendiente pasar a producicon. 15/07/2025 Ya se encuenra en produccion 15/07/2025 Se solcito por parte del usuario incluir una nueva validacion.
A12: MAURICIO | B12: AJUST_REN_2025_001_5 | C12: INCLUIR VALIDACIÓN ADICIONAL PARA RCMA – DDEP. | E12: Rentas | F12: FINALIZADO | G12: 100 | H12: =IF(OR(J12="",K12="",K12<J12),0,NETWORKDAYS(J12,K12,fESTIVOS!$A$2:$A$53)) -> 0 | I12: 45853 | J12: 45853 | L12: 45854 | M12: =IF(OR(J12="",AND(L12="",TODAY()<J12),AND(L12<>"",L12<J12)),0, IF(L12="", NETWORKDAYS(J12,TODAY(),fESTIVOS!$A$2:$A$53), NETWORKDAYS(J12,L12,fESTIVOS!$A$2:$A$53) ) ) -> 2 | Q12: 16/07/2025: Se finaliza ajuste 15 de julio y se realiza despliegue a produccion el 16 de julio en la mañana. | R12: TRUE
A13: MAURICIO | B13: PRV_2025_011 | C13: ANS - TABLERO DE CONTROL - dashboard | E13: Previsional | F13: FINALIZADO | G13: 100 | H13: =IF(OR(J13="",K13="",K13<J13),0,NETWORKDAYS(J13,K13,fESTIVOS!$A$2:$A$53)) -> 2 | I13: 45855 | J13: 45855 | K13: 45857 | L13: 45862 | M13: =IF(OR(J13="",AND(L13="",TODAY()<J13),AND(L13<>"",L13<J13)),0, IF(L13="", NETWORKDAYS(J13,TODAY(),fESTIVOS!$A$2:$A$53), NETWORKDAYS(J13,L13,fESTIVOS!$A$2:$A$53) ) ) -> 6 | Q13: 18/07/2025: Se completó el query de base. Se trabaja en selección de librería gráfica compatible con Laravel. Se estima un 20% de avance general. 21/07/2025: Se esta trabajando en las graficas de ANS, se estima terminar el 22 de julio para paso a pruebas UAT 24/07/2025: El 22/07/2025 se continua en gestión del tablero de control ANS, sacaba error en los gráficos, se estima terminar el 23/07/2025 por compromiso con el cliente. 23/07/2025: Se terminan los gráficos del tablero de control. 24/07/2025: Se trabaja en el export de la data de las estadisticas 25/07/2025. Se entrega al área tablero de ANS finalizado, programado subir los cambios para paso a producción el 25/07/2025 a las 5:00 pm | R13: TRUE | S13: 17/07/2025 Se solicita realizar desarrollo inicial para lo que ya se encuentra en produccion en cuanto a pagos. Este modulo tambien debe conterner lo correpondiente a Auxilio funerario que actualmente se encuentra pausado
A14: CARLOS | B14: PRV_2025_002 | C14: REPORTE ANEXO 1 (Lentantamiento de requerimiento) | E14: Previsional | F14: FINALIZADO | G14: 100 | H14: =IF(OR(J14="",K14="",K14<J14),0,NETWORKDAYS(J14,K14,fESTIVOS!$A$2:$A$53)) -> 26 | J14: 45859 | K14: 45896 | L14: 45944 | M14: =IF(OR(J14="",AND(L14="",TODAY()<J14),AND(L14<>"",L14<J14)),0, IF(L14="", NETWORKDAYS(J14,TODAY(),fESTIVOS!$A$2:$A$53), NETWORKDAYS(J14,L14,fESTIVOS!$A$2:$A$53) ) ) -> 59 | Q14: 21/07/2025: Carlos esta adelantando el levantamiento del requerimiento, para proyectar entrega 23/07/2025: Se encuentra en definición con el cliente, para establecer algunas prioridades en los requerimientos siguientes 25/08/2025: Se retoma el levantamiento del requerimiento y se proyecta entrega a Mauricio para desarrollo el día de mañana, sin embargo, se estan priorizando informes propios de la operación de Imagine. 03/09/2025: Requerimiento en pausa debido a que Imaginex actualmente no cuenta con permisos para creación de vistas, se encuentra en validación por infraestructura para una solución. 26/09/2025: El 22 de septiembre se termino el levantamiento del requerimiento, en el transcurso de la semana se han estado elaborando vistas, sin embargo, Imagine no tiene acceso y permisos para editar o crear vistas en DLL, AUT ni producción. 03/10/2025: El 02 de octubre se obtienen los permisos y se inicia con la creación de las vistas 14/10/2025: Se proyecta finalizar el levantamiento del requerimiento para pasar a desarrollo | R14: TRUE | S14: 17/07/2025 Se esta culminado el query para generar reporte
A15: MAURICIO | B15: PRV_2025_002-1 | C15: REPORTE ANEXO 1 (desarrollo ) | E15: Previsional | F15: FINALIZADO | G15: 100 | H15: =IF(OR(J15="",K15="",K15<J15),0,NETWORKDAYS(J15,K15,fESTIVOS!$A$2:$A$53)) -> 4 | I15: 45940 | J15: 45940 | K15: 45946 | L15: 45951 | M15: =IF(OR(J15="",AND(L15="",TODAY()<J15),AND(L15<>"",L15<J15)),0, IF(L15="", NETWORKDAYS(J15,TODAY(),fESTIVOS!$A$2:$A$53), NETWORKDAYS(J15,L15,fESTIVOS!$A$2:$A$53) ) ) -> 7 | Q15: 17/10/2025: El 15 de octubre se termino el desarrollo del requerimiento Anexo 1, posteriormente se han realizado validaciones y ajustes que se cruzan con otros requerimientos, con el fin de no presentar incindencias | R15: TRUE
A16: MAURICIO | B16: PRV_2025_001 | C16: Ajuste flujo de pagos | E16: Previsional | F16: FINALIZADO | G16: 100 | H16: =IF(OR(J16="",K16="",K16<J16),0,NETWORKDAYS(J16,K16,fESTIVOS!$A$2:$A$53)) -> 0 | I16: 45855 | J16: 45855 | L16: 45860 | M16: =IF(OR(J16="",AND(L16="",TODAY()<J16),AND(L16<>"",L16<J16)),0, IF(L16="", NETWORKDAYS(J16,TODAY(),fESTIVOS!$A$2:$A$53), NETWORKDAYS(J16,L16,fESTIVOS!$A$2:$A$53) ) ) -> 4 | P16: 45885 | Q16: 21/07/2025: El 17/07/2025 Se envía correo por parte de Carlos a Seguros Alfa, solicitando modificar 2 vistas: a. Sipren: Ajustes V_consolidado_reclamaciones_img b. Plus: AjustesV_consolidado_tramites_plus Pendiente presentarlo a comité para efectuar el cambio correspondiente en las vistas. El 18/07/2025, Mauricio realizó un ajuste en el módulo de flujo de pagos, mediante el cual se asocia a cada estado del flujo una ruta u opción de acceso específica. Anteriormente, independientemente del permiso asignado, los usuarios podían visualizar los estados a los que contaban con permiso. 23/07/2025: El 22 de Julio se entrega al cliente para pruebas, al pendiente de aceptacion para paso a produccion. 24/07/2025: Se solicita a Mauricio subir los cambios de flujo de pagos modificados en las vistas que actualizò Carlos. Validar los cambios y ajustes requeridos por el cliente en requerimientos ya cerrados para paso a producción. 25/07/2025: Se finalizan los ajustes solicitados por el área (un campo llamado parentesco y mostrarlo en el export, en el Excel que exporta el cliente). Programado subir cambios para paso a producción el 25/07/2025 a las 5:00 pm 28/07/2025: El viernes 25 de julio sobre las 6:00 pm hasta las 7:30 pm se realiza el despliegue a producción. El dìa de hoy se encuentra validando que los cambiosy ajustes en el paso a producciòn están funcionando correctamente. Se evidencia que hubo una inconsistencia en los datos que Alfa suministra en el cambio a producción. Se encuentra en validación. 01/08/2025: Se vuelve a validar con Alfa la información reportada en el script, sin embargo, se encuentran a la espera de que el área de producción entregue el DLL que se envió en el despliegue. Por parte de Imagine no hay pendientes. 08/08/2025: El 06 de Agosto a raíz de la reunión con el área Previsionales el día 05 de agosto, surgieron ajustes solicitados por parte del vicepresidente de Alfa. 1. Incluir el cálculo IBL dentro del flujo. Validar primero el nombre de las etiquetas. 2. Convertir en cero al exportar el Excel los valores negativos. Solicitud de Patricia Arteaga 3. Resaltar el nombre de la columna Pago Total para que se ubiquen los usuarios. 4. Validar las etiquetas dentro del editar. Falta información 5. Revisar información que sale en la parte izquierda en el editar, ya que no se sale un valor, según valido Hugo Gómez El día de hoy 08 de agosto, se trabaja en en control de cambios en Flujo de pagos solicitado por el Vicepresidente de Alfa. 20/08/2025: Se pasa a producciòn el 16 de agosto | R16: TRUE
A17: Carlos y Cindy | B17: PRV_2025_003 | C17: AVISO A LA RENTA (Levantamiento del requerimiento) | E17: Previsional | F17: FINALIZADO | G17: 100 | H17: =IF(OR(J17="",K17="",K17<J17),0,NETWORKDAYS(J17,K17,fESTIVOS!$A$2:$A$53)) -> 1 | I17: 45863 | J17: 45863 | K17: 45863 | L17: 45885 | M17: =IF(OR(J17="",AND(L17="",TODAY()<J17),AND(L17<>"",L17<J17)),0, IF(L17="", NETWORKDAYS(J17,TODAY(),fESTIVOS!$A$2:$A$53), NETWORKDAYS(J17,L17,fESTIVOS!$A$2:$A$53) ) ) -> 15 | Q17: 25/07/2025: Carlos y Cindy estan trabajando en el levantamiento del requerimiento para pasar a Mauricio y que inicie con el desarrollo para que quede en el paso a producción programado para el 25/07/2025 a las 5:00 pm 28/07/2025: El viernes 25 de julio se hace socializaciòn del requerimiento con Mauricio y Jairo. 20/08/2025: El sabado 16 se realizo el paso a producciòn | R17: TRUE
A18: MAURICIO | B18: PRV_2025_003-1 | C18: AVISO A LA RENTA (Desarrollo) | E18: Previsional | F18: FINALIZADO | G18: 100 | H18: =IF(OR(J18="",K18="",K18<J18),0,NETWORKDAYS(J18,K18,fESTIVOS!$A$2:$A$53)) -> 2 | I18: 45863 | J18: 45866 | K18: 45867 | L18: 45870 | M18: =IF(OR(J18="",AND(L18="",TODAY()<J18),AND(L18<>"",L18<J18)),0, IF(L18="", NETWORKDAYS(J18,TODAY(),fESTIVOS!$A$2:$A$53), NETWORKDAYS(J18,L18,fESTIVOS!$A$2:$A$53) ) ) -> 5 | P18: 45885 | Q18: 28/07/2025, el viernes 25 de julio, debido a una inconsistencia en el aplicativo ALFASST del área SST con unas ordenes de servicio, se tuvo que dar prioridad y Mauricio no pudo iniciar el desarrollo de Avisos a la renta. El día de hoy, luego de terminar validaciones de paso a producción de otros requerimientos, se inicia desarrollo de este requerimiento. 29/07/2025: Mauricio se enfocarà en terminar el requerimiento completamente. 30/07/2025: Se reporta un avance del 50% en el desarrollo del módulo de avisos de renta. Ya se visualizan los pagos correctamente y quedan pendientes las funcionalidades de notificación, descarga de Excel y eliminación de registros. Se espera finalizar hoy. 01/08/2025: A 31 de julio ya esta por entregar, Mauricio el dìa de hoy mostrara el funcionamiento y el flujo del reporte, para identificar posibles desviaciones y validar si es posible automatizarlo. 04/08/2025: El 01 de agosto quedo funcional el requerimiento, esta proyectado para paso a producción el viernes 08 de agosto 13/08/2025. Se proyecta paso a producción el sabado 16 de agosto. 20/08/2025: Paso a produccion realizado 16 de Agosto. | R18: TRUE
A19: MAURICIO | B19: Img_2025_001 | C19: Validar servidor de contingencia | E19: Imagine | F19: FINALIZADO | G19: 100 | H19: =IF(OR(J19="",K19="",K19<J19),0,NETWORKDAYS(J19,K19,fESTIVOS!$A$2:$A$53)) -> 1 | I19: 45870 | J19: 45870 | K19: 45870 | L19: 45877 | M19: =IF(OR(J19="",AND(L19="",TODAY()<J19),AND(L19<>"",L19<J19)),0, IF(L19="", NETWORKDAYS(J19,TODAY(),fESTIVOS!$A$2:$A$53), NETWORKDAYS(J19,L19,fESTIVOS!$A$2:$A$53) ) ) -> 5 | Q19: 01/08/2025: Se realizarà validación del servidor de contingencia el día de hoy, puesto que en meses pasado se presentaron incidencias y debemos garantizar que toda la información se encuentre sincronizada de forma correcta. 04/08/2025: Se programo sesiòn con Wilson y Mauricio para validaciòn y acompañamiento en la sincronización de la contingencia. 08/08/2025: Validación de error de la sincronización de contingencia, con Alfa y Claro - Onpremise 2. Validación cambio de llaves AWS. 12/08/2025: Se encuentra pendiente ajuste a permisos de carpetas para la sincronización y notificación por correo del error en la sincronización o éxito en la misma. La reunión del viernes para cambio de llaves AWS, se reprogramo para hoy a las 9:00 am hasta las 10:15 am aproximadamente. | R19: TRUE
A20: MAURICIO | B20: PRV_2025_004-1 | C20: Ajustes modulo auxilios funerario | E20: Previsional | F20: FINALIZADO | G20: 100 | H20: =IF(OR(J20="",K20="",K20<J20),0,NETWORKDAYS(J20,K20,fESTIVOS!$A$2:$A$53)) -> 0 | I20: 45874 | J20: 45874 | L20: 45882 | M20: =IF(OR(J20="",AND(L20="",TODAY()<J20),AND(L20<>"",L20<J20)),0, IF(L20="", NETWORKDAYS(J20,TODAY(),fESTIVOS!$A$2:$A$53), NETWORKDAYS(J20,L20,fESTIVOS!$A$2:$A$53) ) ) -> 6 | P20: 45885 | Q20: 08/08/2025: el 05 de Agosto, se realiza acompañamiento en la sesión del área de Previsionales con Blanca Romero, Elizabeth Guerrero y Hugo Gomez, por si surgen dudas u observaciones. Se trabaja en informes de Pagos y Auxilios Funerarios. 11/08/2025: A raíz de la sesión del viernes surgieron ajustes adicionales: 1. Incluir el cálculo del IBL dentro del flujo 2. Convertir en cero al exportar el Excel los valores negativos. Solicitud de Patricia Arteaga 3. Resaltar el nombre de la columna Pago Total para que se ubiquen los usuarios 4. Validar las etiquetas dentro del editar. Falta información 5. Revisar información que sale en la parte izquierda en el editar, ya que no sale un valor, según valido Hugo Gomez. Estos puntos ya quedaron gestionados el día de ayer en un 90%, falta culminar: - Control de cambios en flujo de pagos - Incluir el cálculo del IBL dentro del flujo. Validar nombre de las etiquetas 12/08/2025: El viernes hubo incidencia en el cargue del Excel archivo de formalización de Auxilios Funerarios, sin embargo, este ya quedo solucionado. Se continúa trabajando en los ajustes faltantes requeridos por vicepresidencia de Seguridad Social. 13/08/2025: Reunión con el área de coordinación y desarrollo para instrucciones de entrega de documentación. - Creación de documentos técnicos requeridos por Alfa para paso a comité de cambios el día de hoy 13 de agosto y mañana 14. - Ajustes por pruebas de usuario en error de cargue de archivo y mejora de la consulta. - Se proyecta paso a producción de aviso a la renta y auxilios funerarios el sabado 16 de agosto. 20/08/2025: El dìa sabado 16 se realiza paso a producciòn | R20: TRUE
A21: MAURICIO | B21: PRV_2025_004-2 | C21: Ajustes auxilios funerarios y aviso a la renta | E21: Previsional | F21: FINALIZADO | G21: 100 | H21: =IF(OR(J21="",K21="",K21<J21),0,NETWORKDAYS(J21,K21,fESTIVOS!$A$2:$A$53)) -> 0 | I21: 45883 | J21: 45883 | L21: 45883 | M21: =IF(OR(J21="",AND(L21="",TODAY()<J21),AND(L21<>"",L21<J21)),0, IF(L21="", NETWORKDAYS(J21,TODAY(),fESTIVOS!$A$2:$A$53), NETWORKDAYS(J21,L21,fESTIVOS!$A$2:$A$53) ) ) -> 1 | P21: 45885 | Q21: 14/08/2025: Ajuste a bugs reportados por el cliente para Auxilios Funerarios y Aviso a la Renta (formatos y consultas). Ya el dìa de hoy se certifico por parte del cliente el paso a producciòn, el cual se progrma realizar por parte de Mauricio el sabado 16 de agosto. Se requiriò acompañamiento de Mauricio en las sesiones para solucionar de forma inmediata las inconsistencias, durante las horas de la mañana y tarde. 20/08/2025: EL sabado 16 se realizo paso a producciòn | R21: TRUE
A22: MAURICIO | B22: PRV_2025_004-3 | C22: Genera informes generales pagos y auxilios funerarios | D22: Generar un informe con el detalle de mostrar consulta y la trazabilidad de los casos de los procesos entregados a producciòn en semanas anteriores. | E22: Previsional | F22: FINALIZADO | G22: 100 | H22: =IF(OR(J22="",K22="",K22<J22),0,NETWORKDAYS(J22,K22,fESTIVOS!$A$2:$A$53)) -> 0 | J22: 45895 | L22: 45895 | M22: =IF(OR(J22="",AND(L22="",TODAY()<J22),AND(L22<>"",L22<J22)),0, IF(L22="", NETWORKDAYS(J22,TODAY(),fESTIVOS!$A$2:$A$53), NETWORKDAYS(J22,L22,fESTIVOS!$A$2:$A$53) ) ) -> 1 | Q22: 27/08/2025: El 26 de agosto se trabajo en el desarrollo del informe general de pagos y auxilios funerarios. | R22: TRUE
A23: MAURICIO | B23: Img_2025_002 | C23: Validar servidor de contingencia | D23: Crear .bash para notificar sincronización en base de datos | E23: Imagine | F23: FINALIZADO | G23: 100 | H23: =IF(OR(J23="",K23="",K23<J23),0,NETWORKDAYS(J23,K23,fESTIVOS!$A$2:$A$53)) -> 5 | I23: 45884 | J23: 45884 | K23: 45891 | L23: 45947 | M23: =IF(OR(J23="",AND(L23="",TODAY()<J23),AND(L23<>"",L23<J23)),0, IF(L23="", NETWORKDAYS(J23,TODAY(),fESTIVOS!$A$2:$A$53), NETWORKDAYS(J23,L23,fESTIVOS!$A$2:$A$53) ) ) -> 44 | Q23: 15/08/2025: Se reconfiguraron los permisos y Mauricio estarà validando el tema el día de hoy, sincronizaciòn y funcionamiento 20/08/2025: Al 19 de agosto, se encuentra pendiente reporte por parte de Claro informando las actividades realizadas el dìa viernes de acuerdo al refresh de la llave. Pendiente por parte Mauricio crear .bash para notificar cuando sincronice las bases de datos 25/08/2025: El viernes 22 de agosto se creo el .bash solicitado, sin embargo, se esta presentando una incidencia en la actualización, que no actualiza en la base de datos a diferencia del que corre a las 3 am. Mauricio estará validando otras funcionalidades y en caso de que continue la inconsistencia, se apoyará con Jairo y Jenry 27/08/2025: El 25 de agosto se valido con tecnologìa el tema de crear una conexión SSH, el día de hoy 27 de agosto, dieron respuesta que se puede realizar sin problema. 03/09/2025: Mauricio indica que queda pendiente el sabado 06 de septiembre validar la sincronizaciòn y Carlos Rodriguez debe realizar la documentación de la sincronización para presentar a Alfa. 20/10/2025: El 17 de octubre se realizó sincronización manual de producción a contingencia, debido a que el procesos automático de las 3 am, dejo algunos archivos corruptos | R23: TRUE
A24: MAURICIO | B24: SST_2025_001 | C24: Ajustes en servidores QA y PT de ALFASST AWS | E24: SST | F24: FINALIZADO | G24: 100 | H24: =IF(OR(J24="",K24="",K24<J24),0,NETWORKDAYS(J24,K24,fESTIVOS!$A$2:$A$53)) -> 5 | I24: 45894 | J24: 45894 | K24: 45898 | L24: 45897 | M24: =IF(OR(J24="",AND(L24="",TODAY()<J24),AND(L24<>"",L24<J24)),0, IF(L24="", NETWORKDAYS(J24,TODAY(),fESTIVOS!$A$2:$A$53), NETWORKDAYS(J24,L24,fESTIVOS!$A$2:$A$53) ) ) -> 4 | Q24: 29/08/2025: 25/08/2025: Los desarrollos para esta aplicación se encontraban detenidos desde el año pasado. Por lo cual los ambientes no se encontraban actualizados y/o con data actualizada para pruebas. | R24: TRUE
A25: MAURICIO | B25: SST_2025_002 | C25: Ajustes en servidores QA y PT de ALFASST AWS | E25: SST | F25: FINALIZADO | G25: 100 | H25: =IF(OR(J25="",K25="",K25<J25),0,NETWORKDAYS(J25,K25,fESTIVOS!$A$2:$A$53)) -> 5 | I25: 45894 | J25: 45894 | K25: 45898 | L25: 45897 | M25: =IF(OR(J25="",AND(L25="",TODAY()<J25),AND(L25<>"",L25<J25)),0, IF(L25="", NETWORKDAYS(J25,TODAY(),fESTIVOS!$A$2:$A$53), NETWORKDAYS(J25,L25,fESTIVOS!$A$2:$A$53) ) ) -> 4 | Q25: 29/08/2025: 25/08/2025: Se retomaron las pruebas en los entornos QA y PT para validar nuevos requerimientos y hacer seguimiento al estado de aquellos que aún se encuentran pendientes por ser desplegados en producción. | R25: TRUE
A26: MAURICIO | B26: SST_2025_003 | C26: Ajustes en servidores QA y PT de ALFASST AWS | E26: SST | F26: FINALIZADO | G26: 100 | H26: =IF(OR(J26="",K26="",K26<J26),0,NETWORKDAYS(J26,K26,fESTIVOS!$A$2:$A$53)) -> 5 | I26: 45894 | J26: 45894 | K26: 45898 | L26: 45897 | M26: =IF(OR(J26="",AND(L26="",TODAY()<J26),AND(L26<>"",L26<J26)),0, IF(L26="", NETWORKDAYS(J26,TODAY(),fESTIVOS!$A$2:$A$53), NETWORKDAYS(J26,L26,fESTIVOS!$A$2:$A$53) ) ) -> 4 | Q26: 29/08/2025: 25/08/2025: Durante este proceso, se identificaron algunas incidencias en los servidores, por lo que fue necesario realizar ajustes y correcciones técnicas para garantizar un entorno estable que permitiera continuar con la validación de los cambios. | R26: TRUE
A27: MAURICIO | B27: SST_2025_004 | C27: Ajustes en servidores QA y PT de ALFASST AWS | E27: SST | F27: FINALIZADO | G27: 100 | H27: =IF(OR(J27="",K27="",K27<J27),0,NETWORKDAYS(J27,K27,fESTIVOS!$A$2:$A$53)) -> 5 | I27: 45894 | J27: 45894 | K27: 45898 | L27: 45897 | M27: =IF(OR(J27="",AND(L27="",TODAY()<J27),AND(L27<>"",L27<J27)),0, IF(L27="", NETWORKDAYS(J27,TODAY(),fESTIVOS!$A$2:$A$53), NETWORKDAYS(J27,L27,fESTIVOS!$A$2:$A$53) ) ) -> 4 | Q27: 29/08/2025: 25/08/2025: Se restablecieron los cronogramas del año vigente en los entornos QA y PT para habilitar el nuevo módulo de profesionales y permitir sus respectivas pruebas. | R27: TRUE
A28: MAURICIO | B28: SST_2025_005 | C28: Validar el modulo de profesionales para que el àrea pueda realizar pruebas | E28: SST | F28: FINALIZADO | G28: 100 | H28: =IF(OR(J28="",K28="",K28<J28),0,NETWORKDAYS(J28,K28,fESTIVOS!$A$2:$A$53)) -> 4 | I28: 45894 | J28: 45895 | K28: 45898 | L28: 45897 | M28: =IF(OR(J28="",AND(L28="",TODAY()<J28),AND(L28<>"",L28<J28)),0, IF(L28="", NETWORKDAYS(J28,TODAY(),fESTIVOS!$A$2:$A$53), NETWORKDAYS(J28,L28,fESTIVOS!$A$2:$A$53) ) ) -> 3 | Q28: 29/08/2025: 25/08/2025: Se solucionaron errores en el módulo de profesionales y se realizaron correcciones funcionales. | R28: TRUE
A29: MAURICIO | B29: SST_2025_006 | C29: Accesos y configuración técnica QA ALFASST AWS | E29: SST | F29: FINALIZADO | G29: 100 | H29: =IF(OR(J29="",K29="",K29<J29),0,NETWORKDAYS(J29,K29,fESTIVOS!$A$2:$A$53)) -> 4 | I29: 45894 | J29: 45895 | K29: 45898 | L29: 45897 | M29: =IF(OR(J29="",AND(L29="",TODAY()<J29),AND(L29<>"",L29<J29)),0, IF(L29="", NETWORKDAYS(J29,TODAY(),fESTIVOS!$A$2:$A$53), NETWORKDAYS(J29,L29,fESTIVOS!$A$2:$A$53) ) ) -> 3 | Q29: 29/08/2025: 25/08/2025: Se refrescaron claves y accesos, especialmente en el servidor de pruebas, que presentaba problemas de ingreso. | R29: TRUE
A30: MAURICIO | B30: SST_2025_007 | C30: Accesos y configuración técnica QA ALFASST AWS | E30: SST | F30: FINALIZADO | G30: 100 | H30: =IF(OR(J30="",K30="",K30<J30),0,NETWORKDAYS(J30,K30,fESTIVOS!$A$2:$A$53)) -> 4 | I30: 45894 | J30: 45895 | K30: 45898 | L30: 45897 | M30: =IF(OR(J30="",AND(L30="",TODAY()<J30),AND(L30<>"",L30<J30)),0, IF(L30="", NETWORKDAYS(J30,TODAY(),fESTIVOS!$A$2:$A$53), NETWORKDAYS(J30,L30,fESTIVOS!$A$2:$A$53) ) ) -> 3 | Q30: 29/08/2025: 25/08/2025: Se ajustó la configuración de pgAdmin para garantizar la conexión con las distintas bases de datos de ALFASST. | R30: TRUE
A31: MAURICIO | B31: PRV_2025_006 | C31: Sincronización de estados de casos | E31: Previsional | F31: FINALIZADO | G31: 100 | H31: =IF(OR(J31="",K31="",K31<J31),0,NETWORKDAYS(J31,K31,fESTIVOS!$A$2:$A$53)) -> 4 | I31: 45894 | J31: 45895 | K31: 45898 | L31: 45897 | M31: =IF(OR(J31="",AND(L31="",TODAY()<J31),AND(L31<>"",L31<J31)),0, IF(L31="", NETWORKDAYS(J31,TODAY(),fESTIVOS!$A$2:$A$53), NETWORKDAYS(J31,L31,fESTIVOS!$A$2:$A$53) ) ) -> 3 | Q31: 29/08/2025: 25/08/2025: Se implementó el ajuste para que, al cambiar un caso de estado CORRECCIÓN → REVISADO, se ejecute la sincronización individual del valor, considerando posibles modificaciones. | R31: TRUE
A32: MAURICIO | B32: PRV_2025_0011 | C32: Sincronización de estados de casos | E32: Previsional | F32: FINALIZADO | G32: 100 | H32: =IF(OR(J32="",K32="",K32<J32),0,NETWORKDAYS(J32,K32,fESTIVOS!$A$2:$A$53)) -> 4 | I32: 45894 | J32: 45896 | K32: 45901 | L32: 45930 | M32: =IF(OR(J32="",AND(L32="",TODAY()<J32),AND(L32<>"",L32<J32)),0, IF(L32="", NETWORKDAYS(J32,TODAY(),fESTIVOS!$A$2:$A$53), NETWORKDAYS(J32,L32,fESTIVOS!$A$2:$A$53) ) ) -> 25 | Q32: 29/08/2025: 25/08/2025: Queda pendiente el desarrollo de la sincronización masiva, lo cual implica ajustes en las funciones de sincronización entre bases de datos. 03/09/2025: Requerimiento en pausa debido a que Imaginex actualmente no cuenta con permisos para creación de vistas, se encuentra en validación por infraestructura para una solución. 01/10/2025: El 30 de septiembre se obtienen permisos pendientes, lo cual permitio finalizar el desarrollo del requerimiento | R32: TRUE
A33: MAURICIO | B33: PRV_2025_008 | C33: Flujo de Pagos Control de cambios | E33: Previsional | F33: FINALIZADO | G33: 100 | H33: =IF(OR(J33="",K33="",K33<J33),0,NETWORKDAYS(J33,K33,fESTIVOS!$A$2:$A$53)) -> 0 | I33: 45894 | J33: 45930 | K33: 45901 | L33: 45930 | M33: =IF(OR(J33="",AND(L33="",TODAY()<J33),AND(L33<>"",L33<J33)),0, IF(L33="", NETWORKDAYS(J33,TODAY(),fESTIVOS!$A$2:$A$53), NETWORKDAYS(J33,L33,fESTIVOS!$A$2:$A$53) ) ) -> 1 | Q33: 29/08/2025: 25/08/2025: Permitir la modificación del campo VALOR_PAGO en casos específicos, exclusivamente dentro del primer flujo del proceso. 03/09/2025: Requerimiento en pausa debido a que Imaginex actualmente no cuenta con permisos para creación de vistas, se encuentra en validación por infraestructura para una solución. 01/10/2025: El 30 de septiembre se habilita la ediciòn del campo VALOR_PAGO ya que algunos casos lo requieren, modificaciòn restringida unicamente al primer flujo | R33: TRUE
A34: MAURICIO | B34: PRV_2025_012 | C34: Auxilios Funerarios Control de Cambios | E34: Previsional | F34: FINALIZADO | G34: 100 | H34: =IF(OR(J34="",K34="",K34<J34),0,NETWORKDAYS(J34,K34,fESTIVOS!$A$2:$A$53)) -> 0 | I34: 45894 | J34: 45930 | K34: 45901 | L34: 45930 | M34: =IF(OR(J34="",AND(L34="",TODAY()<J34),AND(L34<>"",L34<J34)),0, IF(L34="", NETWORKDAYS(J34,TODAY(),fESTIVOS!$A$2:$A$53), NETWORKDAYS(J34,L34,fESTIVOS!$A$2:$A$53) ) ) -> 1 | Q34: 29/08/2025: 25/08/2025: Sincronizar y actualizar automáticamente la fecha de siniestro según información proveniente de Porvenir. 03/09/2025: Requerimiento en pausa debido a que Imaginex actualmente no cuenta con permisos para creación de vistas, se encuentra en validación por infraestructura para una solución. 01/10/2025: El 30 de septiembre se creo opciòn para cuando se sincronicen las solicitudes permitan actualizar las fechas de siniestro | R34: TRUE
A35: MAURICIO | B35: PRV_2025_010 | C35: Aviso a la Renta Control de Cambios | E35: Previsional | F35: FINALIZADO | G35: 100 | H35: =IF(OR(J35="",K35="",K35<J35),0,NETWORKDAYS(J35,K35,fESTIVOS!$A$2:$A$53)) -> 0 | I35: 45894 | J35: 45947 | K35: 45901 | L35: 45947 | M35: =IF(OR(J35="",AND(L35="",TODAY()<J35),AND(L35<>"",L35<J35)),0, IF(L35="", NETWORKDAYS(J35,TODAY(),fESTIVOS!$A$2:$A$53), NETWORKDAYS(J35,L35,fESTIVOS!$A$2:$A$53) ) ) -> 1 | Q35: 29/08/2025: 25/08/2025: Incluir en el reporte: * fecha_cierre * número de solicitud * fecha de envío de correo 03/09/2025: Requerimiento en pausa debido a que Imaginex actualmente no cuenta con permisos para creación de vistas, se encuentra en validación por infraestructura para una solución. 20/10/2025: Se incluyen campos solicitados por el área | R35: TRUE
... A38: MAURICIO | B38: PRV_2025_014 | C38: Aviso a la Renta Control de Cambios Reporte | E38: Previsional | F38: FINALIZADO | G38: 100 | H38: =IF(OR(J38="",K38="",K38<J38),0,NETWORKDAYS(J38,K38,fESTIVOS!$A$2:$A$53)) -> 3 | I38: 45894 | J38: 45938 | K38: 45940 | L38: 45947 | M38: =IF(OR(J38="",AND(L38="",TODAY()<J38),AND(L38<>"",L38<J38)),0, IF(L38="", NETWORKDAYS(J38,TODAY(),fESTIVOS!$A$2:$A$53), NETWORKDAYS(J38,L38,fESTIVOS!$A$2:$A$53) ) ) -> 7 | Q38: 29/08/2025: 25/08/2025: Automatizar el envío del informe: Frecuencia: todos los viernes a las 6:00 a.m. En caso de festivo, el informe debe enviarse el día hábil anterior. 03/09/2025: Requerimiento en pausa debido a que Imaginex actualmente no cuenta con permisos para creación de vistas, se encuentra en validación por infraestructura para una solución. 20/10/2025: El viernes 17 de octubre se agrego la funcionalidad para la ejecución del proceso Aviso a la Renta, mediante las tareas programadas. | R38: TRUE
A39: MAURICIO | B39: SST_2025_009 | C39: Ajuste modulo profesionales | D39: Se requiere validar y realizar ajustes de errores e incidencias que se están presentando en el módulo para realizar las pruebas por parte del cliente y sea certificado el paso a producción | E39: SST | F39: FINALIZADO | G39: 100 | H39: =IF(OR(J39="",K39="",K39<J39),0,NETWORKDAYS(J39,K39,fESTIVOS!$A$2:$A$53)) -> 3 | I39: 45901 | J39: 45901 | K39: 45903 | L39: 45919 | M39: =IF(OR(J39="",AND(L39="",TODAY()<J39),AND(L39<>"",L39<J39)),0, IF(L39="", NETWORKDAYS(J39,TODAY(),fESTIVOS!$A$2:$A$53), NETWORKDAYS(J39,L39,fESTIVOS!$A$2:$A$53) ) ) -> 15 | Q39: 01/09/2025: El 30 de agosto Mauricio realizando otras pruebas identifico un error en el modulo de profesionales en el ambiente de pruebas Alfa, por tanto se radica caso el 01 de septiembre para soporte de AWS y se contacta co Oscar Pérez para que nos ayuden con la incidencia reportada. Ya que hasta no sea solucionado no podremos realizar pruebas y el cliente tampoco. La fecha estimada relacionada es solo si nos gestionan en soporte ALFA el día de hoy, de lo contrario se verá afectada y cambiará de acuerdo con la solución del caso radicado. 03/09/2025: El 02 de septiembre queda solucionada la incidencia y queda pendiente realizar pruebas internas antes de entregar a Nohora Carolina de SST para pruebas del área. 05/09/2025: El 04 de septiembre se iniciaron pruebas internas, sin embargo, no fue posible culminarlas debido a una incidencia presentada con el plan de trabajo en el ambiente QA. 08/09/2025: El viernes 05 de septiembre, Mauricio trabajo en el cronograma en ambiente de pruebas, ya se libero presupuesto pero se esta validando porque no carga actividades y programas. 11/09/2025: El 10 de septiembre Mauricio continua validando, ajustando incidencias en el ambiente de QA que no han permitido realizar las pruebas correspondientes. 15/09/2025: El viernes 12 de septiembre Mauricio se enfoco en seguri revisando errores que se estan presentando en el módulo de cronogramas y edición de ordenes de servicios 18/09/2025: Durante los días del 15 al 17 Mauricio detecto errores en el desarrollo y ha trabajado en corregir y mejorar su funcionalidad, adicional de mejorar la apariencia siendo mas intuitivo para el usuario. Se refactorizo el diseño de la gestión de profesionales a acreditar y la gestión de proveedores. 22/09/2025: El viernes 19 de septiembre, Mauricio subió los ajustes de los modulos de profesionales y cronograma de trabajo. | R39: TRUE
A40: MAURICIO | B40: PRV_2025_015 | C40: Creaciòn Vistas en DLL Alfa | D40: Creaciòn de vistas en ambiente DLL Alfa para desarrollo de requerimientos previsionales | E40: Previsional | F40: FINALIZADO | G40: 100 | H40: =IF(OR(J40="",K40="",K40<J40),0,NETWORKDAYS(J40,K40,fESTIVOS!$A$2:$A$53)) -> 4 | I40: 45898 | J40: 45898 | K40: 45903 | L40: 45932 | M40: =IF(OR(J40="",AND(L40="",TODAY()<J40),AND(L40<>"",L40<J40)),0, IF(L40="", NETWORKDAYS(J40,TODAY(),fESTIVOS!$A$2:$A$53), NETWORKDAYS(J40,L40,fESTIVOS!$A$2:$A$53) ) ) -> 25 | Q40: 01/09/2025: El 29 de agosto a Mauricio se le entregaron credenciales por parte de infraestructura Alfa para permisos y creación de vistas en Desarrollo Sipren Plus, sin embargo, permitió coneción preo no la creación de las vistas. 03/09/2025: Requerimiento en pausa debido a que Imaginex actualmente no cuenta con permisos para creación de vistas, se encuentra en validación por infraestructura para una solución. 01/10/2025: Desde el 30 de septiembre se obtuvieron los permisos pendientes y se esta adelantando la creaciòn de vistas de los requerimientos que se han levantado 03/10/2025: el 02 de octubre se asignan nuevas vistas en la función de sincronización | R40: TRUE
A41: MAURICIO | B41: PRV_2025_016 | C41: Actualización Tablero de Estadistica y Cumplimiento | D41: Se incluye en las graficas aux funerarios | E41: Previsional | F41: FINALIZADO | G41: 100 | H41: =IF(OR(J41="",K41="",K41<J41),0,NETWORKDAYS(J41,K41,fESTIVOS!$A$2:$A$53)) -> 3 | I41: 45901 | J41: 45901 | K41: 45903 | L41: 45903 | M41: =IF(OR(J41="",AND(L41="",TODAY()<J41),AND(L41<>"",L41<J41)),0, IF(L41="", NETWORKDAYS(J41,TODAY(),fESTIVOS!$A$2:$A$53), NETWORKDAYS(J41,L41,fESTIVOS!$A$2:$A$53) ) ) -> 3 | Q41: 03/09/2025: 01/09/2025 Mauricio trabaja en la inclusión de la data de Auxilios Funerarios en el tablero de ANS. 02/09/2025: Se trabaja en los graficos de aux funerarios y en la consulta requerida para validar datos de flujo de pagos y aux funerario. Pendientes pruebas internas para antes de entregar para pruebas por parte del área de previsionales 04/09/2025: el 03 de septiembre el desarrollo del gráfico está en fase final, restando únicamente ajustes de personalización en los tooltips. Se programó una reunión con el cliente para la socialización de avances, debido a que no alcanzo el tiempo, se reprogramo sesión para el jueves 4 de septiembre a las 9:00 am El día de hoy 04 de septiembre, se realizan unas pruebas internas antes de entregar al cliente para sus respectivas pruebas y certificaciòn, siendo exitosas. En la sesión al momento de ingresar al aplicativo de pruebas Imagine, el cliente no pudo ya que por politicas de la compañia al parecer les quitaron permisos, se encuentran en validaciòn con el area tecnologica y sin embargo, por parte de Imagine les mostramos el módulo, los graficos, los cambios y los reportes. Se entrega para que apenas tengan acceso puedan validar y confirmar funcionalidad. 11/09/2025: Se confirma funcionalidad por parte del área de Previsionales | R41: TRUE
A42: MAURICIO | B42: Img_2025_004 | C42: Conexiones con Ministerio -SAT | E42: Imagine | F42: FINALIZADO | G42: 100 | H42: =IF(OR(J42="",K42="",K42<J42),0,NETWORKDAYS(J42,K42,fESTIVOS!$A$2:$A$53)) -> 1 | I42: 45902 | J42: 45903 | K42: 45903 | L42: 45903 | M42: =IF(OR(J42="",AND(L42="",TODAY()<J42),AND(L42<>"",L42<J42)),0, IF(L42="", NETWORKDAYS(J42,TODAY(),fESTIVOS!$A$2:$A$53), NETWORKDAYS(J42,L42,fESTIVOS!$A$2:$A$53) ) ) -> 1 | Q42: 04/09/2025: Se identificaron cambios en la configuración, por lo que se programó la reconfiguración de servicios en horas de la tarde. | R42: TRUE
A43: MAURICIO | B43: PRV_2025_017 | C43: Consultas y optimización de vistas (Alfa) | D43: Se requiere optimizar rendimiento y capacidad de las funciones del aplicativo Alfasst | E43: Previsional | F43: FINALIZADO | G43: 100 | H43: =IF(OR(J43="",K43="",K43<J43),0,NETWORKDAYS(J43,K43,fESTIVOS!$A$2:$A$53)) -> 3 | I43: 45903 | J43: 45903 | K43: 45905 | L43: 46041 | M43: =IF(OR(J43="",AND(L43="",TODAY()<J43),AND(L43<>"",L43<J43)),0, IF(L43="", NETWORKDAYS(J43,TODAY(),fESTIVOS!$A$2:$A$53), NETWORKDAYS(J43,L43,fESTIVOS!$A$2:$A$53) ) ) -> 92 | Q43: 04/09/2025: El 03 de septiembre Mauricio trabaja en realizar ajustes en consultas y procesos de automatización. Continúa pendiente la optimización de querys para mejorar el rendimiento general. 18/09/2025: Durante los ultimos dìas Mauricio se ha encargado de identificar mejoras en las consultas 29/10/2025: El viernes 24 de octubre Mauricio estuvo validando mejoras en consultas y mejorar el rendimiento del aplicativo. 19/01/2026: Se realizaron ajustes técnicos en las vistas del sistema para optimizar el rendimiento y la velocidad de respuesta. | R43: TRUE
A44: MAURICIO | B44: Img_2025_005 | C44: Conexiones con Ministerio -SAT Independientes | E44: Imagine | F44: FINALIZADO | G44: 100 | H44: =IF(OR(J44="",K44="",K44<J44),0,NETWORKDAYS(J44,K44,fESTIVOS!$A$2:$A$53)) -> 4 | I44: 45905 | J44: 45905 | K44: 45910 | L44: 45910 | M44: =IF(OR(J44="",AND(L44="",TODAY()<J44),AND(L44<>"",L44<J44)),0, IF(L44="", NETWORKDAYS(J44,TODAY(),fESTIVOS!$A$2:$A$53), NETWORKDAYS(J44,L44,fESTIVOS!$A$2:$A$53) ) ) -> 4 | Q44: 08/09/2025: El viernes 05 de septiembre, Mauricio trabajo en la restructuración de BD del ambiente local ya que se encuentra desactualizada para realizar pruebas con el Ministerio. 10/09/2025: Durante los días 08 y 09 de septiembre, Mauricio ha trabajado en las conexiones SAT del Ministerio para el requerimiento de independientes. 11/09/2025: El 10 de septiembre, Mauricio finalizò la conexiòn en integraciòn con la URL del Ministerio. | R44: TRUE
A45: MAURICIO | B45: Img_2025_006 | C45: Conexiones con Ministerio -SAT Independientes | E45: Imagine | F45: FINALIZADO | G45: 100 | H45: =IF(OR(J45="",K45="",K45<J45),0,NETWORKDAYS(J45,K45,fESTIVOS!$A$2:$A$53)) -> 4 | I45: 45905 | J45: 45905 | K45: 45910 | L45: 45910 | M45: =IF(OR(J45="",AND(L45="",TODAY()<J45),AND(L45<>"",L45<J45)),0, IF(L45="", NETWORKDAYS(J45,TODAY(),fESTIVOS!$A$2:$A$53), NETWORKDAYS(J45,L45,fESTIVOS!$A$2:$A$53) ) ) -> 4 | Q45: 08/09/2025: El viernes 05 de septiembre, Mauricio trabajo en la restructuración de BD del ambiente local ya que se encuentra desactualizada para realizar pruebas con el Ministerio. 10/09/2025: Durante los días 08 y 09 de septiembre, Mauricio ha trabajado en las conexiones SAT del Ministerio para el requerimiento de independientes. 11/09/2025: El 10 de septiembre, Mauricio finalizò la conexiòn en integraciòn con la URL del Ministerio. | R45: TRUE
A46: CARLOS | B46: PRV_2025_004-8 | C46: Solicitar acceso a vistas y tablas | E46: Previsional | F46: FINALIZADO | G46: 100 | H46: =IF(OR(J46="",K46="",K46<J46),0,NETWORKDAYS(J46,K46,fESTIVOS!$A$2:$A$53)) -> 0 | I46: 45884 | J46: 45884 | L46: 45888 | M46: =IF(OR(J46="",AND(L46="",TODAY()<J46),AND(L46<>"",L46<J46)),0, IF(L46="", NETWORKDAYS(J46,TODAY(),fESTIVOS!$A$2:$A$53), NETWORKDAYS(J46,L46,fESTIVOS!$A$2:$A$53) ) ) -> 2 | Q46: 15/08/2025: El dìa de hoy se tuvo incidencia debido a una restauraciòn de las bases de datos en SIPREN, en ambiente de pruebas, se borraron algunas vistas. Carlos realizó solicitud de nuevo de los permisos para lectura de tablas y vistas en ambiente de pruebas Sipren y Plus de unavez, ya que el dìa de hoy o mañana tambien realizaran restauración de bases de datos. 20/08/2025: Al 19 de agosto ya se encuentran los permisos e Imagine se encuntra en proceso de restauraciòn de las vistas y tablas borradas | R46: TRUE
A47: MAURICIO | B47: PRV_2025_004-4 | C47: Ajuste Modulo de Pagos 1 | E47: Previsional | F47: FINALIZADO | G47: 100 | H47: =IF(OR(J47="",K47="",K47<J47),0,NETWORKDAYS(J47,K47,fESTIVOS!$A$2:$A$53)) -> 2 | I47: 45889 | J47: 45889 | K47: 45890 | L47: 45889 | M47: =IF(OR(J47="",AND(L47="",TODAY()<J47),AND(L47<>"",L47<J47)),0, IF(L47="", NETWORKDAYS(J47,TODAY(),fESTIVOS!$A$2:$A$53), NETWORKDAYS(J47,L47,fESTIVOS!$A$2:$A$53) ) ) -> 1 | Q47: 21/08/2025: El día 20 de agosto, luego del paso a producciòn y de las pruebas realizadas por el cliente, se identificaron incidencias en los requerimientos que se subiron en el despliegue, para el modulo de pagos, se presentaron las siguientes: Incidencia: En el Excel de reportes se estaban duplicando los registros. Solución: Se ajustó la consulta incorporando la condición WHERE status = TRUE para filtrar únicamente los registros válidos. | R47: TRUE
A48: MAURICIO | B48: PRV_2025_004-5 | C48: Ajuste Modulo de Pagos 2 | E48: Previsional | F48: FINALIZADO | G48: 100 | H48: =IF(OR(J48="",K48="",K48<J48),0,NETWORKDAYS(J48,K48,fESTIVOS!$A$2:$A$53)) -> 2 | I48: 45889 | J48: 45889 | K48: 45890 | L48: 45889 | M48: =IF(OR(J48="",AND(L48="",TODAY()<J48),AND(L48<>"",L48<J48)),0, IF(L48="", NETWORKDAYS(J48,TODAY(),fESTIVOS!$A$2:$A$53), NETWORKDAYS(J48,L48,fESTIVOS!$A$2:$A$53) ) ) -> 1 | Q48: 21/08/2025: El día 20 de agosto, luego del paso a producciòn y de las pruebas realizadas por el cliente, se identificaron incidencias en los requerimientos que se subiron en el despliegue, para el modulo de pagos, se presentaron las siguientes: Incidencia: Los valores del último pago no coincidían. Solución: Se modificó la vista ultimo_pago para incluir el cod_concepto = 2 y se corrigió el cálculo, que anteriormente sumaba pago_total en lugar de valor_concepto. | R48: TRUE
A49: MAURICIO | B49: PRV_2025_004-6 | C49: Ajuste Aviso a la Renta | E49: Previsional | F49: FINALIZADO | G49: 100 | H49: =IF(OR(J49="",K49="",K49<J49),0,NETWORKDAYS(J49,K49,fESTIVOS!$A$2:$A$53)) -> 2 | I49: 45889 | J49: 45889 | K49: 45890 | L49: 45889 | M49: =IF(OR(J49="",AND(L49="",TODAY()<J49),AND(L49<>"",L49<J49)),0, IF(L49="", NETWORKDAYS(J49,TODAY(),fESTIVOS!$A$2:$A$53), NETWORKDAYS(J49,L49,fESTIVOS!$A$2:$A$53) ) ) -> 1 | Q49: 21/08/2025: El día 20 de agosto, luego del paso a producciòn y de las pruebas realizadas por el cliente, se identificaron incidencias en los requerimientos que se subiron en el despliegue, para aviso a la renta, se presentaron las siguientes: Incidencia: Se solicitó revisar el SELECT de la consulta utilizada para el aviso a la renta. Solución: Se validó la formulación de la consulta y se confirmó que es correcta. Nota: Carlos Rodríguez solicitó revisar y analizar el detalle de dicha consulta. | R49: TRUE
A50: MAURICIO | B50: PRV_2025_004-7 | C50: Ajuste Auxilio Funerario | E50: Previsional | F50: FINALIZADO | G50: 100 | H50: =IF(OR(J50="",K50="",K50<J50),0,NETWORKDAYS(J50,K50,fESTIVOS!$A$2:$A$53)) -> 2 | I50: 45889 | J50: 45889 | K50: 45890 | L50: 45889 | M50: =IF(OR(J50="",AND(L50="",TODAY()<J50),AND(L50<>"",L50<J50)),0, IF(L50="", NETWORKDAYS(J50,TODAY(),fESTIVOS!$A$2:$A$53), NETWORKDAYS(J50,L50,fESTIVOS!$A$2:$A$53) ) ) -> 1 | Q50: 21/08/2025: El día 20 de agosto, luego del paso a producciòn y de las pruebas realizadas por el cliente, se identificaron incidencias en los requerimientos que se subieron en el despliegue, para auxilios funerarios, se presentaron las siguientes: Incidencia: Error al cargar el formato Excel de auxilios cuando contiene varias hojas. Solución: Se identificó que el sistema solo procesa correctamente la hoja activa. Se intentó ajustar para cargar únicamente esa hoja; sin embargo, por agilidad operativa, se solicita al usuario dejar una sola hoja en el archivo antes del cargue, mediante validación al cargar y un mensaje informativo. | R50: TRUE
A51: MAURICIO | B51: PRV_2025_004-9 | C51: Ajuste Auxilio Funerario | E51: Previsional | F51: FINALIZADO | G51: 100 | H51: =IF(OR(J51="",K51="",K51<J51),0,NETWORKDAYS(J51,K51,fESTIVOS!$A$2:$A$53)) -> 2 | I51: 45889 | J51: 45889 | K51: 45890 | L51: 45889 | M51: =IF(OR(J51="",AND(L51="",TODAY()<J51),AND(L51<>"",L51<J51)),0, IF(L51="", NETWORKDAYS(J51,TODAY(),fESTIVOS!$A$2:$A$53), NETWORKDAYS(J51,L51,fESTIVOS!$A$2:$A$53) ) ) -> 1 | Q51: 21/08/2025: El día 20 de agosto, luego del paso a producciòn y de las pruebas realizadas por el cliente, se identificaron incidencias en los requerimientos que se subiron en el despliegue, para auxilios funerarios, se presentaron las siguientes: Incidencia: Falta de valor del auxilio funerario. Solución: Se incluyó un ajuste final que complementa la información con la fecha esto solucionando el 70% del trabajo del analista. Se detectó que no se estaba completando el valor calculado del pago; por ello, se actualizó la condición WHERE para que también actualizara dicho valor. | R51: TRUE
A52: MAURICIO | B52: PRV_2025_004-10 | C52: Ajuste Auxilio Funerario | E52: Previsional | F52: FINALIZADO | G52: 100 | H52: =IF(OR(J52="",K52="",K52<J52),0,NETWORKDAYS(J52,K52,fESTIVOS!$A$2:$A$53)) -> 2 | I52: 45889 | J52: 45889 | K52: 45890 | L52: 45889 | M52: =IF(OR(J52="",AND(L52="",TODAY()<J52),AND(L52<>"",L52<J52)),0, IF(L52="", NETWORKDAYS(J52,TODAY(),fESTIVOS!$A$2:$A$53), NETWORKDAYS(J52,L52,fESTIVOS!$A$2:$A$53) ) ) -> 1 | Q52: 21/08/2025: El día 20 de agosto, luego del paso a producciòn y de las pruebas realizadas por el cliente, se identificaron incidencias en los requerimientos que se subiron en el despliegue, para auxilios funerarios, se presentaron las siguientes: Incidencia: Algunas funciones no fueron desplegadas en producción el día 16 de agosto. Solución: Se realizó la creación e implementación de las funciones faltantes en el ambiente productivo. | R52: TRUE
A53: MAURICIO | B53: Img_2025_002-1 | C53: Validar servidor de contingencia - Tarea 1 | E53: Imagine | F53: FINALIZADO | G53: 100 | H53: =IF(OR(J53="",K53="",K53<J53),0,NETWORKDAYS(J53,K53,fESTIVOS!$A$2:$A$53)) -> 2 | I53: 45890 | J53: 45890 | K53: 45891 | L53: 45890 | M53: =IF(OR(J53="",AND(L53="",TODAY()<J53),AND(L53<>"",L53<J53)),0, IF(L53="", NETWORKDAYS(J53,TODAY(),fESTIVOS!$A$2:$A$53), NETWORKDAYS(J53,L53,fESTIVOS!$A$2:$A$53) ) ) -> 1 | Q53: 22/08/2025: El día 21 de agosto Mauricio se ha encargado de atender tareas asignadas por Jenry para mejorar el tema de control y seguimiento en ambiente de contingencia: - Parametrizar el mostrar los tiempos que demora la sincronización | R53: TRUE
A54: MAURICIO | B54: Img_2025_002-2 | C54: Validar servidor de contingencia - Tarea 2 | D54: Crear .bash para mostrar registros de contingencia en producción | E54: Imagine | F54: FINALIZADO | G54: 100 | H54: =IF(OR(J54="",K54="",K54<J54),0,NETWORKDAYS(J54,K54,fESTIVOS!$A$2:$A$53)) -> 1 | I54: 45890 | J54: 45891 | K54: 45891 | L54: 45891 | M54: =IF(OR(J54="",AND(L54="",TODAY()<J54),AND(L54<>"",L54<J54)),0, IF(L54="", NETWORKDAYS(J54,TODAY(),fESTIVOS!$A$2:$A$53), NETWORKDAYS(J54,L54,fESTIVOS!$A$2:$A$53) ) ) -> 1 | Q54: 22/08/2025: El día 21 de agosto Mauricio se ha encargado de atender tareas asignadas por Jenry para mejorar el tema de control y seguimiento en ambiente de contingencia: - Crear .bash que muestre los registros de contingencia con producción 25/08/2025: El viernes 22 de agosto se creo el .bash solicitado | R54: TRUE
A55: MAURICIO | B55: Img_2025_002-3 | C55: Validar servidor de contingencia - Tarea 3 | E55: Imagine | F55: FINALIZADO | G55: 100 | H55: =IF(OR(J55="",K55="",K55<J55),0,NETWORKDAYS(J55,K55,fESTIVOS!$A$2:$A$53)) -> 2 | I55: 45890 | J55: 45890 | K55: 45891 | L55: 45890 | M55: =IF(OR(J55="",AND(L55="",TODAY()<J55),AND(L55<>"",L55<J55)),0, IF(L55="", NETWORKDAYS(J55,TODAY(),fESTIVOS!$A$2:$A$53), NETWORKDAYS(J55,L55,fESTIVOS!$A$2:$A$53) ) ) -> 1 | Q55: 22/08/2025: El día 21 de agosto Mauricio se ha encargado de atender tareas asignadas por Jenry para mejorar el tema de control y seguimiento en ambiente de contingencia: - Revisar cada cuanto se sincronizan las imagenes, si cada hora de lunes a viernes | R55: TRUE
A56: MAURICIO | B56: Img_2025_003 | C56: Restauración BD Pruebas Imagine | D56: Se requiere realizar la homologación y restauración de las bases de datos en el servidor de pruebas de Imagine, con el fin de garantizar la disponibilidad y consistencia de la información para las validaciones correspondientes, según la solicitud presentada por fala. | E56: Imagine | F56: FINALIZADO | G56: 100 | H56: =IF(OR(J56="",K56="",K56<J56),0,NETWORKDAYS(J56,K56,fESTIVOS!$A$2:$A$53)) -> 2 | I56: 45890 | J56: 45890 | K56: 45892 | L56: 45892 | M56: =IF(OR(J56="",AND(L56="",TODAY()<J56),AND(L56<>"",L56<J56)),0, IF(L56="", NETWORKDAYS(J56,TODAY(),fESTIVOS!$A$2:$A$53), NETWORKDAYS(J56,L56,fESTIVOS!$A$2:$A$53) ) ) -> 2 | Q56: 22/08/2025: El día 21 de agosto Mauricio se ha encargado de atender tareas asignadas por Jenry para mejorar el tema de control y seguimiento en ambiente de contingencia: - Renombrar las BD en pruebas y restaurar producción 25/08/2025: Entre el viernes 22 y sabado 23 Mauricio realizo la homologaciòn y restauraciòn de las BD | R56: TRUE
A57: MAURICIO | B57: Img_2025_007 | C57: Servicios SAT Independientes - 1 | D57: Crear servicio del Ministerio de Salud y Protección Social de Afiliaciones Independientes | E57: Imagine | F57: FINALIZADO | G57: 100 | H57: =IF(OR(J57="",K57="",K57<J57),0,NETWORKDAYS(J57,K57,fESTIVOS!$A$2:$A$53)) -> 3 | I57: 45910 | J57: 45910 | K57: 45912 | L57: 45937 | M57: =IF(OR(J57="",AND(L57="",TODAY()<J57),AND(L57<>"",L57<J57)),0, IF(L57="", NETWORKDAYS(J57,TODAY(),fESTIVOS!$A$2:$A$53), NETWORKDAYS(J57,L57,fESTIVOS!$A$2:$A$53) ) ) -> 20 | Q57: 11/09/2025: El 10 de septiembre se realizó el despliegue del servicio de Afiliaciones de Independientes en el ambiente de pruebas OnPremise Falta realizar pruebas iniciales en el primer servicio de 13 servicios. 18/09/2025: Se culmina el desarrollo, falta que el Ministerio certifique funcionalidad. 08/10/2025: Se terminan desarrollos del servicio SAT afiliaciones independientes | R57: TRUE
A58: MAURICIO | B58: Img_2025_008 | C58: Servicios SAT Independientes - 2 | D58: Crear servicio del Ministerio de Salud y Protección Social de Retractación | E58: Imagine | F58: FINALIZADO | G58: 100 | H58: =IF(OR(J58="",K58="",K58<J58),0,NETWORKDAYS(J58,K58,fESTIVOS!$A$2:$A$53)) -> 2 | I58: 45912 | J58: 45912 | K58: 45915 | L58: 45937 | M58: =IF(OR(J58="",AND(L58="",TODAY()<J58),AND(L58<>"",L58<J58)),0, IF(L58="", NETWORKDAYS(J58,TODAY(),fESTIVOS!$A$2:$A$53), NETWORKDAYS(J58,L58,fESTIVOS!$A$2:$A$53) ) ) -> 18 | Q58: 15/09/2025: El viernes 12 de septiembre se realizó el despliegue del servicio de Retractación de afiliaciones de Trabajadores Independientes en el ambiente de pruebas OnPremise Falta realizar pruebas 18/09/2025: Se culmina el desarrollo, falta que el Ministerio certifique funcionalidad. 08/10/2025: Se terminan desarrollos del servicio SAT retractacciones independientes | R58: TRUE
A59: MAURICIO | B59: Img_2025_009 | C59: Servicios SAT Independientes - 3 | D59: Crear servicio del Ministerio de Salud y Protección Social de Terminación de Afiliación | E59: Imagine | F59: FINALIZADO | G59: 100 | H59: =IF(OR(J59="",K59="",K59<J59),0,NETWORKDAYS(J59,K59,fESTIVOS!$A$2:$A$53)) -> 2 | I59: 45912 | J59: 45912 | K59: 45915 | L59: 45937 | M59: =IF(OR(J59="",AND(L59="",TODAY()<J59),AND(L59<>"",L59<J59)),0, IF(L59="", NETWORKDAYS(J59,TODAY(),fESTIVOS!$A$2:$A$53), NETWORKDAYS(J59,L59,fESTIVOS!$A$2:$A$53) ) ) -> 18 | Q59: 15/09/2025: El viernes 12 de septiembre se realizó el despliegue del servicio de Terminaciòn de afiliaciones de la ARL de Trabajadores Independientes en el ambiente de pruebas OnPremise Falta realizar pruebas 18/09/2025: Se culmina el desarrollo, falta que el Ministerio certifique funcionalidad. 08/10/2025: Se terminan desarrollos del servicio SAT terminacion de afiliacion independientes | R59: TRUE
A60: MAURICIO | B60: Img_2025_010 | C60: Servicios SAT Independientes - 4 | D60: Crear servicio del Ministerio de Salud y Protección Social de Traslado de ARL | E60: Imagine | F60: FINALIZADO | G60: 100 | H60: =IF(OR(J60="",K60="",K60<J60),0,NETWORKDAYS(J60,K60,fESTIVOS!$A$2:$A$53)) -> 3 | I60: 45917 | J60: 45917 | K60: 45919 | L60: 45937 | M60: =IF(OR(J60="",AND(L60="",TODAY()<J60),AND(L60<>"",L60<J60)),0, IF(L60="", NETWORKDAYS(J60,TODAY(),fESTIVOS!$A$2:$A$53), NETWORKDAYS(J60,L60,fESTIVOS!$A$2:$A$53) ) ) -> 15 | Q60: 18/09/2025: El 17 de septiembre se creo el servicio de Traslado de ARL de Trabajadores Independientes. Pendiente ajuste en el maestro de empleados. 08/10/2025: Se terminan desarrollos en el servicio SAT para traslado de ARL independientes | R60: TRUE
A61: MAURICIO | B61: Img_2025_011 | C61: Servicios SAT Independientes - 5 | D61: Crear servicio del Ministerio de Salud y Protección Social de Cambio de Ocupación en Independientes Voluntarios | E61: Imagine | F61: FINALIZADO | G61: 100 | H61: =IF(OR(J61="",K61="",K61<J61),0,NETWORKDAYS(J61,K61,fESTIVOS!$A$2:$A$53)) -> 3 | I61: 45917 | J61: 45917 | K61: 45919 | L61: 45937 | M61: =IF(OR(J61="",AND(L61="",TODAY()<J61),AND(L61<>"",L61<J61)),0, IF(L61="", NETWORKDAYS(J61,TODAY(),fESTIVOS!$A$2:$A$53), NETWORKDAYS(J61,L61,fESTIVOS!$A$2:$A$53) ) ) -> 15 | Q61: 18/09/2025: El 17 de septiembre se creo el servicio de Cambio de Ocupación en Independientes Voluntarios de Trabajadores Independientes. Pendiente ajuste en el maestro de empleados. 08/10/2025: Se terminan desarrollos del servicio SAT cambio de ocupacion u oficio en independientes voluntarios | R61: TRUE
A62: MAURICIO | B62: PRV_2025_018 | C62: ANS - TABLERO DE CONTROL - Ajuste | D62: Se requiere crear un nuevo grupo para incluir los estados ANULADOS, en las gráficas del tablero de estadisticas | E62: Previsional | F62: FINALIZADO | G62: 100 | H62: =IF(OR(J62="",K62="",K62<J62),0,NETWORKDAYS(J62,K62,fESTIVOS!$A$2:$A$53)) -> 1 | I62: 45919 | J62: 45919 | K62: 45919 | L62: 45919 | M62: =IF(OR(J62="",AND(L62="",TODAY()<J62),AND(L62<>"",L62<J62)),0, IF(L62="", NETWORKDAYS(J62,TODAY(),fESTIVOS!$A$2:$A$53), NETWORKDAYS(J62,L62,fESTIVOS!$A$2:$A$53) ) ) -> 1 | Q62: 22/09/2025: El 19 de septiembre, Mauricio trabajo en la correcciòn del error Bad Request y se agrego un nuevo estado Anulado a flujos de pagos y auxilios funerarios. Pendientes las pruebas por parte de Imagine para posterior entrega actualizaciones al cliente y certifiquen el ajuste. | R62: TRUE
A63: MAURICIO | B63: Img_2025_012 | C63: Servicios SAT Independientes - Consultas | D63: Desarrollar consultas de los servicios creados en SAT para independientes de afiliaciones activas | E63: Imagine | F63: FINALIZADO | G63: 100 | H63: =IF(OR(J63="",K63="",K63<J63),0,NETWORKDAYS(J63,K63,fESTIVOS!$A$2:$A$53)) -> 0 | I63: 45922 | J63: 45922 | L63: 45937 | M63: =IF(OR(J63="",AND(L63="",TODAY()<J63),AND(L63<>"",L63<J63)),0, IF(L63="", NETWORKDAYS(J63,TODAY(),fESTIVOS!$A$2:$A$53), NETWORKDAYS(J63,L63,fESTIVOS!$A$2:$A$53) ) ) -> 12 | Q63: 22/09/2025: Desarrollar formulario de consulta para servicios del Ministerio: - Consulta de trabajadores independientes de afiliaciòn activa a la ARL, incluyendo traslados y retractaciones de afiliaciòn. - Consulta de trabajadores independientes trasladables de ARL. 25/09/2025: Entre los días 22 y 23 de septiembre, Mauricio ha trabajado en la consulta de independientes activos y en mora 26/09/2025:El 25 de septiembre se trabajo en la consulta de Independiente afiliación activa ARL Pendiente: Actualmente el servicio Consulta Trabajador Independiente Mora ARL, no esta arrojando resultados. Ya fue notificado al área encargada para revisión. 08/10/2025: Se termina la consulta de afiliaciones activas | R63: TRUE
A64: MAURICIO | B64: Img_2025_013 | C64: Servicios SAT Independientes - Consultas | D64: Desarrollar consultas de los servicios creados en SAT para independientes en Mora ARL | E64: Imagine | F64: FINALIZADO | G64: 100 | H64: =IF(OR(J64="",K64="",K64<J64),0,NETWORKDAYS(J64,K64,fESTIVOS!$A$2:$A$53)) -> 0 | I64: 45922 | J64: 45922 | L64: 45937 | M64: =IF(OR(J64="",AND(L64="",TODAY()<J64),AND(L64<>"",L64<J64)),0, IF(L64="", NETWORKDAYS(J64,TODAY(),fESTIVOS!$A$2:$A$53), NETWORKDAYS(J64,L64,fESTIVOS!$A$2:$A$53) ) ) -> 12 | Q64: 22/09/2025: Desarrollar formulario de consulta para servicios del Ministerio: - Consulta de trabajadores independientes de afiliaciòn activa a la ARL, incluyendo traslados y retractaciones de afiliaciòn. - Consulta de trabajadores independientes trasladables de ARL. 25/09/2025: Entre los días 22 y 23 de septiembre, Mauricio ha trabajado en la consulta de independientes activos y en mora 26/09/2025:El 25 de septiembre se trabajo en la consulta de Independiente afiliación activa ARL Pendiente: Actualmente el servicio Consulta Trabajador Independiente Mora ARL, no esta arrojando resultados. Ya fue notificado al área encargada para revisión. 08/10/2025: Se termina la consulta de independiente en Mora ARL | R64: TRUE
A65: MAURICIO | B65: REN_2025_05 | C65: Validación Documental_Ajuste | D65: Validar y parametrizar los documentos en validacion documental para el nuevo origen Sustitucion, sin embargo, en el parentesco Hijos no mostraba informaciòn correcta | E65: Imagine | F65: FINALIZADO | G65: 100 | H65: =IF(OR(J65="",K65="",K65<J65),0,NETWORKDAYS(J65,K65,fESTIVOS!$A$2:$A$53)) -> 1 | I65: 45925 | J65: 45925 | K65: 45925 | L65: 45925 | M65: =IF(OR(J65="",AND(L65="",TODAY()<J65),AND(L65<>"",L65<J65)),0, IF(L65="", NETWORKDAYS(J65,TODAY(),fESTIVOS!$A$2:$A$53), NETWORKDAYS(J65,L65,fESTIVOS!$A$2:$A$53) ) ) -> 1 | Q65: 26/09/2025: El 25 de septiembre, se brinda soporte a Rentas, dando solución a una incidencia presentada en la parametrización de origen de archivos de Sustitucion con el parentesco Hijos. | R65: TRUE
A66: MAURICIO | B66: SST_2025_010 | C66: Ajuste modulo profesionales-Lentitud | D66: Se requiere validar el modulo de profesionales ya que en pruebas no carga para realizar el test correspondiente, adicional presenta lentitud en algunas funciones | E66: SST | F66: FINALIZADO | G66: 100 | H66: =IF(OR(J66="",K66="",K66<J66),0,NETWORKDAYS(J66,K66,fESTIVOS!$A$2:$A$53)) -> 1 | I66: 45931 | J66: 45932 | K66: 45932 | L66: 45932 | M66: =IF(OR(J66="",AND(L66="",TODAY()<J66),AND(L66<>"",L66<J66)),0, IF(L66="", NETWORKDAYS(J66,TODAY(),fESTIVOS!$A$2:$A$53), NETWORKDAYS(J66,L66,fESTIVOS!$A$2:$A$53) ) ) -> 1 | Q66: 03/10/2025: El 02 de octubre, Mauricio valida incidencia en la lentitud o no cargue al editar en modulo de profesionales en el rol Gestor en pruebas. | R66: TRUE
A67: MAURICIO | B67: PRV_2025_019 | C67: Revisión error en URL | D67: Validar error de restricción de URL/Bad Request | E67: Previsional | F67: FINALIZADO | G67: 100 | H67: =IF(OR(J67="",K67="",K67<J67),0,NETWORKDAYS(J67,K67,fESTIVOS!$A$2:$A$53)) -> 0 | I67: 45932 | J67: 45934 | K67: 45934 | L67: 45934 | M67: =IF(OR(J67="",AND(L67="",TODAY()<J67),AND(L67<>"",L67<J67)),0, IF(L67="", NETWORKDAYS(J67,TODAY(),fESTIVOS!$A$2:$A$53), NETWORKDAYS(J67,L67,fESTIVOS!$A$2:$A$53) ) ) -> 0 | Q67: 03/10/2025: Se recibe caso reportado por el área, sobre un error de restricción de URL/Bad Request. Se proyecta que hoy Mauricio inicie soluciòn a estas incidencias presentadas. 06/10/2025: El sabado 04 de octubre Mauricio con apoyo de Jairo Niño, resuelve la incidencia presentada | R67: TRUE
A68: MAURICIO | B68: PRV_2025_020 | C68: Revisión generación de correo doble | D68: Validar error de generación de doble correo en flujo de pagos | E68: Previsional | F68: FINALIZADO | G68: 100 | H68: =IF(OR(J68="",K68="",K68<J68),0,NETWORKDAYS(J68,K68,fESTIVOS!$A$2:$A$53)) -> 0 | I68: 45932 | J68: 45934 | K68: 45934 | L68: 45934 | M68: =IF(OR(J68="",AND(L68="",TODAY()<J68),AND(L68<>"",L68<J68)),0, IF(L68="", NETWORKDAYS(J68,TODAY(),fESTIVOS!$A$2:$A$53), NETWORKDAYS(J68,L68,fESTIVOS!$A$2:$A$53) ) ) -> 0 | Q68: 03/10/2025: Se recibe caso reportado por el área, sobre notificación de correos dobles en el flujo de pagos. Se proyecta que hoy Mauricio inicie soluciòn a estas incidencias presentadas. 06/10/2025: El sabado 04 de octubre Mauricio con apoyo de Jairo Niño, resuelve la incidencia presentada | R68: TRUE
A69: MAURICIO | B69: Img_2025_014 | C69: Restauración BD Pruebas Imagine | D69: Se requiere realizar la homologación y restauración de las bases de datos en el servidor de pruebas de Imagine, con el fin de garantizar la disponibilidad y consistencia de la información para las validaciones correspondientes, según la solicitud presentada por Alfa | E69: Imagine | F69: FINALIZADO | G69: 100 | H69: =IF(OR(J69="",K69="",K69<J69),0,NETWORKDAYS(J69,K69,fESTIVOS!$A$2:$A$53)) -> 0 | I69: 45932 | J69: 45934 | K69: 45934 | L69: 45934 | M69: =IF(OR(J69="",AND(L69="",TODAY()<J69),AND(L69<>"",L69<J69)),0, IF(L69="", NETWORKDAYS(J69,TODAY(),fESTIVOS!$A$2:$A$53), NETWORKDAYS(J69,L69,fESTIVOS!$A$2:$A$53) ) ) -> 0 | Q69: 03/10/2025: Hoy se creará el plan de trabajo para restaurar las bases de datos de producción en el ambiente de pruebas., Esto incluyendo la revisión de tablas, funciones, procedimientos y disparadores (triggers). 06/10/2025: El 04 de octubre se procedió con la restauración de la base de datos de pruebas. Se realizó la homologación de tablas, funciones, procedimientos y demás elementos. Queda pendiente realizar pruebas funcionales de las aplicaciones | R69: TRUE
A70: MAURICIO | B70: PRV_2025_021 | C70: Modulo Objeciones y Devoluciones | E70: Previsional | F70: FINALIZADO | G70: 100 | H70: =IF(OR(J70="",K70="",K70<J70),0,NETWORKDAYS(J70,K70,fESTIVOS!$A$2:$A$53)) -> 2 | I70: 45936 | J70: 45936 | K70: 45937 | L70: 45937 | M70: =IF(OR(J70="",AND(L70="",TODAY()<J70),AND(L70<>"",L70<J70)),0, IF(L70="", NETWORKDAYS(J70,TODAY(),fESTIVOS!$A$2:$A$53), NETWORKDAYS(J70,L70,fESTIVOS!$A$2:$A$53) ) ) -> 2 | Q70: 08/10/2025: Entre 06 y 07 de octubre, se crea modulo para el requerimiento de notificaciòn Objeciones y Devoluciones, asociado a casos sincronizados con la vista de inventario. Pendiente: Crear tarea programada para que se ejecute a diario de lunes a viernes a las 4 pm. | R70: TRUE
A71: MAURICIO | B71: PRV_2025_022 | C71: Aviso a la Renta - Ajuste | D71: Se requiere agregar campos solicitados por el cliente | E71: Previsional | F71: FINALIZADO | G71: 100 | H71: =IF(OR(J71="",K71="",K71<J71),0,NETWORKDAYS(J71,K71,fESTIVOS!$A$2:$A$53)) -> 2 | I71: 45936 | J71: 45936 | K71: 45937 | L71: 45937 | M71: =IF(OR(J71="",AND(L71="",TODAY()<J71),AND(L71<>"",L71<J71)),0, IF(L71="", NETWORKDAYS(J71,TODAY(),fESTIVOS!$A$2:$A$53), NETWORKDAYS(J71,L71,fESTIVOS!$A$2:$A$53) ) ) -> 2 | Q71: 08/10/2025: El 07 de octubre se agregan los campos de fecha cierre y fecha de notificaciòn, solicitados por el área. Pendientes: Automatizar envio de informe y correr sincronizacion al cargar el Excel | R71: TRUE
A72: MAURICIO | B72: Img_2025_015 | C72: Servicios SAT Independientes - 6 | D72: Crear servicio del Ministerio de Salud y Protección Social de Reporte en Mora | E72: Imagine | F72: FINALIZADO | G72: 100 | H72: =IF(OR(J72="",K72="",K72<J72),0,NETWORKDAYS(J72,K72,fESTIVOS!$A$2:$A$53)) -> 2 | I72: 45936 | J72: 45936 | K72: 45937 | L72: 45937 | M72: =IF(OR(J72="",AND(L72="",TODAY()<J72),AND(L72<>"",L72<J72)),0, IF(L72="", NETWORKDAYS(J72,TODAY(),fESTIVOS!$A$2:$A$53), NETWORKDAYS(J72,L72,fESTIVOS!$A$2:$A$53) ) ) -> 2 | Q72: 08/10/2025: Entre 06 y 07 de octubre, se realizó el despliegue del servicio de Reporte de mora, acuerdos de pago e incumplimiento de Independientes en el ambiente de pruebas OnPremise | R72: TRUE
A73: MAURICIO | B73: Img_2025_016 | C73: Servicios SAT Independientes - Consultas | D73: Desarrollar consultas de los servicios creados en SAT para independientes de detalle de afiliaciones activas | E73: Imagine | F73: FINALIZADO | G73: 100 | H73: =IF(OR(J73="",K73="",K73<J73),0,NETWORKDAYS(J73,K73,fESTIVOS!$A$2:$A$53)) -> 2 | I73: 45936 | J73: 45936 | K73: 45937 | L73: 45937 | M73: =IF(OR(J73="",AND(L73="",TODAY()<J73),AND(L73<>"",L73<J73)),0, IF(L73="", NETWORKDAYS(J73,TODAY(),fESTIVOS!$A$2:$A$53), NETWORKDAYS(J73,L73,fESTIVOS!$A$2:$A$53) ) ) -> 2 | Q73: 08/10/2025: Entre 06 y 07 de octubre, se desarrolla formulario de consulta para servicios del Ministerio del detalle de afiliaciones activas en la ARL | R73: TRUE
A74: MAURICIO | B74: Img_2025_017 | C74: Servicios SAT Independientes - Consultas | D74: Desarrollar consultas de los servicios creados en SAT para independientes de trabajadores trasladables | E74: Imagine | F74: FINALIZADO | G74: 100 | H74: =IF(OR(J74="",K74="",K74<J74),0,NETWORKDAYS(J74,K74,fESTIVOS!$A$2:$A$53)) -> 2 | I74: 45936 | J74: 45936 | K74: 45937 | L74: 45937 | M74: =IF(OR(J74="",AND(L74="",TODAY()<J74),AND(L74<>"",L74<J74)),0, IF(L74="", NETWORKDAYS(J74,TODAY(),fESTIVOS!$A$2:$A$53), NETWORKDAYS(J74,L74,fESTIVOS!$A$2:$A$53) ) ) -> 2 | Q74: 08/10/2025: Entre 06 y 07 de octubre, se desarrolla formulario de consulta para servicios del Ministerio de Trabajadores Independientes Trasladables de ARL. | R74: TRUE
A75: MAURICIO | B75: PRV_2025_023 | C75: Modulo Objeciones y Devoluciones - Ajuste | D75: Implementar tarea programada para envío de notificaciones | E75: Previsional | F75: FINALIZADO | G75: 100 | H75: =IF(OR(J75="",K75="",K75<J75),0,NETWORKDAYS(J75,K75,fESTIVOS!$A$2:$A$53)) -> 2 | I75: 45938 | J75: 45938 | K75: 45939 | L75: 45938 | M75: =IF(OR(J75="",AND(L75="",TODAY()<J75),AND(L75<>"",L75<J75)),0, IF(L75="", NETWORKDAYS(J75,TODAY(),fESTIVOS!$A$2:$A$53), NETWORKDAYS(J75,L75,fESTIVOS!$A$2:$A$53) ) ) -> 1 | Q75: 14/10/2025: El 08 de octubre Mauricio implementò la opcion de tarea programada en el modulo de Objeciones y Devoluciones, para notificación diaria a las 4 pm | R75: TRUE
A76: MAURICIO | B76: PRV_2025_024 | C76: Modulo de Indicadores Pendientes | D76: Se implementa modulo para mostrar los casos sin resolucion | E76: Previsional | F76: FINALIZADO | G76: 100 | H76: =IF(OR(J76="",K76="",K76<J76),0,NETWORKDAYS(J76,K76,fESTIVOS!$A$2:$A$53)) -> 2 | I76: 45939 | J76: 45939 | K76: 45940 | L76: 45939 | M76: =IF(OR(J76="",AND(L76="",TODAY()<J76),AND(L76<>"",L76<J76)),0, IF(L76="", NETWORKDAYS(J76,TODAY(),fESTIVOS!$A$2:$A$53), NETWORKDAYS(J76,L76,fESTIVOS!$A$2:$A$53) ) ) -> 1 | Q76: 14/10/2025: El 09 de octubre, Mauricio desarrolla el modulo de indicadores de pendientes, el cual muestra los casos sin resolver, clasificados por rangos de tiempo: Del dia 1 al dia 8, y mas de 8 dias. Este informe se presenta por usuario | R76: TRUE
A77: MAURICIO | B77: Img_2025_018 | C77: Servidor de Produccion y Contingencia | D77: Sincronizacion BD | E77: Imagine | F77: FINALIZADO | G77: 100 | H77: =IF(OR(J77="",K77="",K77<J77),0,NETWORKDAYS(J77,K77,fESTIVOS!$A$2:$A$53)) -> 1 | I77: 45940 | J77: 45940 | K77: 45940 | L77: 45940 | M77: =IF(OR(J77="",AND(L77="",TODAY()<J77),AND(L77<>"",L77<J77)),0, IF(L77="", NETWORKDAYS(J77,TODAY(),fESTIVOS!$A$2:$A$53), NETWORKDAYS(J77,L77,fESTIVOS!$A$2:$A$53) ) ) -> 1 | Q77: 14/10/2025: El viernes 10 de octubre, se notifico al area de TI Alfa, sobre la imposobilidad de sincronizar el servidor de produccion con el servidor de contingencia | R77: TRUE
A78: MAURICIO | B78: SST_2025_011 | C78: Ajuste modulo profesionales-Ajuste | D78: Se requiere validar el cargue de documentos en la creacion del profesional, ya que no quedan adjuntos | E78: SST | F78: FINALIZADO | G78: 100 | H78: =IF(OR(J78="",K78="",K78<J78),0,NETWORKDAYS(J78,K78,fESTIVOS!$A$2:$A$53)) -> 1 | I78: 45937 | J78: 45940 | K78: 45940 | L78: 45940 | M78: =IF(OR(J78="",AND(L78="",TODAY()<J78),AND(L78<>"",L78<J78)),0, IF(L78="", NETWORKDAYS(J78,TODAY(),fESTIVOS!$A$2:$A$53), NETWORKDAYS(J78,L78,fESTIVOS!$A$2:$A$53) ) ) -> 1 | Q78: 14/10/2025: El 10 de octubre, Mauricio realiza validacion y ajustes correspondientes en la incidencia presentada en cuanto al cargue de documentos como hoja de vida y licencia en la creaciòn de un profesional. | R78: TRUE
A79: MAURICIO | B79: PRV_2025_025 | C79: Modulo de Inventarios - Ajuste 1 | D79: Crear export de detalles | E79: Previsional | F79: FINALIZADO | G79: 100 | H79: =IF(OR(J79="",K79="",K79<J79),0,NETWORKDAYS(J79,K79,fESTIVOS!$A$2:$A$53)) -> 1 | I79: 45944 | J79: 45944 | K79: 45944 | L79: 45944 | M79: =IF(OR(J79="",AND(L79="",TODAY()<J79),AND(L79<>"",L79<J79)),0, IF(L79="", NETWORKDAYS(J79,TODAY(),fESTIVOS!$A$2:$A$53), NETWORKDAYS(J79,L79,fESTIVOS!$A$2:$A$53) ) ) -> 1 | Q79: 15/10/2025: El 14 de octubre se agrega opción para exportar informe. Pendiente definir por el área que campos se mostrarán, ya que actualmente exporta todos los datos | R79: TRUE
A80: MAURICIO | B80: Img_2025_019 | C80: Servicios SAT Independientes - Consultas | D80: Ajuste en vista | E80: Imagine | F80: FINALIZADO | G80: 100 | H80: =IF(OR(J80="",K80="",K80<J80),0,NETWORKDAYS(J80,K80,fESTIVOS!$A$2:$A$53)) -> 1 | I80: 45944 | J80: 45944 | K80: 45944 | L80: 45944 | M80: =IF(OR(J80="",AND(L80="",TODAY()<J80),AND(L80<>"",L80<J80)),0, IF(L80="", NETWORKDAYS(J80,TODAY(),fESTIVOS!$A$2:$A$53), NETWORKDAYS(J80,L80,fESTIVOS!$A$2:$A$53) ) ) -> 1 | Q80: 15/10/2025: El 14 de octubre se realiza ajuste a la vista de búsqueda de los servicios SAT Independientes | R80: TRUE
A81: MAURICIO | B81: PRV_2025_026 | C81: Modulo de Inventarios - Ajuste 2 | D81: Crear tarea programada | E81: Previsional | F81: FINALIZADO | G81: 100 | H81: =IF(OR(J81="",K81="",K81<J81),0,NETWORKDAYS(J81,K81,fESTIVOS!$A$2:$A$53)) -> 1 | I81: 45944 | J81: 45944 | K81: 45944 | L81: 45944 | M81: =IF(OR(J81="",AND(L81="",TODAY()<J81),AND(L81<>"",L81<J81)),0, IF(L81="", NETWORKDAYS(J81,TODAY(),fESTIVOS!$A$2:$A$53), NETWORKDAYS(J81,L81,fESTIVOS!$A$2:$A$53) ) ) -> 1 | Q81: 15/10/2025: El 14 de octubre se crea tarea programada para la sincronización de inventarios cada media hora. | R81: TRUE
A82: MAURICIO | B82: PRV_2025_027 | C82: Modulo Procesos Juridicos | D82: Se requiere crear opción de sincronizaciòn de información | E82: Previsional | F82: FINALIZADO | G82: 100 | H82: =IF(OR(J82="",K82="",K82<J82),0,NETWORKDAYS(J82,K82,fESTIVOS!$A$2:$A$53)) -> 1 | I82: 45945 | J82: 45945 | K82: 45945 | L82: 45945 | M82: =IF(OR(J82="",AND(L82="",TODAY()<J82),AND(L82<>"",L82<J82)),0, IF(L82="", NETWORKDAYS(J82,TODAY(),fESTIVOS!$A$2:$A$53), NETWORKDAYS(J82,L82,fESTIVOS!$A$2:$A$53) ) ) -> 1 | Q82: 17/10/2025: El 15 de octubre Se refactorizó el módulo de procesos jurídicos, implementando un botón para la sincronización de información | R82: TRUE
... A90: MAURICIO | B90: REN_2025_06 | C90: Validación Documental_Ajuste | D90: Validar y parametrizar los documentos en validacion documental en tipificación de documentos | E90: rentas | F90: FINALIZADO | G90: 100 | H90: =IF(OR(J90="",K90="",K90<J90),0,NETWORKDAYS(J90,K90,fESTIVOS!$A$2:$A$53)) -> 3 | I90: 45957 | J90: 45957 | K90: 45959 | L90: 45958 | M90: =IF(OR(J90="",AND(L90="",TODAY()<J90),AND(L90<>"",L90<J90)),0, IF(L90="", NETWORKDAYS(J90,TODAY(),fESTIVOS!$A$2:$A$53), NETWORKDAYS(J90,L90,fESTIVOS!$A$2:$A$53) ) ) -> 2 | Q90: 29/10/2025: Se soluciona la incidencia reportada en la validación documental para la tipificación DDEP | R90: TRUE
A91: MAURICIO | B91: REN_2025_07 | C91: Validación Documental_Ajuste | E91: Rentas | F91: FINALIZADO | G91: 100 | H91: =IF(OR(J91="",K91="",K91<J91),0,NETWORKDAYS(J91,K91,fESTIVOS!$A$2:$A$53)) -> 1 | I91: 45961 | J91: 45961 | K91: 45961 | L91: 45961 | M91: =IF(OR(J91="",AND(L91="",TODAY()<J91),AND(L91<>"",L91<J91)),0, IF(L91="", NETWORKDAYS(J91,TODAY(),fESTIVOS!$A$2:$A$53), NETWORKDAYS(J91,L91,fESTIVOS!$A$2:$A$53) ) ) -> 1 | Q91: 05/11/2025:Se brinda apoyo a rentas vitalicias en cuanto a la validación documental y unos errores que se estaban presentando con una tipología. | R91: TRUE
A92: MAURICIO | B92: SST_2025_012 | C92: Soporte a Seguridad y Salud en el Trabajo - SST | E92: SST | F92: FINALIZADO | G92: 100 | H92: =IF(OR(J92="",K92="",K92<J92),0,NETWORKDAYS(J92,K92,fESTIVOS!$A$2:$A$53)) -> 2 | I92: 45961 | J92: 45965 | K92: 45966 | L92: 45965 | M92: =IF(OR(J92="",AND(L92="",TODAY()<J92),AND(L92<>"",L92<J92)),0, IF(L92="", NETWORKDAYS(J92,TODAY(),fESTIVOS!$A$2:$A$53), NETWORKDAYS(J92,L92,fESTIVOS!$A$2:$A$53) ) ) -> 1 | Q92: 05/11/2025: Se brinda soporte en ALFASST, para la definición de actividades transversales | R92: TRUE
A93: MAURICIO | B93: Img_2025_020 | C93: Soporte a Wilson Aponte | E93: Imagine | F93: FINALIZADO | G93: 100 | H93: =IF(OR(J93="",K93="",K93<J93),0,NETWORKDAYS(J93,K93,fESTIVOS!$A$2:$A$53)) -> 1 | I93: 45965 | J93: 45966 | K93: 45966 | L93: 45966 | M93: =IF(OR(J93="",AND(L93="",TODAY()<J93),AND(L93<>"",L93<J93)),0, IF(L93="", NETWORKDAYS(J93,TODAY(),fESTIVOS!$A$2:$A$53), NETWORKDAYS(J93,L93,fESTIVOS!$A$2:$A$53) ) ) -> 1 | Q93: 05/11/2025: Se brinda soporte en el ambiente de pruebas de Imaginex para el proceso masivo de certificados | R93: TRUE
A94: MAURICIO | B94: Img_2025_021 | C94: Soporte a Wilson Aponte | E94: Imagine | F94: FINALIZADO | G94: 100 | H94: =IF(OR(J94="",K94="",K94<J94),0,NETWORKDAYS(J94,K94,fESTIVOS!$A$2:$A$53)) -> 1 | I94: 45967 | J94: 45967 | K94: 45967 | L94: 45967 | M94: =IF(OR(J94="",AND(L94="",TODAY()<J94),AND(L94<>"",L94<J94)),0, IF(L94="", NETWORKDAYS(J94,TODAY(),fESTIVOS!$A$2:$A$53), NETWORKDAYS(J94,L94,fESTIVOS!$A$2:$A$53) ) ) -> 1 | Q94: 06/11/2025: Se clona maquina local y se genera export por solicitud de Wilson Aponte, para montar el ambiente en su maquina virtual. | R94: TRUE
A95: MAURICIO | B95: Img_2025_022 | C95: Sin conexión | E95: Imagine | F95: FINALIZADO | G95: 100 | H95: =IF(OR(J95="",K95="",K95<J95),0,NETWORKDAYS(J95,K95,fESTIVOS!$A$2:$A$53)) -> 1 | I95: 45967 | J95: 45967 | K95: 45967 | L95: 45967 | M95: =IF(OR(J95="",AND(L95="",TODAY()<J95),AND(L95<>"",L95<J95)),0, IF(L95="", NETWORKDAYS(J95,TODAY(),fESTIVOS!$A$2:$A$53), NETWORKDAYS(J95,L95,fESTIVOS!$A$2:$A$53) ) ) -> 1 | Q95: 06/11/2025: El dìa 06 de noviembre Mauricio no tuvo conexiòn debido al traslado de equipo fisico a otro punto. Por tanto, no pudo avanzar en requerimientos. | R95: TRUE
A96: MAURICIO | B96: SST_2025_013 | C96: Soporte a Seguridad y Salud en el Trabajo - SST | D96: Validar incidencia en creaciòn de cronograma | E96: SST | F96: FINALIZADO | G96: 100 | H96: =IF(OR(J96="",K96="",K96<J96),0,NETWORKDAYS(J96,K96,fESTIVOS!$A$2:$A$53)) -> 1 | I96: 45968 | J96: 45968 | K96: 45968 | L96: 45968 | M96: =IF(OR(J96="",AND(L96="",TODAY()<J96),AND(L96<>"",L96<J96)),0, IF(L96="", NETWORKDAYS(J96,TODAY(),fESTIVOS!$A$2:$A$53), NETWORKDAYS(J96,L96,fESTIVOS!$A$2:$A$53) ) ) -> 1 | Q96: 07/11/2025: Se brinda soporte a SST en el módulo Alfasst ya que presentaba incidencia en la creaciòn de una OD en el cronograma | R96: TRUE
A97: MAURICIO | B97: REN_2025_08 | C97: Validación Documental_Ajuste | E97: Rentas | F97: FINALIZADO | G97: 100 | H97: =IF(OR(J97="",K97="",K97<J97),0,NETWORKDAYS(J97,K97,fESTIVOS!$A$2:$A$53)) -> 1 | I97: 45968 | J97: 45968 | K97: 45968 | L97: 45968 | M97: =IF(OR(J97="",AND(L97="",TODAY()<J97),AND(L97<>"",L97<J97)),0, IF(L97="", NETWORKDAYS(J97,TODAY(),fESTIVOS!$A$2:$A$53), NETWORKDAYS(J97,L97,fESTIVOS!$A$2:$A$53) ) ) -> 1 | Q97: 07/11/2025: Se brinda soporte a Rentas Vitalicias ya que estaba presentando error en el cargue de unas imagenes. | R97: TRUE
A98: MAURICIO | B98: Img_2025_023 | C98: Despliegue a producción | D98: Realizar paso a producciòn de 3 requerimientos de Previsionales | E98: Imagine | F98: FINALIZADO | G98: 100 | H98: =IF(OR(J98="",K98="",K98<J98),0,NETWORKDAYS(J98,K98,fESTIVOS!$A$2:$A$53)) -> 0 | I98: 45970 | J98: 45970 | K98: 45970 | L98: 45970 | M98: =IF(OR(J98="",AND(L98="",TODAY()<J98),AND(L98<>"",L98<J98)),0, IF(L98="", NETWORKDAYS(J98,TODAY(),fESTIVOS!$A$2:$A$53), NETWORKDAYS(J98,L98,fESTIVOS!$A$2:$A$53) ) ) -> 0 | Q98: 09/11/2025: Se realiza despliegue de los modulos Inventario, Devoluciòn y Objeciones y ANS Devoluciones y Objeciones. El proceso arranco a las 11:00 am y finalizó a las 3:00 pm | R98: TRUE
A99: MAURICIO | B99: Img_2025_024 | C99: Soporte a Wilson Aponte - Certificados Masivos | D99: Subir funcionalidad de certificados masivos | E99: Imagine | F99: FINALIZADO | G99: 100 | H99: =IF(OR(J99="",K99="",K99<J99),0,NETWORKDAYS(J99,K99,fESTIVOS!$A$2:$A$53)) -> 1 | I99: 45972 | J99: 45972 | K99: 45972 | L99: 45972 | M99: =IF(OR(J99="",AND(L99="",TODAY()<J99),AND(L99<>"",L99<J99)),0, IF(L99="", NETWORKDAYS(J99,TODAY(),fESTIVOS!$A$2:$A$53), NETWORKDAYS(J99,L99,fESTIVOS!$A$2:$A$53) ) ) -> 1 | Q99: 11/11/2025: Se desplegó en el ambiente de pruebas de Imagine, nueva funcionalidad de generaciòn de certificados masivos. | R99: TRUE
A100: MAURICIO | B100: SST_2025_014 | C100: Soporte a Seguridad y Salud en el Trabajo - SST | D100: Se requiere eliminar imagenes | E100: SST | F100: FINALIZADO | G100: 100 | H100: =IF(OR(J100="",K100="",K100<J100),0,NETWORKDAYS(J100,K100,fESTIVOS!$A$2:$A$53)) -> 3 | I100: 45974 | J100: 45974 | K100: 45979 | L100: 46040 | M100: =IF(OR(J100="",AND(L100="",TODAY()<J100),AND(L100<>"",L100<J100)),0, IF(L100="", NETWORKDAYS(J100,TODAY(),fESTIVOS!$A$2:$A$53), NETWORKDAYS(J100,L100,fESTIVOS!$A$2:$A$53) ) ) -> 42 | Q100: 13/11/2025: El área de SST reportan que necesitan eliminar unos archivos que se adjuntaron a la OS amp-118-2025, que no corresponden a la misma. Se procede a dar gestión y solución. Pendiente novedad que al momento del usuario eliminar no borró y lo lleva a la pestaña de adjunto. 18/01/2026: Gestiòn de Archivos: Se ejecutó el borrado masivo de las imágenes solicitadas en los repositorios correspondientes. | R100: TRUE
A101: MAURICIO | B101: REN_2025_09 | C101: Validación Documental_Ajuste | D101: Se requiere un ajuste para que muestre todos los beneficiarios de las rentas y no solo prioridad | E101: Rentas | F101: FINALIZADO | G101: 100 | H101: =IF(OR(J101="",K101="",K101<J101),0,NETWORKDAYS(J101,K101,fESTIVOS!$A$2:$A$53)) -> 1 | I101: 45974 | J101: 45974 | K101: 45974 | L101: 45974 | M101: =IF(OR(J101="",AND(L101="",TODAY()<J101),AND(L101<>"",L101<J101)),0, IF(L101="", NETWORKDAYS(J101,TODAY(),fESTIVOS!$A$2:$A$53), NETWORKDAYS(J101,L101,fESTIVOS!$A$2:$A$53) ) ) -> 1 | Q101: 13/11/2025: Solicitan habilitar gestión de documentos para que muestre todos los documentos de todos los beneficiarios y no solo prioridad de unas rentas en particular, para unos temas de auditoría. Ya finalizada la auditoría se realizó actualización y reversión del ajuste. | R101: TRUE
A102: MAURICIO | B102: Img_2025_025 | C102: Soporte a Wilson Aponte | D102: Se requiere soporte para despliegue a producciòn y pruebas del modulo certificados masivos | E102: Imagine | F102: FINALIZADO | G102: 100 | H102: =IF(OR(J102="",K102="",K102<J102),0,NETWORKDAYS(J102,K102,fESTIVOS!$A$2:$A$53)) -> 1 | I102: 45979 | J102: 45979 | K102: 45979 | L102: 45979 | M102: =IF(OR(J102="",AND(L102="",TODAY()<J102),AND(L102<>"",L102<J102)),0, IF(L102="", NETWORKDAYS(J102,TODAY(),fESTIVOS!$A$2:$A$53), NETWORKDAYS(J102,L102,fESTIVOS!$A$2:$A$53) ) ) -> 1 | Q102: 18/11/2025: Se brinda soporte a Wilson Aponte para bajar cambios de este modulo nuevo en producciòn y en pruebas. Durante el proceso se presento inconveniente con el repositorio debido a connection time out. | R102: TRUE
A103: MAURICIO | B103: SST_2025_015 | C103: Soporte a Seguridad y Salud en el Trabajo - SST | D103: Validar incidencia reportada por el àrea en cierre de ordenes de servicio | E103: SST | F103: FINALIZADO | G103: 100 | H103: =IF(OR(J103="",K103="",K103<J103),0,NETWORKDAYS(J103,K103,fESTIVOS!$A$2:$A$53)) -> 1 | I103: 45980 | J103: 45980 | K103: 45980 | L103: 45980 | M103: =IF(OR(J103="",AND(L103="",TODAY()<J103),AND(L103<>"",L103<J103)),0, IF(L103="", NETWORKDAYS(J103,TODAY(),fESTIVOS!$A$2:$A$53), NETWORKDAYS(J103,L103,fESTIVOS!$A$2:$A$53) ) ) -> 1 | Q103: 19/11/2025: El àrea reporta lentitud en el proceso de auditoria de prefactura, donde se generaba un error 500. Este error indicaba que el servidor se quedo sin espacio, lo que impedia finalizar o cerrar OS, se procede a dar soluciòn reubicando los soportes y actas a un disco con mas capacidad. | R103: TRUE
A104: MAURICIO | B104: SST_2025_016 | C104: Soporte a Seguridad y Salud en el Trabajo - SST | D104: Validar incidencia reportada por el àrea para el cargue de documentos por parte de los proveedores | E104: SST | F104: FINALIZADO | G104: 100 | H104: =IF(OR(J104="",K104="",K104<J104),0,NETWORKDAYS(J104,K104,fESTIVOS!$A$2:$A$53)) -> 1 | I104: 45981 | J104: 45981 | K104: 45981 | L104: 45981 | M104: =IF(OR(J104="",AND(L104="",TODAY()<J104),AND(L104<>"",L104<J104)),0, IF(L104="", NETWORKDAYS(J104,TODAY(),fESTIVOS!$A$2:$A$53), NETWORKDAYS(J104,L104,fESTIVOS!$A$2:$A$53) ) ) -> 1 | Q104: 20/11/2025: Nos reportan incidencia en el cargue de los soportes por parte de los proveedores, por lo cual se procediò a corregir el tema debido a la contingencia reportada el dia anterior, no se tuvo en cuenta los permisos de carpeta, se corrige y se notifica al cliente. | R104: TRUE
A105: MAURICIO | B105: PRV_2025_034 | C105: Informe Anexo 1 | D105: Se requiere reajustar la vista del requerimiento | E105: Previsional | F105: FINALIZADO | G105: 100 | H105: =IF(OR(J105="",K105="",K105<J105),0,NETWORKDAYS(J105,K105,fESTIVOS!$A$2:$A$53)) -> 77 | I105: 45981 | J105: 45981 | K105: 46093 | L105: 46093 | M105: =IF(OR(J105="",AND(L105="",TODAY()<J105),AND(L105<>"",L105<J105)),0, IF(L105="", NETWORKDAYS(J105,TODAY(),fESTIVOS!$A$2:$A$53), NETWORKDAYS(J105,L105,fESTIVOS!$A$2:$A$53) ) ) -> 77 | Q105: 20/11/2025: Se refactoriza script de anexo 1, acorde a lo enviado por el àrea para ser ajustadocon base a la lògica solicitada. Se realiza el ajuste pertinente , sin embargo se presenta inconsistencia con la informaciòn, en espera de respuesta del àrea para finalizar el tema. 12/03/2026: Se finaliza desarrollo y se entrega para pruebas del cliente. Se proyecta paso a producciòn el sabado 15 de marzo | R105: TRUE
A106: MAURICIO | B106: Img_2025_026 | C106: Soporte modulo Imaginex | D106: Se requiere validaciòn en cambio de contraseña, arroja error | E106: Imagine | F106: FINALIZADO | G106: 100 | H106: =IF(OR(J106="",K106="",K106<J106),0,NETWORKDAYS(J106,K106,fESTIVOS!$A$2:$A$53)) -> 1 | I106: 45982 | J106: 45982 | K106: 45982 | L106: 45982 | M106: =IF(OR(J106="",AND(L106="",TODAY()<J106),AND(L106<>"",L106<J106)),0, IF(L106="", NETWORKDAYS(J106,TODAY(),fESTIVOS!$A$2:$A$53), NETWORKDAYS(J106,L106,fESTIVOS!$A$2:$A$53) ) ) -> 1 | Q106: 21/11/2025: Se brindo apoyo para el cambio de contraseña a la Doc Claudia Vargas, ya que generaba error al redirigirla en la opciòn de cambiar la contraseña | R106: TRUE
A107: MAURICIO | B107: Img_2025_027 | C107: Soporte a Wilson Aponte | D107: Se requiere soporte para despliegue a producciòn y pruebas del modulo certificados masivos | E107: Imagine | F107: FINALIZADO | G107: 100 | H107: =IF(OR(J107="",K107="",K107<J107),0,NETWORKDAYS(J107,K107,fESTIVOS!$A$2:$A$53)) -> 1 | I107: 45981 | J107: 45981 | K107: 45981 | L107: 45981 | M107: =IF(OR(J107="",AND(L107="",TODAY()<J107),AND(L107<>"",L107<J107)),0, IF(L107="", NETWORKDAYS(J107,TODAY(),fESTIVOS!$A$2:$A$53), NETWORKDAYS(J107,L107,fESTIVOS!$A$2:$A$53) ) ) -> 1 | Q107: 20/11/2025: Se monta caso a tecnologia notificando que nos encontramos sin conexiòn con el repositorio. En horas de la tarde en sesiòn con Jenry Henao, nos manifesto que este inconveniente se presento debido a una falla en github, lo que impedia realizar Pull. Una vez restabecido el servicio, se procediò a desplegar los cambios en pruebas y producciòn. | R107: TRUE
A108: MAURICIO | B108: Img_2025_028 | C108: Aviso de Incumplimiento | D108: Se require validar fechas de envio de notificaciones de aviso de incumplimiento | E108: Imagine | F108: FINALIZADO | G108: 100 | H108: =IF(OR(J108="",K108="",K108<J108),0,NETWORKDAYS(J108,K108,fESTIVOS!$A$2:$A$53)) -> 2 | I108: 45986 | J108: 45986 | K108: 45987 | L108: 45986 | M108: =IF(OR(J108="",AND(L108="",TODAY()<J108),AND(L108<>"",L108<J108)),0, IF(L108="", NETWORKDAYS(J108,TODAY(),fESTIVOS!$A$2:$A$53), NETWORKDAYS(J108,L108,fESTIVOS!$A$2:$A$53) ) ) -> 1 | Q108: 25/11/2025: Llega solicitud que el envio masivo de incumplimiento esta llegando con fecha de pago incorrecta por lo cual nos solicitan corregir esto con base a los días hábiles de acuerdo a los rangos de los últimos dos dígitos del nit. Se está analizando el codigo que realiza el proceso o si no aplicar funcionalidad para obtener los días hábiles de acuerdo a las reglas establecidas. | R108: TRUE
A109: MAURICIO | B109: PRV_2025_035 | C109: Modulo Honorarios Jurídicos - Ajuste | D109: Validar incidencias y cambios de control que surgieron en sesiòn de pruebas UAT | E109: Previsional | F109: FINALIZADO | G109: 100 | H109: =IF(OR(J109="",K109="",K109<J109),0,NETWORKDAYS(J109,K109,fESTIVOS!$A$2:$A$53)) -> 2 | I109: 45987 | J109: 45987 | K109: 45988 | L109: 45995 | M109: =IF(OR(J109="",AND(L109="",TODAY()<J109),AND(L109<>"",L109<J109)),0, IF(L109="", NETWORKDAYS(J109,TODAY(),fESTIVOS!$A$2:$A$53), NETWORKDAYS(J109,L109,fESTIVOS!$A$2:$A$53) ) ) -> 7 | Q109: 26/11/2025: En la sesión tenia con el cliente surgieron algunos temas de mejoras, se procedió a realizar los ajustes requeridos y se solucionaron los issus reportados. 28/11/2025: se realiza sesión para revisar los temas propuestos en las sesiones pasadas, se realizan las pruebas satisfactoriamente, a excepción de dos cosas que no realizo cierre del mes de junio y se debe ajustar el campo rubro ya que hay formatos donde llega item-rubro. 04/12/2025: Se tuvo reunión con el cliente para la realización de pruebas por parte de la funcionaria que realiza los pagos, y pidieron ajuste en los formatos de plus, sipren y tesoreria. Se realizo el respectivo a ajuste. | R109: TRUE
...

Sheet PRUEBAS BOLIVAR
A1: Asignado | B1: Requerimiento | C1: Actividad | D1: ESTADO | E1: F.Asignado | F1: Fecha inicio | G1: F. estimada de entrega | H1: Finalizado | I1: Dias | J1: TEST | K1: PRODUCCION | L1: Observacion
A2: JAIRO NIÑO | B2: MDSB-642019 Cargue archivo tarifas y autorizaciones salud | D2: PRUEBAS BOLIVAR | E2: 45526 | F2: 45526 | L2: ok
A3: JAIRO NIÑO | B3: Gestión aplicativo reembolso salud | C3: Implementación de cartas (Devolución, glosa y pago). | D3: FINALIZADO | E3: 45560 | F3: 45560 | H3: 45567 | I3: =IF(ISBLANK(H3), NETWORKDAYS(F3, TODAY(),fESTIVOS!$A$1:$A$18), NETWORKDAYS(F3, H3, fESTIVOS!$A$1:$A$18)) -> 6 | J3: 45567 | L3: *02/10/2024 ya se encuentra implementado
A4: LUIS BAYONA | B4: MDSB-659398 Ajuste campos archivo Autorizaciones EPS | C4: Ajustar la tabla y el cargue del archivo | D4: CONTROL CAMBIOS PRD | E4: 45581 | F4: 45581 | G4: 45582 | H4: 45590 | I4: =IF(ISBLANK(H4), NETWORKDAYS(F4, TODAY(),fESTIVOS!$A$1:$A$18), NETWORKDAYS(F4, H4, fESTIVOS!$A$1:$A$18)) -> 8 | J4: 45590 | L4: *17/10/2024 Validación del desarrollo. *18/10/2024 Continuara despues de terminar la incidendia de "Caso internet" *21/10/2024 ajustar campos y pruebas *22/10/2024 Subir ajustes a test, se debe solicitar control de cambios en test. *24/10/2024 Se deben ajustar inconsitencias en las fechas del informe. *25/10/2024 Se suben ajustes a test *12/11/2024 se debe subir a produccion (Solicitar control de cambios). *13/11/2024 se escala control de cambios a produccion MDSB-705441.
A5: JAIRO NIÑO | B5: MDSB-683637 REQ Ajustes datos migración EPS-Davinci | C5: Ajustar Glosa por procedimiento | D5: EN TEST | E5: 45572 | F5: 45590 | H5: 45594 | I5: =IF(ISBLANK(H5), NETWORKDAYS(F5, TODAY(),fESTIVOS!$A$1:$A$18), NETWORKDAYS(F5, H5, fESTIVOS!$A$1:$A$18)) -> 3 | J5: 45594 | L5: *29/10/2024 Continua con el desarrollo *30/10/2024 Finalizado
A6: DANILO RAMIREZ | B6: GD772-52 Eliminar envio de correo de notificación de tipologia | C6: Para la tipologia "Creación O Cambio De Usuario Administrador Pagina Web - Ap" se debe eliminar el envio al correo servicioalcliente@segurosbolivar.com cuado se radica en el portal solicitudes ARL. | D6: PRUEBA BOLIVAR | E6: 45602 | F6: 45602 | H6: 45602 | I6: =IF(ISBLANK(H6), NETWORKDAYS(F6, TODAY(),fESTIVOS!$A$1:$A$18), NETWORKDAYS(F6, H6, fESTIVOS!$A$1:$A$18)) -> 1 | K6: 45602 | L6: *07/11/2024 Pendiente pruebas por bolivar en produccion.
A7: JAIRO NIÑO | B7: Gestión aplicativo reembolso salud | C7: Cargue archivo de pago y cambio estado a "Terminado o rechado de pago" e implementación de la carta correspondiente | D7: EN TEST | E7: 45589 | F7: 45589 | H7: 45603 | I7: =IF(ISBLANK(H7), NETWORKDAYS(F7, TODAY(),fESTIVOS!$A$1:$A$18), NETWORKDAYS(F7, H7, fESTIVOS!$A$1:$A$18)) -> 10 | J7: 45603 | L7: *28/10/2024 pendiente definir que estados se deben tomar para llevar el Reembolso a rechazo *01/11/2024 Reinicia Validando la logica de la bandeja. *05/11/2024 aclarar dudas para implementar carta de bancolombia y en pruebas de archivo de pagos *06/11/2024 devolucion por causal. *07/11/2024 devolucion por causal lista para test.
A8: JAIRO NIÑO | B8: MDSB-657409 Modulo para adicionar RG para gestion de respuestas a Glosa EPS | D8: EN TEST | E8: 45603 | F8: 45603 | H8: 45610 | I8: =IF(ISBLANK(H8), NETWORKDAYS(F8, TODAY(),fESTIVOS!$A$1:$A$18), NETWORKDAYS(F8, H8, fESTIVOS!$A$1:$A$18)) -> 5 | J8: 45610 | L8: *12/11/2024 Listo para entrega a Jenry *13/11/2024 pendiente validación con jenry para pasar a dev y test. *14/11/2024 pendiente pasar a test *15/11/2024 Se pasa a test para pruebas bolivar
A9: JESUS PEÑA | B9: GD772-71 Radicación de juntas | C9: Estimar tiempo de desarrollo | D9: EN PRUEBAS BOLIVAR | E9: 45671 | F9: 45673 | G9: 10 Dias | H9: 45680 | I9: =IF(ISBLANK(H9), NETWORKDAYS(F9, TODAY(),fESTIVOS!$A$1:$A$18), NETWORKDAYS(F9, H9, fESTIVOS!$A$1:$A$18)) -> 6 | J9: 45680 | L9: 23/01/2025 Inicio de pruebas para pasar a test 31/01/2025 entregado a prubas Bolivar
A10: JESUS PEÑA | C10: HU 1 Crear en el portal de solicitudes ARL la opción de radicación de JCI - EPS- AFP | D10: EN PRUEBAS BOLIVAR | E10: 45671 | F10: 45673 | H10: 45674 | I10: =IF(ISBLANK(H10), NETWORKDAYS(F10, TODAY(),fESTIVOS!$A$1:$A$18), NETWORKDAYS(F10, H10, fESTIVOS!$A$1:$A$18)) -> 2 | L10: 20/01/2025 pendiente ajustes en yii 31/01/2025 entregado a prubas Bolivar
A11: JESUS PEÑA | C11: HU 2 Creación de formulario para radicación en el portal | D11: EN PRUEBAS BOLIVAR | E11: 45671 | F11: 45673 | H11: 45674 | I11: =IF(ISBLANK(H11), NETWORKDAYS(F11, TODAY(),fESTIVOS!$A$1:$A$18), NETWORKDAYS(F11, H11, fESTIVOS!$A$1:$A$18)) -> 2 | L11: 20/01/2025 pendiente ajustes en yii 31/01/2025 entregado a prubas Bolivar
A12: JESUS PEÑA | C12: HU 3 Parte 2 formulario de radicación Descripción | D12: EN PRUEBAS BOLIVAR | E12: 45671 | F12: 45673 | H12: 45674 | I12: =IF(ISBLANK(H12), NETWORKDAYS(F12, TODAY(),fESTIVOS!$A$1:$A$18), NETWORKDAYS(F12, H12, fESTIVOS!$A$1:$A$18)) -> 2 | L12: 20/01/2025 pendiente ajustes en yii 31/01/2025 entregado a prubas Bolivar
A13: JESUS PEÑA | C13: H4 Opción consulta casos en portal ARL | D13: EN PRUEBAS BOLIVAR | E13: 45671 | F13: 45673 | H13: 45677 | I13: =IF(ISBLANK(H13), NETWORKDAYS(F13, TODAY(),fESTIVOS!$A$1:$A$18), NETWORKDAYS(F13, H13, fESTIVOS!$A$1:$A$18)) -> 3 | L13: 20/01/2025 pendiente ajustes en yii 31/01/2025 entregado a prubas Bolivar
A14: JESUS PEÑA | C14: H5 Radicación individual | D14: EN PRUEBAS BOLIVAR | E14: 45671 | F14: 45678 | H14: 45678 | I14: =IF(ISBLANK(H14), NETWORKDAYS(F14, TODAY(),fESTIVOS!$A$1:$A$18), NETWORKDAYS(F14, H14, fESTIVOS!$A$1:$A$18)) -> 1 | L14: 31/01/2025 entregado a prubas Bolivar
A15: JESUS PEÑA | C15: H6 Adjunto | D15: EN PRUEBAS BOLIVAR | E15: 45671 | F15: 45679 | H15: 45679 | I15: =IF(ISBLANK(H15), NETWORKDAYS(F15, TODAY(),fESTIVOS!$A$1:$A$18), NETWORKDAYS(F15, H15, fESTIVOS!$A$1:$A$18)) -> 1 | L15: 31/01/2025 entregado a prubas Bolivar
A16: JESUS PEÑA | C16: VALIDAR HALLAZGO DE LAS PRUEBAS | D16: EN PRUEBAS BOLIVAR | E16: 45681 | F16: 45684 | H16: 45685 | I16: =IF(ISBLANK(H16), NETWORKDAYS(F16, TODAY(),fESTIVOS!$A$1:$A$18), NETWORKDAYS(F16, H16, fESTIVOS!$A$1:$A$18)) -> 2 | L16: 27/01/2025 pendiente ajustar caso internet en nativo 28/01/2025 ajustes en test para pruebas 28/01/2025 Pendiente ajuste en el campo identificacion en el 2do paso. 31/01/2025 entregado a prubas Bolivar

Sheet FINALIZADOS 2
A1: Asignado a | B1: Jira Caja | C1: Requerimiento | D1: ESTADO | E1: % | F1: dias estimados | G1: F.Asignado | H1: Fecha inicio | I1: F. estimada de entrega | J1: Finalizado | K1: Dias | L1: Jira TEST | M1: TEST | N1: jira PROD | O1: PRODUCCION | P1: OBSERVACIONES | Q1: Seguimiento 28 Abril | R1: Seguimiento 28 Abril 2 | S1: Seguimiento 5 mayo | T1: seguimiento 7 mayo | U1: seguimiento 9 mayo | V1: seguimiento 9 mayo 2 | W1: seguimiento 12 mayo | X1: seguimiento 14 mayo | Y1: seguimiento 15 mayo | Z1: seguimiento 16 mayo | AA1: seguimiento 19 mayo | AB1: seguimiento 21 mayo | AC1: seguimiento 23 mayo | AD1: seguimiento 26 mayo | AE1: seguimiento 28 mayo | AF1: seguimiento 30 mayo | AG1: seguimiento 4 Junio | AH1: seguimiento 6 Junio | AI1: seguimiento 9 Junio | AJ1: seguimiento 11 Junio | AK1: seguimiento 13 Junio | AL1: seguimiento 16 Junio | AM1: Column 4 | AN1: Column 5
A2: DANILO RAMIREZ | B2: GD772-94 | C2: tablero de analisis de la operación de reembolsos | D2: FINALIZADO | G2: 45751 | H2: 45756 | I2: 45760 | J2: 45759 | K2: =IF(ISBLANK(J2), NETWORKDAYS(H2, TODAY(),fESTIVOS!$A$1:$A$18), NETWORKDAYS(H2, J2, fESTIVOS!$A$1:$A$18)) -> 3 | P2: 07/04/2025:Iniciara tan pronto finalice las vulnerabilidades pendientes. 09/04/2025: Ayer Danilo no avanzó por vulnerabilidades; hoy inicia la implementación, coordinará con Jairo (extrae datos del informe); estiman 3-4 días (hasta el jueves o viernes) 10/04/2025: No avanzó ayer por otras prioridades; hoy dedicará tiempo y coordinará con Jairo para el contexto; estiman 3-4 días. 11/04/2025: Ayer ajustó el API del informe de digitación (puerto 888 en producción); hoy termina ajustes finales y avanza en la implementación en Yii, coordinado con Jairo para evitar duplicidad; Se solicita control de cambios MDSB-795762 en test, quedo ejecutado con exito y se escala control de cambios a produccion MDSB-796132. 14/04/2025: Se encentra terminando los ajustes necesarios para pasar el req a test para pruebas. 22/04/2025: Se realiza paso a producción.
A3: DANILO RAMIREZ | C3: vulnerabilidades claudia | D3: FINALIZADO | E3: 90 | G3: 45749 | H3: 45754 | I3: 45772 | J3: 45783 | K3: =IF(ISBLANK(J3), NETWORKDAYS(H3, TODAY(),fESTIVOS!$A$1:$A$18), NETWORKDAYS(H3, J3, fESTIVOS!$A$1:$A$18)) -> 22 | M3: 45755 | P3: 07/04/2025: Pendiente de revisar; implica cambiar librerías como JavaScript o Bootstrap, lo que evaluará hoy para determinar viabilidad,Iniciara tan pronto finalice implementación de la Vulnerabilidad- Web Application Information Disclosure. 08/04/2025: Inicio 09/04/2025:Ayer finalizó y resolvió esta vulnerabilidad; todas las vulnerabilidades están cerradas por ahora. | Q3: Se trabajaran alternando espacios con que permita la IA | R3: Pendiente cipres | S3: Paso a produccion 5 mayo | T3: finalizado 6 mayo
A4: DANILO RAMIREZ | C4: Vulnerabilidades Retest | D4: FINALIZADO | E4: 60 | G4: 45749 | H4: 45749 | I4: 45779 | J4: 45783 | K4: =IF(ISBLANK(J4), NETWORKDAYS(H4, TODAY(),fESTIVOS!$A$1:$A$18), NETWORKDAYS(H4, J4, fESTIVOS!$A$1:$A$18)) -> 25 | M4: 45754 | P4: 02/04/2025: Inicia con la implementación 03/04/2025: Ayer comenzó esta vulnerabilidad, avanzó poco por otras tareas; hoy continuará trabajando en ella. 04/04/2025: Unque avanzó bastante, la tarea aún no está finalizada. Hoy se continuará con ese objetivo. 07/04/2025 Finalizada en test 07/04/2025: haciendo un cambio en Application error messages y subira a test 08/04/2025: Finalizo implementación en test | Q4: Se trabajaran alternando espacios con que permita la IA | R4: pendiente 2 vulnerabilidades se entrega hoy | S4: Paso a produccion 5 mayo | T4: finaliado 6 mayo
A5: DANILO RAMIREZ | C5: Vulnerabilidades Edgar | D5: FINALIZADO | E5: 100 | G5: 45770 | H5: 45770 | I5: 45770 | J5: 45770 | K5: =IF(ISBLANK(J5), NETWORKDAYS(H5, TODAY(),fESTIVOS!$A$1:$A$18), NETWORKDAYS(H5, J5, fESTIVOS!$A$1:$A$18)) -> 1 | P5: 25/03/2025: El viernes trabajó en esta vulnerabilidad, resolviendo varios detalles; estima terminarla hoy al mediodía y luego pasará a Lectura de Autorizaciones Médicas con IA. 26/03/2025: Ayer terminó esta vulnerabilidad y la subió a test; ya está resuelta, se realizaran pruebas y se subira a produccion. 28/03/2025: Subida a test el anteayer con pruebas listas; pendiente pasar a producción. 31/03/2025: Se soliitara crear una ventana para subirlo, se realizara una solicitud a Leydi Mayorga. 01/04/2025: falta pasar a producción; requiere reiniciar Apache (5 minutos), planeado para la noche para minimizar impacto. 03/04/2025: Listo en test, solo falta reiniciar Apache (segundos); lo hará hoy, preferiblemente en la noche para evitar interrupciones. 04/04/2025: Se aplicaron cambios relacionados con vulnerabilidades en Apache, pero no se reflejaron en producción, Hoy se hará validación para identificar el problema. 07/04/2025:No avanzó el viernes por priorizar Web Application Information Disclosure; hoy sacará tiempo para realizar la validación. 09/04/2025: Un se encuentra pendiente validar el porque los cambios nose replicaron en produccion. 10/04/2025: Ayer tarde intentó cambios en los cifrados; funciona en test pero no en producción tras mucho tiempo invertido; lo dejará pendiente para buscar una solucion.
A6: DANILO RAMIREZ | B6: MDSB-707440 | C6: Portal reembolsos ARL | D6: FINALIZADO | E6: 50 | K6: =IF(ISBLANK(J6), NETWORKDAYS(H6, TODAY(),fESTIVOS!$A$1:$A$18), NETWORKDAYS(H6, J6, fESTIVOS!$A$1:$A$18)) -> 32982 | Q6: Pausado por otras prioridades del negocio | R6: Todo este requerimiento es de Jairto
A7: DANILO RAMIREZ | B7: MDSB-707440 | C7: Implementación de observacion en la consulta de "Reconsideración Negativa de Servicios" | D7: FINALIZADO | G7: 45666 | H7: 45684 | J7: 45685 | K7: =IF(ISBLANK(J7), NETWORKDAYS(H7, TODAY(),fESTIVOS!$A$1:$A$18), NETWORKDAYS(H7, J7, fESTIVOS!$A$1:$A$18)) -> 2 | M7: 45685 | P7: 28/01/2025 continua con la implementación del cargue y eliminación de los archivos | Q7: Relacionado con 440 jira | R7: Todo este requerimiento es de Jairto
A8: JAIRO NIÑO | C8: Cambio de nombres en pensiones | D8: FINALIZADO | G8: 45756 | H8: 45756 | J8: 45756 | K8: =IF(ISBLANK(J8), NETWORKDAYS(H8, TODAY(),fESTIVOS!$A$1:$A$18), NETWORKDAYS(H8, J8, fESTIVOS!$A$1:$A$18)) -> 1 | P8: 09/04/2025: Liyibet pidió por correo ajustar nombres en pensiones; proponen una opción manual con rol (como Jesús hizo antes), evitando cambios manuales frecuentes; Jairo lo revisará. 10/04/2025: Hoy ajustara por base de datos el registro solicitado por Liyibet y quedara pendiente la implementación de la opcion automatica para la autogestion. 11/04/2025: no lo ha hecho por no encontrar el correo; lo reenvían hoy para avanzar con un update. 14/04/2025: Hoy realizo modificacion solicitada, quedara pendiente la implementación de la opcion automatica para la autogestion.
A9: JAIRO NIÑO | C9: Confirguración de Tipología internacional (dudas). | D9: FINALIZADO | G9: 45750 | H9: 45750 | J9: 45755 | K9: =IF(ISBLANK(J9), NETWORKDAYS(H9, TODAY(),fESTIVOS!$A$1:$A$18), NETWORKDAYS(H9, J9, fESTIVOS!$A$1:$A$18)) -> 4 | M9: 45755 | O9: 45761 | P9: 04/04/2025: Hoy continuara con la confirguración de la tipologia. 07/04/2025: No trabajó en esto el viernes por otros temas; hoy configurará consultas y evaluará si se puede copiar o ajustar 09/04/2025: Ayer finalizó y pasó a test; listo para que Santiago inicie pruebas; incluye ajustes de fase 1 y 2 de reembolsos (dudas, retoma, informe). 10/04/2025: Santiago aprueba paso a produccion, se estima pasarlo junto con el req GD772-61. 11/04/2025: Pendiente realizar paso a produccion. 14/04/2025:Realizo paso a produccion hoy en la mañana.
A10: JAIRO NIÑO | C10: Gestión de glosas y anticipos (Se identificaron errores por glosas parciales enviadas sin completar el flujo de anticipos) | D10: FINALIZADO | G10: 45750 | H10: 45751 | K10: =IF(ISBLANK(J10), NETWORKDAYS(H10, TODAY(),fESTIVOS!$A$1:$A$18), NETWORKDAYS(H10, J10, fESTIVOS!$A$1:$A$18)) -> 319 | N10: MDSB-797891 | P10: 04/04/2025: Se propuso agregar un botón de confirmación para validar el monto con el usuario antes de enviar la diferencia al centralizador contable, Iniciara al finalizar la Confirguración de Tipología internacional (dudas). 07/04/2025:Bolivat debera radicar un jira con los cambios requeridos.
Q11: Hoy se pasa a produccion el comando | R11: pendiente pasar a produccion | S11: Finalizado viernes 2 Mayo
A12: JESUS PEÑA | B12: MDSB-791997 | C12: Listado solicitudes 1de enero de 2024 al 31 de marzo de 2024 | D12: FINALIZADO | G12: 45751 | H12: 45755 | J12: 45758 | K12: =IF(ISBLANK(J12), NETWORKDAYS(H12, TODAY(),fESTIVOS!$A$1:$A$18), NETWORKDAYS(H12, J12, fESTIVOS!$A$1:$A$18)) -> 4 | P12: 04/04/2025: Bolivar requiere listado del total de solicitudes tramitadas por imagine mensualmente de 1de enero de 2024 al 31 de marzo de 2024, Continuara despues de finalizar GD772-84 Comunicaciones gestión de aportes sin afiliacion 09/04/2025: Ayer creó un query para contar casos por origen (masivos, portales, etc.) para ARL (nativo, medicamentos, incapacidades, fallos); Jairo ejecutó uno y dará tabla de fallos; sigue pendiente para incapacidades y medicamentos. 10/04/2025: Ayer avanzó en query para casos por origen; falta la tabla de fallos (Jairo la proporcionará hoy); 14/04/2025: Se envia informe solicitado por Bolivar.
A13: JESUS PEÑA | C13: Consulta de estado del CUPS en la malla | D13: FINALIZADO | G13: 45757 | K13: =IF(ISBLANK(J13), NETWORKDAYS(H13, TODAY(),fESTIVOS!$A$1:$A$18), NETWORKDAYS(H13, J13, fESTIVOS!$A$1:$A$18)) -> 32982 | P13: 10/04/2025: Se sugiere implementar consulta directa del estado del CUPS (activo/inactivo) en la vista de carga, incluyendo usuario y fecha de inactivación. Se puede reutilizar la función existente.
A14: JESUS PEÑA | B14: GD772-84 | C14: Comunicaciones gestión de aportes sin afiliacion (masivos) | D14: FINALIZADO | G14: 45748 | H14: 45749 | J14: 45755 | K14: =IF(ISBLANK(J14), NETWORKDAYS(H14, TODAY(),fESTIVOS!$A$1:$A$18), NETWORKDAYS(H14, J14, fESTIVOS!$A$1:$A$18)) -> 5 | M14: 45755 | P14: 02/04/2025: Iniciara tan pronto finalice GD772-92 - Malla CUPS en Nativo 03/04/2025: Iniciara hoy con el desarrollo. 04/04/2025: avanzó en la implementación para leer una segunda hoja de los archivos Excel de masivos, hoy se continuará con el armado de la respuesta y se realizarán pruebas en la tarde. 07/04/2025: El viernes probó con Fabio dos PDFs nuevos para masivos; funcionó bien, pero las plantillas están quemadas; hoy ajustarán un editor dinámico para plantillas y corregirán detalles menores, evaluando paso a producción. 09/04/2025: Ayer corrigió fechas en PDFs para dos tipologías; listo en test para pruebas del cliente, pendiente paso a producción. 10/04/2025: Se realizara entrega al cliente hoy. 11/04/2025: En pruebas con el cliente se presentó un hallazgo: el sistema tomó el mismo comunicado para las dos tipologías, cuando cada una debe tener un comunicado diferente. Se validará, ya que este error no ocurrió en pruebas previas. 14/04/2025 Realizara validción y ajuste del hallazgo de las pruebas realizadas el 10 de Abril con el cliente. 14/04/2025:Se realizan ajustes, se remite al cliente para pruebas y aprueba paso a produccion.
A15: JAIRO NIÑO | B15: GD772-95 | C15: MONTOS MINIMO GLOSA | D15: FINALIZADO | G15: 45754 | H15: 45757 | J15: 45761 | K15: =IF(ISBLANK(J15), NETWORKDAYS(H15, TODAY(),fESTIVOS!$A$1:$A$18), NETWORKDAYS(H15, J15, fESTIVOS!$A$1:$A$18)) -> 3 | O15: 45761 | P15: 10/04/2025: Se plantea restricción para glosas parciales menores a $6.000. Se mostrará mensaje al usuario y se bloqueará si no cumple con el mínimo. 11/04/2025: Implementado en local (mensaje para glosas parciales < 6.000 pesos); hoy lo pasará a producción tras pruebas en test. 14/04/2025: Requerimiento en test 14/04/2025: Se realiza pasoa produccion.
A16: JAIRO NIÑO | B16: GD772-96 | C16: VALOR RIPS | D16: FINALIZADO | G16: 45754 | H16: 45757 | J16: 45761 | K16: =IF(ISBLANK(J16), NETWORKDAYS(H16, TODAY(),fESTIVOS!$A$1:$A$18), NETWORKDAYS(H16, J16, fESTIVOS!$A$1:$A$18)) -> 3 | O16: 45761 | P16: 10/04/2025: Hoy implementará que los campos de valor en JSON (ValorServices) sean mayores a cero en el portal, evitando RIPS en cero; tarea rápida de la mañana. 11/04/2025: Implementado en local (valor > 0 en ValorServices); hoy lo pasará a producción tras pruebas en test. 14/04/2025: Requerimiento en test 14/04/2025: Se realiza paso a produccion
A17: JAIRO NIÑO | B17: GD772-97 | C17: BOTON ENVIO PAGO DE FACTURAS RESPUESTA A GLOSA PARA EPS | D17: FINALIZADO | G17: 45754 | H17: 45761 | J17: 45761 | K17: =IF(ISBLANK(J17), NETWORKDAYS(H17, TODAY(),fESTIVOS!$A$1:$A$18), NETWORKDAYS(H17, J17, fESTIVOS!$A$1:$A$18)) -> 1 | O17: 45761 | P17: 11/04/2025: No lo entiende; pendiente de aclaración con el usuario para avanzar 14/04/2025:Se realiza paso a produccion.
A18: JAIRO NIÑO | B18: GD772-98 | C18: FACTURA PAGO ANTICIPO EPS | D18: FINALIZADO | G18: 45754 | H18: 45757 | J18: 45761 | K18: =IF(ISBLANK(J18), NETWORKDAYS(H18, TODAY(),fESTIVOS!$A$1:$A$18), NETWORKDAYS(H18, J18, fESTIVOS!$A$1:$A$18)) -> 3 | O18: 45761 | P18: 11/04/2025: Implementado en local; hoy lo pasará a producción tras pruebas en test. 14/04/2025: Requerimiento en test 14/04/2025: Se realiza paso a producción
A19: JAIRO NIÑO | B19: MDSB-796714 | C19: . JIRA SERVIENTREGA | D19: FINALIZADO | G19: 45793 | H19: 45793 | I19: 45793 | J19: 45793 | K19: 1
A20: jESUS PEÑA | B20: MDSB-729146 | C20: Jiras dia a dia | D20: FINALIZADO | G20: 45763 | H20: 45763 | I20: 45763 | J20: 45763 | K20: 1 | M20: 45763 | O20: 45763
A21: jESUS PEÑA | B21: MDSB-764755 | C21: Jiras dia a dia | D21: FINALIZADO | G21: 45763 | H21: 45763 | I21: 45763 | J21: 45763 | K21: 1 | M21: 45763 | O21: 45763
A22: jESUS PEÑA | B22: MDSB-765184 | C22: Jiras dia a dia | D22: FINALIZADO | G22: 45763 | H22: 45763 | I22: 45763 | J22: 45763 | K22: 1 | M22: 45763 | O22: 45763
A23: jESUS PEÑA | B23: MDSB-780326 | C23: Jiras dia a dia | D23: FINALIZADO | G23: 45763 | H23: 45763 | I23: 45763 | J23: 45763 | K23: 1 | M23: 45763 | O23: 45763
A24: jESUS PEÑA | B24: MDSB-781420 | C24: Jiras dia a dia | D24: FINALIZADO | G24: 45763 | H24: 45763 | I24: 45763 | J24: 45763 | K24: 1 | M24: 45763 | O24: 45763
A25: jESUS PEÑA | B25: MDSB-788689 | C25: Jiras dia a dia | D25: FINALIZADO | G25: 45763 | H25: 45763 | I25: 45763 | J25: 45763 | K25: 1 | M25: 45763 | O25: 45763
A26: jESUS PEÑA | B26: MDSB-793360 | C26: Jiras dia a dia | D26: FINALIZADO | G26: 45763 | H26: 45763 | I26: 45763 | J26: 45763 | K26: 1 | M26: 45763 | O26: 45763
A27: jESUS PEÑA | B27: MDSB-792179 | C27: Jiras dia a dia | D27: FINALIZADO | G27: 45763 | H27: 45763 | I27: 45763 | J27: 45763 | K27: 1 | M27: 45763 | O27: 45763
A28: jESUS PEÑA | B28: MDSB-796714 | C28: Jiras dia a dia | D28: FINALIZADO | G28: 45763 | H28: 45763 | I28: 45763 | J28: 45763 | K28: 1 | M28: 45763 | O28: 45763
A29: jESUS PEÑA | B29: Interno | C29: Publicación informe analitica en nativo | D29: FINALIZADO | G29: 45770 | H29: 45771 | I29: 45772 | Q29: Se realizo ajuste en prod el vienres
A30: jESUS PEÑA | B30: MDSB-803317 | C30: Error de recobros (Consulta Masiva de Soportes) | D30: FINALIZADO | F30: 1 | G30: 45775 | H30: 45775 | I30: 45775 | J30: 45775 | Q30: Se subió a produccion en la mañana el ajuste
A31: jESUS PEÑA | B31: Interno | C31: Control para casos anulados en trazabilidad | D31: FINALIZADO | E31: 100 | G31: 45770 | H31: 45770 | I31: 45770 | J31: 45770 | K31: 1
A32: jESUS PEÑA | B32: Interno | C32: Control para casos sin usuario radicacion | D32: FINALIZADO | E32: 100 | G32: 45770 | H32: 45770 | I32: 45770 | J32: 45770 | K32: 1
A33: WILSON APONTE | B33: Interno | C33: Analitica de factura de cuentas medicas | D33: FINALIZADO | E33: 90 | F33: 2 | G33: 45773 | H33: 45776 | I33: 45783 | J33: 45785 | V33: Se entregó el 8 de mayo
A34: JAIRO NIÑO | B34: Interno | C34: Informe de RIPS (soporte) | D34: FINALIZADO | G34: 45779 | H34: 45779 | I34: 45782 | J34: 45782 | S34: Se iniicia soporte | T34: finalizado el 5 mayo
A35: FABIO FORERO | C35: Manual MDSB-707440 - Portal Reembolsos ARL | D35: FINALIZADO | G35: 45714 | H35: 45784 | J35: 45785 | P35: 05/03/2025: Se iniciara al finalizar Prueba en test GD772-82 Tipología sin flujo de radicación sisalud.
A36: DANILO RAMIREZ | B36: Interno | C36: Reemplazo negocio Proteccion | D36: FINALIZADO | E36: 80 | F36: 15 | G36: 45778 | H36: 45778 | J36: 45793 | K36: =IF(ISBLANK(J36), NETWORKDAYS(H36, TODAY(),fESTIVOS!$A$1:$A$18), NETWORKDAYS(H36, J36, fESTIVOS!$A$1:$A$18)) -> 12 | V36: Medio dia dedicado a proteccion, lo demas bolivar responsive | W36: Se tiene previsto avanzar lo máximo posible en Protección y luego retomar el nuevo requerimiento relacionado con autorizaciones médica | X36: Termino documentación y seguimiento, Aunque se ha avanzado en el tema de protección, no se da por cerrado, ya que surgen casos constantemente. Ayer no se reportaron incidentes nuevos, pero en los días anteriores sí hubo, por lo cual se mantendrá como una tarea en proceso hasta que Alejandro retome la responsabilidad. | Z36: Se trabajara en casos de protección que surjan | AC36: La gestión fue retomada por Alejandro desde el martes. No se han realizado más acciones sobre este tema desde el viernes 16 de mayo anterior, por lo que se da por cerrado el soporte temporal.
A37: DANILO RAMIREZ | B37: Interno | C37: Ajuste validación un cero al inicio en la lectura de IA CUPS | D37: FINALIZADO | F37: 1 | G37: 45785 | H37: 45785 | I37: 45786 | J37: 45786 | K37: =IF(ISBLANK(J37), NETWORKDAYS(H37, TODAY(),fESTIVOS!$A$1:$A$18), NETWORKDAYS(H37, J37, fESTIVOS!$A$1:$A$18)) -> 2 | O37: 45786 | V37: Se entrega el dia de hoy | W37: Se confirma que el ajuste implementado el viernes 9 de mayo fue desplegado exitosamente en producción hacia las 6:00 p.m.
A38: DANILO RAMIREZ | B38: Interno | C38: Corrección de vulnerabilidad en la consulta de solicitudes ARL | D38: FINALIZADO | G38: 45791 | H38: 45791 | J38: 45791 | K38: =IF(ISBLANK(J38), NETWORKDAYS(H38, TODAY(),fESTIVOS!$A$1:$A$18), NETWORKDAYS(H38, J38, fESTIVOS!$A$1:$A$18)) -> 1 | X38: Se abordó una vulnerabilidad reportada a Lidy relacionada con la consulta de solicitudes ARL. Aunque los cambios necesarios ya habían sido desarrollados y aprobados por Fabio, no se habían subido a producción por razones desconocidas. Al encontrarse con una rama de código desactualizada, se optó por crear una nueva rama y migrar los cambios para solventar el problema. | Z38: El 14 de mayo,Se abordó una vulnerabilidad reportada a Lidy relacionada con la consulta de solicitudes ARL. Aunque los cambios necesarios ya habían sido desarrollados y aprobados por Fabio, no se habían subido a producción por razones desconocidas. Al encontrarse con una rama de código desactualizada, se optó por crear una nueva rama y migrar los cambios para solventar el problema.
A39: JESUS PEÑA | B39: GD772-102 | C39: Ajuste informe Autorizaciones salud (2) | D39: FINALIZADO | F39: 1 | G39: 45779 | H39: 45779 | I39: 45779 | J39: 45779 | K39: =IF(ISBLANK(J39), NETWORKDAYS(H39, TODAY(),fESTIVOS!$A$1:$A$18), NETWORKDAYS(H39, J39, fESTIVOS!$A$1:$A$18)) -> 1 | M39: 45782 | O39: 45789 | S39: Se entregó a test, el vienres 2 de mayo | W39: Bolivar da visto bueno para pasar a produccion. | X39: El 12 de mayo se realizo paso a produccion
A40: jESUS PEÑA | B40: MDSB-809245 | C40: Jira dia a dia ( Generar informe tipologias 10007, 10008, 10581 de pensiones | D40: FINALIZADO | G40: 45789 | H40: 45789 | J40: 45790 | K40: =IF(ISBLANK(J40), NETWORKDAYS(H40, TODAY(),fESTIVOS!$A$1:$A$18), NETWORKDAYS(H40, J40, fESTIVOS!$A$1:$A$18)) -> 2 | W40: Iniciara con la generación del informe por DB | X40: Informe generado 13 de mayo y enviado 14 de mayo
A41: jeSUS PEÑA | B41: MDSB-792259 | C41: Jira dia a dia ( Generar informe de casos radicados inicialmente bajo la tipología “Otro tipo de solicitud” | D41: FINALIZADO | G41: 45789 | H41: 45789 | J41: 45790 | K41: =IF(ISBLANK(J41), NETWORKDAYS(H41, TODAY(),fESTIVOS!$A$1:$A$18), NETWORKDAYS(H41, J41, fESTIVOS!$A$1:$A$18)) -> 2 | W41: Iniciara con la generación del informe por DB | X41: Informe generado y enviado 13 de mayo
A42: jESUS PEÑA | B42: GD772-81 | C42: Calificador automático (Ajuste de carta de respuesta) | D42: FINALIZADO | E42: 90 | G42: 45791 | H42: 45792 | I42: 45793 | J42: 45793 | K42: =IF(ISBLANK(J42), NETWORKDAYS(H42, TODAY(),fESTIVOS!$A$1:$A$18), NETWORKDAYS(H42, J42, fESTIVOS!$A$1:$A$18)) -> 2 | M42: 45793 | Z42: subira a test para pruebas | AA42: El viernes 16 de mayo Se subieron a test varios ajustes, incluyendo el PDF de salida para nueve tipologías distintas, no solo una. También se configuró el administrador de cartas, permitiendo edición según cada tipología
A43: jESUS PEÑA | B43: MDSB-786579 | C43: No permite enlazar tipologías (Nativo | D43: FINALIZADO | E43: 0 | G43: 45796 | H43: 45796 | J43: 45796 | K43: =IF(ISBLANK(J43), NETWORKDAYS(H43, TODAY(),fESTIVOS!$A$1:$A$18), NETWORKDAYS(H43, J43, fESTIVOS!$A$1:$A$18)) -> 1 | AA43: Inicia validación
A44: jESUS PEÑA | B44: MDSB-812125 | C44: Error en generación de cartas no furat (Nativo) | D44: FINALIZADO | E44: 80 | G44: 45796 | H44: 45796 | J44: 45796 | K44: =IF(ISBLANK(J44), NETWORKDAYS(H44, TODAY(),fESTIVOS!$A$1:$A$18), NETWORKDAYS(H44, J44, fESTIVOS!$A$1:$A$18)) -> 1 | AA44: Se realiza validación con la usuaria y se identifica una carta adicional creada en el administrador que no permitia que el proceso tomara la carta correcta, se inactiva la carta y se espera que el usuario realice pruebas y nos confirme que ha quedado correcto. | AB44: El 20 de Mayo lLeidy mayorga confirma que la carta se esta generando bien.
A45: jESUS PEÑA | B45: interno | C45: Validar funcionamiento listas blancas en test | D45: FINALIZADO | G45: 45797 | H45: 45798 | J45: 45799 | K45: =IF(ISBLANK(J45), NETWORKDAYS(H45, TODAY(),fESTIVOS!$A$1:$A$18), NETWORKDAYS(H45, J45, fESTIVOS!$A$1:$A$18)) -> 2 | M45: 45799 | AB45: Iniciara con la Validación hoy | AC45: Se solucionó un error que impedía el correcto funcionamiento de listas blancas en ambiente de pruebas
A46: jESUS PEÑA | B46: interno | C46: Adicionar sleep(1) en la DB en Nativo | D46: FINALIZADO | G46: 45797 | H46: 45797 | J46: 45799 | K46: =IF(ISBLANK(J46), NETWORKDAYS(H46, TODAY(),fESTIVOS!$A$1:$A$18), NETWORKDAYS(H46, J46, fESTIVOS!$A$1:$A$18)) -> 3 | AB46: Ya lo tiene creado en local para subir a produccion | AC46: El 22 de mayo se subio s produccion La instrucción sleep(1) se implementó para mitigar problemas de duplicación de actividades. Sin embargo, se detectó que otras funciones también abren/cierra casos
A47: jESUS PEÑA | B47: MDSB-818098 | C47: Jira solicitud de información(Informe seguimiento x actividades) | D47: FINALIZADO | G47: 45799 | H47: 45799 | J47: 45799 | K47: =IF(ISBLANK(J47), NETWORKDAYS(H47, TODAY(),fESTIVOS!$A$1:$A$18), NETWORKDAYS(H47, J47, fESTIVOS!$A$1:$A$18)) -> 1 | AC47: Se genero informe a partir de una solicitud JIRA. El informe ya está elaborado, pero requiere apoyo para su generación final.
A48: jESUS PEÑA | B48: MDSB-814988 | C48: jiras dia a dia (Ajustar roll usuario 1024539753) | D48: FINALIZADO | G48: 45798 | H48: 45799 | J48: 45799 | K48: =IF(ISBLANK(J48), NETWORKDAYS(H48, TODAY(),fESTIVOS!$A$1:$A$18), NETWORKDAYS(H48, J48, fESTIVOS!$A$1:$A$18)) -> 1
A49: jESUS PEÑA | B49: MDSB-818156 | C49: jiras dia a dia (Ajustar roll usuario 1082157117) | D49: FINALIZADO | G49: 45799 | H49: 45799 | J49: 45799 | K49: =IF(ISBLANK(J49), NETWORKDAYS(H49, TODAY(),fESTIVOS!$A$1:$A$18), NETWORKDAYS(H49, J49, fESTIVOS!$A$1:$A$18)) -> 1
A50: jESUS PEÑA | B50: Interno | C50: Cerrar trazabilidad de Tipologias cierre automatico | D50: FINALIZADO | G50: 45796 | H50: 45798 | J50: 45798 | K50: =IF(ISBLANK(J50), NETWORKDAYS(H50, TODAY(),fESTIVOS!$A$1:$A$18), NETWORKDAYS(H50, J50, fESTIVOS!$A$1:$A$18)) -> 1 | AB50: Realizara hoy el cierre
A51: jESUS PEÑA | B51: MDSB-812348 | C51: Jiras dia a dia ( Generacion de informe formato at 031 año 2024 | D51: FINALIZADO | G51: 45791 | H51: 45792 | J51: 45792 | K51: =IF(ISBLANK(J51), NETWORKDAYS(H51, TODAY(),fESTIVOS!$A$1:$A$18), NETWORKDAYS(H51, J51, fESTIVOS!$A$1:$A$18)) -> 1 | Y51: Informe generado y enviado al usuario
A52: JAIRO NIÑO | B52: GD772-104 | C52: campos glosa aceptada y glosa conciliacion (pend JIRA) | D52: FINALIZADO | E52: 80 | G52: 45763 | H52: 45779 | I52: 45776 | J52: 45799 | K52: =IF(ISBLANK(J52), NETWORKDAYS(H52, TODAY(),fESTIVOS!$A$1:$A$18), NETWORKDAYS(H52, J52, fESTIVOS!$A$1:$A$18)) -> 15 | L52: MDSB-803316 | M52: 45777 | N52: MDSB-814807 | O52: 45799 | Q52: Se debe revisar el error de los campos de tamaño, sin eso no se puede avanzar este req, ya se encuentra proximo a test | R52: Se entrega para TEST miercoles 30 abril | S52: Se pausó para soporte de informe RIPS | W52: Se realizaron ajustes solicitados relacionados con los campos de GLOSA, específicamente desde la línea 39. También se atendieron solicitudes de cambios adicionales | X52: se han aplicado algunos cambios solicitados en Campus Glossa, los cuales ya están en ambiente de pruebas. Solo se espera la validación final por parte del equipo solicitante, Adicional se está revisando si ese orden de la carta solicitado se encuentra implementado correctamente o si requiere ajustes. | Z52: Se solicita control de cambios a produccion MDSB-814807 | AA52: aún se está esperando el Jira MDSB-814807, se requiere aprobación por parte de varios actores | AB52: El control de cambios se encuentra pendiente por aprovación de Juan David Leon, se estima la aprovación hoy para que sea incluido en comite de cambios digitales *Control de cambios aprobado y ejecutado 21 de mayo a las 4pm. | AC52: El desarrollo fue pasado a producción e incluye los nuevos campos solicitados. Sin embargo, el informe presenta limitaciones si existen más de tres Glosas, por lo que se propuso desarrollar un nuevo informe más claro y funcional.
A53: FABIO FORERO | C53: Manual MDSB-707440 - Portal Reembolsos ARL | D53: FINALIZADO | G53: 45714 | H53: 45784 | J53: 45785 | P53: 05/03/2025: Se iniciara al finalizar Prueba en test GD772-82 Tipología sin flujo de radicación sisalud.
A54: JAIRO NIÑO | B54: INTERNO | C54: Botón para radicación directa de nota crédito | D54: FINALIZADO | E54: 100 | G54: 45800 | J54: 45804 | AC54: Se propuso automatizar la radicación de notas crédito mediante un botón que simplifique el proceso repetitivo. El desarrollo aún no ha iniciado, pero se estima de rápida implementación. | AE54: ya está en producción y deben ser mostradas a los usuarios.(John)
A55: jESUS PEÑA | B55: interno | C55: Validación informe general ARL-prd | D55: FINALIZADO | E55: 100 | G55: 45798 | H55: 45803 | J55: 45803 | K55: =IF(ISBLANK(J55), NETWORKDAYS(H55, TODAY(),fESTIVOS!$A$1:$A$18), NETWORKDAYS(H55, J55, fESTIVOS!$A$1:$A$18)) -> 1 | O55: 45803 | AC55: El informe presenta demoras al abrirse en Excel debido al alto volumen de registros. Se recomendó reducir el rango de fechas a 15 días y exportar en formato CSV para evitar bloqueos del sistema y mejorar el rendimiento. | AD55: IIniciara hoy con la validación del imforme | AE55: 26 de Mayo finalizza ajuste del informe cambiando el formato de descarga a .csv, haciendo mas ligera la generación y apertura del informe.
A56: jESUS PEÑA | B56: MDSB-794658 | C56: jira dia a dia ( No muestra infromación actualizada en consulta de autorizaciones) | D56: FINALIZADO | G56: 45804 | H56: 45804 | J56: 45804 | K56: =IF(ISBLANK(J56), NETWORKDAYS(H56, TODAY(),fESTIVOS!$A$1:$A$18), NETWORKDAYS(H56, J56, fESTIVOS!$A$1:$A$18)) -> 1 | AE56: Se ajusta el limit de la consulta
A57: jESUS PEÑA | B57: Interno | C57: Apertura de flujo caso 38929896 (Nativo Dictamen Jrci) | D57: FINALIZADO | G57: 45805 | H57: 45806 | J57: 45806 | K57: =IF(ISBLANK(J57), NETWORKDAYS(H57, TODAY(),fESTIVOS!$A$1:$A$18), NETWORKDAYS(H57, J57, fESTIVOS!$A$1:$A$18)) -> 1 | AF57: El 29 de Mayo se realiza apertura del fllujo ya que el caso habia quedado con una sola actividad.
A58: jESUS PEÑA | B58: MDSB-822809 | C58: Jira dia a dia ( Descarga soportes AT 031 y AT 028) | D58: FINALIZADO | G58: 45807 | H58: 45807 | J58: 45811 | K58: =IF(ISBLANK(J58), NETWORKDAYS(H58, TODAY(),fESTIVOS!$A$1:$A$18), NETWORKDAYS(H58, J58, fESTIVOS!$A$1:$A$18)) -> 3 | AF58: Se implementara una consulta para realizar la descarga de los soportes ya que son demasioado pesados.
A59: jESUS PEÑA | B59: Interno | C59: Buscar Tabla Log de calificación | D59: FINALIZADO | G59: 45811 | H59: 45812 | J59: 45812 | K59: =IF(ISBLANK(J59), NETWORKDAYS(H59, TODAY(),fESTIVOS!$A$1:$A$18), NETWORKDAYS(H59, J59, fESTIVOS!$A$1:$A$18)) -> 1 | AG59: Jesús debe ubicar la tabla y realizar una consulta select para continuar con esta tarea, Falizada hoy
A60: jESUS PEÑA | B60: GD772-109 | C60: Nuevos datos de ordenes medicas con IA (Adicion de campos informe cups) | D60: FINALIZADO | G60: 45811 | H60: 45811 | J60: 45814 | K60: =IF(ISBLANK(J60), NETWORKDAYS(H60, TODAY(),fESTIVOS!$A$1:$A$18), NETWORKDAYS(H60, J60, fESTIVOS!$A$1:$A$18)) -> 4 | M60: 45811 | O60: 45814 | AF60: *** | AG60: Está en ambiente de prueba; faltan dos columnas cuya fuente debe identificarse | AH60: El 5 de junio se realizan prueba y ajustes de los hallazgo en test, hoy realizara despliegue a produccion | AI60: Los Ajustes del informe se pasaron a produccion el 6 de Junio.
A61: JESUS PEÑA | B61: GD772-88 | C61: Requerimiento gestión Medicamentos fase 2 - Sprint 1 | D61: FINALIZADO | E61: 95 | F61: 3 | G61: 45784 | H61: 45784 | I61: 45786 | J61: 45803 | K61: =IF(ISBLANK(J61), NETWORKDAYS(H61, TODAY(),fESTIVOS!$A$1:$A$18), NETWORKDAYS(H61, J61, fESTIVOS!$A$1:$A$18)) -> 14 | M61: 45786 | O61: 45814 | T61: inicia requerimiento | V61: Se entrega para hoy | W61: Jesus subio a justes a test 9 de mayo, Fabio iniciara pruebas | X61: Jesus realiza ajustes de hallazgos evidenciados en las pruebas, se realizara validación de los ajustes y realizar entrega al cliente hoy. | AG61: En sesion de seguimiento con Bolivar confirman paso a produccion | AH61: Se programa paso a produccion para hoy en la tarde (5 pm) | AI61: Se realiza paso a produccion
A62: jESUS PEÑA | B62: MDSB-827826 | C62: Jira dia a dia (Modificación texto carta comunicaciones masivas) | D62: FINALIZADO | G62: 45818 | H62: 45818 | J62: 45818 | K62: =IF(ISBLANK(J62), NETWORKDAYS(H62, TODAY(),fESTIVOS!$A$1:$A$18), NETWORKDAYS(H62, J62, fESTIVOS!$A$1:$A$18)) -> 1 | AJ62: El 10 de junio se realiza ajuste de las cartas por base de datos
A63: DANILO RAMIREZ | B63: CNTI-271 | C63: Vulnerabilidad, CVE-2017-18214 (Moment.js) – ReDoS al procesar cadenas de fecha maliciosas (< v2.19.3) | D63: FINALIZADO | E63: 100 | F63: 1 | G63: 45818 | H63: 45819 | I63: 45819 | J63: 45819 | K63: =IF(ISBLANK(J63), NETWORKDAYS(H63, TODAY(),fESTIVOS!$A$1:$A$18), NETWORKDAYS(H63, J63, fESTIVOS!$A$1:$A$18)) -> 1 | AJ63: Permite ataques DoS por expresiones regulares (ReDoS) al manejar fechas especialmente diseñadas en Moment.js para Node.js | AK63: Se actualizó a la versión 2.29.4 para corregir la vulnerabilidad
A64: DANILO RAMIREZ | B64: CNTI-271 | C64: Vulnerabilidad,CVE-2017-18214 (Linux Kernel) – Error en el subsistema DCCP del kernel de Linux | D64: FINALIZADO | E64: 100 | F64: 1 | G64: 45818 | H64: 45820 | I64: 45820 | J64: 45821 | K64: =IF(ISBLANK(J64), NETWORKDAYS(H64, TODAY(),fESTIVOS!$A$1:$A$18), NETWORKDAYS(H64, J64, fESTIVOS!$A$1:$A$18)) -> 2 | AJ64: Vulnerabilidad distinta con mismo identificador CVE, afecta al kernel de Linux y no está relacionada con Moment.js. | AK64: Se cierre vulnerabilidad debido a que la Versión de kernel es superior (5.15.0-1084-aws)
A65: JAIRO NIÑO | B65: Interno | C65: Analitica de factura de cuentas medicas (ingresar en el portal de yii) ArL | D65: FINALIZADO | E65: 100 | F65: 1 | G65: 45786 | H65: 45786 | J65: 45825 | K65: =IF(ISBLANK(J65), NETWORKDAYS(H65, TODAY(),fESTIVOS!$A$1:$A$18), NETWORKDAYS(H65, J65, fESTIVOS!$A$1:$A$18)) -> 28 | S65: Pendiente hasta que lo active wilson | V65: Se inica dado que wilson ya entregó informe | W65: confirma estar trabajando en el portal. Comenta que durante el jueves y viernes estuvo enfocado principalmente en el informe elaborado por Wilson, sin embargo, encontró errores que ya fueron comunicados a Wlson, los cuales parecen estar relacionados con cambios que sufrió el informe después de haber comenzado su desarrollo | X65: El script que estaba utilizando Wilson se encuentra desactualizado respecto a la nueva estructura del informe. Es importante actualizar el script o definir un responsable para garantizar compatibilidad y evitar errores de ejecución. | AA65: SE indicó por correo que el desarrollo estaba listo para subir, pero al hacerlo se detectaron errores. Aún no se ha recibido respuesta posterior de Wilson, posiblemente porque está involucrado en otros temas. | AB65: Realizara validación e informara a Jairo cuando este listo. | AC65: Wilson entrega informe en HTML con imágenes a Jiaro, pero presenta inconvenientes técnicos para su visualización correcta. Se requiere solución que permita mostrar el contenido de forma segura e integrada. | AD65: El 23 de Mayo inició la revisión del informe de analítica de facturas de cuentas médicas en el portal Yii de la ARL, basado en el trabajo de Wilson, pero no alcanzó a completarla. | AE65: No se reportan avances | AF65: No se han realizado avances en este requerimiento. Continúa pendiente de priorización frente a otras tareas. | AJ65: Aún no se ha retomado este requerimiento. Se planea revisarlo tan pronto como sea posible. | AK65: Se retomará el desarrollo durante la mañana de hoy. El objetivo es mostrar resultados concretos en esta jornada | AL65: No se ha retomado el desarrollo. Se planea continuar una vez finalizado la Mejora informe glosa req GD772-104 | AM65: Ya fue desplegada en producción desde el 17 de junio. Pendiente revisión con el cliente (actualmente en vacaciones).
A66: jESUS PEÑA | B66: MDSB-820704 | C66: Jira dia a dia Error en generación informe mail 472 (Prefactura) | D66: FINALIZADO | E66: 100 | G66: 45805 | H66: 45825 | J66: 45825 | K66: =IF(ISBLANK(J66), NETWORKDAYS(H66, TODAY(),fESTIVOS!$A$1:$A$18), NETWORKDAYS(H66, J66, fESTIVOS!$A$1:$A$18)) -> 1 | AF66: En cola de trabajo | AL66: Retomara validación de la incidencia | AM66: Se identifica que el problema fue causado por un valor en el campo direccion_destino, donde la descripción de la dirección incluía un punto y coma (;) como parte del texto, Se añadió una codificación UTF-8 al tratamiento del texto, permitiendo omitir o interpretar correctamente el punto y coma, evitando así el desbordamiento de columnas al momento de cargar el archivo .csv
A67: jESUS PEÑA | C67: Jira dia a dia Marcar como envio certificado tipologia 10665 Solicitud paz y salvo prestadores asistenciales. | D67: FINALIZADO | F67: 1 | G67: 45825 | H67: 45825 | I67: 45825 | K67: =IF(ISBLANK(J67), NETWORKDAYS(H67, TODAY(),fESTIVOS!$A$1:$A$18), NETWORKDAYS(H67, J67, fESTIVOS!$A$1:$A$18)) -> 267 | AM67: Se realiza maracación solicitada para la tipologia 10665 Solicitud paz y salvo prestadores asistenciales.
A68: JAIRO NIÑO | B68: Interno | C68: Automatización de notas crédito | D68: FINALIZADO | E68: 100 | G68: 45825 | H68: 45825 | J68: 45825 | K68: =IF(ISBLANK(J68), NETWORKDAYS(H68, TODAY(),fESTIVOS!$A$1:$A$18), NETWORKDAYS(H68, J68, fESTIVOS!$A$1:$A$18)) -> 1 | O68: 45825 | AM68: Se implementó automatización basada en lectura del XML para reconocer y anular automáticamente notas crédito. Ya se encuentra en producción desde el 17 de Junio.

Sheet FINALIZADOS
A1: Asignado | B1: Requerimiento | C1: Actividad | D1: ESTADO | E1: F.Asignado | F1: Fecha inicio | G1: F. estimada de entrea | H1: Finalizado | I1: Dias | J1: TEST | K1: PRODUCCION | L1: Observacion
A2: DANILO RAMIREZ | B2: VULNERABILIDADES ALTAS | C2: Cross site scripting | E2: 45561 | F2: 45561 | H2: 45565 | I2: =IF(ISBLANK(H2), NETWORKDAYS(F2, TODAY(),fESTIVOS!$A$1:$A$18), NETWORKDAYS(F2, H2, fESTIVOS!$A$1:$A$18)) -> 3 | J2: 45565 | K2: 45566 | L2: *01/10/2024 Se encuentra en pruebas en test *02/10/2024 desplegado a produccion el 1de octubre
A3: DANILO RAMIREZ | C3: Arbitrary file upload | E3: 45561 | F3: 45562 | H3: 45565 | I3: =IF(ISBLANK(H3), NETWORKDAYS(F3, TODAY(),fESTIVOS!$A$1:$A$18), NETWORKDAYS(F3, H3, fESTIVOS!$A$1:$A$18)) -> 2 | J3: 45565 | K3: 45566 | L3: *01/10/2024 Se encuentra en pruebas en test *01/10/2024 desplegado a produccion.
A4: DANILO RAMIREZ | B4: VULNERABILIDADES MEDIAS | C4: Database Error Message Disclosure | E4: 45566 | F4: 45566 | H4: 45566 | I4: =IF(ISBLANK(H4), NETWORKDAYS(F4, TODAY(),fESTIVOS!$A$1:$A$18), NETWORKDAYS(F4, H4, fESTIVOS!$A$1:$A$18)) -> 1 | J4: 45566 | K4: 45566 | L4: *02/10/2024 finalizado
A5: DANILO RAMIREZ | C5: Application error messages | E5: 45566 | F5: 45566 | H5: 45566 | I5: =IF(ISBLANK(H5), NETWORKDAYS(F5, TODAY(),fESTIVOS!$A$1:$A$18), NETWORKDAYS(F5, H5, fESTIVOS!$A$1:$A$18)) -> 1 | J5: 45566 | K5: 45566 | L5: *02/10/2024 finalizado
A6: DANILO RAMIREZ | C6: Development configuration files | E6: 45566 | F6: 45566 | H6: 45566 | I6: =IF(ISBLANK(H6), NETWORKDAYS(F6, TODAY(),fESTIVOS!$A$1:$A$18), NETWORKDAYS(F6, H6, fESTIVOS!$A$1:$A$18)) -> 1 | J6: 45566 | K6: 45566 | L6: *02/10/2024 finalizado
A7: JAIRO NIÑO | B7: MDSB-679569 No estan ingresando casi casos a la bandeja de con Externa y Crónicos. | D7: FINALIZADO | E7: 45566 | F7: 45566 | H7: 45567 | I7: =IF(ISBLANK(H7), NETWORKDAYS(F7, TODAY(),fESTIVOS!$A$1:$A$18), NETWORKDAYS(F7, H7, fESTIVOS!$A$1:$A$18)) -> 2 | L7: *02/10/2024 Validar estadistico y no se evidencia intermitencia en el servicio.
A8: LUIS BAYONA | B8: Cargue masivo de imágenes a casos reportados por John | D8: FINALIZADO | E8: 45566 | F8: 45566 | H8: 45566 | I8: =IF(ISBLANK(H8), NETWORKDAYS(F8, TODAY(),fESTIVOS!$A$1:$A$18), NETWORKDAYS(F8, H8, fESTIVOS!$A$1:$A$18)) -> 1 | K8: 45566 | L8: *02/10/2024, las imágenes se encuentran en una maquina local se debe validar la forma de como pasarlas al servidor
A9: LUIS BAYONA | B9: Validar creacion de plantillas de respuesta en nativo salud | D9: PRUEBAS | E9: 45566 | F9: 45566 | G9: 45567 | H9: 45566 | I9: =IF(ISBLANK(H9), NETWORKDAYS(F9, TODAY(),fESTIVOS!$A$1:$A$18), NETWORKDAYS(F9, H9, fESTIVOS!$A$1:$A$18)) -> 1 | J9: 45568 | L9: * 02/10/2024 Realizando pruebas en local.
A10: JHOAN QUICENO | B10: MDSB-679787 Error cargue Constitución en Mora | D10: FINALIZADO | E10: 45567 | F10: 45567 | H10: 45567 | I10: =IF(ISBLANK(H10), NETWORKDAYS(F10, TODAY(),fESTIVOS!$A$1:$A$18), NETWORKDAYS(F10, H10, fESTIVOS!$A$1:$A$18)) -> 1 | K10: 45568 | L10: *03/10/2024 Se realiza despliegue a produccion.
A11: JESUS PEÑA | B11: VULNERABILIDADES MEDIAS | C11: Ausencia de control de peticiones | D11: FINALIZADO | E11: 45566 | F11: 45566 | G11: 45567 | H11: 45567 | I11: =IF(ISBLANK(H11), NETWORKDAYS(F11, TODAY(),fESTIVOS!$A$1:$A$18), NETWORKDAYS(F11, H11, fESTIVOS!$A$1:$A$18)) -> 2 | J11: 45567 | K11: 45568 | L11: *03/10/2024 Pendiente paso a produccion
A12: JESUS PEÑA | B12: VULNERABILIDADES ALTAS | C12: Enumeración de usuarios | D12: FINALIZADO | E12: 45566 | F12: 45566 | G12: 45567 | H12: 45567 | I12: =IF(ISBLANK(H12), NETWORKDAYS(F12, TODAY(),fESTIVOS!$A$1:$A$18), NETWORKDAYS(F12, H12, fESTIVOS!$A$1:$A$18)) -> 2 | J12: 45567 | K12: 45568 | L12: *03/10/2024 Pendiente paso a produccion
A13: JHOAN QUICENO | B13: MDSB-665946 La lista blanca no esta tomando las IP | D13: PENDIENTE | E13: 45567 | H13: 45569 | I13: =IF(ISBLANK(H13), NETWORKDAYS(F13, TODAY(),fESTIVOS!$A$1:$A$18), NETWORKDAYS(F13, H13, fESTIVOS!$A$1:$A$18)) -> 32538 | L13: *03/10/2024 se validara con Jenry la incidencia *04/10/2024 Se debe escalar a seguridad.
A14: JESUS PEÑA | B14: GD772-39-incluir registro histórico de incapacidades por CC en bandeja de pendientes de cada analista | D14: PRUEBAS BOLIVAR | E14: 45561 | F14: 45561 | H14: 45562 | I14: =IF(ISBLANK(H14), NETWORKDAYS(F14, TODAY(),fESTIVOS!$A$1:$A$18), NETWORKDAYS(F14, H14, fESTIVOS!$A$1:$A$18)) -> 2 | J14: 45562 | K14: 45569 | L14: *04/10/2024 Jose da el go para el paso a produccion, *04/10/2024 Se realiza paso a producción. | M14: https://github.com/Imaginesas/bolivar/compare/master...hotfix/anadirBotonCedulas
A15: FABIO FORERO | B15: MDSB-679787 Error cargue Constitución en Mora | C15: Dar respuesta al jira | D15: FINALIZADO | E15: 45568 | F15: 45568 | G15: 45568 | H15: 45568 | I15: =IF(ISBLANK(H15), NETWORKDAYS(F15, TODAY(),fESTIVOS!$A$1:$A$18), NETWORKDAYS(F15, H15, fESTIVOS!$A$1:$A$18)) -> 1 | L15: *04/10/2024 Se da respuesta al caso
A16: DANILO RAMIREZ | B16: ENVIO DE ADJUNTOS DE ORDENES AFI | C16: No envia los adjuntos en el primer envio | D16: FINALIZADO | E16: 45569 | F16: 45569 | H16: 45569 | I16: =IF(ISBLANK(H16), NETWORKDAYS(F16, TODAY(),fESTIVOS!$A$1:$A$18), NETWORKDAYS(F16, H16, fESTIVOS!$A$1:$A$18)) -> 1 | K16: 45569 | L16: *04/10/2024 se agregó un delayed de 1 segundo para darle el tiempo que necesita el disco en reconstruir la imagen.
A17: DANILO RAMIREZ | C17: Casos que no se no se encuentra el adjunto | D17: FINALIZADO | E17: 45569 | F17: 45569 | H17: 45569 | I17: =IF(ISBLANK(H17), NETWORKDAYS(F17, TODAY(),fESTIVOS!$A$1:$A$18), NETWORKDAYS(F17, H17, fESTIVOS!$A$1:$A$18)) -> 1
A18: DANILO RAMIREZ | B18: ADJUNTAR DOCUMENTOS PORTAL SALUD (Reembolsos) | C18: Agregar ipload para el cargue documentos por el usuario y reabra los casos | D18: EN PROCESO | E18: 45567 | F18: 45567 | G18: 45568 | H18: 45568 | I18: =IF(ISBLANK(H18), NETWORKDAYS(F18, TODAY(),fESTIVOS!$A$1:$A$18), NETWORKDAYS(F18, H18, fESTIVOS!$A$1:$A$18)) -> 2 | J18: 45568 | L18: 03/10/2024; reabrir casos *04/10/2024 Cambios en test para pruebas. 07/10/2024 pruebaS.
A19: JHOAN QUICENO | B19: Requerimiento salud nativo | C19: Ajustar creación y edición de tipologías por un roll en específico | D19: EN PRUEBAS | E19: 45566 | F19: 45566 | G19: 45567 | H19: 45567 | I19: =IF(ISBLANK(H19), NETWORKDAYS(F19, TODAY(),fESTIVOS!$A$1:$A$18), NETWORKDAYS(F19, H19, fESTIVOS!$A$1:$A$18)) -> 2 | J19: 45568 | L19: * 02/10/2024 creacion de un super roll y se solicitara control de cambios a test. * 03/10/2024 controles de cambios MDSB-680626 y MDSB-680647 ejecutados correctamente, Se realizara despliegue a test para pruebas.
A20: JHOAN QUICENO | C20: Corrección en la creación y actualización de usuarios por cada negocio en administracion de usuarios | D20: EN PRUEBAS | E20: 45561 | F20: 45561 | G20: 45567 | H20: 45568 | I20: =IF(ISBLANK(H20), NETWORKDAYS(F20, TODAY(),fESTIVOS!$A$1:$A$18), NETWORKDAYS(F20, H20, fESTIVOS!$A$1:$A$18)) -> 6 | J20: 45568 | L20: *02/10/2024, se subiran los ajustes pendientes reportados en las pruebabas del 26 de septiembre. *03/10/2024 Se programara sesion para validar los ajustes.
A21: JHOAN QUICENO | C21: Administracion menu | D21: EN PRUEBAS | E21: 45561 | F21: 45568 | H21: 45568 | I21: =IF(ISBLANK(H21), NETWORKDAYS(F21, TODAY(),fESTIVOS!$A$1:$A$18), NETWORKDAYS(F21, H21, fESTIVOS!$A$1:$A$18)) -> 1 | J21: 45568 | L21: *04/10/2024 en test para pruebas
A22: JOHN ROLON | B22: Cargue masivo de imágenes a casos reportados por John | C22: Paso de imágenes al servidor | D22: FINALIZADO | E22: 45567 | F22: 45567 | G22: 45567 | H22: 45569 | I22: =IF(ISBLANK(H22), NETWORKDAYS(F22, TODAY(),fESTIVOS!$A$1:$A$18), NETWORKDAYS(F22, H22, fESTIVOS!$A$1:$A$18)) -> 3 | L22: *02/10/2024 Validar la forma de pasar las imágenes al servidor. * 03/10/2024 Se realizara validacion hoy. *04/10/2024 se cargan 651 casos, quedan pendinetes 81 imágenes por procesar por falta del numero de caso.
A23: JHOAN QUICENO | B23: Requerimiento salud nativo | C23: Ajustar visualizacion de Actividades, informacion caso internet y visor de imágenes, no se activan al radicar un caso. | D23: FINALIZADO | E23: 45569 | F23: 45572 | H23: 45572 | I23: =IF(ISBLANK(H23), NETWORKDAYS(F23, TODAY(),fESTIVOS!$A$1:$A$18), NETWORKDAYS(F23, H23, fESTIVOS!$A$1:$A$18)) -> 1 | J23: 45572
A24: FABIO FORERO | B24: Validar creacion de plantillas de respuesta en nativo salud | C24: Realizar pruebas en test | D24: FINALIZADO | E24: 45568 | F24: 45568 | G24: 45568 | H24: 45568 | I24: =IF(ISBLANK(H24), NETWORKDAYS(F24, TODAY(),fESTIVOS!$A$1:$A$18), NETWORKDAYS(F24, H24, fESTIVOS!$A$1:$A$18)) -> 1 | L24: *04/10/2024 Se evidencia hallazgo en el borrado de plantillas y queda pendiente la validacion de las plantillas en gestion del caso. *07/10/2024 a un no se ha desplegado el ajuste a test *07/10/2024 Las plantillas de no salen en gestion de caso
A25: JESUS PEÑA | B25: Error 500 al consultar CC del radicado 30890192 | D25: PENDIENTE | E25: 45572 | F25: 45573 | H25: 45573 | I25: =IF(ISBLANK(H25), NETWORKDAYS(F25, TODAY(),fESTIVOS!$A$1:$A$18), NETWORKDAYS(F25, H25, fESTIVOS!$A$1:$A$18)) -> 1 | K25: 45573 | L25: *08/10/2024 Revisar log de errores *08/10/2024 Error producido por una modficación erronea de la fecha inc de la incapacidad.
A26: JAIRO NIÑO | C26: Ajustes visuales en la vista de gestión | D26: FINALIZADO | E26: 45572 | F26: 45572 | H26: 45572 | I26: =IF(ISBLANK(H26), NETWORKDAYS(F26, TODAY(),fESTIVOS!$A$1:$A$18), NETWORKDAYS(F26, H26, fESTIVOS!$A$1:$A$18)) -> 1 | J26: 45573 | L26: *08/10/2024 Se realizara paso a test para pruebas con Jenry
A27: LUIS BAYONA | B27: Validar creación de plantillas de respuesta en nativo salud | C27: Validación de error al borrar plantillas | D27: FINALIZADO | E27: 45566 | F27: 45568 | G27: 45568 | H27: 45569 | I27: =IF(ISBLANK(H27), NETWORKDAYS(F27, TODAY(),fESTIVOS!$A$1:$A$18), NETWORKDAYS(F27, H27, fESTIVOS!$A$1:$A$18)) -> 2 | L27: *07/10/2024 Pendiente despliegue a test. * 08/10/2024 se realiza validación y a un no permite el borrado *09/10/2024 ajuste aplicado correctamente, permite borrar la plantilla
A28: JHOAN QUICENO | B28: MDSB-672997 Error en creación de usuario proveedores nit 811007144 | D28: FINALIZADO | E28: 45572 | F28: 45573 | H28: 45573 | I28: =IF(ISBLANK(H28), NETWORKDAYS(F28, TODAY(),fESTIVOS!$A$1:$A$18), NETWORKDAYS(F28, H28, fESTIVOS!$A$1:$A$18)) -> 1 | L28: * 08/10/2024 No permite crear usuario como proveedor debido a que ya se encuentra creado como usuario de gestión, se dará respuesta de acuerdo a esta validación *09/10/2024 Se evidencia error en el roll asignado
A29: JHOAN QUICENO | B29: Requerimiento salud nativo | C29: Creación del API | D29: EN PROCESO | E29: 45573 | F29: 45573 | G29: 45573 | H29: 45573 | I29: =IF(ISBLANK(H29), NETWORKDAYS(F29, TODAY(),fESTIVOS!$A$1:$A$18), NETWORKDAYS(F29, H29, fESTIVOS!$A$1:$A$18)) -> 1 | L29: *08/10/2024 Compromiso de entrega hoy en la tarde. *09/10/2024 pendiente despliegue del jira
A30: DANILO RAMIREZ | C30: Implementación del API en los servicios para actualizacion de estados. | D30: IMPLEMENTADO | E30: 45573 | F30: 45573 | L30: *09/10/2024 Pendiente creación de la tabla de estados en test para probar.
A31: JESUS PEÑA | B31: MDSB-685249 Erroren la recuperacion de contraseña Yii | D31: FINALIZADO | E31: 45574 | F31: 45574 | H31: 45574 | I31: =IF(ISBLANK(H31), NETWORKDAYS(F31, TODAY(),fESTIVOS!$A$1:$A$18), NETWORKDAYS(F31, H31, fESTIVOS!$A$1:$A$18)) -> 1 | J31: 45574 | K31: 45574 | L31: *09/10/2024no tenía permisos la carpeta cache
A32: JESUS PEÑA | B32: Ajustar validacion de la fecha inicial de inc en la edicion de fechas | D32: FINALIZADO | E32: 45574 | F32: 45574 | H32: 45574 | I32: =IF(ISBLANK(H32), NETWORKDAYS(F32, TODAY(),fESTIVOS!$A$1:$A$18), NETWORKDAYS(F32, H32, fESTIVOS!$A$1:$A$18)) -> 1 | J32: 45574 | K32: 45574 | L32: *09/10/2024 Fabio,realiza validación en produccion y funciona correctamente | M32: https://github.com/Imaginesas/bolivar/compare/master...hotfix/fechaEnGestionEdicion
A33: JESUS PEÑA | B33: MDSB-683770 ERROR EN EL ENVIO NOTIFICACIONES DE PAGO | C33: Confirmar que la notificación se envié al correo registrado. | D33: FINALIZADO | E33: 45572 | F33: 45572 | H33: 45572 | I33: =IF(ISBLANK(H33), NETWORKDAYS(F33, TODAY(),fESTIVOS!$A$1:$A$18), NETWORKDAYS(F33, H33, fESTIVOS!$A$1:$A$18)) -> 1 | J33: 45574 | K33: 45574 | L33: *07/10/2024 Pendiente subir ajuste *08/10/2024 Pendiente subir a producción *09/10/2024 Subira a test y posteriomente a producción | M33: https://github.com/Imaginesas/bolivar/compare/master...hotfix/correosMasivos
A34: JESUS PEÑA | B34: VULNERABILIDADES BAJAS | C34: Web Server Allows Password Auto-Completion | D34: FINALIZADO | E34: 45567 | F34: 45567 | G34: 45569 | H34: 45568 | I34: =IF(ISBLANK(H34), NETWORKDAYS(F34, TODAY(),fESTIVOS!$A$1:$A$18), NETWORKDAYS(F34, H34, fESTIVOS!$A$1:$A$18)) -> 2 | J34: 45569 | L34: *04/10/2024 pruebas * 07/10/2024 se entrega a Danilo para pruebas y posterior despliegue a producción * 09/10/2024 Confirmar entrega de rama a Danilo * 10/10/2024 Etregadas a Danilo 9 de octubre
A35: JESUS PEÑA | C35: Autocomplete Enabled | D35: FINALIZADO | E35: 45567 | F35: 45567 | G35: 45569 | H35: 45568 | I35: =IF(ISBLANK(H35), NETWORKDAYS(F35, TODAY(),fESTIVOS!$A$1:$A$18), NETWORKDAYS(F35, H35, fESTIVOS!$A$1:$A$18)) -> 2 | J35: 45569 | L35: *04/10/2024 pruebas * 07/10/2024 se entrega a Danilo para pruebas y posterior despliegue a producción * 09/10/2024 Confirmar entrega de rama a Danilo * 10/10/2024 Etregadas a Danilo 9 de octubre
A36: JESUS PEÑA | B36: VULNERABILIDADES MEDIAS | C36: Internal Server Error | D36: FINALIZADO | E36: 45567 | F36: 45567 | G36: 45569 | H36: 45569 | I36: =IF(ISBLANK(H36), NETWORKDAYS(F36, TODAY(),fESTIVOS!$A$1:$A$18), NETWORKDAYS(F36, H36, fESTIVOS!$A$1:$A$18)) -> 3 | J36: 45569 | L36: *04/10/2024 pruebas * 07/10/2024 se entrega a Danilo para pruebas y posterior despliegue a producción * 09/10/2024 Confirmar entrega de rama a Danilo * 10/10/2024 Etregadas a Danilo 9 de octubre
A37: JHOAN QUICENO | B37: Requerimiento salud nativo | C37: Reabrir casos devueltos por falta de documentación | D37: FINALIZADO | E37: 45572 | F37: 45572 | H37: 45574 | I37: =IF(ISBLANK(H37), NETWORKDAYS(F37, TODAY(),fESTIVOS!$A$1:$A$18), NETWORKDAYS(F37, H37, fESTIVOS!$A$1:$A$18)) -> 3 | J37: 45574 | L37: *07/10/2024 Se escala jira MDSB-684400 para creación de tabla de estados en test * 08/10/2024 Se realizara sesión para validar el proceso de estados. *09/10/2024 pendiente creación de tabla de estados solicitad en jira MDSB-684795 *10/10/2024 implementación de la lógica reabrir casos en devolución por documentos.
A38: JHOAN QUICENO | B38: Requerimiento salud nativo | C38: Crear combo obligatorio en generación de respuesta (Aceptado o Devolución ) Para casos radicados por el portal | D38: FINALIZADO | E38: 45572 | F38: 45572 | G38: 45573 | H38: 45575 | I38: =IF(ISBLANK(H38), NETWORKDAYS(F38, TODAY(),fESTIVOS!$A$1:$A$18), NETWORKDAYS(F38, H38, fESTIVOS!$A$1:$A$18)) -> 4 | L38: *07/10/2024 Se escala jira MDSB-684400 para creación de tabla de estados en test *08/10/2024 se escala nuevo jira MDSB-684795, por errores en el anterior. *09/10/2024 pendiente creación de tabla de estados solicitad en jira MDSB-684795 *10/10/2024 Tabla de estados creada.
A39: DANILO RAMIREZ | B39: Ajustes de hallazgos obtenidos en pruebas de portal autorizaciones (Enviado por correo) | C39: Ordenar alfabeticamente tipo de solicitud | D39: FINALIZADO | E39: 45574 | F39: 45576 | H39: 45576 | I39: =IF(ISBLANK(H39), NETWORKDAYS(F39, TODAY(),fESTIVOS!$A$1:$A$18), NETWORKDAYS(F39, H39, fESTIVOS!$A$1:$A$18)) -> 1 | L39: *15/10/2024 finlizado
A40: JAIRO NIÑO | B40: Gestión aplicativo reembolso salud | C40: Consumo de sisalud (Recurso de Bolívar) | D40: FINALIZADO | E40: 45560 | F40: 45572 | H40: 45573 | I40: =IF(ISBLANK(H40), NETWORKDAYS(F40, TODAY(),fESTIVOS!$A$1:$A$18), NETWORKDAYS(F40, H40, fESTIVOS!$A$1:$A$18)) -> 2 | J40: 45573 | L40: *08/10/2024 se encuentra realizando la lógica para enviar el recurso a sisalud después de pagar. *09/10/2024 Pruebas con Jenry *10/10/2024 Se crearon los nuevos campos para homologar los estados de sisalud, pendiente crear campo para el cambio de servicio. * 15/10/2024 ya permite el cambio de servicio.
A41: JAIRO NIÑO | B41: Buscar la ciudad con respecto al archivo de pagos( Facturas asistenciales) | C41: Creacion de indices | D41: FINALIZADO | E41: 45575 | F41: 45576 | G41: 45581 | H41: 45576 | I41: =IF(ISBLANK(H41), NETWORKDAYS(F41, TODAY(),fESTIVOS!$A$1:$A$18), NETWORKDAYS(F41, H41, fESTIVOS!$A$1:$A$18)) -> 1 | J41: 45576 | K41: 45576 | L41: * 15/10/2024 Finalizado
A42: JHOAN QUICENO | B42: MDSB-684778 Modificación texto carta de comunicaciones de cartera | D42: PASO A PRODUCCION | E42: 45573 | F42: 45574 | H42: 45574 | I42: =IF(ISBLANK(H42), NETWORKDAYS(F42, TODAY(),fESTIVOS!$A$1:$A$18), NETWORKDAYS(F42, H42, fESTIVOS!$A$1:$A$18)) -> 1 | J42: 45574 | K42: 45575 | L42: *09/10/2024 Se habilitan plantillas para las tipologías de comunicados de cartera para que puedan ser modificadas, Aprobado para realizar paso a producción 10 de Octubre. *10/10/2024 Se realizara paso a producción hoy.
A43: DANILO RAMIREZ | B43: Ajustes de hallazgos obtenidos en pruebas de portal autorizaciones (Enviado por correo) | C43: Campo Razon social sea alfanumerico. | D43: FINALIZADO | E43: 45576 | F43: 45576 | H43: 45576 | I43: =IF(ISBLANK(H43), NETWORKDAYS(F43, TODAY(),fESTIVOS!$A$1:$A$18), NETWORKDAYS(F43, H43, fESTIVOS!$A$1:$A$18)) -> 1 | J43: 45580 | L43: 15/10/2024, se subira ajuste hoy 15/10/2024 Fabio, Valida y el ajuste quedo ok
A44: DANILO RAMIREZ | B44: Cambio de cuenta de correo de salida del nuevo portal de autorizaciones | C44: Cambio de cuenta de correo (POLIZAS DE SEGUROS) | D44: FINALIZADO | E44: 45561 | F44: 45569 | G44: 45572 | H44: 45572 | I44: =IF(ISBLANK(H44), NETWORKDAYS(F44, TODAY(),fESTIVOS!$A$1:$A$18), NETWORKDAYS(F44, H44, fESTIVOS!$A$1:$A$18)) -> 2 | J44: 45580 | L44: *Iniciara tan pronto finalice la gestión de vulnerabilidades *03/10/2024 Inicio al finalizar ADJUNTAR DOCUMENTOS PORTAL SALUD (Reembolsos) *07/10/2024 Inicio con los ajustes desde el 4 de octubre. *08/10/2024 Finalizado en local en pruebas *09/10/2024 Pendiente ejecución de jira MDSB-684795 para iniciar pruebas en test. *10/10/2024 Crear el campo en la administración y adaptarla lógica para agregarlo a la cola se subirá a test hoy para pruebas. *15/10/2024, Fabio, Valida y el correo llega por la cuenta indicada. (31022012).
A45: JHOAN QUICENO | B45: Requerimiento salud nativo | C45: Dejar registro de la "devolucion por documentos en la observación del caso" | D45: FINALIZADO | E45: 45576 | F45: 45576 | G45: 45580 | H45: 45576 | I45: =IF(ISBLANK(H45), NETWORKDAYS(F45, TODAY(),fESTIVOS!$A$1:$A$18), NETWORKDAYS(F45, H45, fESTIVOS!$A$1:$A$18)) -> 1 | J45: 45580
A46: JHOAN QUICENO | B46: Requerimiento salud nativo | C46: En la observacion del caso en nativo se debe registrar el usuario "Internet" con una observacion que indique que el caso fue reabierto desde el portal | D46: FINALIZADO | E46: 45576 | F46: 45576 | G46: 45580 | H46: 45576 | I46: =IF(ISBLANK(H46), NETWORKDAYS(F46, TODAY(),fESTIVOS!$A$1:$A$18), NETWORKDAYS(F46, H46, fESTIVOS!$A$1:$A$18)) -> 1 | J46: 45580 | L46: *15/10/2024 Subira ajuste hoy
A47: DANILO RAMIREZ | B47: Ajustes de hallazgos obtenidos en pruebas de portal Reembolsos (Enviado por correo) | C47: Ajustar variable reportada por Jenry | D47: FINALIZADO | E47: 45580 | F47: 45580 | H47: 45580 | I47: =IF(ISBLANK(H47), NETWORKDAYS(F47, TODAY(),fESTIVOS!$A$1:$A$18), NETWORKDAYS(F47, H47, fESTIVOS!$A$1:$A$18)) -> 1 | J47: 45580 | L47: 15/10/2024 inicio de ajuste. *16/10/2024 se adiciono una validacion adicional
A48: JHOAN QUICENO | B48: Requerimiento salud nativo | C48: Ajustas plantilla genérica para que no aparezca el Warning | D48: FINALIZADO | E48: 45576 | F48: 45576 | G48: 45580 | H48: 45576 | I48: =IF(ISBLANK(H48), NETWORKDAYS(F48, TODAY(),fESTIVOS!$A$1:$A$18), NETWORKDAYS(F48, H48, fESTIVOS!$A$1:$A$18)) -> 1 | L48: *15/10/2024 pendiente validar el ajuste *15/10/2024, A un sale en Warning
A49: JHOAN QUICENO | B49: Requerimiento salud nativo | C49: Quitar opciones "Pendientes por segmentación" se encuentran en la pantalla de consulta. | D49: FINALIZADO | E49: 45580 | F49: 45580 | H49: 45581 | I49: =IF(ISBLANK(H49), NETWORKDAYS(F49, TODAY(),fESTIVOS!$A$1:$A$18), NETWORKDAYS(F49, H49, fESTIVOS!$A$1:$A$18)) -> 2
A50: JHOAN QUICENO | B50: Requerimiento salud nativo | C50: En la bandeja de pendientes se debe identificar que el caso fue reabierto por cargue de documentos en el portal | D50: FINALIZADO | E50: 45576 | F50: 45581 | H50: 45582 | I50: =IF(ISBLANK(H50), NETWORKDAYS(F50, TODAY(),fESTIVOS!$A$1:$A$18), NETWORKDAYS(F50, H50, fESTIVOS!$A$1:$A$18)) -> 2 | J50: 45582 | L50: *21/10/2024 prueba en test realizadas el viernes 18 de octubre boton funciona ok.
A51: LUIS BAYONA | B51: Ajustes de hallazgos obtenidos en pruebas de portal autorizaciones (Enviado por correo) | C51: Consulta "Caso internet" en nativo | D51: FINALIZADO | E51: 45581 | F51: 45582 | H51: 45583 | I51: =IF(ISBLANK(H51), NETWORKDAYS(F51, TODAY(),fESTIVOS!$A$1:$A$18), NETWORKDAYS(F51, H51, fESTIVOS!$A$1:$A$18)) -> 2 | L51: *18/10/2024, pendiente ajuste de la consulta en Laravel de parte de Danilo
A52: JAIRO NIÑO | B52: Gestión aplicativo reembolso salud | C52: Implementar Causales deglosas | D52: EN PROCESO | E52: 45582 | F52: 45582 | H52: 45582 | I52: =IF(ISBLANK(H52), NETWORKDAYS(F52, TODAY(),fESTIVOS!$A$1:$A$18), NETWORKDAYS(F52, H52, fESTIVOS!$A$1:$A$18)) -> 1 | J52: 45582 | L52: 17/10/2024 Realizando la logica para incluir las casusales * 22/10/2024 Finalizado 17 de octubre
A53: JAIRO NIÑO | B53: Gestión aplicativo reembolso salud | C53: Cargue de archivo de pagos | D53: FINALIZADO | E53: 45560 | F53: 45572 | H53: 45574 | I53: =IF(ISBLANK(H53), NETWORKDAYS(F53, TODAY(),fESTIVOS!$A$1:$A$18), NETWORKDAYS(F53, H53, fESTIVOS!$A$1:$A$18)) -> 3 | J53: 45582 | L53: *26/09/2024 cargue del archivo después de finalizar la implementación de cartas. * 02/10/2024 continuara después de realizar paso a producción del nuevo portal. *09/10/2024 control de cambios en test para agregar campos y posterior pruebas con Jenry 10/10/2024 realizar pruebas en test * 15/10/2024 pendiente cruce cuando esta pagado en validación *16/10/2024 Corregir incidencias en pruebas, corregir envio de formulario al dar F5 *17/10/2024 mostrar resumen de la radicacion *22/10/2024 Finalizado 17 de octubre
A54: JHOAN QUICENO | B54: Requerimiento salud nativo | C54: Ajustar el administrador de cartas para que salgan todas las tipologias. | D54: FINALIZADO | E54: 45583 | F54: 45583 | H54: 45586 | I54: =IF(ISBLANK(H54), NETWORKDAYS(F54, TODAY(),fESTIVOS!$A$1:$A$18), NETWORKDAYS(F54, H54, fESTIVOS!$A$1:$A$18)) -> 2 | J54: 45586 | L54: *22/10/2024 Probado en test y funciona correctamente, Fabio
A55: JHOAN QUICENO | B55: Requerimiento salud nativo | C55: Crear una opcion Plantillas para la visualizacion de la tipologia en el administrador de cartas | D55: FINALIZADO | E55: 45583 | F55: 45583 | H55: 45583 | I55: =IF(ISBLANK(H55), NETWORKDAYS(F55, TODAY(),fESTIVOS!$A$1:$A$18), NETWORKDAYS(F55, H55, fESTIVOS!$A$1:$A$18)) -> 1 | J55: 45583
A56: JHOAN QUICENO | B56: Requerimiento salud nativo | C56: Validar geneación de informes de pendinete ARL y Salud | D56: FINALIZADO | E56: 45586 | F56: 45586 | H56: 45587 | I56: =IF(ISBLANK(H56), NETWORKDAYS(F56, TODAY(),fESTIVOS!$A$1:$A$18), NETWORKDAYS(F56, H56, fESTIVOS!$A$1:$A$18)) -> 2 | J56: 45587 | L56: *22/10/2024 se escala control de cambios MDSB-692401 para la modificación de la vista sql.
A57: JHOAN QUICENO | B57: Requerimiento salud nativo | C57: Validar informe generación de volumenes y oportunidad | D57: FINALIZADO | E57: 45586 | F57: 45587 | H57: 45587 | I57: =IF(ISBLANK(H57), NETWORKDAYS(F57, TODAY(),fESTIVOS!$A$1:$A$18), NETWORKDAYS(F57, H57, fESTIVOS!$A$1:$A$18)) -> 1 | J57: 45587 | L57: *22/10/2024 Inicia Separación por negocios.
A58: DANILO RAMIREZ | B58: Ajustes de hallazgos obtenidos en pruebas de portal autorizaciones (Enviado por correo) | C58: Hallazgos enviado 26 de septiembre | D58: FINALIZADO | E58: 45561 | F58: 45572 | H58: 45587 | I58: =IF(ISBLANK(H58), NETWORKDAYS(F58, TODAY(),fESTIVOS!$A$1:$A$18), NETWORKDAYS(F58, H58, fESTIVOS!$A$1:$A$18)) -> 11 | J58: 45587 | L58: *07/10/2024, Iniciara con los ajustes. * 08/10/2024 Continúa con los ajustes *09/10/2024 Subirá los puntos resueltos hasta el momento para pruebas. *11/10/2024 Pendiente quitar bloqueo "Caso internet" y cola de correos. *15/10/2024 ajustado el envio de correo por colas. *16/10/2024 pendiente consulta de "caso internet" se le asigna a juste a Luis Bayona *21/10/2024 Ajustar consulta en laravel para mostrar "Caso internet" en nativo
A59: JAIRO NIÑO | B59: Agregar la cuenta de correo de medicamentos | C59: gestion.farmaceutica@segurosbolivar.com | D59: FINALIZADO | E59: 45576 | F59: 45576 | H59: 45576 | I59: =IF(ISBLANK(H59), NETWORKDAYS(F59, TODAY(),fESTIVOS!$A$1:$A$18), NETWORKDAYS(F59, H59, fESTIVOS!$A$1:$A$18)) -> 1 | J59: 45576 | K59: 45587 | L59: *08/10/2024 se validara con Liyibet la cuenta que se debe cambiar *09/10/2024 Pendiente confirmación de la contraseña de la cuenta * 11/10/2024 Liyibet envia credenciales 10/10/2023 *15/10/2024 finalizado para pruebas. * Paso a produccion 22 de octbre
A60: DANILO RAMIREZ | B60: Preparacion de scritp para paso a produccion oficina virtual salud | C60: Jira pqr_bolivar | D60: FINALIZADO | E60: 45587 | F60: 45588 | H60: 45588 | I60: =IF(ISBLANK(H60), NETWORKDAYS(F60, TODAY(),fESTIVOS!$A$1:$A$18), NETWORKDAYS(F60, H60, fESTIVOS!$A$1:$A$18)) -> 1 | L60: *23/10/2024 jira radicado MDSB-693206 en aprobación QA
A61: DANILO RAMIREZ | B61: Preparacion de scritp para paso a produccion oficina virtual salud | C61: Jira riesgos | D61: FINALIZADO | E61: 45587 | F61: 45588 | H61: 45588 | I61: =IF(ISBLANK(H61), NETWORKDAYS(F61, TODAY(),fESTIVOS!$A$1:$A$18), NETWORKDAYS(F61, H61, fESTIVOS!$A$1:$A$18)) -> 1 | L61: 24/10/2024 jira radicado MDSB-693891 en aprobación QA
A62: DANILO RAMIREZ | B62: Preparacion de scritp para paso a produccion oficina virtual salud | C62: Jira radicador | D62: FINALIZADO | E62: 45587 | F62: 45588 | H62: 45588 | I62: =IF(ISBLANK(H62), NETWORKDAYS(F62, TODAY(),fESTIVOS!$A$1:$A$18), NETWORKDAYS(F62, H62, fESTIVOS!$A$1:$A$18)) -> 1 | L62: *23/10/2024 jira radicado MDSB-693912 en aprobación QA
A63: LUIS BAYONA | B63: GD772-44 - Ajuste en la consulta del informe datos contactos solicitudes ARL (Rango de consulta no debe superar un mes) | C63: No muestras en algunos casos el numero de identificación y nombres en los informes de producción | D63: EN PRODUCCION | E63: 45559 | F63: 45576 | H63: 45581 | I63: =IF(ISBLANK(H63), NETWORKDAYS(F63, TODAY(),fESTIVOS!$A$1:$A$18), NETWORKDAYS(F63, H63, fESTIVOS!$A$1:$A$18)) -> 3 | J63: 45581 | K63: 45583 | L63: *09/10/2024 paso a producción *11/10/2024 Validando incidencia * 15/10/2024 Se reunirá con Johan para validar dudas para la sl de la incidencia. * 16/10/2024 se realiza sesión con jairo y se ajusta campo identificación trabajador, luis ajustara el campo identificación empresa. *18/10/2024 presenta error al generar el informe de prefactura. *21/10/2024 Despliegue a produccion 18 de octubre
A64: JESUS PEÑA | B64: GD772-48 Bloqueo de radicación de incapacidades que ya se encuentren radicadas y pagadas con el mismo número de CC y fecha de inicio | D64: EN PRODUCCIÓN | E64: 45562 | F64: 45562 | H64: 45566 | I64: =IF(ISBLANK(H64), NETWORKDAYS(F64, TODAY(),fESTIVOS!$A$1:$A$18), NETWORKDAYS(F64, H64, fESTIVOS!$A$1:$A$18)) -> 3 | J64: 45566 | K64: 45590 | L64: *01/10/2024 Pendiente go para paso a produccion. *25/10/2024 Se realiza paso a producion a las 9:57 a. m.
A65: JAIRO NIÑO | B65: Gestión aplicativo reembolso salud | C65: Encriptar numero de cuenta (Dejar visibles los promeros 5 numeros, EN CONSULTA y BANDEJA DE AUDITORIA | D65: FINALIZADO | E65: 45587 | F65: 45587 | H65: 45589 | I65: =IF(ISBLANK(H65), NETWORKDAYS(F65, TODAY(),fESTIVOS!$A$1:$A$18), NETWORKDAYS(F65, H65, fESTIVOS!$A$1:$A$18)) -> 3 | J65: 45589 | L65: *23/10/2024 Continua trabajando. *25/10/2024 Encripta los ultimos 4 digitos de la cluenta
A66: JAIRO NIÑO | B66: MDSB-683637 REQ Ajustes datos migración EPS-Davinci | C66: Generar el ajuste para adicionar el campo del ID en la integración de Glosas | D66: CONTROL CAMBIOS PROD/ stand by | E66: 45572 | F66: 45574 | H66: 45574 | I66: =IF(ISBLANK(H66), NETWORKDAYS(F66, TODAY(),fESTIVOS!$A$1:$A$18), NETWORKDAYS(F66, H66, fESTIVOS!$A$1:$A$18)) -> 1 | J66: 45574 | L66: *07/10/2024 Entrega de estimación 8 de octubre *09/10/2024 Pendiente estimación *10/10/2024 jira para alterar la tabla MDSB-685532 ejecutado correctamente, se solicitara control de cambios para producción. 11/10/2024 Se continuara finalizando rembolsos. *15/10/2024 Pendiente incluir campo en el envio. *16/10/2024 jira MDSB-689499 control de cambios prod. *21/10/2024 Control de cambios ejecutado 18 de octubre
A67: JHOAN QUICENO | B67: Resoluion de jiras Incidencias | C67: MDSB-588398 asignacion de casos a usuaria inhabilitada para la tipologia Control vencimiento recomendaciones laborales | D67: FINALIZADO | E67: 45588 | F67: 45589 | H67: 45589 | I67: =IF(ISBLANK(H67), NETWORKDAYS(F67, TODAY(),fESTIVOS!$A$1:$A$18), NETWORKDAYS(F67, H67, fESTIVOS!$A$1:$A$18)) -> 1 | L67: *24/10/2024 En el requerimiento inicial se contemplo la opcion de como se asignaria los casos de control de vencimiento si el usuario asignado en el caso padre ya no trabajara en la compañía.
A68: WILSON | B68: Pruebas imágenes fs a s3 | C68: Pruebas copiar imágenes en desarrollo | D68: FINALIZADO | E68: 45568 | F68: 45568 | H68: 45589 | I68: =IF(ISBLANK(H68), NETWORKDAYS(F68, TODAY(),fESTIVOS!$A$1:$A$18), NETWORKDAYS(F68, H68, fESTIVOS!$A$1:$A$18)) -> 15 | J68: 45589 | L68: *15/10/2024 revisara si la tarea en que porcentaje va
A69: LUIS BAYONA | B69: Oficina virtual (nuevo portal) | C69: Ajuste en la fecha de autorizacion en la consulta del proveedor | D69: FINALIZADO | E69: 45588 | F69: 45588 | G69: 45590 | H69: 45590 | I69: =IF(ISBLANK(H69), NETWORKDAYS(F69, TODAY(),fESTIVOS!$A$1:$A$18), NETWORKDAYS(F69, H69, fESTIVOS!$A$1:$A$18)) -> 3 | J69: 45590 | L69: *24/10/2024 Sitio de laravel ajustado para iniciar validaciones. *25/10/2024 Inicia validacion del hallazgo
A70: LUIS BAYONA | B70: Oficina virtual (nuevo portal) | C70: Validación de campos requeridos al cargar excel | D70: FINALIZADO | E70: 45588 | F70: 45588 | G70: 45590 | H70: 45590 | I70: =IF(ISBLANK(H70), NETWORKDAYS(F70, TODAY(),fESTIVOS!$A$1:$A$18), NETWORKDAYS(F70, H70, fESTIVOS!$A$1:$A$18)) -> 3 | J70: 45593 | L70: *24/10/2024 Sitio de laravel ajustado para iniciar validaciones. *25/10/2024 Inicia validacion del hallazgo *28/10/2024 soliictar paso a test y crear jira control de cmbios prod
A71: JAIRO NIÑO | B71: Gestión aplicativo reembolso salud | C71: carta de pago en validación | D71: FINALIZADO | E71: 45588 | F71: 45588 | H71: 45589 | I71: =IF(ISBLANK(H71), NETWORKDAYS(F71, TODAY(),fESTIVOS!$A$1:$A$18), NETWORKDAYS(F71, H71, fESTIVOS!$A$1:$A$18)) -> 2 | J71: 45589 | L71: *24/10/2024 en proceso de implementación
A72: JAIRO NIÑO | B72: Gestión aplicativo reembolso salud | C72: inconsistencia en la asignación de usuarios a las tipologias | D72: FINALIZADO | E72: 45589 | F72: 45589 | H72: 45590 | I72: =IF(ISBLANK(H72), NETWORKDAYS(F72, TODAY(),fESTIVOS!$A$1:$A$18), NETWORKDAYS(F72, H72, fESTIVOS!$A$1:$A$18)) -> 2 | J72: 45590 | L72: x
A73: JAIRO NIÑO | B73: MDSB-683637 REQ Ajustes datos migración EPS-Davinci | C73: Desarrollo para el control de ID consecutivo por parte de Imagine en la integración de Glosas | D73: FINALIZADO | E73: 45572 | F73: 45574 | H73: 45574 | I73: =IF(ISBLANK(H73), NETWORKDAYS(F73, TODAY(),fESTIVOS!$A$1:$A$18), NETWORKDAYS(F73, H73, fESTIVOS!$A$1:$A$18)) -> 1 | L73: *07/10/2024 Entrega de estimación 8 de octubre *09/10/2024 Pendiente estimación. 10/10/2024 Se creo un campo nuevo en la tabla para manejar un consecutivo que se enviara en el reporte davinci, solicitara control de cambios para producción 11/10/2024 Se continuara finalizando rembolsos. *25/10/2024 reinicia con esta actividad.
A74: DANILO RAMIREZ | B74: Ajustes de hallazgos obtenidos en pruebas de portal autorizaciones (Enviado por correo) | C74: Adicionar en reenvió en portales (Autorizaciones y Reembolsos) | D74: FINALIZADO | E74: 45576 | F74: 45579 | H74: 45590 | I74: =IF(ISBLANK(H74), NETWORKDAYS(F74, TODAY(),fESTIVOS!$A$1:$A$18), NETWORKDAYS(F74, H74, fESTIVOS!$A$1:$A$18)) -> 9 | J74: 45590 | L74: 15/10/2024 Continua con este ajuste. *16/10/2024 continua con el ajuste para Reembolsos y después de terminado continuara con autorizaciones *17/10/2024 probar reenvió de rembolsos y continua con autorizaciones. *18/10/2024 Lógica para reenvió ya se encuentra, validar encolamiento *21/10/2024 Validar consumo de colas para el reenvio. *22/10/2024 Queda ajustado el reenvio para nativo *24/10/2024 Presenta inconsistencia en el reevio en autorizaciones, Reenvia la primera respuesta no la ultima. *25/10/2024 Ajustara notificación del reenvio de correo de envio donde muestre la cuenta de correo a que se envio el reenvio. *28/10/2024 Notificación de correo de reenvio ajustado.
A75: DANILO RAMIREZ | B75: Oficina virtual (nuevo portal) | C75: Mejoras autorizaciones, mensajes y respuestas | D75: FINALIZADO | E75: 45587 | F75: 45589 | H75: 45593 | I75: =IF(ISBLANK(H75), NETWORKDAYS(F75, TODAY(),fESTIVOS!$A$1:$A$18), NETWORKDAYS(F75, H75, fESTIVOS!$A$1:$A$18)) -> 3 | J75: 45593 | L75: *25/10/2024 se han realizado modificaciónes *25/10/2024 pendiente ajus messajes en el formulario de salud. *28/10/2024 Validacion de mas campos.
A76: JESUS PEÑA | B76: Oficina virtual (nuevo portal) | C76: Realizar a justes de hallazgos de las pruebas consulta de autorizaciones en oficina virtual | D76: FINALIZADO | E76: 45582 | F76: 45582 | H76: 45582 | I76: =IF(ISBLANK(H76), NETWORKDAYS(F76, TODAY(),fESTIVOS!$A$1:$A$18), NETWORKDAYS(F76, H76, fESTIVOS!$A$1:$A$18)) -> 1 | J76: 45582 | L76: *21/10/2024 Se realiza validación de ajustes en test y a un queda pendiente que la fecha de autorización cargano no coincide con la arrojada en la consulta y permite el cargue de una misma autorizacion a diferente paciente. *22/10/2024 Jesus se encuentra incapacitado hasta del 21 hasta el 29 de Octubre
A77: DANILO RAMIREZ | B77: Cierre de actividades de casos de incapacidades ya cerrados ( Solicitud reportada por Liyibet) | C77: Cierre de actividades abiertas | D77: FINALIZADO | E77: 45587 | F77: 45590 | H77: 45593 | I77: =IF(ISBLANK(H77), NETWORKDAYS(F77, TODAY(),fESTIVOS!$A$1:$A$18), NETWORKDAYS(F77, H77, fESTIVOS!$A$1:$A$18)) -> 2
A78: JAIRO NIÑO | B78: Devolver caso 30554693 a la actividad correspondencia avisado (Pensionados) | C78: Devolver actividad | D78: FINALIZADO | E78: 45590 | F78: 45593 | H78: 45593 | I78: =IF(ISBLANK(H78), NETWORKDAYS(F78, TODAY(),fESTIVOS!$A$1:$A$18), NETWORKDAYS(F78, H78, fESTIVOS!$A$1:$A$18)) -> 1
A79: JHOAN QUICENO | B79: Requerimiento salud nativo | C79: Caso 31022540 registra 2 veces en la bandeja de pendientes Autorizaciones | D79: FINALIZADO | E79: 45589 | F79: 45593 | H79: 45593 | I79: =IF(ISBLANK(H79), NETWORKDAYS(F79, TODAY(),fESTIVOS!$A$1:$A$18), NETWORKDAYS(F79, H79, fESTIVOS!$A$1:$A$18)) -> 1 | J79: 45593 | L79: *30/10/2024 Al realizar la prueba en test presenta error en la gestion de casos, hasta no resolver esta incidencia no es posible balidar ajuste de la bandeja. *31/10/2024 Fabio valida ajuste y funciona correctamnete.
A80: JAIRO NIÑO | B80: Gestión aplicativo reembolso salud | C80: Modificaciones del flujo y codigo. | D80: FINALIZADO | E80: 45594 | F80: 45594 | G80: 45596 | I80: =IF(ISBLANK(H80), NETWORKDAYS(F80, TODAY(),fESTIVOS!$A$1:$A$18), NETWORKDAYS(F80, H80, fESTIVOS!$A$1:$A$18)) -> 429 | J80: 45596 | L80: *30/10/2024 continua con las modificaciones. *31/10/2024 Continua en la logica de cada boton. *01/11/2024 en test
A81: JHOAN QUICENO | B81: Resoluion de jiras Incidencias | C81: MDSB-700005 Solicitud de imágenes lote 158660 | D81: FINALIZADO | E81: 45601 | F81: 45601 | H81: 45602 | I81: =IF(ISBLANK(H81), NETWORKDAYS(F81, TODAY(),fESTIVOS!$A$1:$A$18), NETWORKDAYS(F81, H81, fESTIVOS!$A$1:$A$18)) -> 2
A82: JESUS PEÑA | B82: GD772-50 Actualización Guía depuración de inconsistencias | C82: Cambiar archivo descarble de la tipologia " 11 Conciliación y Depuración de inconsistencias de aportes" | D82: FINALIZADO | E82: 45602 | F82: 45602 | H82: 45603 | I82: =IF(ISBLANK(H82), NETWORKDAYS(F82, TODAY(),fESTIVOS!$A$1:$A$18), NETWORKDAYS(F82, H82, fESTIVOS!$A$1:$A$18)) -> 2 | J82: 45603 | K82: 45603 | L82: *07/11/2024 En paso a produccion
A83: Requerimiento salud nativo | B83: Requerimiento salud nativo | C83: Warning en gestion del caso | D83: FINALIZADO | E83: 45576 | F83: 45576 | H83: 45604 | I83: =IF(ISBLANK(H83), NETWORKDAYS(F83, TODAY(),fESTIVOS!$A$1:$A$18), NETWORKDAYS(F83, H83, fESTIVOS!$A$1:$A$18)) -> 19 | L83: *12/11/2024 se correguen en la estibilización del sistema.
A84: DANILO RAMIREZ | B84: Reporte de caida del servidor | C84: Verificación de procesos y recoleccion de evidencias | D84: FINALIZADO | E84: 45602 | F84: 45602 | G84: 45603 | H84: 45603 | I84: =IF(ISBLANK(H84), NETWORKDAYS(F84, TODAY(),fESTIVOS!$A$1:$A$18), NETWORKDAYS(F84, H84, fESTIVOS!$A$1:$A$18)) -> 2
A85: DANILO RAMIREZ | B85: Oficina virtual (nuevo portal) | C85: Preparar sitio para paso a producción | D85: EN PROCESO | E85: 45587 | F85: 45587 | H85: 45603 | I85: =IF(ISBLANK(H85), NETWORKDAYS(F85, TODAY(),fESTIVOS!$A$1:$A$18), NETWORKDAYS(F85, H85, fESTIVOS!$A$1:$A$18)) -> 12 | L85: *22/10/2024 solicitar creación de tablas en producción *23/10/2024 continuar con la adaptación del sitio, DNS funcional *24/10/2024 continuara con la preparación apuntando a test *24/10/2024 Queda montado el sitio en la url de producción hace falta las claves para el recaptcha. *25/10/2024 Liyibet envio solicitud de las claves del recapcha *29/10/2024 Pendiente aprobación de jiras a producción y la entrega del Recapchat *31/10/2024 Recapchat implemtendo, pendiente control de cambios *05/11/2024 Ejecutar los insert del restos de los formularios y cambiar la url de test a producción. *06/11/2024 Pendiente la creación de 2 tipologías una nacional y otra internacional (descripción muy larga) - pendiente ejecución del control de cambios MDSB-700129 *07/11/2024 control de cambios ejecutado y se ajusta tipología con descripción de la tiologia
A86: LUIS BAYONA | B86: GD772-30 Informe cuentas médicas 472 ( Informe de prefactura) | C86: Cargue de Excel y validaciones entre tablas | D86: EN PRODUCCION | E86: 45569 | F86: 45572 | G86: 0 | H86: 45581 | I86: =IF(ISBLANK(H86), NETWORKDAYS(F86, TODAY(),fESTIVOS!$A$1:$A$18), NETWORKDAYS(F86, H86, fESTIVOS!$A$1:$A$18)) -> 7 | J86: 45587 | K86: 45609 | L86: *04/10/2024 Pendiente socializar req * 08/10/2024 entregara 9 de octubre *09/10/2024 adaptar lógica * 10/10/2024 pruebas locales entrega 10 am 11/10/2024 Solicitud de control de cambios a test MDSB-687277 *15/10/2024 debe ajustar el SQL para solicitar otro control de cambios ya que el MDSB-687277 presento error. *16/10/2024 subira ajuste a test 16 de octubre *17/10/2024 Debe validar encolamiento y la vista del imforme en el aplicativo. *22/10/2024 Debe finalizar ajustes indicados por Jenry. *24/10/2024 se debe solicitar cotrol de cambios en produccion. *25/10/2024 Se adjunta documento de pruebas de imagine alGD772-30 *07/11/2024 Control de cambios ejecutado 6 de noviembre, se realizara paso a produccion despues del paso de portales salud. *12/11/2024 Se debe realizar despliegue a produccion *13/11/2024 paso a produccion realizado el 12 de noviembre en la tarde.
A87: DANILO RAMIREZ | B87: MDSB-670944 REENVIO DE CORREO CUENTA NOVEDADES | D87: FINALIZADO | E87: 45596 | F87: 45596 | H87: 45608 | I87: =IF(ISBLANK(H87), NETWORKDAYS(F87, TODAY(),fESTIVOS!$A$1:$A$18), NETWORKDAYS(F87, H87, fESTIVOS!$A$1:$A$18)) -> 7 | L87: *31/10/2024 se realiza Validación y se evidencia que la cuenta esta inhabilitada, Se realizara nueva validación del reenvió después de que la cuenta este activa nuevamente . *06/11/2024 La cuenta ya se encuentra habilitada para realizar nuevamente la validación del reenvió. *12/11/2024 Reinicia Validación. *13/11/2024 Danilo realiza pruebas y la cuenta esta funcionado correctamente, se debe validar codigo desde nativo. se asignara a Johan para su validación.
A88: DANILO RAMIREZ | B88: HABILITAR PERMISOS EN DEV PARA S3 | C88: Habilitar permisos en las carpetas de dev | D88: FINALIZADO | E88: 45601 | F88: 45601 | H88: 45608 | I88: =IF(ISBLANK(H88), NETWORKDAYS(F88, TODAY(),fESTIVOS!$A$1:$A$18), NETWORKDAYS(F88, H88, fESTIVOS!$A$1:$A$18)) -> 5 | L88: *06/11/2024 Validar como dar permiso definitivo a las carpetas para el ingreso a dev. *13/11/2024 se va a realizar cambio de disco por tanto no se realizara modificaciones.
A89: JHOAN QUICENO | B89: ESTABILIZACIÓN DEL SISTEMA. | C89: Ajustar busqueda de casos por secuencia y cronograma | D89: FINALIZADO | E89: 45608 | F89: 45608 | H89: 45609 | I89: =IF(ISBLANK(H89), NETWORKDAYS(F89, TODAY(),fESTIVOS!$A$1:$A$18), NETWORKDAYS(F89, H89, fESTIVOS!$A$1:$A$18)) -> 2 | K89: 45609
A90: JHOAN QUICENO | B90: Resoluion de jiras Incidencias | C90: MDSB-700537 Cargue de adjunto al caso 29831254 | D90: FINALIZADO | E90: 45602 | F90: 45602 | H90: 45603 | I90: =IF(ISBLANK(H90), NETWORKDAYS(F90, TODAY(),fESTIVOS!$A$1:$A$18), NETWORKDAYS(F90, H90, fESTIVOS!$A$1:$A$18)) -> 2 | L90: *07/11/2024 se realizara el cargue en compañía de Jenry *08/11/2024 Jenry realiza en cargue del documento.
A91: JAIRO NIÑO | B91: Envió de correo de notificaciones de pago cuentas médicas (Respuesta glosa Adición de 5 correos) | D91: EN PRODUCCION | E91: 45336 | F91: 45336 | H91: 45470 | I91: =IF(ISBLANK(H91), NETWORKDAYS(F91, TODAY(),fESTIVOS!$A$1:$A$18), NETWORKDAYS(F91, H91, fESTIVOS!$A$1:$A$18)) -> 90 | J91: 45470 | K91: 45610 | L91: *02/10/2024 pasara a producción con el portal *03/10/2024 pendiente pasar código a producción, el control de cambios ya esta realizado *13/11/2024 realizo estbilización de rama y se realizara paso a produccion 13 de noviembre *14/11/2024 en produccion
A92: DANILO RAMIREZ | B92: REQUERIMIENTO GD772-45,CLARITY Y ANALYTICS EN OFICINA VIRTUAL | C92: Implementación ambiente en dev | D92: EN PRODUCCIÓN | E92: 45545 | F92: 45546 | H92: 45609 | I92: =IF(ISBLANK(H92), NETWORKDAYS(F92, TODAY(),fESTIVOS!$A$1:$A$18), NETWORKDAYS(F92, H92, fESTIVOS!$A$1:$A$18)) -> 43 | J92: 45609 | K92: 45610 | L92: *12/09/2024 A la espera de la confirmación del dominio de desarrollo de la plataforma. *07/11/2024 Colocar rama en clarity *08/11/2024 implementado dev *13/11/2024 Se corrigio administración de Clarity y validara si se estan generando estadisticas. *14/11/2024 realizo cambio de url e implementación en test. *15/11/2024 Realiza paso a producción el 14 de noviembre.
A93: JHOAN QUICENO | B93: ESTABILIZACIÓN DEL SISTEMA. | C93: CONSULTAS POR NIT | D93: EN PRODUCCIÓN | E93: 45610 | F93: 45610 | I93: =IF(ISBLANK(H93), NETWORKDAYS(F93, TODAY(),fESTIVOS!$A$1:$A$18), NETWORKDAYS(F93, H93, fESTIVOS!$A$1:$A$18)) -> 419 | K93: 45611 | L93: *15/11/2024 Se desplegara a test *18/11/2024 se pasa ajuste directamente a produccion debido aque test no esta habilitado, se realiza prueba con el nt 800216345 y se pueden consultar los casos correctamente.
A94: DANILO RAMIREZ | B94: Cambio carta de autorizacion de pago de beneficiario diferente a tomador en reembolsos | D94: FINALIZADO | E94: 45615 | F94: 45615 | H94: 45615 | I94: =IF(ISBLANK(H94), NETWORKDAYS(F94, TODAY(),fESTIVOS!$A$1:$A$18), NETWORKDAYS(F94, H94, fESTIVOS!$A$1:$A$18)) -> 1 | L94: *19/11/2024 Liyibet comparte carta para produccion *19/11/2024 Implementación realizada.
A95: JHOAN QUICENO | B95: ESTABILIZACIÓN DEL SISTEMA. | C95: Generar listado de usuarios para reasignación (Validar con Leidy cuales de esos usuarios deben salir en reasignación) | D95: FINALIZADO | E95: 45610 | F95: 45610 | H95: 45610 | I95: =IF(ISBLANK(H95), NETWORKDAYS(F95, TODAY(),fESTIVOS!$A$1:$A$18), NETWORKDAYS(F95, H95, fESTIVOS!$A$1:$A$18)) -> 1
A96: JHOAN QUICENO | B96: ESTABILIZACIÓN DEL SISTEMA. | C96: informe de pendientes ARL arroja información de masivos | D96: FINALIZADO | E96: 45609 | F96: 45609 | H96: 45610 | I96: =IF(ISBLANK(H96), NETWORKDAYS(F96, TODAY(),fESTIVOS!$A$1:$A$18), NETWORKDAYS(F96, H96, fESTIVOS!$A$1:$A$18)) -> 2 | L96: *14/11/2024 Se escala jira MDSB-705234 para ajustar la vista. *18/11/2024 Ya no se registra información de masivos y aun se detectan lineas corridas a la derecha. *20/11/2024 Se debe incluir la actividad.
A97: JHOAN QUICENO | B97: Error de masivos en producción, no pasa del punto 4 al usuario 1013628744 para la tipología aviso incumplimiento | D97: FINALIZADO | E97: 45615 | F97: 45615 | H97: 45615 | I97: =IF(ISBLANK(H97), NETWORKDAYS(F97, TODAY(),fESTIVOS!$A$1:$A$18), NETWORKDAYS(F97, H97, fESTIVOS!$A$1:$A$18)) -> 1 | L97: *19/11/2024 Se aumenta el limit en PHP.
A98: DANILO RAMIREZ | B98: ESTABILIZACIÓN DEL SISTEMA. | C98: Está permitiendo radicar casos sin adjuntar los soportes en el portal de Arl Ejemplo: 29907461 | D98: FINALIZADO | E98: 45610 | F98: 45610 | H98: 45610 | I98: =IF(ISBLANK(H98), NETWORKDAYS(F98, TODAY(),fESTIVOS!$A$1:$A$18), NETWORKDAYS(F98, H98, fESTIVOS!$A$1:$A$18)) -> 1 | L98: *18/11/2024 pediente validar a profuncidad la incidencia ya que se realizan pruebas y no permite la radicación sin adjuntos
A99: DANILO RAMIREZ | B99: Caida del servidor | C99: Revisar los servicios activos de FTP, para evaluar si hay usuarios haciendo uso del servicio. | D99: FINALIZADO | E99: 45614 | F99: 45614 | H99: 45618 | I99: =IF(ISBLANK(H99), NETWORKDAYS(F99, TODAY(),fESTIVOS!$A$1:$A$18), NETWORKDAYS(F99, H99, fESTIVOS!$A$1:$A$18)) -> 5 | L99: *19/11/2024 Inicia validación 18 de noviembre. *22/11/2024 Enviar correo con las ulr de la reunion del 21 de noviembre y otro reportando lo que se le han echo al servidor.
A100: JAIRO NIÑO | B100: Error en la tabla facturas pendientes para la radicación de Country. | D100: EN PRODUCCION | E100: 45621 | F100: 45621 | H100: 45621 | I100: =IF(ISBLANK(H100), NETWORKDAYS(F100, TODAY(),fESTIVOS!$A$1:$A$18), NETWORKDAYS(F100, H100, fESTIVOS!$A$1:$A$18)) -> 1 | J100: 45621 | K100: 45621 | L100: *25/11/2024 en Pruebas locales y se sube a produccion
...

Sheet fESTIVOS
A1: 45292 | B1: Año Nuevo
A2: 45299 | B2: Día de los Reyes Magos
A3: 45376 | B3: Día de San José
A4: 45379 | B4: Jueves Santo (Semana Santa)
A5: 45380 | B5: Viernes Santo (Semana Santa)
A6: 45413 | B6: Día del Trabajo
A7: 45425 | B7: Día de la Ascensión
A8: 45446 | B8: Corpus Christi
A9: 45453 | B9: Sagrado Corazón
A10: 45474 | B10: San Pedro y San Pablo
A11: 45493 | B11: Día de la Independencia
A12: 45511 | B12: Batalla de Boyacá
... A53: 46381 | B53: Navidad

Sheet ASISTENCIA
A1: ASISTENCIA DAYLI
A3: INTEGRANTE | B3: 45596 | C3: 45597 | D3: 45601 | E3: 45602 | F3: 45603 | G3: 45604 | H3: 45608 | I3: 45609 | J3: 45610 | K3: 45611 | L3: 45614 | M3: 45615 | N3: 45616 | O3: 45617 | P3: 45618 | Q3: 45621 | R3: 45622 | S3: 45623 | T3: 45624 | U3: 45625 | V3: 45628 | W3: 45629 | X3: 45630 | Y3: 45631 | Z3: 45632 | AA3: 45635 | AB3: 45636 | AC3: 45637 | AD3: 45638 | AE3: 45639 | AF3: 45642 | AG3: 45643 | AH3: 45644 | AI3: 45645 | AJ3: 45646 | AK3: 45649 | AL3: 45650 | AM3: 45652 | AN3: 45653 | AO3: 45656 | AP3: 45656 | AQ3: 45664 | AR3: 45665 | AS3: 45666 | AT3: 45667 | AU3: 45670 | AV3: 45671 | AW3: 45672 | AX3: 45673 | AY3: 45674 | AZ3: 45677 | BA3: 45678 | BB3: 45679 | BC3: 45680 | BD3: 45681 | BE3: 45684 | BF3: 45685 | BG3: 45686 | BH3: 45687 | BI3: 45688 | BJ3: 45691 | BK3: 45692 | BL3: 45693 | BM3: 45694 | BN3: 45695 | BO3: 45698 | BP3: 45699 | BQ3: 45700 | BR3: 45701 | BS3: 45702 | BT3: 45705 | BU3: 45706 | BV3: 45707 | BW3: 45708 | BX3: 45709 | BY3: 45712 | BZ3: 45713 | CA3: 45714 | CB3: 45715 | CC3: 45716 | CD3: 45719 | CE3: 45720 | CF3: 45721 | CG3: 45722 | CH3: 45723 | CI3: 45726 | CJ3: 45727 | CK3: 45728 | CL3: 45729 | CM3: 45730 | CN3: 45733 | CO3: 45734 | CP3: 45735 | CQ3: 45736 | CR3: 45737 | CS3: 45741
A4: DANILO RAMIREZ | B4: SI | C4: no (Dia de la familia) | D4: SI | E4: SI | F4: SI | G4: SI | H4: SI | I4: SI | J4: SI | K4: SI | L4: SI | M4: SI | N4: SI | O4: No hubo sesion | P4: SI | Q4: SI | R4: SI | S4: SI | T4: SI | U4: NO | V4: SI | W4: SI | X4: SI | Y4: SI | Z4: SI | AA4: SI | AB4: SI | AC4: SI | AD4: SI | AE4: No hubo sesión | AF4: SI | AG4: SI | AH4: SI | AI4: SI | AJ4: SI | AK4: SI | AL4: NO HUBO SESION | AM4: NO | AN4: NO | AO4: SI | AP4: NO HAY SESION | AQ4: SI | AR4: SI | AS4: NO HAY SESION | AT4: SI | AU4: SI | AV4: SI | AW4: SI | AX4: SI | AY4: NO HAY SESION | AZ4: SI | BA4: SI | BB4: SI | BC4: SI | BD4: SI | BE4: SI | BF4: SI | BG4: SI | BH4: SI | BI4: SI | BJ4: NO HAY SESION | BK4: Vacaciones | BL4: Vacaciones | BM4: Vacaciones | BN4: Vacaciones | BO4: Vacaciones | BP4: Vacaciones | BQ4: Vacaciones | BR4: SI | BS4: SI | BT4: SI | BU4: SI | BV4: SI | BW4: SI | BX4: SI | BY4: SI | BZ4: SI | CA4: SI | CB4: SI | CC4: SI | CD4: SI | CE4: SI | CF4: SI | CI4: No hobo sesion por caida de los sitios. | CS4: SI
A5: JAIRO NIÑO | B5: SI | C5: SI | D5: SI | E5: SI | F5: SI | G5: SI | H5: SI | I5: SI | J5: SI | K5: SI | L5: Vacaciones | M5: Vacaciones | N5: Vacaciones | O5: Vacaciones | P5: Vacaciones | Q5: SI | R5: SI | S5: SI | T5: SI | U5: SI | V5: SI | W5: SI | X5: SI | Y5: SI | Z5: SI | AA5: SI | AB5: SI | AC5: SI | AD5: SI | AF5: SI | AG5: SI | AH5: SI | AI5: SI | AJ5: SI | AK5: SI | AM5: SI | AN5: SI | AO5: SI | AQ5: Vacaciones | AR5: Vacaciones | AT5: Vacaciones | AU5: Vacaciones | AV5: Vacaciones | AW5: Vacaciones | AX5: Vacaciones | AZ5: Vacaciones | BA5: SI | BB5: SI | BC5: SI | BD5: SI | BE5: SI | BF5: SI | BG5: SI | BH5: SI | BI5: SI | BK5: SI | BL5: SI | BM5: SI | BN5: SI | BO5: SI | BP5: SI | BQ5: SI | BR5: SI | BS5: SI | BT5: SI | BU5: SI | BV5: SI | BW5: SI | BX5: SI | BY5: SI | BZ5: SI | CA5: SI | CB5: SI | CC5: SI | CD5: SI | CE5: SI | CF5: SI | CS5: SI
A6: JESUS PEÑA | B6: SI | C6: SI | D6: SI | E6: SI | F6: SI | G6: SI | H6: SI | I6: SI | J6: SI | K6: Dia de la familia | L6: SI | M6: SI | N6: SI | O6: No hubo sesion | P6: SI | Q6: SI | R6: SI | S6: SI | T6: SI | U6: SI | V6: SI | W6: SI | X6: SI | Y6: SI | Z6: SI | AA6: SI | AB6: SI | AC6: SI | AD6: SI | AF6: SI | AG6: SI | AH6: SI | AI6: SI | AJ6: SI | AK6: SI | AM6: SI | AN6: SI | AO6: SI | AQ6: SI | AR6: SI | AT6: SI | AU6: SI | AV6: SI | AW6: SI | AX6: SI | AZ6: SI | BA6: SI | BB6: SI | BC6: SI | BD6: SI | BE6: SI | BF6: SI | BG6: SI | BH6: SI | BI6: SI | BK6: SI | BL6: SI | BM6: Falla electrica | BN6: SI | BO6: SI | BP6: SI | BQ6: SI | BR6: SI | BS6: SI | BT6: SI | BU6: SI | BV6: SI | BW6: SI | BX6: SI | BY6: SI | BZ6: SI | CA6: SI | CB6: SI | CC6: SI | CD6: SI | CE6: SI | CF6: SI | CS6: SI
A7: LUIS BEDOYA | B7: SI | C7: SI | D7: SI | E7: SI | F7: SI | G7: SI | H7: SI | I7: SI | J7: SI | K7: SI | L7: Dia de la familia | M7: SI | N7: SI | O7: No hubo sesion | P7: SI | Q7: SI | R7: SI | S7: SI | T7: SI | U7: SIN INTERNET | V7: SI | W7: SI | X7: SI | Y7: SI | Z7: NO | AA7: SI | AB7: SI | AC7: SI | AD7: SI | AF7: SI | AG7: SI | AH7: SI | AI7: SI | AJ7: SI | AK7: SI | AM7: SI | AN7: SI | AO7: SI | AQ7: SI | AR7: SI | AT7: SI | AU7: NO | AV7: SI | AW7: SI | AX7: SI | AZ7: SI | BA7: SI | BB7: SI | BC7: SI | BD7: SI | BE7: SI | BF7: SI | BG7: SI | BH7: SI | BI7: SI | BK7: SI | BL7: SI | BM7: SI | BN7: SI | BO7: NO | BU7: SI | BV7: SI | BW7: SI | BX7: SI
A8: JOHAN QUICENO | B8: SI | C8: SI | D8: SI | E8: SI | F8: SI | G8: SI | H8: SI | I8: SI | J8: SI | K8: SI | L8: NO | M8: SI | N8: SI | O8: No hubo sesion | P8: SI | Q8: SI | R8: SI | S8: SI | T8: SI | U8: SI | V8: SI | W8: Permiso | X8: SI | Y8: SI | Z8: SI | AA8: SI | AB8: NO | AC8: SI | AD8: SI | AF8: SI | AG8: SI | AH8: SI | AI8: SI | AJ8: SI | AK8: SI | AM8: SI | AN8: NO | AO8: SI | AQ8: SI | AR8: SI | AT8: SI | AU8: SI | AV8: SI | AW8: SI | AX8: SI | AZ8: SI | BA8: SI | BB8: SI | BC8: SI | BD8: SI | BE8: SI | BF8: SI | BG8: sin internet | BH8: SI | BI8: SI | BK8: SI | BL8: SI | BM8: SI | BN8: SI | BO8: SI | BP8: SI | BQ8: SI | BR8: SI | BS8: SI | BT8: SI | BU8: SI | BV8: SI | BW8: SI | BX8: TRABAJO HASTA HOY
A9: FABIO FORERO | B9: SI | C9: SI | D9: SI | E9: SI | F9: SI | G9: SI | H9: SI | I9: SI | J9: SI | K9: SI | L9: SI | M9: SI | N9: SI | O9: Dia de la familia | P9: SI | Q9: SI | R9: SI | S9: SI | T9: SI | U9: SI | V9: SI | W9: SI | X9: SI | Y9: SI | Z9: SI | AA9: SI | AB9: SI | AC9: SI | AD9: SI | AF9: SI | AG9: SI | AH9: SI | AI9: SI | AJ9: SI | AK9: SI | AM9: SI | AN9: SI | AO9: SI | AQ9: SI | AR9: SI | AT9: SI | AU9: SI | AV9: SI | AW9: SI | AX9: SI | AZ9: SI | BA9: SI | BB9: SI | BC9: SI | BD9: SI | BE9: SI | BF9: SI | BG9: SI | BH9: SI | BI9: SI | BK9: SI | BL9: SI | BM9: SI | BN9: SI | BO9: SI | BP9: SI | BQ9: SI | BR9: SI | BS9: SI | BT9: SI | BU9: SI | BV9: SI | BW9: SI | BX9: SI | BY9: SI | BZ9: SI | CA9: SI | CB9: SI | CC9: SI | CD9: SI | CE9: SI | CF9: SI | CS9: SI
A10: JENRY HENAO | B10: SI | C10: SI | D10: SI | E10: SI | F10: SI | G10: SI | H10: SI | I10: NO | J10: SI | K10: NO | L10: SI | M10: SI | N10: NO | O10: No hubo sesion | P10: NO | Q10: NO | R10: SI | S10: SI | T10: SI | U10: NO | V10: SI | W10: SI | X10: SI | Y10: SI | Z10: SI | AA10: SI | AB10: SI | AC10: SI | AD10: SI | AF10: SI | AG10: SI | AH10: SI | AI10: SI | AJ10: SI | AK10: NO | AM10: NO | AN10: SI | AO10: SI | AQ10: SI | AR10: SI | AT10: SI | AU10: SI | AV10: SI | AW10: SI | AX10: SI | AZ10: SI | BA10: NO | BB10: NO | BC10: NO | BD10: NO | BE10: NO | BF10: SI | BG10: SI | BH10: SI | BI10: SI | BK10: SI | BL10: SI | BM10: SI | BN10: SI | BO10: SI | BP10: SI | BQ10: SI | BR10: SI | BS10: SI | BT10: SI | BU10: SI | BV10: SI | BW10: NO | BX10: SI | BY10: SI | BZ10: SI | CA10: SI | CB10: SI | CC10: SI | CD10: SI | CE10: SI | CF10: SI | CS10: SI
A11: LIYIBET PEREZ | B11: SI | C11: SI | D11: SI | E11: SI | F11: SI | G11: SI | H11: SI | I11: SI | J11: nomina | K11: NO | L11: SI | M11: NO | N11: SI | O11: No hubo sesion | P11: SI | Q11: SI | R11: SI | S11: NO | T11: NO | U11: NO | V11: SI | W11: SI | X11: SI | Y11: SI | Z11: SI | AA11: SI | AB11: SI | AC11: SI | AD11: NO | AF11: SI | AG11: SI | AH11: SI | AI11: SI | AJ11: SI | AK11: SI | AM11: SI | AN11: SI | AO11: SI | AQ11: SI | AR11: SI | AT11: SI | AU11: NO | AV11: NO | AW11: SI | AX11: SI | AZ11: NO | BA11: SI | BB11: SI | BC11: SI | BD11: SI | BE11: NO | BF11: NO | BG11: NO | BH11: SI | BI11: SI | BK11: SI | BL11: SI | BM11: SI | BN11: SI | BO11: NO | BP11: SI | BQ11: SI | BR11: NOMINA | BS11: SI | BT11: SI | BU11: SI | BV11: SI | BW11: SI | BX11: SI | BY11: SI | BZ11: SI | CA11: SI | CB11: NO | CC11: NO | CD11: SI | CE11: SI | CF11: SI | CS11: SI
A12: WILSON APONTE | B12: SI | C12: NO | D12: SI | E12: SI | F12: NO | G12: NO | H12: SI | I12: NO | J12: SI | K12: NO | L12: SI | M12: NO | N12: NO | O12: No hubo sesion | P12: SI | Q12: NO | R12: NO | S12: NO | T12: NO | U12: NO | V12: NO | W12: SI | X12: NO | Y12: NO | Z12: SI | AA12: NO | AB12: NO | AC12: SI | AD12: NO | AF12: NO | AG12: NO | AH12: NO | AI12: NO | AJ12: SI | AK12: SI | AM12: NO | AN12: NO | AO12: NO | AQ12: NO | AR12: NO | AT12: NO | AU12: NO | AV12: SI | AW12: SI | AX12: NO | AZ12: NO | BA12: NO | BB12: NO | BC12: SI | BD12: NO | BE12: SI | BF12: NO | BG12: NO | BH12: SI | BI12: NO | BK12: NO | BL12: NO | BM12: SI | BN12: NO | BO12: NO | BP12: NO | BQ12: NO | BR12: SI | BS12: NO | BT12: NO | BU12: SI | BV12: SI | BW12: NO | BX12: NO | BY12: SI | BZ12: NO | CA12: NO | CB12: SI | CC12: NO | CD12: NO | CE12: SI | CF12: NO | CS12: NO
A13: JOHN ROLON | B13: SI | C13: NO | D13: NO | E13: NO | F13: NO | G13: NO | H13: NO | I13: NO | J13: SI | K13: NO | L13: NO | M13: SI | N13: NO | O13: No hubo sesion | P13: NO | Q13: NO | R13: NO | S13: NO | T13: NO | U13: NO | V13: SI | W13: NO | X13: NO | Y13: NO | Z13: NO | AA13: NO | AB13: NO | AC13: SI | AD13: NO | AF13: NO | AG13: NO | AH13: NO | AI13: SI | AJ13: NO | AK13: NO | AM13: NO | AN13: NO | AO13: NO | AQ13: NO | AR13: NO | AT13: NO | AU13: NO | AV13: NO | AW13: NO | AX13: NO | AZ13: NO | BA13: NO | BB13: NO | BC13: NO | BD13: NO | BE13: NO | BF13: NO | BG13: NO | BH13: NO | BI13: NO | BK13: NO | BL13: NO | BM13: NO | BN13: NO | BO13: NO | BP13: NO | BQ13: NO | BR13: NOMINA | BS13: NO | BT13: NO | BU13: NO | BV13: NO | BW13: NO | BX13: NO | BY13: NO | BZ13: NO | CA13: NO | CB13: NO | CC13: NO | CD13: SI | CE13: SI | CF13: SI | CS13: NO

Sheet Caidas del sistema
A1: Fecha Caida | B1: Hora Inicio | C1: Hora Fin | D1: Duración | E1: Mesa de crisis | F1: Observaciones
A2: 45793 | B2: 0.38333333 | C2: 0.46527778 | D2: =C2-B2 -> 0.081944444 | E2: SI | F2: El balanceador se quedo sin Ips, se creo un nuevo cidr vinculado a la misma etc para extender las ips
A3: 45817 | B3: 0.44236111 | C3: 0.45069444 | D3: =C3-B3 -> 0.0083333333 | E3: SI | F3: 504 Gateway Time-out INC-SOFTWARE-Imagine-MASTER - MDSB-827224
A4: 45817 | B4: 0.63263889 | C4: 0.64791667 | D4: =C4-B4 -> 0.015277778 | E4: SI | F4: La conexión SSH se ha terminado con un error. Razón: Clase de error: Desconexión SSH local (LocalSshDisconn), CPor la aplicación (ByApplication), Mensaje: FlowSshPacketDecoder: tiempo de espera por falta de respuesta.

Sheet pruebas i
A1: Asignado | B1: Requerimiento | C1: Actividad | D1: ESTADO | E1: F.Asignado | F1: Fecha inicio | G1: F. estimada de entrega | H1: Finalizado | I1: Dias | J1: TEST | K1: PRODUCCION | L1: Observacion
A2: LUIS BAYONA | B2: Encolar informe de efectividad de salud | D2: FINALIZADO | E2: 45567 | F2: 45567 | G2: 45568 | H2: 45569 | I2: =IF(ISBLANK(H2), NETWORKDAYS(F2, TODAY(),fESTIVOS!$A$1:$A$18), NETWORKDAYS(F2, H2, fESTIVOS!$A$1:$A$18)) -> 3 | J2: 45572 | L2: *02/10/2024 inicia gestion. *03/10/2024 Finalizar la consulta y realizar pruebas * 07/10/2024 desarrollo en test para pruebas
A3: FABIO FORERO | B3: VULNERABILIDADES BAJAS | C3: Web Server Allows Password Auto-Completion | D3: PENDIENTE | E3: 45575 | H3: 0 | I3: =IF(ISBLANK(H3), NETWORKDAYS(F3, TODAY(),fESTIVOS!$A$1:$A$18), NETWORKDAYS(F3, H3, fESTIVOS!$A$1:$A$18)) -> 0 | J3: 45569 | L3: *04/10/2024 pruebas * 07/10/2024 se entrega a Danilo para pruebas y posterior despliegue a producción * 09/10/2024 Confirmar entrega de rama a Danilo * 10/10/2024 Etregadas a Danilo 9 de octubre,
A4: FABIO FORERO | C4: Autocomplete Enabled (15 Y 18) | D4: PENDIENTE | E4: 45575 | H4: 0 | I4: =IF(ISBLANK(H4), NETWORKDAYS(F4, TODAY(),fESTIVOS!$A$1:$A$18), NETWORKDAYS(F4, H4, fESTIVOS!$A$1:$A$18)) -> 0 | J4: 45569 | L4: *04/10/2024 pruebas * 07/10/2024 se entrega a Danilo para pruebas y posterior despliegue a producción * 09/10/2024 Confirmar entrega de rama a Danilo * 10/10/2024 Etregadas a Danilo 9 de octubre
A5: FABIO FORERO | B5: VULNERABILIDADES MEDIAS | C5: Internal Server Error | D5: PENDIENTE | E5: 45575 | H5: 0 | I5: =IF(ISBLANK(H5), NETWORKDAYS(F5, TODAY(),fESTIVOS!$A$1:$A$18), NETWORKDAYS(F5, H5, fESTIVOS!$A$1:$A$18)) -> 0 | J5: 45569 | L5: *04/10/2024 pruebas * 07/10/2024 se entrega a Danilo para pruebas y posterior despliegue a producción * 09/10/2024 Confirmar entrega de rama a Danilo * 10/10/2024 Etregadas a Danilo 9 de octubre
