Workbook

Sheet EN PROCESO (Bolivar)
A1: Asignado a | B1: Jira Caja | C1: Requerimiento | D1: Descripcion req | E1: Actividad | F1: ESTADO | G1: % Avance | H1: Dias estimados desarrollo | I1: F.Asignado | J1: Fecha inicio | K1: Fecha estimada de entrega | L1: Finalizado | M1: Dias total desarrollo | N1: Fecha compromiso cliente | O1: TEST | P1: PRODUCCION | Q1: OBSERVACIONES | R1: VISIBLE | S1: Prioridad | T1: Jira TEST | U1: jira PROD | V1: Rama | W1: Seguimiento 5 mayo | X1: seguimiento 7 mayo | Y1: seguimiento 9 mayo | Z1: seguimiento 9 mayo 2 | AA1: seguimiento 12 mayo | AB1: seguimiento 14 mayo | AC1: seguimiento 15 mayo | AD1: seguimiento 16 mayo | AE1: seguimiento 19 mayo | AF1: seguimiento 21 mayo | AG1: seguimiento 23 mayo | AH1: seguimiento 26 mayo | AI1: seguimiento 28 mayo | AJ1: seguimiento 30 mayo | AK1: seguimiento 4 Junio | AL1: seguimiento 6 Junio | AM1: seguimiento 9 Junio | AN1: seguimiento 11 Junio | AO1: seguimiento 13 Junio | AP1: seguimiento 16 Junio | AQ1: seguimiento 18 Junio | AR1: seguimiento 20 Junio | AS1: seguimiento 25 Junio | AT1: seguimiento 26 Junio | AU1: seguimiento 27 Junio | AV1: seguimiento 01 de Julio | AW1: seguimiento 02 de Julio | AX1: seguimiento 04 de Julio | AY1: seguimiento 07 de Julio | AZ1: seguimiento 08 de Julio | BA1: seguimiento 09 de Julio | BB1: seguimiento 10 de Julio | BC1: seguimiento 11 de Julio | BD1: seguimiento 14 de Julio | BE1: seguimiento 15 de Julio | BF1: seguimiento 16 de Julio | BG1: seguimiento 17 de Julio | BH1: seguimiento 18 de Julio | BI1: seguimiento 21 de Julio | BJ1: seguimiento 23 de Julio | BK1: seguimiento 23 de Julio 2 | BL1: Column 61 | BM1: Column 62 | BN1: Column 63 | BO1: Column 64
A2: DANILO | B2: INTERNO-D001 | C2: Radicación Express con IA ( SALUD ) | F2: PRUEBAS CLIENTE | G2: 90 | H2: =IF(OR(J2="",K2="",K2<J2),0,NETWORKDAYS(J2,K2,fESTIVOS!$A$2:$A$53)) -> 40 | I2: 45715 | J2: 45715 | K2: 45775 | L2: 45734 | M2: =IF(OR(J2="",AND(L2="",TODAY()<J2),AND(L2<>"",L2<J2)),0, IF(L2="", NETWORKDAYS(J2,TODAY(),fESTIVOS!$A$2:$A$53), NETWORKDAYS(J2,L2,fESTIVOS!$A$2:$A$53) ) ) -> 14 | O2: 45734 | Q2: 28/02/2025: modificó el script para entrenar con lenguaje natural; el modelo propio (basado en Verner) reconoce respuestas rápidas (ej. segunda opinión médica) tras retirar el destilado. Es ligero y responde rápido. Planea ajustar, subir a dev/test y usar una base preentrenada para optimizar. 03/03/2025: El viernes 28 se subieron las modificaciones a un repositorio, pero aún falta un cambio que planea terminar y desplegar hoy, tras ajustes adicionales que retrasaron el despliegue inicial a dev y test. 04/03/2025: Ajustó el algoritmo del modelo (impresión y entrenamiento) el día anterior, subiendo los cambios al repositorio, pero falta un ajuste en el API para desplegarlo, ya que se alojará en un servidor distinto al de Oficina Virtual por limitaciones de capacidad; espera terminarlo pronto. 05/03/2025: No ha avanzado más en Radicación Express por priorizar el API de Recobros; habló con Jenry sobre cambios adicionales y planea retomarlo tras finalizar el API esta semana. 06/03/2025: Trabajó en una modificación para Radicación Express, pero no la finalizó por requerir más cambios; no dio más detalles ni avances significativos. 07/03/2025: Se detiene ya que se dedicara al API de recobros. 10/03/2025: Detenido ya que se encuentra trabajando en la Lectura de incapacidadaes por Python 12/03/2025 : Si es posible y se da el espacio en la sesion de presentación del API de recobros se realizara presentación de este requerimiento. 14/03/2025: Ayer se presentó el avance del proyecto al cliente y Se realizó un ajuste en la implementación, cambiando el modelo de multi-language a una versión en español para mejorar el rendimiento. Este cambio impactó parcialmente el entrenamiento, pero se espera recuperar la estabilidad durante la semana. 17/03/2025: El viernes avanzó en Radicación Express, resolviendo problemas menores, y ajustó la lógica para llevar al usuario al segundo o tercer paso tras confirmar; hoy sigue dedicado a esto, ajustando los datos enviados al formulario para finalizar esa parte. 18/03/2025: Terminó la integración del formulario de Radicación Express con autorizaciones médicas, autocompletando datos (ciudad, IPS, médico) si están completos o dejando en el primer paso si no; hoy subirá los cambios tras reunirse con Jenry para validar o ajustar. 19/03/2025: Desplegó Radicación Express en test, pero enfrentó problemas de capacidad en el servidor para entrenar el modelo (100 registros fallaron); ajustó el entrenamiento a un registro cada 15 minutos, logrando 3-4 ejemplos ayer, y hoy seguirá entrenando y ajustando. 20/03/2025:Verificó el modelo ayer, ajustó un fallo donde Python mataba el proceso a la mitad, y continuó el entrenamiento (pocos ciclos aún); hoy planea alcanzar 100 ciclos con registros diferentes. 21/03/2025: Revisó el entrenamiento del modelo, que ya superó 100 ejemplos sin problemas ayer; hoy seguirá monitoreando y avanzando en el entrenamiento 27/03/2025: El modelo ya se entrenó con los casos previos y reconoce información; hoy buscará tiempo para añadir 200 registros más para entrenar entre hoy y mañana. 28/03/2025: Ayer no adiocno 28/03/2025: No revisada ayer por falta de tiempo; hoy planea agregar 500 registros para entrenar y retomar el avance. 31/03/2025: El viernes agregó 173 ejemplos más (total 473 casos); el modelo entrena bien, reconoce 4 de 5 casos con léxico colombiano; hoy o mañana terminará esta tanda y planea sumar 500 registros más. 01/04/2025: Ayer insertó nuevos registros para entrenar el modelo esta semana. 09/04/2025: Entrenado con 800 casos, listo en test para pruebas por Santiago o usuarios; hoy se entregará oficialmente para pruebas por el cliente, con entrenamiento continuo; estiman 8 días para producción si se prioriza. 03/09/2025: Se corrigieron errores recientes y se entregó una nueva versión a Santiago. Se encuentra en proceso de validación, 27/02/2026: Hasta la fecha no se ha obtenido respuesta del cliente. | R2: False | V2: Se entrega para TEST | AU2: 1
A3: DANILO | B3: INTERNO-D002 | C3: Lectura de incapacidades por Python | F3: FINALIZADO | G3: 100 | H3: =IF(OR(J3="",K3="",K3<J3),0,NETWORKDAYS(J3,K3,fESTIVOS!$A$2:$A$53)) -> 64 | I3: 45702 | J3: 45702 | K3: 45797 | L3: 45713 | M3: =IF(OR(J3="",AND(L3="",TODAY()<J3),AND(L3<>"",L3<J3)),0, IF(L3="", NETWORKDAYS(J3,TODAY(),fESTIVOS!$A$2:$A$53), NETWORKDAYS(J3,L3,fESTIVOS!$A$2:$A$53) ) ) -> 8 | Q3: 14/02/2025 Se encuentra ajustando cambio de OCR para minimizar el tiempo de lectura realizando entrenamiento. 17/02/2025 Se realizo cambio de OCR, y pruebas 18/02/2025 ajustar un modelo diferente a ollama para mejorar la lectura del OCR. 19/02/2025 Continuara con los ajustes 20/02/2025 Realizar ajustes para hacer una entrega parcial hoy 21/02/2025 En pruebas de entrenamiento al nuevo modelo. 24/02/2025 Organizar datos y consultas e implementarlos en el entrenamiento del modelo para posteriormente pasar a produccion. 25/02/2025 Se adelanta las consultas par la construccion del dataset para entrenar el modelo (Bert), despues de terminar la construccion serla a los ambientes y comenzar con el entrenamiento. 26/02/2025 Se re ealiza despliegue a produccion el 25 de febrero, se realizara una modificacion en el dataset desplegarla a produccion para que se encuentre lista para usar, realizar pruebas e iniciar entrenamiento en las noche. 26/02/2025: Se suben a produccion las modificaciones y al iniciar el entrenamiento del modelo se presentaron varios inconveniestes encuanto a nombres de facientes y fechas con la data de produccion para lo cual se debio ajustar el dataset. 27/02/2025:se le daran tres ciclos de incapacidades y a medio dia validar cual fue el nivle de aprendizaje. 28/02/2025:Culminó una etapa del modelo, entrenándolo con 2 ciclos (20 registros cada uno), logrando identificar nombre del paciente, fechas y número de incapacidades. Planea entrenar con un dataset más grande en la noche (por uso de RAM) y mejorar la clasificación con datos existentes 04/03/2025: Ayer ajusto los scripts de entrenamiento para que esta semana se pueda entrenar más rápido el modelo. 05/03/2025: Las últimas modificaciones se subieron el viernes 28 de febrero, el modelo se entrena en la noche y los fines de semana cada 6 horas con dataset construido dos horas antes; revisará resultados la próxima semana para evaluar el entrenamiento. 10/03/2025; Se encuentra realizando validaciones a los resutados del entrenamiento de la semana anterior y mejorando el regex mientras el modelo mejora su entrenamiento. 11/03/2025: Está trabajando en un tab para el portal de incapacidades que muestre la información leída por el modelo de IA; planea avanzar lo más posible hoy o terminarlo, sin bloqueos ni dudas reportadas. 12/03/2025: Ya se encuentra ajustado el algorimo de la lectura y se guarda la información en una tabla para mostrar la información extraida en el aplicativo de incapacidades, hoy se ajustara la vista para mostrar la información en la consulta de incapacidades. 13/03/2025: Ayer finalizó una vista para mostrar la información procesada por el modelo de IA, con ajustes adicionales completados; hoy espera definir prioridades tras una reunión de las 9 a.m. 14/03/2025: Se presentó el avance del proyecto a un grupo de personas, generando gran interés Se resolvieron dudas sobre la tecnología y se trabajará en una versión más completa. 18/03/2025: No está trabajando activamente en esto; el modelo se entrena en la noche con un dataset de imágenes, pero con pocos casos aún para mejorar efectividad, y planea revisar pronto el porcentaje de precisión. 28/03/2025: No le dedicó tiempo ayer; hoy buscará agregar más registros para entrenar el modelo. 01/04/2025: Revisó el modelo ayer; avanza poco, pero ajustó el entrenamiento para que sea más rápido sin afectar el servidor; entrena cada 6 horas los fines de semana para aprovechar recursos. 09/04/2025: Entrenado lentamente por recursos limitados (pocos ciclos para no afectar el servidor); lleva 15-20 días así, hoy revisarán su efectividad para decidir si ajustar o buscar alternativas. | R3: TRUE | AB3: Se correra un comando para revisar el estado de lectura de incapacidades, medir el avance del entrenamiento y validar los resultados obtenidos. | AE3: No se pudo validar completamente el avance debido a una caída del servidor ocasionada por falta de direcciones IP, un problema que no había ocurrido anteriormente, validara hoy el avance | AF3: El 19 de mayo,Se modifico el OCR para mejorar la lectura y confirma que ha alcanzado una efectividad del 85% | AI3: Falta un detalle menor para terminar la integración de la información extraída sobre incapacidades. Planea cerrarlo hoy. | AJ3: El 28 de mayo Se implementó la ejecución automática de solicitudes de incapacidades a partir de la lectura con IA. Se visualiza en una pestaña separada para mostrar resultados al cliente. Se discutió que, aunque Bolívar no usa actualmente los datos extraídos, la información será útil para validaciones futuras. | AN3: Los porcentajes de efectividad no superan el 50 % en pruebas recientes. En casos revisados, los valores más comunes rondan el 37 %, incluso en incapacidades actuales. Se recomienda revisar la calidad de los documentos fuente y optimizar la lógica de extracción | AO3: No se ha podido validar el rendimiento del modelo | AR3: entrenamiento fines semana | AU3: 27/06/2025:Pendiente validacion de efectividad en la lectura y ajuste del OCR para disminuir el consumos de recusos.
A4: DANILO | B4: GD772-103 | C4: Paso de documentos de fs a s3 | D4: Fecha de entrega al clente: 10/11/2025 | F4: CANCELADO | G4: 95 | H4: =IF(OR(J4="",K4="",K4<J4),0,NETWORKDAYS(J4,K4,fESTIVOS!$A$2:$A$53)) -> 3 | I4: 45701 | J4: 45762 | K4: 45768 | L4: 45799 | M4: =IF(OR(J4="",AND(L4="",TODAY()<J4),AND(L4<>"",L4<J4)),0, IF(L4="", NETWORKDAYS(J4,TODAY(),fESTIVOS!$A$2:$A$53), NETWORKDAYS(J4,L4,fESTIVOS!$A$2:$A$53) ) ) -> 25 | O4: 45939 | Q4: 19/02/2025 se tuvo sesion Con Juan Angel para validar como hacer la copia de los documentos y se definio un orden para hacer las trasferencias, se programara la tarea para el 20 de Febrero y se validara el 21 de febrero el resultado 21/02/2025 La tarea programada para la trasferencia de las imagenes se ejecuto ayer 20 de febrero y hoy se realizara la validación de resultados. 24/02/2025 Se realizó la validación, pero no se evidenciaron resultados. Se consultará con la persona encargada para determinar la razón por la cual la transferencia no fue exitosa 26/02/2025 Se radica ticket MDSB-770619 solicitando apoyo para ejecutar la transferencia de archivos desde el disco FS hacia el bucket S3. 27/02/2025 El Ticket MDSB-770619 escalado a bolivar solicitando apoyo para ejecutar la transferencia de archivos desde el disco FS hacia el bucket S3 se en cuentra en estado en proceso. 28/02/2025 El Ticket MDSB-770619 escalado a bolivar solicitando apoyo para ejecutar la transferencia de archivos desde el disco FS hacia el bucket S3 se en cuentra en estado en proceso. 04/03/2025 No hay avances ni respuestas al ticket MDSB-770619 sobre el paso de documentos; 11/03/2025: Se comenta el ticket MDSB-770619 solicitando avances en la solicitud o si se requiere alguna información adicional o algún ajuste de nuestra parte para avanzar con la sincronización. 13/03/2025: A un no se obtiene avances del progreso del ticket MDSB-770619. 28/03/2025: Depende de Bolívar para transferir archivos; no hay avances locales por ahora. 02/04/2025: Ayer Infraestructura de Bolivar realizo la sincronizacion del primer directorio Sincronización de /opt/storage/img04/arp, e indican que seguiran migrando los directorios en las noches ya que generan afectacion en el servidor. 03/04/2025: Hoy infraestructura informa la fecha tentativa de finalizacion es el 4 de abril. el dia de hoy estan terminando la carpeta IMG02 04/04/2025: el 3 de abril en la noche se detuvo la transferencia de documentos debido a que ocaciono la caida del servidor a 10:52 pm. 07/04/2025: Confirman finalizacion del paso de documentos, Se solverificar que el tamaño del disco S3 corresponda al mismo del FS. 09/04/2025: De acuerdo a la sesion con infraestructura de bolivar se Construira plan de paso Fs a S3, hoy se pasa el faltante y se expone el s3 a producción. 10/04/2025 se confirma paso de toda la informacion MDSB-770619 01/10/2025: Se tiene previsto iniciar el trabajo de migración alrededor del 15 de octubre. Actualmente infraestructura ya realizó una transferencia hacia un repositorio intermedio (“grandote”), pero es necesario garantizar que la información también se replique en nuestro entorno para validar la integridad de los datos. Se sugiere solicitar a infraestructura un avance formal del estado de la migración, dado que el proceso lleva aproximadamente un mes en ejecución. El equipo considera importante iniciar desde ya la planeación de las pruebas de validación para asegurar que la transferencia se haya completado de manera correcta y sin pérdida de información. 06/10/2025: Se estima un tiempo de implementación de aproximadamente una semana, considerando revisión de sincronizaciones y definición del punto de partida 08/10/2025: Entre el 6 y 7 de octubre se avanzó en el mapeo de campos relacionados con las rutas de almacenamiento (campo BAT) y en la normalización de URLs para garantizar la correcta transferencia de archivos. Se detectaron registros fuera de estándar que serán reportados. Se implementa la lógica para transferencias diarias y eliminación de archivos con más de 90 días, con trazabilidad mediante logs. Se acordó definir una variable de entorno para el almacenamiento híbrido (local y S3), asegurando compatibilidad en los visores y consultas de archivos. 09/10/2025: Se escala control de cambios a test MDSB-907732 para la creación del esquema auditoria y de la tabla auditoria.verificacion_efs_s3. Control de cambios ejecutado con exito. 09/10/2025: Se escala control de cambios a Producción MDSB-907823 para la creación del esquema auditoria y de la tabla auditoria.verificacion_efs_s3. 10/10/2025: Durante los días anteriores se avanzó en múltiples tareas asociadas al requerimiento. Se implementó y probó con éxito la lógica de sincronización diaria de los archivos del día anterior, con un tiempo promedio de ejecución de 6 minutos. Se desarrolló e implementó la lógica para eliminación automática de archivos del disco FS con más de 90 días de antigüedad, validada en el entorno PRUN mediante pruebas exitosas. Se ajustó la lógica de consulta de archivos desde las aplicaciones, la cual ya se encuentra funcional. Se creó un control de certificación de migración, que valida la existencia de los archivos en S3 15/10/2025: El proceso de migración se encuentra finalizado en un 95 %. Falta aprobación del control de cambios para ejecutar las pruebas en producción y completar la verificación de registros. El script de validación está implementado y funcional. 17/10/2025: A la espera de la aprobación de control de cambios para ejecutar los scripts en producción y validar la integridad de la información migrada. 20/10/2025: En espera de aprobación del control de cambios por parte del QA (Ricardo) para poder continuar con la sincronización de archivos 24/10/2025: El control de cambios se ejecutó correctamente en el ambiente de producción; sin embargo, se evidenció que faltan los permisos necesarios para acceder a la tabla. 27/10/2025: Se escala control de cambios MDSB-918655 para los permisos requeridos. 29/10/2025: Control de cambios MDSB-918655 ya obtuvo las aprovaciones necesarias para avanzar, se estima sea incluido en el comité de cambios digitales de hoy, una vez ejecutado se continuará con la verificación y validación de las imágenes transferidas. 05/11/2025: Control de cambios MDSB-918655 ejwcutado con exito el 29 de octubre, a hoy no se 11/11/2025: Requerimiento cancelado según instrucción de la gerencia de Imagine. | R4: FALSE | S4: 0 | T4: MDSB-907732 | U4: MDSB-907823 / MDSB-918655 | AB4: verificar la transferencia de archivos, ya que se completó la transferencia de los documentos faltantes | AD4: Validara la cantidad de documentos tranferidos y dara respuesta al correo | AE4: se revisó la transferencia de archivos, donde se detectaron diferencias que fueron comentadas en el jira. | AF4: Implementara logica para el conteo de imagenes y se prepara para realizar el cambio del disco el jueves 22 de mayo a las 6pm | AG4: El 21 de mayo se implementó una lógica para el conteo de archivos transferidos, como parte de la preparación para el paso a producción programado para el lunes 26 de mayo. Las pruebas realizadas el 22 de mayo permitieron validar el montaje del FS en una unidad alternativa, lo cual ofrece flexibilidad para intervenir manualmente en caso de archivos faltantes o fallidos. Infraestructura será responsable de la transferencia de los registros faltantes durante el fin de semana, con posibilidad de apoyo nuestro si es necesario. | AH4: Se avanzó en los conteos correspondientes a img04. Se espera consolidar los resultados en el transcurso del día para dar respuesta formal con evidencias a los correos correspondientes. | AI4: El conteo de datos para FS y S3 sigue pendiente. se planea terminar hoy el conteo y compartir evidencias para análisis, el paso a produccion sigue pendiente. | AJ4: El 28 de mayo se termina el conteo y se envian evidencias, pendiente confirmación de Bolivar | AO4: Se ajustaron fechas para realizar un nuevo reconteo de archivos transferidos | AR4: Para el viernes 20 de junio se programo Ventana de mantenimiento a las 5 pm para realizar paso a producción. | AS4: 25/06/2025: El viernes 20 de junio se intentó realizar el paso a producción, pero no fue exitoso, ya que al momento de cargar archivos el sistema no lo permitía debido a temas de permisos que no pudieron resolverse en ese momento,Por esta razón, fue necesario reversar la implementación.Se estima realizar nuevamente el paso a producción el día jueves 26 de junio. | AT4: 26/06/2025: Se programa paso a producción el día miércoles 2 de julio de 10:00 a 11:00 pm. | AW4: 02/07/2025: Para hoy esta programado el paso a producción a las 10 Pm. | AX4: 04/07/2025: El paso programado para el 2 de julio no fue exitoso debido aque se presentaron dificultades al levantar el servicio, Bolivar propone clonar la máquina actual para probar configuraciones antes hacer el paso a producción. Se acordó que la máquina estaría lista para pruebas el lunes 7 de julio, con la realización de estas programadas para el martes 8 de julio. | BA4: 09/07/2025:Ayer 8 de junio se recibió el ambiente con S3 para pruebas de parte del cliente, se confirmó que la copia es fiel a producción realizando pruebas básicas de navegación. Se planea probar el montaje completo con S3 y revisar si el problema de bloqueo persiste al montar EBS. | BB4: 10/07/2025:Se escala solicitud MDSB-844713 para habilitar el acceso a la instancia de pruebas_s3 para validar localmente la implementación de los discos, antes del paso a producción. | BC4: 11/07/2025: Pendiente respuesta del ticketMDSB-844713 ya que el bloqueo impide validar completamente las aplicaciones. Mientras tanto, se ha avanzado con otras tareas técnicas en ese entorno. | BD4: 14/07/2025: El viernes 11 de julio se supero el bloqueo de red que impedía comunicación con el puerto 80, lo cual permitió avanzar en el montaje del EC3. Se identificó un problema con el RECAPTCHA debido a que este está configurado para un dominio específico, y en el ambiente actual se está usando una IP directa, Se continuará en lo posible de solucionar y comenzar a realizar pruebas. | BF4: 16/07/2025: Se continúa con las pruebas y estabilización del S3 y el EBS. Ayer se intentó actualizar Apache, lo que obligó a reinstalar el sistema operativo por incompatibilidad de librerías. Se realizó la restauración del sistema para continuar con las pruebas hoy. Se está evaluando si el EBS es viable dado que su integración obliga a actualizar todo el sistema operativo. | BG4: 17/07/2025: Se aplican las actualizaciones necesarias para corregir el problema con el disco EBS pero la actualización no concluyó como se esperaba, nuevamente los discos en el ambiente de pruebas, manteniendo una estructura lógica diferente a la anterior | BH4: 18/07/2025: El 17 de julio se realizaron pruebas satisfactorias en el ambiente de pruebas S3. Se planea continuar con pruebas de rendimiento simulando entre 40 y 80 sesiones activas para validar el comportamiento similar al entorno productivo. Se espera finalizar hoy para liberar el ambiente y continuar con otras tareas como la actualización de Apache. | BI4: 21/07/2025: El viernes 18 de julio se realizaron pruebas de carga y funcionales, corrigiendo errores detectados. Se entregó informe y el ambiente quedó listo para el paso a producción. Se identificó mejora en la latencia desde FPM. Se requiere confirmación del cliente para la fecha de paso a producción. | BJ4: 23/07/2025: Se realizara paso a produccion 23 de julio a las 10 pm | BK4: 25/07/2025: El día miércoles 23 de julio se realizó un despliegue exitoso al entorno S3. Sin embargo, el 24 de julio fue necesario revertir los cambios debido a fallos de rendimiento detectados tras la implementación. Se requiere evaluar la capacidad actual del servidor y documentar lo ocurrido, con el fin de identificar las causas del problema y definir acciones correctivas que garanticen la estabilidad del sistema en futuros despliegues. | BM4: 30/07/2025:El proceso se encuentra en pausa hasta que se defina el método para el traspaso de imágenes
A5: DANILO | B5: GD772-64 | C5: Api de recobros | F5: DETENIDO CLIENTE | H5: =IF(OR(J5="",K5="",K5<J5),0,NETWORKDAYS(J5,K5,fESTIVOS!$A$2:$A$53)) -> 0 | I5: 45712 | J5: 45715 | L5: 45723 | M5: =IF(OR(J5="",AND(L5="",TODAY()<J5),AND(L5<>"",L5<J5)),0, IF(L5="", NETWORKDAYS(J5,TODAY(),fESTIVOS!$A$2:$A$53), NETWORKDAYS(J5,L5,fESTIVOS!$A$2:$A$53) ) ) -> 7 | Q5: 24/02/2025 Retomara esta tarea que estaba asignada a Jhoan. 26/02/2025 se encuentra pendiente hasta terminnar el desarrollo de la lectura de incapacidadaes por Python 27/02/2025: Se intentara leer las URLs prefirmadas en T3. y revisar si lo que Joan desarrollo sirve o si se necesita crear una implementación distinta para que funcione bien. 28/02/2025: Avanzó en pruebas; las URL prefirmadas funcionan, pero faltan credenciales completas (Access Key ID y Secret Access Key) para permisos. Dejó un comentario al respecto en el ticket MDSB-766368. 03/03/2025: El viernes se recibe respuesta a un ticket relacionado con credenciales de usuario y una URL prefirmada. Validó que las credenciales funcionaran y logró resolver el tema del usuario quedando pendiente Implementar la URL prefirmada (o listado de URLs) en la consulta exitosa. 04/03/2025: Avanzó configurando el ambiente en su máquina y revisando la lógica del API; hoy planea implementar el consumo de URLs prefirmadas y dejarlo listo si es posible. 05/03/2025 ajustó la recepción de parámetros y consultas del API, corrigiendo errores como la confusión entre siniestro y cédula, y añadió claves "not found" para identificar imágenes no disponibles en S3; falta terminar la consulta de facturas y revisar un PATH en tipologías, planeando compartir resultados de incapacidades hoy a las 10 y avanzar en facturas. 05/03/2025: No permite conectar al ambiente de desarrollo por el Administrador de Sesiones de AWS se radica ticket MDSB-774334 06/03/2025: Ayer por la mañana tuvo problemas de acceso al ambiente por un agente, pero en la tarde probó los cambios en incapacidades, generando URLs prefirmadas con claves "found" y "not found" (código 200), indicando imágenes no disponibles en S3; hoy planea avanzar en facturas, revisar tipologías y un posible Paht. 07/03/2025: Estandarizó consultas corrigiendo errores de sintaxis y añadió una validación para mostrar un mensaje genérico en errores 500 (con logs internos detallados); ya funciona la búsqueda de facturas, y hoy ajustará y compartirá la búsqueda de tipologías que usa la tabla Nexos para URLs prefirmadas. 10/03/2025: El viernes 7 de marzo finalizo el requerimiento y reslizo entrega al cliente para pruebas. 12/03/2025 : Se escala solicitud MDSB-778771 implementar un control de acceso al dominio de imaginex-dev-recobros.segurosbolivar.com.para que únicamente se permita la comunicación desde los siguientes orígenes: API Gateway de AWS Seguros Bolívar Refactoring ARL: SegurosBolivar-Bienestar-ARL-DEV SegurosBolivar-Bienestar-ARL-STG SegurosBolivar-Bienestar-ARL-PROD 13/03/2025: La solicitud MDSB-778771 escalada a infraestructura se en cuentra en estado en proceso. 18/03/2025: ayer infroman que los ajustes fueron realizados. 20/03/2025: Dedicó tiempo ayer a privatizar el dominio tras un ticket previo; DEV ya funciona con reglas, y hoy solicitará el dominio de test para avanzar. 20/03/2025: Solicita dominio en el ticket MDSB-783892 21/03/2025: Ayer radicó el ticket MDSB-783892 para solicitar el dominio de test, ya que DEV funciona bien sin errores reportados, Realizara paso a test tan pronto se reciba una respuesta positiva de la solicitud. 26/03/2025: En el ticket MDSB-783892 solictan diligenciamiento de información, Danilo envia formato solicitado, confirman la generación del registro. 27/03/2025: Si todo sale bien con Autorizaciones Médicas esta mañana, por la tarde iniciará la implementación del host virtual en test. 28/03/2025: Ayer implementó el host virtual para test y validó reglas con el ticket MDSB-787645, restringiendo acceso al dominio; está avanzado, pendiente de pruebas finales. 01/04/2025:Ticket MDSB-787645 ejecutado con exito, y se escala Ticket MDSB-789767 solicitando la creación del subdominio imaginex-recobros.segurosbolivar.com. (Produccion). 03/04/2025: Bolívar detuvo el requerimiento hasta aprobar fase 2; sigue avanzando el ticket MDSB-789767 para el DNS, falta completar el formato solicitado con el dato "value" (buscará apoyo de Edgar hoy). 04/04/2025: Se resolvió el ticket MDSB-789767 pendiente para la creación del DNS en producción, aunque la funcionalidad aún no está habilitada, Esto se hizo para evitar retrasos cuando se autorice el paso a producción. | R5: FALSE
A6: DANILO | B6: INTERNO-D003 | C6: Comprimir información del body de la tabla cola_correos | F6: DETENIDO CLIENTE | H6: =IF(OR(J6="",K6="",K6<J6),0,NETWORKDAYS(J6,K6,fESTIVOS!$A$2:$A$53)) -> 0 | I6: 45747 | J6: 45747 | M6: =IF(OR(J6="",AND(L6="",TODAY()<J6),AND(L6<>"",L6<J6)),0, IF(L6="", NETWORKDAYS(J6,TODAY(),fESTIVOS!$A$2:$A$53), NETWORKDAYS(J6,L6,fESTIVOS!$A$2:$A$53) ) ) -> 295 | Q6: 01/04/2025: Ayer trabajó en comprimir el body de la tabla cola_correos; una extensión externa logró un 25-26% de compresión (32 GB en producción), pero no tiene soporte para Postgres 15.5; propuso un script en Python que reduce hasta 50%, aunque se evita depender de scripts por ser implementación adicional; sigue en evaluación. 02/04/2025: Se define que antes de implementar cualquier cambio, se debe consultar con el cliente (Bolívar). Se discutirán los resultados obtenidos y se determinará si la solución es aceptable. Se sugiere la alternativa de utilizar un trigger en la base de datos, lo que permitiría comprimir y descomprimir automáticamente los datos sin necesidad de modificaciones en el código de la aplicación. Esto simplificaría la implementación y reduciría la carga de desarrollo. 03/04/2025: De acuerdo a la sesion con Bolivar, quedó pendiente enviar la especificación técnica a Leidy para escalarla a tecnología y aprobar la solución propuesta por imagine (compresión del 25-26% o script al 50%); redactará el correo hoy con Jenry. 09/04/2025: Pendiente de confirmación de Bolívar sobre la solución propuesta; Jenny sugirió pasarlo a producción, pero requiere una implementación (1 semana estimada) | R6: FALSE
A7: JAIRO | B7: MDSB-707440/GD772-74 | C7: Portal reembolsos ARL (FLUJO YII) | F7: FINALIZADO | G7: 100 | H7: =IF(OR(J7="",K7="",K7<J7),0,NETWORKDAYS(J7,K7,fESTIVOS!$A$2:$A$53)) -> 11 | I7: 45719 | J7: 45779 | K7: 45793 | L7: 45791 | M7: =IF(OR(J7="",AND(L7="",TODAY()<J7),AND(L7<>"",L7<J7)),0, IF(L7="", NETWORKDAYS(J7,TODAY(),fESTIVOS!$A$2:$A$53), NETWORKDAYS(J7,L7,fESTIVOS!$A$2:$A$53) ) ) -> 9 | P7: 45883 | Q7: 03/03/2025: Iniciara despues de finalizar el req GD772-83 Boton Glosa parcial del total de la factura 10/03/2025; Inicia con el desarrollo. 11/03/2025 : Inicio bajando el sitio, pero no avanzó mucho debido a que Jenry le asignó otro requerimiento (Captura de datos e informe). 21/03/2025:Se iniciara con el desarrollo despues de cerrar el req GD772-72 Requerimiento Captura de datos e informe (Reembolsos). 27/03/2025: Continuará con este requerimiento tras subir GD772-72 a test; no reportó avances ayer. 28/03/2025: Iniciará hoy tras subir GD772-72 a test; no avanzó ayer. 02/04/2025: Espera reiniciar despues del medio dia con el req. 10/04/2025: Se realizaron cambios menores previos a la activación. Se planea iniciar la activación hoy del req. 11/04/2025: tiene el ambiente listo pero no ha iniciado código; espera mostrar avances esta tarde. 14/04/2025: tiene el ambiente listo pero no ha iniciado código,Informa que a un no ha reactivado el req. 11/08/2025: Aprueban control de cambios en comite de cambios digitales y se ejecutara hoy 11 de agosto a las 4:20pm 20/08/2025: El requerimiento ya fue implementado y migrado a producción el jueves 14 de agosto. Se estabilizó el viernes y quedó consolidado en la rama máster. | R7: TRUE | T7: MDSB-814902 | U7: MDSB-856139 | V7: Se retoma luego del 104 | W7: Se inicia requerimiento el 5 de mayo , en 2 semanas se entrega | X7: seguimos en el proceso | Z7: Se pausa y se da inicio a analiticia fila 56 | AA7: Se está analizando el tema de asignación por valores y explorando cómo incorporar el componente de servicios. | AB7: En el proceso de reembolsos se ha llegado a la etapa de asignación y radicación en "sí salud" | AD7: pasar pacial, solicitara cambios en test, se escala control de cambios a test MDSB-814902 | AE7: Control de cambios MDSB-814902 ejecutado el viernes 16 de mayo, está desarrollando actividades relacionadas con la radicación en salud. Se espera pasar un avance parcial pronto a tets para que Jenry pueda comenzar las pruebas de digitación | AF7: Se realiza paso a test 20 de mayo un parcial y continuara trabajando en el restante del requerimiento | AG7: Se realizaron ajustes en inconsistencias, permisos y roles. Se pasó un parcial para pruebas, y se está a la espera de validaciones para continuar con los ajustes finales. | AI7: Se está trabajando en unificar los informes de ARL con los de Reembolso Salud en una misma pestaña, Las pruebas dependen de un servicio de Bolívar que aún no está disponible | AJ7: Se creó el primer informe específico para ARL basado en los ya existentes para Reembolso Salud. Está en proceso de pruebas, | AK7: El API presenta fallas en ambiente de pruebas; según tecnología, se propondrá apuntar el sitio de test a produccion para poder llevar acabo las pruebas y autoricen el paso a produccion. Se debe considerar personalizar plantillas de respuesta para ARL. | AL7: Desarrollo ya se encuentra en test, a la espera de confirmación si el rachivo de pagos en igual al de salud. | AM7: El viernes 6 de junio se informa a Bolívar que pueden iniciar las pruebas con la implementación de la simulación del sistema SISalud, con el fin de validar el flujo completo de radicación en ausencia del entorno funcional | AN7: A la espera de habilitación del ambiente de pruebas para que Bolivar continue con las pruebas, Bolivar debe gestionar la activación para continuar. | AO7: El requerimiento sigue en ambiente de pruebas. No hay confirmación de validaciones de parte de Bolivar. | AQ7: Sigue en pruebas por Bolivar. | AU7: 27/06/2025: Se estima tiempo de entrega del resultado de las pruebas el 1 de julio por parte de bolivar | BF7: 16/07/2025: El 15 de julio el portal fue entregado al cliente para pruebas, se entregaron tanto las cartas como la funcionalidad del flujo completo. | BJ7: Cambio en las cartas | BK7: Pendiente confirmar que modificaciòn se requiere | BM7: 30/07/2025: El cliente ha dado visto bueno para realizar el paso a producción. Se procede a escalar el control de cambios MDSB-856139
A8: JESUS | B8: MDSB-780227 | C8: Duplicación de actividades en Nativo | E8: 1. comando quitar duplicados 2. Revisar la funcio´n de reasignar. 3. Revisar flujos (en nativo) | F8: FINALIZADO | G8: 100 | H8: =IF(OR(J8="",K8="",K8<J8),0,NETWORKDAYS(J8,K8,fESTIVOS!$A$2:$A$53)) -> 0 | I8: 45730 | J8: 45733 | L8: 45824 | M8: =IF(OR(J8="",AND(L8="",TODAY()<J8),AND(L8<>"",L8<J8)),0, IF(L8="", NETWORKDAYS(J8,TODAY(),fESTIVOS!$A$2:$A$53), NETWORKDAYS(J8,L8,fESTIVOS!$A$2:$A$53) ) ) -> 61 | Q8: 18/03/2025: No alcanzo a revisar la duplicación de casos; hoy analizará los radicados por buzón (flujo correcto pero con actividades duplicadas), y podría crear un comando si no encuentra la causa. 19/03/2025: Revisó ayer por la mañana la duplicación de actividades en Nativo sin encontrar errores en el código; hoy continuará investigando la causa. 20/03/2025: Se detiene para darle pioridad al req GD772-92 - Malla CUPS en Nativo. 03/04/2025: Continua detenida ya que se debe dar prioridad al Req GD772-84 Comunicaciones gestión de aportes sin afiliacion (masivos). | R8: TRUE | AP8: Retomara validación de la incidencia. | AU8: se implemento check para colocar flujo en administracion. Se identificó que el error se debía a que algunas tipologías no tenían definido el tipo de asignación como "flujo", lo que permitía la apertura de múltiples actividades para un mismo caso. Se actualizó la configuración de dichas tipologías,
A9: JESUS | B9: GD772-87 | C9: Implementar en laravel la autenticación con QR | F9: DETENIDO CLIENTE | G9: 97 | H9: =IF(OR(J9="",K9="",K9<J9),0,NETWORKDAYS(J9,K9,fESTIVOS!$A$2:$A$53)) -> 2 | I9: 45691 | J9: 45688 | K9: 45691 | L9: 45700 | M9: =IF(OR(J9="",AND(L9="",TODAY()<J9),AND(L9<>"",L9<J9)),0, IF(L9="", NETWORKDAYS(J9,TODAY(),fESTIVOS!$A$2:$A$53), NETWORKDAYS(J9,L9,fESTIVOS!$A$2:$A$53) ) ) -> 9 | O9: 45723 | Q9: 03/02/2025 Generacion de la Vista del codigo de 2 pasos en login de Bolivar 05/02/2025 Se mostraran avances para el 7 de Febrero 07/02/2025 Inicia encriptación de datos, sesion a 4pm hoy para mostrar avances en dev 10/02/2025 Quitar la autorecuperación del QR. 12/02/2025 Se sube a dev el login de laravel 21/02/2025: se debe incluir a donde se envia el correo de recuperación. 24/02/2025: se escaló el control de cambios a test con el ticket MDSB-768688. 25/02/2025: Se encuentra pendiente creacion de req caja para asociarlo al control de cambios y se de la aprobacion de QA. 28/02/2025: Pendiente creacion de requerimiento caja de parte de Bolivar, Imagine reaizara el envio del manual de usuario. 03/03/2025 : El dia viernes 28 de febrero Bolivar crea el requerimiento caja GD772-87 para adjuntarlo al control de cambios MDSB-768688 en test y continuar con el proceso. 04/03/2025: Control de cambios MDSB-768688 se encuentra en estado aprobacion QA de Bolivar. 05/03/2025: Control aprobado por QA, Control de cambios ejecutado con éxito 06/03/2025: Subió el doble factor a test ayer, pero no compara bien el código del Authenticator; sospecha confusión por claves en Develop o un fallo en la librería, y lo revisará hoy. 07/03/2025: El doble factor no valida bien el código; ayer descartó conflictos en Develop borrando registros, y hoy investigará si es la librería o el dominio compartido. 10/03/2025. El viernes 7 de marzo identifico que la hora del servidor de tets esta adelantada respecto a la hora del celular, quedo ajustado. 21/03/2025: Pendiente resultado de pruebas de Bolivar y el visto bueno para realizar paso a produccion. 26/03/2025: Bolivar informa que el resultado de las pruebas las enviaran la semana del 31 de marzo y confirman la implementación en los 2 aplicativos (Nativo y Yii) 03/04/2025:Bolivar tiene programadas para el 3 y 4 de abril con diferentes perfiles de usuario, de acuerdo al resultado solicitaran paso a producción la próxima semana. 10/04/2025: Bolívar autorizó ayer iniciarlo en test para los ambientes de Yii y nativo 25/09/2025: Deacuerdo a nuevo mentodo de autenticación propuesto por el cliente seda por cancelado este requerimiento y se iniciara el GD772-146 | R9: FALSE | T9: MDSB-768688 | U9: MDSB-849084 | AO9: Esta pendiente resultados de las pruebas de Bolivar | AR9: El 18 de Junio Bolivar informa que realizan las pruebas en test y aun realizando la exclusión de usuario (Listas blancas) se está solicitando doble factor de autenticación Se identificó que la funcionalidad de Listas Blancas no está operando correctamente desde el navegador debido al score del CAPTCHA. Como propuesta, se sugiere implementar una validación directa por cédula, eliminando la dependencia del CAPTCHA. | AS9: 24/06/2025: Jesus entrega el viernes 20 de junio ajuste de Listas blancas, el usuario activo en listas blancas se le debe omitir la solicitud del codigo de verificación. 24/06/2025: Se aplica ajuste, se confirma funcionalidad y se le notifica al cliente para su validación. | BE9: 15/07/2025: El cliente confirma la aprobación para el paso a producción; sin embargo, la ejecución queda pendiente de definir la fecha, ya que se requiere realizar previamente la divulgación al equipo de trabajo, y por parte de Imagine se debe solicitar control de cambios en produccion. | BF9: solicitar control de cambios
A10: JESUS | B10: GD772-87 | C10: Implementar en Yii y Nativo la autenticación con QR | F10: DETENIDO CLIENTE | G10: 97 | H10: =IF(OR(J10="",K10="",K10<J10),0,NETWORKDAYS(J10,K10,fESTIVOS!$A$2:$A$53)) -> 0 | I10: 45761 | J10: 45761 | L10: 45771 | M10: =IF(OR(J10="",AND(L10="",TODAY()<J10),AND(L10<>"",L10<J10)),0, IF(L10="", NETWORKDAYS(J10,TODAY(),fESTIVOS!$A$2:$A$53), NETWORKDAYS(J10,L10,fESTIVOS!$A$2:$A$53) ) ) -> 7 | O10: 45771 | Q10: 14/04/2025: Se estima iniciar con la implementación tras terminar con los ajustes del req GD772-84. 05/09/2025: En pruebas con nuevos usuarios se identificó un error: el mismo código no funciona en las tres plataformas, obligando a generar múltiples claves. Este comportamiento no se presentó en fases de prueba inicial. Se solicitó revisión técnica. 17/09/2025:El cliente informa que se requiere adicionar un segundo método de autenticación, similar al utilizado para la recuperación de clave 25/09/2025: Deacuerdo a nuevo mentodo de autenticación propuesto por el cliente seda por cancelado este requerimiento y se iniciara el GD772-146 | R10: FALSE | T10: MDSB-768688 | U10: MDSB-849084 | AB10: Bolivar reporta 2 halazgo en la pruebas. | AF10: El 20 de mayo se realiza ajuste en la recuperación de codigo y queda pendiente la inclusion de lsitas blancas tan pronto se ajuste el modulo en yii. | AG10: continúa ajustando la lógica para excluir la validación de listas blancas en el doble factor. | AH10: Se finalizó e implementó exitosamente en TES la funcionalidad pendiente de lista blanca relacionada con el doble factor. Este entregable ya está en ambiente de pruebas, se Realizaran pruebas de funcionamiento | AI10: El 26 de mayo Se finalizan los ajustes indiecados por Bolivar y se infroma para que realicen las pruebas. | AO10: Esta pendiente resultados de las pruebas de Bolivar | AR10: El 18 de Junio Bolivar informa que realizan las pruebas en test y aun realizando la exclusión de usuario (Listas blancas) se está solicitando doble factor de autenticación Se identificó que la funcionalidad de Listas Blancas no está operando correctamente desde el navegador debido al score del CAPTCHA. Como propuesta, se sugiere implementar una validación directa por cédula, eliminando la dependencia del CAPTCHA. | AS10: 24/06/2025: Jesus entrega el viernes 20 de junio ajuste de Listas blancas, el usuario activo en listas blancas se le debe omitir la solicitud del codigo de verificación. 24/06/2025: Se aplica ajuste, se confirma funcionalidad y se le notifica al cliente para su validación. | BE10: 15/07/2025: El cliente confirma la aprobación para el paso a producción; sin embargo, la ejecución queda pendiente de definir la fecha, ya que se requiere realizar previamente la divulgación al equipo de trabajo, y por parte de Imagine se debe solicitar control de cambios en produccion.
A11: JESUS | B11: GD772-116 | C11: Requerimiento gestión Medicamentos fase 2 - Sprint 2 | F11: FINALIZADO | G11: 100 | H11: =IF(OR(J11="",K11="",K11<J11),0,NETWORKDAYS(J11,K11,fESTIVOS!$A$2:$A$53)) -> 11 | I11: 45814 | J11: 45826 | K11: 45842 | L11: 45849 | M11: =IF(OR(J11="",AND(L11="",TODAY()<J11),AND(L11<>"",L11<J11)),0, IF(L11="", NETWORKDAYS(J11,TODAY(),fESTIVOS!$A$2:$A$53), NETWORKDAYS(J11,L11,fESTIVOS!$A$2:$A$53) ) ) -> 16 | O11: 45849 | P11: 45924 | Q11: 09/06/2025: Estimación inicial de desarrollo 9 dias 16/06/2025: Se acordó iniciar el desarrollo el 18 de junio, una vez se finalicen tareas pendientes de giras 20/06/2025:El 19 de junio finalizó el punto 2,continuara con el punto 3. 25/06/2025:El desarrollo avanza en el punto 4 de la fase 2 (creación de tipología y actividades). Se ha completado aproximadamente el 40% del requerimiento 27/06/2025: 27/06/2025: Se reporta un avance del 60%. 02/07/2025:Se avanza en un 75% del desarrollo de la Fase 2 de Medicamentos. Ya se encuentra funcional la creación individual de casos con su trazabilidad completa cuando un proveedor indica no entrega. Se han realizado pruebas exitosas en flujo y visualización. Actualmente se trabaja en la gestión masiva desde Excel para validar múltiples casos simultáneamente y asegurar la correcta apertura e identificación de cada uno. Pendiente finalizar el manejo masivo y ajustes en bandejas administrativas. 04/07/2025: El desarrollo alcanza un 85% de avance. Ya se construyó la generación de carta para proveedor nuevo. Queda pendiente recibir el modelo de carta de cancelación y completar dos botones adicionales. La validación masiva vía Excel fue pospuesta para el final 07/07/2025: Avance parcial durante el viernes 4 de julio en una nueva funcionalidad vinculada a botones de acción. Se priorizó el análisis de flujos con doble actividad y se atenderá el requerimiento de medicamentos durante la jornada de hoy, se estima entrega de desarrollo 8 de julio. 09/07/2025: El desarrollo se encuentra en su fase final, aunque ha experimentado algunos retrasos debido a revisiones relacionadas con otros temas. Actualmente, hay una duda funcional pendiente sobre el comportamiento del botón “Copiar y Reabrir Caso”, la cual está en revisión.Se solicitará el respectivo control de cambios para realizar las pruebas en el ambiente de test. 09/07/2025: Se escala control de cambios en test bajo el jira MDSB-844308. 10/07/2025: Control de cambios MDSB-844308 ejecutado con éxito. 11/07/2025: : El desarrollo fue completado y subido a TES. Se agregó retroalimentación para la carga masiva de Excel. Está pendiente desarrollar la pestaña de trazabilidad y adjuntos, que fue solicitada en reunión con el cliente. Las plantillas de correo fueron entregadas y se está integrando para las pruebas. 16/07/2025: Avanza la estabilización con enfoque en mejoras de experiencia de usuario. Faltan validaciones en gestión y pequeñas correcciones funcionales. Plantillas ya están disponibles. 18/07/2025: Se completó el flujo y ajustes hallados en las pruebas de medicamentos. 23/07/2025: Se realizaron los ajustes solicitados, los cuales incluyen la separación de vistas en pestañas para mejorar la organización de la información, así como la inclusión de botones para la gestión de casos relacionados. 30/07/2025: El día 28 de julio se realizó la entrega del desarrollo al cliente, quien iniciará el proceso de pruebas. 14/08/2025: El cliente ha dado su visto bueno para realizar el paso a producción del requerimiento. 15/08/2025: Se solicita al cliente proporcionar un listado similar al que habitualmente cargan los proveedores, preferiblemente con un volumen considerable, con el fin de realizar pruebas de carga en el aplicativo. 20/08/2025: Cliente envia Archivo solicitado. 25/08/2025: Se identificó riesgo de saturación del sistema si se procesa en línea. Se propuso implementar un proceso en segundo plano con validaciones y notificación por correo al finalizar. 29/08/2025: Se finalizan ajustes y pruebas 15/09/2025: Se escala control de cambios MDSB-890762 para producción. 22/09/2025: Control de cambios ejecutado con exito en 20 de septiembre, código revisado y listo para desplegar en producción hoy a las 5 p.m. 24/09/2025: se corrigió la URL de despliegue, pasando de consulta salud a consulta ARL. El desarrollo quedó listo para pruebas en ambiente de test y posterior despliegue a producción. 25/09/2025: Se realizo despiegue a producción el 24 de septiembre y se encuentra en estabilización... 26/09/2025: En la estabilizacion se corrigió error en producción relacionado con variables y trazabilidad de actividades. Queda pendiente definir ejecución de colas sin duplicación entre servidores para proceso de encolado de cargue masivo en la consulta de autorizaciones. 29/09/2025: Se inicia incluision de nuevas columnas al informe de de tiempos | R11: TRUE | T11: MDSB-844308 | U11: MDSB-890762 | AM11: Estimación inicial de desarrollo 9 dias | AP11: Se acordó iniciar el desarrollo el 18 de junio, una vez se finalicen tareas pendientes de giras | AQ11: Inicia desarrollo | AR11: 20/06/2025:El 19 de junio finalizó el punto 2,continuara con el punto 3. | AS11: 25/06/2025:El desarrollo avanza en el punto 4 de la fase 2 (creación de tipología y actividades). Se ha completado aproximadamente el 40% del requerimiento | AU11: 27/06/2025: Se reporta un avance del 60% | AW11: 02/07/2025: Se avanza en un 75% del desarrollo de la Fase 2 de Medicamentos. Ya se encuentra funcional la creación individual de casos con su trazabilidad completa cuando un proveedor indica no entrega. Se han realizado pruebas exitosas en flujo y visualización. Actualmente se trabaja en la gestión masiva desde Excel para validar múltiples casos simultáneamente y asegurar la correcta apertura e identificación de cada uno. Pendiente finalizar el manejo masivo y ajustes en bandejas administrativas. | AX11: 04/07/2025: El desarrollo alcanza un 85% de avance. Ya se construyó la generación de carta para proveedor nuevo. Queda pendiente recibir el modelo de carta de cancelación y completar dos botones adicionales. La validación masiva vía Excel fue pospuesta para el final | AY11: 07/07/2025: Avance parcial durante el viernes 4 de julio en una nueva funcionalidad vinculada a botones de acción. Se priorizó el análisis de flujos con doble actividad y se atenderá el requerimiento de medicamentos durante la jornada, se estima entrega de desarrollo 8 de julio. | BA11: 09/07/2025: El desarrollo se encuentra en su fase final, aunque ha experimentado algunos retrasos debido a revisiones relacionadas con otros temas. Actualmente, hay una duda funcional pendiente sobre el comportamiento del botón “Copiar y Reabrir Caso”, la cual está en revisión. Se solicitará el respectivo control de cambios para realizar las pruebas en el ambiente de test. 09/07/2025: Se escala control de cambios en test bajo el jira MDSB-844308 | BB11: 10/07/2025: Control de cambios MDSB-844308 ajecutado con exito. | BC11: 10/07/2025:El desarrollo fue completado y subido a TES. Se agregó retroalimentación para la carga masiva de Excel. Está pendiente desarrollar la pestaña de trazabilidad y adjuntos, que fue solicitada en reunión con el cliente. Las plantillas de correo fueron entregadas y se está integrando para las pruebas. | BD11: 14/07/2025: El desarrollo fue montado en TES con todas las actividades, tipologías y configuración básica. Se encuentra en etapa de estabilización y pruebas conjuntas. | BF11: 16/07/2025: Avanza la estabilización con enfoque en mejoras de experiencia de usuario. Faltan validaciones en gestión y pequeñas correcciones funcionales. Plantillas ya están disponibles. | BH11: 18/07/2025: Se completo el flujo y ajustes hallados en las prubas de medicamentos. | BJ11: 23/07/2025: Se realizaron los ajustes solicitados, los cuales incluyen la separación de vistas en pestañas para mejorar la organización de la información, así como la inclusión de botones para la gestión de casos relacionados. | BM11: 30/07/2025:El día 28 de julio se realizó la entrega del desarrollo al cliente, quien iniciará el proceso de pruebas.
A12: JESUS | B12: MDSB-1045072 | C12: Extracción histórica de Casos existentes en Nativo de los años de 2001 a 2016 | D12: Se solicita por favor una base de datos con la relación de caso, fecha de radicación, tipologia y área; de los casos correspondientes a los años de 2001 a 2016, por favor entregar la información en excel un archivo por año (la información con todos los estados, anulados, cerrados, pendientes, todo) Ejemplo de estructura esperada: CASO , FECHA DE RADICACIÓN, ÁREA DE CIERRE, TIPOLOGIA DE CIERRE (1234566) , (1/01/2001), (Administrativo), (Novedades) Por favor me confirman si se requiere crear un Jira por cada año o si en este mismo se pueden realizar entrega parciales. | F12: FINALIZADO | G12: 100 | H12: =IF(OR(J12="",K12="",K12<J12),0,NETWORKDAYS(J12,K12,fESTIVOS!$A$2:$A$53)) -> 0 | I12: 46170 | J12: 46170 | L12: 46171 | M12: =IF(OR(J12="",AND(L12="",TODAY()<J12),AND(L12<>"",L12<J12)),0, IF(L12="", NETWORKDAYS(J12,TODAY(),fESTIVOS!$A$2:$A$53), NETWORKDAYS(J12,L12,fESTIVOS!$A$2:$A$53) ) ) -> 2 | Q12: 28/05/2026: Se identificó que antes de 2016 el sistema manejaba una estructura distinta sin flujos ni tipologías para lo cual se deben ubicar casos históricos de referencia e identificar tablas relacionadas.. 02/06/2026: Los informes correspondientes a este jira ya se encuentran disponibles y a la espera de la confirmación de Jenry para hacer la entrega al cliente. 10/06/2026: Se realiza entrega a cliente de la información solicitada | R12: True
A13: JESUS | B13: INTERNO-JE050 | C13: Análisis y control de eliminación de registros y soportes de incapacidades en Imagine | D13: Se requiere identificar el origen de la eliminación de registros asociados a incapacidades y sus documentos soporte en Imagine, debido a que se han presentado casos donde la información deja de estar disponible para consulta. El objetivo es determinar qué procesos o componentes están realizando dichas eliminaciones, fortalecer los mecanismos de trazabilidad y auditoría, e implementar controles que permitan conservar la información de soportes y conocer el origen de cualquier eliminación realizada sobre los registros. | F13: FINALIZADO | G13: 100 | H13: =IF(OR(J13="",K13="",K13<J13),0,NETWORKDAYS(J13,K13,fESTIVOS!$A$2:$A$53)) -> 0 | I13: 46171 | J13: 46171 | L13: 46175 | M13: =IF(OR(J13="",AND(L13="",TODAY()<J13),AND(L13<>"",L13<J13)),0, IF(L13="", NETWORKDAYS(J13,TODAY(),fESTIVOS!$A$2:$A$53), NETWORKDAYS(J13,L13,fESTIVOS!$A$2:$A$53) ) ) -> 3 | Q13: 29/05/2026: Se realizó la validación del caso 31149409, identificando que el registro de la incapacidad había sido eliminado y posteriormente fue restaurado 02/06/2026: Durante el análisis se evidenció que el documento PDF asociado no pudo ser recuperado, debido a que la trazabilidad actual únicamente conserva información de la tabla de incapacidades y no de la tabla de soportes. Como siguiente actividad, se iniciará un barrido y análisis de las aplicaciones relacionadas con el proceso de incapacidades para identificar el origen de las eliminaciones y determinar si existen más registros afectados por esta situación. 04/06/2026: El 2 de junio se identificó una falla en el flujo antiguo de incapacidades que permitía a los usuarios eliminar registros y adjuntos ya radicados al regresar a pasos anteriores del proceso. El análisis determinó que la causa estaba asociada a la navegación posterior a la radicación y no a errores adicionales del código. Debido a la migración del proceso hacia un nuevo flujo basado en OCR y API, el módulo afectado dejó de utilizarse. | R13: True
A14: JESUS | B14: MDSB-1045076 | C14: Consolidado Cantidad de Imagenes del 2001 la 2025 | D14: Se solicita un consolidado general con la siguiente información: Teniendo en cuenta desde el 2001 hasta el 2025 y todos los productos. | F14: EN PROCESO | G14: 40 | H14: =IF(OR(J14="",K14="",K14<J14),0,NETWORKDAYS(J14,K14,fESTIVOS!$A$2:$A$53)) -> 0 | I14: 46175 | J14: 46175 | M14: =IF(OR(J14="",AND(L14="",TODAY()<J14),AND(L14<>"",L14<J14)),0, IF(L14="", NETWORKDAYS(J14,TODAY(),fESTIVOS!$A$2:$A$53), NETWORKDAYS(J14,L14,fESTIVOS!$A$2:$A$53) ) ) -> 9 | N14: 46199 | Q14: 04/06/2026: Se desarrolló un script para verificar la existencia física de archivos históricos registrados en las diferentes tablas de almacenamiento documental de Nativo. El objetivo es validar aproximadamente 25 años de información almacenada. Durante las pruebas se evidenció que consultar simultáneamente los diferentes repositorios de almacenamiento generaba tiempos de respuesta muy altos, por lo que el proceso fue optimizado para ejecutarse por períodos y consultar inicialmente únicamente el almacenamiento histórico. El resultado se genera progresivamente en archivos CSV para evitar problemas de memoria. Se verificara si el proceso actualmente en ejecución finalizó correctamente, revisar los resultados generados y continuar con la validación masiva del histórico documental. 05/06/2026: Se ajusta lalogica para la descarga del informe para que permita relacionar el numero del caso, Se programan la generaciòn de reportes, desde el 2001 al 2025. 09/06/2026: Se desarrolló un proceso para generar un inventario histórico de imágenes asociadas a casos de los últimos 25 años. El proceso consulta aproximadamente 10 u 11 tablas documentales de Nativo y genera archivos consolidados. Tras ejecutarse masivamente durante el fin de semana, se detectó una posible afectación al rendimiento del servidor, motivo por el cual la tarea fue cancelada y los resultados eliminados. Se espera realizar una reevaluaciòn de como ejecutar el proceso de extraccón para no afcectar el redimiento del servidor. 11/06/2026: Se estima entrega al cliente el 26 de junio | R14: True
A15: JESUS | B15: INTERNO-JE051 | C15: Optimización y monitoreo de colas Default PM2 | D15: Se reportó una acumulación cercana a 700 procesos pendientes en la cola principal del sistema, afectando funcionalidades críticas como el envío de correos, replicación de casos y otros procesos automáticos. La situación fue mitigada mediante el reinicio de los servicios, restableciendo el procesamiento normal. Se requiere implementar un mecanismo de monitoreo y notificación automática que alerte al equipo de soporte y desarrollo cuando la cantidad de elementos en cola supere los umbrales definidos, permitiendo actuar de manera preventiva antes de que el cliente perciba la afectación o reporte la incidencia. | F15: EN PROCESO | G15: 30 | H15: =IF(OR(J15="",K15="",K15<J15),0,NETWORKDAYS(J15,K15,fESTIVOS!$A$2:$A$53)) -> 0 | I15: 46184 | J15: 46185 | M15: =IF(OR(J15="",AND(L15="",TODAY()<J15),AND(L15<>"",L15<J15)),0, IF(L15="", NETWORKDAYS(J15,TODAY(),fESTIVOS!$A$2:$A$53), NETWORKDAYS(J15,L15,fESTIVOS!$A$2:$A$53) ) ) -> 2 | Q15: 16/06/2026: El 12 de Junio se realizó una investigación técnica sobre los problemas presentados en la cola Default. Durante el análisis se identificó que existen configuraciones nativas del Ecosystem de PM2 que permiten ejecutar múltiples procesos para una misma cola, configurar redundancia ante fallos y mejorar la resiliencia del procesamiento sin necesidad de realizar desarrollos adicionales. El objetivo es evitar bloqueos que afecten el envío de correos y otros procesos críticos. Hoy se continura con la implementarción y pruebas de configuraciones avanzadas de PM2, validar el comportamiento bajo carga, definir mecanismos de recuperación automática y complementar el monitoreo para detectar oportunamente problemas en las colas de procesamiento. | R15: True
A16: JESUS | B16: INTERNO-JE069 | C16: Validación de usuario 1065580157 no visible en tablero de efectividad de cuidado al trabajador /Drummond | D16: El cliente reporta un caso donde el usuario 1065580157 no aparece reflejado en un tablero de efectividad de cuidado al trabajador /Drummond. Se verificaron controles básicos, estados de nómina y configuraciones visibles, sin encontrar inconsistencias evidentes. | F16: FINALIZADO | G16: 100 | H16: =IF(OR(J16="",K16="",K16<J16),0,NETWORKDAYS(J16,K16,fESTIVOS!$A$2:$A$53)) -> 0 | I16: 46185 | J16: 46189 | L16: 46189 | M16: =IF(OR(J16="",AND(L16="",TODAY()<J16),AND(L16<>"",L16<J16)),0, IF(L16="", NETWORKDAYS(J16,TODAY(),fESTIVOS!$A$2:$A$53), NETWORKDAYS(J16,L16,fESTIVOS!$A$2:$A$53) ) ) -> 1 | Q16: 16/06/2026: Se identifico faltaba insertar la cedula en la tabla wf_efec_funcionarios | R16: True
A17: JESUS | B17: INTERNO-JE049 | C17: Ajuste funcional para relación de cajas físicas en aplicativo nativo - Gestión documental | D17: Se requiere realizar un ajuste sobre la funcionalidad existente en el aplicativo nativo utilizada para la relación de cajas físicas enviadas a archivo documental. Actualmente, dicha funcionalidad dejó de utilizarse desde que disminuyó el volumen del proceso de manejo de documentos físicos, motivo por el cual la trazabilidad de ubicación documental se viene gestionando mediante listados manuales externos. Debido a la necesidad de fortalecer nuevamente el control y localización de documentos físicos, se requiere reactivar y ajustar la funcionalidad existente para permitir la asociación entre los casos y las cajas archivísticas correspondientes. Objetivo del requerimiento Permitir que el aplicativo nativo registre y consulte la relación entre: Número de caso. Caja física archivística. Información documental asociada. Con el fin de: Garantizar trazabilidad documental. Facilitar la ubicación física de documentos. Evitar dependencia de archivos manuales. Mantener continuidad operativa ante cambios de personal. Ajustes requeridos El desarrollo deberá validar y ajustar la funcionalidad existente para: Permitir registrar el consecutivo o label de la caja física asociado a uno o varios casos. Consultar la caja relacionada a un caso específico. Mantener la relación histórica de cajas y casos. Validar compatibilidad con la estructura actual del proceso documental. Permitir futuras consultas operativas y de auditoría. Consideraciones técnicas y funcionales Actualmente correspondencia entrega archivos con: Consecutivo de caja. Número de caso. Documento asociado. Nombre del titular. El consecutivo de las cajas conserva una nomenclatura estándar. Existen archivos históricos que podrían utilizarse para cargue o validación inicial de información. La funcionalidad ya existía en el aplicativo nativo, por lo cual el requerimiento corresponde a un ajuste/reactivación y no a un desarrollo desde cero. Resultado esperado Contar nuevamente con una funcionalidad operativa dentro del aplicativo nativo que permita gestionar y consultar la relación de cajas físicas archivísticas asociadas a los casos documentales, garantizando trazabilidad y control de la información física almacenada. | F17: PENDIENTE | H17: =IF(OR(J17="",K17="",K17<J17),0,NETWORKDAYS(J17,K17,fESTIVOS!$A$2:$A$53)) -> 0 | M17: =IF(OR(J17="",AND(L17="",TODAY()<J17),AND(L17<>"",L17<J17)),0, IF(L17="", NETWORKDAYS(J17,TODAY(),fESTIVOS!$A$2:$A$53), NETWORKDAYS(J17,L17,fESTIVOS!$A$2:$A$53) ) ) -> 0 | R17: FALSE
A18: JESUS | B18: INTERNO-JE046 | C18: Migración y actualización de Nativo a PHP 8.5 (Local) | D18: Actualización de la infraestructura y aplicaciones del sistema Nativo para garantizar compatibilidad con Ubuntu 26 y PHP 8.5, incluyendo ajustes de seguridad, migración de librerías y corrección de funciones obsoletas para asegurar la continuidad operativa en los nuevos ambientes. | F18: FINALIZADO | G18: 100 | H18: =IF(OR(J18="",K18="",K18<J18),0,NETWORKDAYS(J18,K18,fESTIVOS!$A$2:$A$53)) -> 0 | I18: 46154 | J18: 46154 | L18: 46164 | M18: =IF(OR(J18="",AND(L18="",TODAY()<J18),AND(L18<>"",L18<J18)),0, IF(L18="", NETWORKDAYS(J18,TODAY(),fESTIVOS!$A$2:$A$53), NETWORKDAYS(J18,L18,fESTIVOS!$A$2:$A$53) ) ) -> 8 | Q18: 19/05/2026: Se avanza en el proceso de migración y actualización. La actividad se encuentra en desarrollo continuo, sujeto a validaciones técnicas y ajustes derivados de compatibilidades y actualizaciones del sistema. 21/05/2026: Se continúa trabajando en paralelo sobre la migración de los aplicativos Nativo y Bolívar hacia PHP 8.5. Se realizaron ajustes de compatibilidad en vistas y funciones, ejecución de escaneos con Rector y Cloud, resolución de conflictos entre ramas y validaciones locales con Docker. También se inició la preparación de despliegues hacia ambiente Dev para identificar posibles errores posteriores a la migración Pendiente: Ejecutar barridos finales, desplegar en ambiente y validar errores resultantes. 26/05/2026: El Viernes 22 de mayo termino la migración y desplego a desarrollo. | R18: TRUE
A19: JESUS | B19: INTERNO-JE046_1 | C19: Pruebas tecnicas de Nativo a PHP 8.5 (Desarrollo) | F19: PENDIENTE | H19: =IF(OR(J19="",K19="",K19<J19),0,NETWORKDAYS(J19,K19,fESTIVOS!$A$2:$A$53)) -> 0 | I19: 46164 | M19: =IF(OR(J19="",AND(L19="",TODAY()<J19),AND(L19<>"",L19<J19)),0, IF(L19="", NETWORKDAYS(J19,TODAY(),fESTIVOS!$A$2:$A$53), NETWORKDAYS(J19,L19,fESTIVOS!$A$2:$A$53) ) ) -> 0 | R19: faLSE
A20: JESUS | B20: INTERNO-JE047 | C20: Migración y actualización de Laravel a PHP 8.5 (Local) | F20: FINALIZADO | G20: 100 | H20: =IF(OR(J20="",K20="",K20<J20),0,NETWORKDAYS(J20,K20,fESTIVOS!$A$2:$A$53)) -> 0 | I20: 46161 | J20: 46161 | L20: 46167 | M20: =IF(OR(J20="",AND(L20="",TODAY()<J20),AND(L20<>"",L20<J20)),0, IF(L20="", NETWORKDAYS(J20,TODAY(),fESTIVOS!$A$2:$A$53), NETWORKDAYS(J20,L20,fESTIVOS!$A$2:$A$53) ) ) -> 5 | Q20: 19/05/2026: Hoy se dara Inicio a la migración del aplicativo 21/05/2026: Se continúa trabajando en paralelo sobre la migración de los aplicativos Nativo y Bolívar hacia PHP 8.5. Se realizaron ajustes de compatibilidad en vistas y funciones, ejecución de escaneos con Rector y Cloud, resolución de conflictos entre ramas y validaciones locales con Docker. También se inició la preparación de despliegues hacia ambiente Dev para identificar posibles errores posteriores a la migración Pendiente: Ejecutar barridos finales, desplegar en ambiente y validar errores resultantes. 26/05/2026: El Lunes 25 de mayo termino la migración y desplego a desarrollo. | R20: TRUE
A21: JESUS | B21: INTERNO-JE047_1 | C21: Pruebas tecnicas de Laravel a PHP 8.5 (Desarrollo) | F21: PENDIENTE | H21: =IF(OR(J21="",K21="",K21<J21),0,NETWORKDAYS(J21,K21,fESTIVOS!$A$2:$A$53)) -> 0 | I21: 46167 | M21: =IF(OR(J21="",AND(L21="",TODAY()<J21),AND(L21<>"",L21<J21)),0, IF(L21="", NETWORKDAYS(J21,TODAY(),fESTIVOS!$A$2:$A$53), NETWORKDAYS(J21,L21,fESTIVOS!$A$2:$A$53) ) ) -> 0 | R21: faLSE
A22: JESUS | B22: INTERNO-JE048 | C22: Depuración y ocultamiento de opciones de menú no utilizadas previo a migración de Nativo | D22: Se requiere identificar y ocultar en el ambiente de producción de Nativo las opciones de menú que actualmente no se encuentran en uso o presentan fallas funcionales, como parte de la preparación para la migración a la nueva tecnología. Esta acción permitirá validar con los usuarios finales si alguna opción ocultada debe ser reactivada antes del proceso de migración; de lo contrario, dichas opciones no serán consideradas en la nueva versión del sistema. | F22: PAUSADO | G22: 10 | H22: =IF(OR(J22="",K22="",K22<J22),0,NETWORKDAYS(J22,K22,fESTIVOS!$A$2:$A$53)) -> 0 | I22: 46156 | J22: 46162 | M22: =IF(OR(J22="",AND(L22="",TODAY()<J22),AND(L22<>"",L22<J22)),0, IF(L22="", NETWORKDAYS(J22,TODAY(),fESTIVOS!$A$2:$A$53), NETWORKDAYS(J22,L22,fESTIVOS!$A$2:$A$53) ) ) -> 18 | Q22: 21/05/2026: Las opciones fueron ocultadas en la migracion de PHP 8.5, pero para continuar y ocultarlas en produccion se debe esperar a tener test arriba | R22: faLSE
A23: JESUS | B23: GD772-161 | C23: Automatización actas de prevención Formato AT- 031 Agr” | D23: Fecha entrega al cliente: 1. DESCRIPCIÓN DEL REQUERIMIENTO Se requiere crear una funcionalidad que permita la creación masiva de casos a partir de adjuntos y generación de respuesta por correo electrónico certificado bajo la tipología “Formato AT- 031 Agr”. 1.2 OBJETIVO Automatizar el proceso de envío de actas 1.3 EQUIPO DE TRABAJO Nombre Área ANA MILDRED BURGOS M Innovación y Desarrollo ARL FREDY DIAZ HERRERA Gerencia ARL VANESSA ESTHER ALVAREZ R Subgerencia de Prevención ARL 2. REQUERIMIENTOS FUNCIONALES Se requiere crear una funcionalidad que permita la creación masiva de casos a partir de adjuntos y generación de respuesta por correo electrónico certificado bajo la tipología “Formato AT- 031 Agr”. 2.1 Módulo para creación de casos 2.1.1 Cargue de pdf Se requiere la creación de un módulo en el cual se pueda realizar el cargue de archivos en formato pdf de manera masiva para la creación y generación de respuesta por correo electrónico certificado bajo la tipología “Formato AT- 031 Agr”. Modelo de pdf\r\nOpción 1 - Url de Drive. En el módulo se debe poder seleccionar la tipología (Formato AT 031 Agr) y el sistema debe solicitar la url de drive para traer la información, una vez el usuario coloque la url, el sistema deberá de guardar esa url para cargues futuro y únicamente solicitar la confirmación del usuario; sin embargo en cualquier momento el usuario podrá cambiar la url de cargue. Opción 2 - Selección de carpeta. En el módulo se debe poder seleccionar la tipología (Formato AT- 031 Agr) y el sistema debe solicitar los archivos en pdf sobre los cuales se requiere la creación del caso, para lo cual el usuario deberá de seleccionar la carpeta del PC y el sistema deberá de tomar todos los pdf que registren en dicha carpeta. 2.1.1 Creación de casos Una vez cargado los pdf el sistema deberá realizar la creación de los casos con la información que está nombrado en el pdf, se propone la siguiente estructura: NIT_NOMBREEMPRESA_CRONOGRAMA_SECUENCIA_CONSECUTIVO (CANTIDAD DE HOJAS), con esta información el sistema deberá realizar la creación de los casos. Si el pdf coincide en Nit,nombre,cronograma y secuencia en dos archivos o mas, se deberá de anexar la cantidad de pdf´s a un solo caso. Los datos obligatorios para la creación del caso son: nit, nombre , cronograma y secuencia. Si hay algún dato faltante para la creación del caso, este no deberá crear y se deberá notificar el error. De deberá de notificar al usuario los casos creados con la siguiente estructura: Si no es posible la creación del caso deberá indicar el error. 2.1.2 Proforma de respuesta Esta tipología deberá tener la proforma de respuesta con los campos variables indicados (ver anexo). 2.1.2 Generación de respuesta y envío Los casos creados por esta funcionalidad, deberán generar respuesta de manera automática al cliente por correo electrónico certificado, remitiendo los adjuntos cargados y la proforma anexa a este requerimiento (ver anexo). El correo electrónico del envío se deberá leer desde el pdf cargado. Tanto la actividad de generación de respuesta como la de radicación, deberá quedar a nombre del usuario que realiza el proceso. En caso de Los envíos no deben quedar en la misma cola de los masivos, estos deben salir el mismo día de radicación.devolución el caso debe quedar en la bandeja del usuario que radicó para gestión individual.\r\n | F23: PAUSADO | G23: 90 | H23: =IF(OR(J23="",K23="",K23<J23),0,NETWORKDAYS(J23,K23,fESTIVOS!$A$2:$A$53)) -> 0 | I23: 45958 | J23: 45988 | L23: 46000 | M23: =IF(OR(J23="",AND(L23="",TODAY()<J23),AND(L23<>"",L23<J23)),0, IF(L23="", NETWORKDAYS(J23,TODAY(),fESTIVOS!$A$2:$A$53), NETWORKDAYS(J23,L23,fESTIVOS!$A$2:$A$53) ) ) -> 8 | O23: 45995 | Q23: 29/09/2025: Requerimiento aún en etapa de entendimiento. Reunión próxima con el cliente para detallar proceso y asignar responsables. 01/10/2025: El requerimiento se encuentra en etapa de análisis; hasta el momento solo se han revisado documentos y definiciones iniciales. No se han realizado desarrollos técnicos ni configuraciones. Se requiere concertar con el área de tecnología los posibles ajustes a implementar para definir un plan de trabajo. 28/10/2025: Se estima 20 dias habiles de desarrollo. 04/11/2025: Se envia al cliente las historias de usuario para validación y aprobación. 10/11/2025: Cliente confirma aceptación de las HU 27/11/2025: Se inicia con el desarrollo. 01/12/2025: El desarrollo avanzó al 35%. Ya se tienen listas las carpetas (.zip) en la ruta correspondiente y hoy se inicia el procesamiento de los activos según el requerimiento. Se estima terminar antes del tiempo inicialmente previsto. 03/12/2025: El desarrollo se encuentra en un avance aproximado del 70%. El comando ya crea los casos correctamente. Pendiente implementar lectura de PDF, extracción del correo y los pasos finales del flujo antes de completar el desarrollo. Se trabajará en ello durante el día. 05/12/2025: El desarrollo ya enlaza correctamente la lectura de PDF y la asociación de cada archivo a un caso independiente. Está listo para envío de correos certificados, pero se requiere ajustar el correo destino utilizado en Test y validar el cuerpo del correo para presentación a las 4 p.m. Solo faltan ajustes menores en visualización y pruebas finales del flujo. 10/12/2025: Se corrigieron las validaciones de nombres de archivos encontradas por Fabio. Se creó un nuevo comando para el envío de correos masivos y se logró el envío correcto utilizando la plantilla oficial. El único pendiente es guardar el correo enviado en PDF como adjunto del caso, lo cual será abordado hoy 11/12/2025: Se encuentran pendientes los siguientes ajustes: 1. Ajustar que los casos que presenten error de envío por ausencia de correo en el PDF queden asignados al usuario responsable que realizó el cargue masivo, con el fin de que pueda efectuar el envío manual correspondiente. 2. Ajustar que los casos que generen “devolución mail” queden igualmente asignados al usuario que realizó el cargue masivo, para que pueda gestionarlos manualmente. 21/01/2026: Se encuentra pausado hata que el cliente priorice el req 17/03/2026: Entre el 16 y 17 de marzo se realizaron los ajustes en la descripcion de errores y la asignacion de usuarios cuando el envio del acta falla por falta o error en el correo del pdf. El requerimiento ya se encuentra funcional. 26/03/2026: El 25 de marzo se definió la implementación de un nuevo script independiente para el proceso AT-031, con el fin de evitar sobrecarga en la vista actual de masivos y mejorar la mantenibilidad, considerando la complejidad del proceso que incluye múltiples subprocesos y colas; el desarrollo de esta solución se iniciará con el objetivo de ser entregado hoy en el transcurso de la mañana.. 31/03/2026: Se entrega desarrollo al cliente para pruebas. 12/05/2026: De acuerdo a la confirmación del cliente se realizara paso a produccion el 13 de mayo. 13/05/2026: Se pospone paso a produccion hasta tanto se tengan disponible ambientes bajos | R23: TRUE
A24: FABIO | B24: GD772-116_4 | C24: Validación en test de columnas informe medicamentos fase2 | F24: FINALIZADO | G24: 100 | H24: =IF(OR(J24="",K24="",K24<J24),0,NETWORKDAYS(J24,K24,fESTIVOS!$A$2:$A$53)) -> 0 | I24: 45938 | J24: 45938 | L24: 45946 | M24: =IF(OR(J24="",AND(L24="",TODAY()<J24),AND(L24<>"",L24<J24)),0, IF(L24="", NETWORKDAYS(J24,TODAY(),fESTIVOS!$A$2:$A$53), NETWORKDAYS(J24,L24,fESTIVOS!$A$2:$A$53) ) ) -> 6 | Q24: 16/10/2025: Se envian envidencias de los hallazgos en las pruebas realizadas al informe 17/10/2025: Se definio subir el informe a producción para vaqlidar su generación con data real. | R24: TRUE
A25: jESUS | B25: GD772-177 | C25: Mejora oficina entidades | F25: FINALIZADO | G25: 100 | H25: =IF(OR(J25="",K25="",K25<J25),0,NETWORKDAYS(J25,K25,fESTIVOS!$A$2:$A$53)) -> 0 | I25: 46001 | J25: 46002 | K25: 45970 | L25: 46009 | M25: =IF(OR(J25="",AND(L25="",TODAY()<J25),AND(L25<>"",L25<J25)),0, IF(L25="", NETWORKDAYS(J25,TODAY(),fESTIVOS!$A$2:$A$53), NETWORKDAYS(J25,L25,fESTIVOS!$A$2:$A$53) ) ) -> 6 | O25: 46009 | P25: 46021 | Q25: 10/12/2025: El equipo validará nuevamente para estimar tiempos. La actividad está en revisión inicial. 12/12/2025: El desarrollo inició el 11 de diciembre. Aunque la estimación de tiempo aún no estaba completamente definida, podría considerarse un plazo de tres días, con entrega prevista para el martes 16 de diciembre. A la fecha, ya se encuentran creadas las dos opciones de cargue: individual y masivo. 15/12/2025: Se avanzó al 50 % en el requerimiento, El objetivo es finalizar el desarrollo entre el día siguiente y, como máximo, el miércoles en la mañana, sujeto a pruebas finales. 17/12/2025: Se avanzó significativamente en el requerimiento de juntas, pasando de un 50% a un 70%. El principal cambio consiste en modificar la lógica de radicación individual a radicación masiva, lo que implicó analizar cómo generar múltiples IDs por sesión para cada registro. Se configuró la carta de notificación y se realizaron varios ajustes adicionales. El requerimiento no se finalizará hoy debido a retrasos por priorización de otras tareas, pero se espera completarlo entre la mañana. 18/12/2025: Hoy se esta validando el envio del correo de radicación Y migrando los job creados de portales a bolivar para quitarle procesos a ese servidor 19/12/2025: Se finalizó la lógica de radicación masiva de juntas, ajustando el procesamiento de jobs para evitar el envío de correos uno a uno. Actualmente, el sistema agrupa los casos y envía una notificación consolidada. La radicación y réplica funcionan correctamente. Quedan pendientes ajustes visuales menores y edición de algunos campos, ya habilitados para modificación 22/12/2025: El requerimiento de juntas se encuentra prácticamente finalizado. Se identificaron ajustes pendientes en los correos de notificación (asunto incorrecto en radicación masiva e individual) y en el refresco de variables para evitar que se reporten radicaciones anteriores. Estos ajustes se consideran menores y se acordó finalizarlos durante el día para entregar el requerimiento al cliente. 23/12/2025: El 22 de diciembre se realizo la entrega al cliente para la ejecución de sus pruebas y, posteriormente, la autorización del go para el paso a producción. 29/12/2025: Cliente reporta en horas de la tarde 4 hallazgos 1. Modificar grupo de Autorizaciones. 2. cuando se realiza el cargue de archivos de gran tamaño (aproximadamente 2 GB) y el proceso no finaliza correctamente, el sistema no genera una notificación clara ni oportuna que informe al usuario sobre el fallo del cargue 3. Durante el proceso de cargue rápido, se identifica que si un archivo aún no ha finalizado su carga y, de manera simultánea, se adjunta un documento correspondiente a otro trabajador, el sistema asocia ambos archivos al último trabajador seleccionado 4. Se requiere validar que el archivo cargado contenga únicamente dos columnas; en caso contrario, el sistema debe bloquear el proceso y mostrar un mensaje de error indicando: “El archivo no cumple el parámetro de 2 columnas.” 30/12/2025: Se resuelven hallazgos y se obtiene confirmación de paso a producción. | R25: TRUE | V25: https://github.com/Imaginesas/portales/compare/master...feature/juntasFase2?expand=1
A26: JESUS | B26: GD772-116_2 | C26: Encolar cargue de reporte de entrega efectiva mayor a 1000 registros ( Medicamentos fase 2 - Sprint 2) | D26: Se recibió un archivo con 13.000 registros para actualización masiva. Se identificó riesgo de saturación del sistema si se procesa en línea. Se propuso implementar un proceso en segundo plano con validaciones y notificación por correo al finalizar. | F26: FINALIZADO | G26: 100 | H26: =IF(OR(J26="",K26="",K26<J26),0,NETWORKDAYS(J26,K26,fESTIVOS!$A$2:$A$53)) -> 0 | I26: 45894 | J26: 45894 | L26: 45895 | M26: =IF(OR(J26="",AND(L26="",TODAY()<J26),AND(L26<>"",L26<J26)),0, IF(L26="", NETWORKDAYS(J26,TODAY(),fESTIVOS!$A$2:$A$53), NETWORKDAYS(J26,L26,fESTIVOS!$A$2:$A$53) ) ) -> 2 | O26: 45898 | Q26: 27/08/2025: desarrollo listo para las pruebas de encolamiento. 28/08/2025: Se está trabajando en la validación de las causas por las cuales no llega el correo de confirmación del cargue y la fecha de entrega no queda registrada después del proceso. 29/08/2025:Se finalizan las pruebas y ajustes en el ambiente de test relacionados con el encolamiento del reporte de no efectivos en la consulta. Se informa al cliente para que proceda con la validación correspondiente. | R26: TRUE
A27: JESUS | B27: GD772-146_4 | C27: Eliminar posibilidad en laravel de actualizar correo | D27: Por favor ingresar dentro de los pendientes esta solicitud, va relacionada al Jira doble factor de autenticación. Eliminar posibilidad de actualizar el campo correo electrónico en laravel Opción perfi / correo electrónico | F27: FINALIZADO | G27: 100 | H27: =IF(OR(J27="",K27="",K27<J27),0,NETWORKDAYS(J27,K27,fESTIVOS!$A$2:$A$53)) -> 0 | I27: 45994 | J27: 46003 | L27: 46003 | M27: =IF(OR(J27="",AND(L27="",TODAY()<J27),AND(L27<>"",L27<J27)),0, IF(L27="", NETWORKDAYS(J27,TODAY(),fESTIVOS!$A$2:$A$53), NETWORKDAYS(J27,L27,fESTIVOS!$A$2:$A$53) ) ) -> 1 | O27: 46003 | P27: 46003 | Q27: 12/12/2025: Opcion de actualización de correo elininada en test y producción | R27: TRUE
A28: jESUS | B28: GD772-177_2 | C28: Crear informe entidades (Nativo) | F28: FINALIZADO | G28: 100 | H28: =IF(OR(J28="",K28="",K28<J28),0,NETWORKDAYS(J28,K28,fESTIVOS!$A$2:$A$53)) -> 0 | I28: 46014 | J28: 46014 | L28: 46014 | M28: =IF(OR(J28="",AND(L28="",TODAY()<J28),AND(L28<>"",L28<J28)),0, IF(L28="", NETWORKDAYS(J28,TODAY(),fESTIVOS!$A$2:$A$53), NETWORKDAYS(J28,L28,fESTIVOS!$A$2:$A$53) ) ) -> 1 | O28: 46014 | P28: 46021 | Q28: 23/12/2025: Infrome en pruebas.. 29/12/2025: la semana anterior se desarrolló desde cero un nuevo informe para juntas en Nativo, reutilizando componentes centralizados previamente definidos para facilitar futuros desarrollos. | R28: TRUE
A29: FABIO | B29: INTERNO-F015 | C29: Recoleccion informacion, servicio de Olimpia, 472 y Calificación | D29: Se requiere recolectar toda la información posible que halla en el correo de los servicio de Olimpia, 472 y Calificación y almacenarla en el menu "Instructivos/ biblioteca documental tecnica" en nativo. | F29: FINALIZADO | G29: 100 | H29: =IF(OR(J29="",K29="",K29<J29),0,NETWORKDAYS(J29,K29,fESTIVOS!$A$2:$A$53)) -> 0 | I29: 46042 | J29: 46062 | L29: 46063 | M29: =IF(OR(J29="",AND(L29="",TODAY()<J29),AND(L29<>"",L29<J29)),0, IF(L29="", NETWORKDAYS(J29,TODAY(),fESTIVOS!$A$2:$A$53), NETWORKDAYS(J29,L29,fESTIVOS!$A$2:$A$53) ) ) -> 2 | Q29: 10/02/2026; El 9 de febrero se realiza la recoleccion de información y hoy se realiza el cargue en la ruta Marisopa/Instructivos/BIB_DOC_TECNICA/ARL/ DOC PROCESOS | R29: true
A30: FABIO | B30: GD772-177_3 | C30: Documentación tecnica - Mejora oficina entidades | F30: FINALIZADO | G30: 100 | H30: =IF(OR(J30="",K30="",K30<J30),0,NETWORKDAYS(J30,K30,fESTIVOS!$A$2:$A$53)) -> 0 | I30: 46022 | J30: 46064 | L30: 46064 | M30: =IF(OR(J30="",AND(L30="",TODAY()<J30),AND(L30<>"",L30<J30)),0, IF(L30="", NETWORKDAYS(J30,TODAY(),fESTIVOS!$A$2:$A$53), NETWORKDAYS(J30,L30,fESTIVOS!$A$2:$A$53) ) ) -> 1 | Q30: 31/12/2025: Se solicita a Jesus los script para generar la documentación. Script entregados por Jesus. 11/02/2026: Se realiza documentación y se carga al directorio de la Biblioteca tecnica. | R30: true
A31: JESUS | B31: MDSB-943252 | C31: Jiras día a día( El radicado que arroja el portal ARL en la radicación de autorizaciones no se visualiza en nativo. | D31: LA PAGINA WEB ESTÁ ARROJANDO UN RADICADO Y LUEGO NO APARECE “ Buenos días Solicito su colaboración, porque estoy radicando archivos por la pagina web y me arroja un radicado, luego voy a consultar ese radicado para cambiarle la tipología o asignarlo al medico encargado y no aparecen, consulto con la cedula del trabajador y me aparece el caso creado, pero con otro radicado, esto pasa desde la semana pasada, pero apenas hoy noto que es repetitivo y adjunto evidencia de dos casos en esta mañana. Cordialmente | F31: FINALIZADO | G31: 100 | H31: =IF(OR(J31="",K31="",K31<J31),0,NETWORKDAYS(J31,K31,fESTIVOS!$A$2:$A$53)) -> 0 | I31: 46000 | J31: 46001 | L31: 46009 | M31: =IF(OR(J31="",AND(L31="",TODAY()<J31),AND(L31<>"",L31<J31)),0, IF(L31="", NETWORKDAYS(J31,TODAY(),fESTIVOS!$A$2:$A$53), NETWORKDAYS(J31,L31,fESTIVOS!$A$2:$A$53) ) ) -> 7 | O31: 46009 | P31: 46020 | Q31: 10/12/2025: Se reportó un error intermitente donde el número de radicado generado no coincide con el que queda registrado en Nativo. Se presentaron tres casos recientes. El equipo identificó que el origen probablemente está en un job que se ejecuta desde Portales y podría estar produciendo inconsistencias. Jesús revisará el job para determinar si hay fallas puntuales o si puede estar afectando más usuarios de los que han reportado el problema. 12/12/2025:El 11 de diciembre se crea validación para consultar caso y así no se duplique el numero de radicado, se encuentra en test pero se presenta error la pagina en portales expirando demasiado rapido con error 419. 15/12/2025: Fabio; Se valida y a un persite el inconveniente en test. 17/12/2025: Se soluciono la conexcion a la instancia privada de test, se rpueba pero los casos no replican, se espera ayuda para subir la cola job_queue_portales en test. 18/12/2025: Se realiza prueba de radicación en test y radica bien, se debe pasar ajuste a producción 19/12/2025: El ajuste de radicación del portal está temporalmente detenido debido a una decisión arquitectónica relacionada con el manejo de colas.Se acordó centralizar la ejecución de jobs en el servidor Laravel (servidor público) y no en el servidor privado de portales, con el fin de evitar saturación, duplicidad de procesos y problemas de mantenimiento. Se requieren pruebas adicionales antes de liberar el ajuste. 29/12/2025: Se realizan paso a producción de los ajustes y se monitoreara durante el dia si se presenta un nuevo caso con error, si no se presenta se dara respuesta al Jira. Se realiza validación al final del dia y no se evidencia que se halla generado el error, por lo cual se da respuesta el jira. | R31: TRUE
A32: JAIRO | B32: GD772-100 | C32: Cambio de flujo radicación de facturas EPS | E32: Se requiere la modificación del flujo de radicación de facturas EPS, de acuerdo con el archivo anexo | F32: DETENIDO CLIENTE | H32: =IF(OR(J32="",K32="",K32<J32),0,NETWORKDAYS(J32,K32,fESTIVOS!$A$2:$A$53)) -> 0 | I32: 45757 | M32: =IF(OR(J32="",AND(L32="",TODAY()<J32),AND(L32<>"",L32<J32)),0, IF(L32="", NETWORKDAYS(J32,TODAY(),fESTIVOS!$A$2:$A$53), NETWORKDAYS(J32,L32,fESTIVOS!$A$2:$A$53) ) ) -> 0 | R32: FALSE | V32: sin cambios por parte de Bolivar | AG32: No se han recibido nuevas indicaciones sobre este requerimiento de partes de Bolivar | AP32: req fue cancelado por Bolivar
A33: JAIRO | B33: INTERNO-JA001 | C33: Mejora informe glosa req GD772-104 Campos glosa aceptada y glosa conciliación | E33: PENDIENTE | F33: FINALIZADO | G33: 100 | H33: =IF(OR(J33="",K33="",K33<J33),0,NETWORKDAYS(J33,K33,fESTIVOS!$A$2:$A$53)) -> 0 | I33: 45800 | J33: 45800 | L33: 45825 | M33: =IF(OR(J33="",AND(L33="",TODAY()<J33),AND(L33<>"",L33<J33)),0, IF(L33="", NETWORKDAYS(J33,TODAY(),fESTIVOS!$A$2:$A$53), NETWORKDAYS(J33,L33,fESTIVOS!$A$2:$A$53) ) ) -> 17 | O33: 45825 | P33: 45835 | R33: TRUE | AG33: el informe presenta limitaciones si existen más de tres Glosas, por lo que se propuso desarrollar un nuevo informe más claro y funcional. | AH33: El 23 de mayo avanzó en la construcción del informe de glosas como parte del requerimiento de valores de glosa. | AI33: No se reportan avances | AJ33: Se encuentra pausado, se prioriza la validación Informes de reembolso y colas de procesamiento | AM33: Se trabajó parcialmente el viernes 6 de Junio (avance estimado: 30 %), Faltan datos completos en los queries para continuar el desarrollo | AN33: Se ha avanzado con un script funcional; el desarrollo está en aproximadamente un 50 %. Faltan ajustes adicionales en los datos generados | AO33: Se cometió un error durante el desarrollo, pero se continúa con los ajustes. Se espera mostrar avances en la tarde. | AP33: Se realizaron pruebas exitosas en producción del nuevo informe, aunque aún no está disponible para descarga, Falta conectar correctamente el enlace que lo activa desde la interfaz del sistema | AQ33: Se ajustó la lógica del informe. Está listo para pasarse a producción entre hoy y mañana. | AR33: Se acordó pasar informe actualizado a producción el martes para no afectar la migración S3 | AS33: 25/06/2025: Aunque el nuevo informe está listo desde el viernes 20 de junio, no se ha pasado aún a producción debido a restricciones técnicas. Se planifica realizar este despliegue durante el día de hoy. | AU33: Se finalizó se pasa hoy a produccion | AW33: 02/07/2025: El informe fue pasado a producción el viernes 27 de Junio. Se ajustó ordenamiento y visibilidad por usuario. Se encuentra completamente operativo.
A34: JAIRO | B34: INTERNO-JA002 | C34: Restablecimiento de contraseña en Laravel | E34: PENDIENTE | F34: FINALIZADO | G34: 100 | H34: =IF(OR(J34="",K34="",K34<J34),0,NETWORKDAYS(J34,K34,fESTIVOS!$A$2:$A$53)) -> 0 | I34: 45800 | J34: 45813 | L34: 45835 | M34: =IF(OR(J34="",AND(L34="",TODAY()<J34),AND(L34<>"",L34<J34)),0, IF(L34="", NETWORKDAYS(J34,TODAY(),fESTIVOS!$A$2:$A$53), NETWORKDAYS(J34,L34,fESTIVOS!$A$2:$A$53) ) ) -> 16 | O34: 45813 | P34: 45835 | R34: TRUE | AG34: Se identificó un conflicto entre correos de usuarios en tablas diferentes, lo que impide el correcto restablecimiento de contraseñas. Se propone sincronizar los datos o generar mensajes de error amigables para el usuario final. | AI34: No se reportan avances | AK34: Se mencionó que es una tarea rápida: solo validar el correo y generar un mensaje en caso de error. Se iniciara ajuste hoy. | AL34: El 5 de Junio se realiza ajuste a test; Se realizan pruebas y se identifican 2 hallazgos pendiente su solución , | AM34: Se pausa debido a que en el momento no tiene acceso al entorno de pruebas (test) | AN34: Se confirmó que no se muestra el mensaje de “usuario no existe” cuando aplica. Para los usuarios nuevos que no pueden iniciar sesión después de restablecer la clave, Fabio realizara pruebas. | AS34: 25/06/2025: Pendiente realizar pruebas por Fabio | AU34: Se pasa hoy a produccion | AW34: 02/07/2025: Se realizó el despliegue a producción el día viernes 27 de junio, correspondiente al ajuste que permite actualizar la tabla de usuarios en el aplicativo Laravel al momento de crear un nuevo usuario o restablecer la contraseña.
A35: JESUS | B35: GD772-81 | C35: Calificador automático (1) | F35: DETENIDO CLIENTE | G35: 90 | H35: =IF(OR(J35="",K35="",K35<J35),0,NETWORKDAYS(J35,K35,fESTIVOS!$A$2:$A$53)) -> 3 | I35: 45772 | J35: 45775 | K35: 45777 | M35: =IF(OR(J35="",AND(L35="",TODAY()<J35),AND(L35<>"",L35<J35)),0, IF(L35="", NETWORKDAYS(J35,TODAY(),fESTIVOS!$A$2:$A$53), NETWORKDAYS(J35,L35,fESTIVOS!$A$2:$A$53) ) ) -> 277 | Q35: 13/08/2025: El 8 de agosto, el cliente reporta una incidencia en el envío físico. Tras la validación, no se evidencia el error, por lo cual se solicita una sesión para realizar una prueba conjunta y evidenciar la situación. La sesión queda programada para el 14 de agosto a las 10:00 a.m. 27/08/2025: La sesion del 14 de agosto no se llevo acabo debido a falta de casos de prueba en el ambiente de test, 22/10/2025: En reestructuración tablas AFP y EPS por parte de Paola Conde, David Prieto | R35: FALSE | V35: El miercoles se paso a TEST parte del requerimiento | W35: Se entregó a test, el vienres 2 de mayo | X35: se realizó pruebas el dia 6 de mayo | AE35: El viernes 16 de mayo Se realizaron mejoras en la parte de envío físico, mostrando información completa (dirección, teléfono, nombre, etc.) cuando el caso es físico. incluyendo el PDF de salida para nueve tipologías distintas, no solo una. También se configuró el administrador de cartas, permitiendo edición según cada tipología | AZ35: 08/07/2025: El 26 de junio el cliente envió los resultados de las pruebas, en los cuales informa que los soportes de 472 no están quedando adjuntos al caso. La validación de este comportamiento se realizará una vez se finalicen las actividades correspondientes a la fase 2 de Medicamentos. | BA35: 16/07/2025: Se retoma el requerimiento tras avanzar con medicamentos. Se planea dedicarle más tiempo esta semana para cumplir con entrega. | BD35: Iniciaa | BF35: Continua revisando | BH35: 18/07/2025: El 17 de julio se identificaron diferencias en la forma de almacenamiento de los casos certificados y problemas con un script ausente en el entorno local. Se retomará hoy con foco total en este desarrollo, se buscará ajustar el script faltante con apoyo del Jairo. | BI35: 21/07/2025: Se corrigieron errores en la asignación de usuarios y en el procesamiento de datos. Se ajustó el script para que consulte correctamente el caso padre. Falta implementar el registro de logs para asegurar trazabilidad de acciones como envío de correos o procesos automáticos. | BJ35: ajustando firma en carta y boton que muesytre casoas hijo cali | BK35: 25/07/2025: El 23 de julio se envia ajuste de los hallazgos reportados
A36: DANILO | B36: INTERNO-D004 | C36: Migración S3 y aplicaciones a EBS | F36: FINALIZADO | G36: 100 | H36: =IF(OR(J36="",K36="",K36<J36),0,NETWORKDAYS(J36,K36,fESTIVOS!$A$2:$A$53)) -> 2 | I36: 45827 | J36: 45827 | K36: 45828 | L36: 45867 | M36: =IF(OR(J36="",AND(L36="",TODAY()<J36),AND(L36<>"",L36<J36)),0, IF(L36="", NETWORKDAYS(J36,TODAY(),fESTIVOS!$A$2:$A$53), NETWORKDAYS(J36,L36,fESTIVOS!$A$2:$A$53) ) ) -> 27 | R36: TRUE | AR36: El 19 de junio inicia la migración activa de archivos y logs a nuevo almacenamiento EBS. 20/06/2025: Continua continúa con la migración y validación de servicios. | AS36: 25/06/2025: Se realizaron pruebas exitosas de carga de documentos con estructuras similares a producción. Se simularon distintos escenarios y cargas. Se espera aprobación para paso a producción el jueves, sujeto a pruebas de hoy de parte de bolivar. El componente EBS queda postergado por estabilidad. | AU36: Mejorar el rendimiento del EBS por parte de bolivar | BJ36: 23/07/2025:Durante los días anteriores se trabajó en la transferencia de aplicaciones y logs desde las instancias actuales al servicio de almacenamiento EBS y S3, como parte del proceso de migración. | BK36: 25/07/2025: El día miércoles 23 se avanzó en la organización de uno de los temas relacionados con la migración. Específicamente, se trabajó en la copia y transferencia de aplicaciones desde el entorno OPT hacia EBS. Adicionalmente, se realizó la organización del ambiente, actividad necesaria para preparar las condiciones adecuadas que permitan una migración efectiva y sin contratiempos. | BM36: 30/07/2025: Genero reporte de incidencia , esta tarea se da como finalizada para dar paso a una nueva opcion de almacenamiento hibrido.
A37: DANILO | B37: GD772-109 | C37: Lectura de nuevos datos de ordenes medicas con IA | F37: FINALIZADO | G37: 100 | H37: =IF(OR(J37="",K37="",K37<J37),0,NETWORKDAYS(J37,K37,fESTIVOS!$A$2:$A$53)) -> 0 | I37: 45785 | J37: 45791 | L37: 45972 | M37: =IF(OR(J37="",AND(L37="",TODAY()<J37),AND(L37<>"",L37<J37)),0, IF(L37="", NETWORKDAYS(J37,TODAY(),fESTIVOS!$A$2:$A$53), NETWORKDAYS(J37,L37,fESTIVOS!$A$2:$A$53) ) ) -> 123 | Q37: 11/08/2025: El viernes 8 de agosto se agregan nuevos registros para entrenamiento. Se prevé entregar esta semana un porcentaje estimado de precisión del modelo. 20/08/2025: El 15 de agosto se agregó nueva información de órdenes médicas para entrenamiento. El modelo ya alcanza más del 70% de efectividad en lecturas. Se prevé que con poca información adicional quede listo para uso. 29/08/2025: Se realizara adicion de registros para entrenamiento durante el fin de semana. 07/11/2025: Proximo a reiniciar ejecucion, Se acordó enfocar el entrenamiento en dos formatos específicos para optimizar tiempo y precisión. El ajuste se realizará tanto en la lógica como en las expresiones regulares (regex) para mejorar la identificación de los formatos. Se estima un tiempo de uno a dos días para completar los ajustes y pruebas. 11/11/2025: Requerimiento Finalizado según instrucción de la gerencia de Imagine | R37: TRUE | AA37: Se iniciara tan pronto finalice el "Reemplazo negocio Proteccion ". | AB37: Iniciara con la lectura de los nuevos datos. | AD37: Continua en el desarrollo de la logica de la lectura. | AE37: El viernes 16 de mayo alcanzo en un 30% de avance, Pretende avanzar significativamente hoy y, si no surgen nuevos inconvenientes, para finalizar mañana | AF37: Ha logrado un avance de 70 %, continuara trabajando en paralelo con Paso de documentos de fs a s3. | AG37: Se requiere ajustar el trayecto y la heurística del script de lectura de órdenes médicas, además de continuar el entrenamiento del modelo de imágenes para mejorar el reconocimiento automatizado. | AH37: Se completaron avances significativos en el ajuste del dataset y en la implementación de lógica con heurísticas y expresiones regulares. Se logró una efectividad preliminar del 52% sin entrenamiento, lo que demuestra un buen desempeño inicial del modelo. Quedan pendientes ajustes menores para iniciar el entrenamiento formal. | AI37: Está ajustando el dataset y espera avanzar significativamente en su implementación, e incluso programar el entrenamiento del modelo si es posible, ayer trabajó en organizar la tabla base para el dataset y que la heurística de extracción está entre el 39% y el 50%. | AJ37: El modelo aún no ha sido entrenado. Están pendientes pruebas previas para validar la efectividad antes de programar su entrenamiento | AK37: Pausado por Vacaciones de Danilo | AN37: retomara entre hoy y mañana un espacio de 1 a 2 horas para insertar más registros y así permitir que el sistema se entrene diariamente de forma continua. | AQ37: El modelo no ha sido entrenado aún. Se plantea insertar registros progresivamente (1.000 diarios) para alcanzar una base de 5.000, se revisara hoy | AR37: 20/06/2025: Se pausa para dar prioridad de la migración S3, se planea iniciar entrenamiento durante la proxima semana. | AU37: 27/06/2025: El fin de semana del 28 de junio se entrenara con mas de 800 registros. | AX37: 04/07/2025:Se continúa con el entrenamiento del modelo de IA. Se planea insertar aproximadamente 2.000 registros hoy para que el sistema se entrene durante el fin de semana. Debido a las limitaciones del asistente automático, el proceso de carga debe realizarse de forma incremental. | BC37: 11/07/2025: Se ingresaran mas registros para continuar con el entrenamiento. | BI37: 21/07/2025: Se pretende iniciar entrenamienro en el ambiente de contingencia (Anbiente generado para probar paso S3) | BJ37: 23/07/2025: Se está ajustando el ambiente de contingencia, el cual fue generado para realizar pruebas relacionadas con el paso a S3. Una vez finalicen los ajustes, se dará inicio al proceso de entrenamiento. | BK37: 25/07/2025: Como ya quedó ajustado el tema de la instancia, ahora será necesario agregar registros para poder continuar con el entrenamiento del modelo de órdenes médicas. | BL37: 28/07/2025: El viernes 25 se agregaron registros y se actualizó la librería Selerator para corregir incidencias. | BN37: 01/08/2025: Se planea cargar aproximadamente 10.000 registros esta semana para mejorar la efectividad del sistema.
A38: JESUS | B38: MDSB-944059 | C38: Jiras día a día( SOLICITUD HABILITAR E INHABILITAR DE 3 TIPOLOGIAS A 3 USUARIOS. | D38: : 1. favor habiiltar a JOHN ALEJANDRO MARTÍNEZ _1032366925 y a GIOVANNY STIVEN NIETO1003530364 en las tipologías Mesa de conciliacion presencial, Mesa de conciliacion Virtual y Traslado de polizas, dejar por favor las mismas actividades con las que cuenta el usuario NATALIA ROCIO CUBIDES_1007155376. 2. Por favor inhabilitar a LILIA ANDREA VELASQUEZ__1015430797 de las tipologias Mesa de conciliacion presencial, Mesa de conciliacion Virtual y Traslado de polizas, por vacaciones del funcionario. 3. Solicitamos pro favor nos puedan confirmar qué usuarios se encuentran actualmente activos en las tres tipologías: Mesa de Conciliación Presencial, Mesa de Conciliación Virtual y Traslado de Pólizas | F38: FINALIZADO | G38: 100 | H38: =IF(OR(J38="",K38="",K38<J38),0,NETWORKDAYS(J38,K38,fESTIVOS!$A$2:$A$53)) -> 0 | I38: 46002 | J38: 46003 | L38: 46003 | M38: =IF(OR(J38="",AND(L38="",TODAY()<J38),AND(L38<>"",L38<J38)),0, IF(L38="", NETWORKDAYS(J38,TODAY(),fESTIVOS!$A$2:$A$53), NETWORKDAYS(J38,L38,fESTIVOS!$A$2:$A$53) ) ) -> 1 | Q38: 12/12/2025: Se realizó la habilitación e inhabilitación de usuarios en las tipologías solicitadas. Adicionalmente, se adjunta la relación de usuarios actualmente asignados a dichas tipologías. user_actividades_desc.csv | R38: TRUE
A39: JESUS | B39: MDSB-945492 | C39: jiras dia adia ( tipología malla de asignación no funciona) | D39: Nos encontramos escalando un caso a través de imagine para la tipología 10617- Datos Contacto - Riesgo Biológico, esta tipología se encuentra parametrizada en la asignación de tipologías por malla, sin embargo al realizar la radicación del caso se evidencia que no esta asignando de acuerdo a este parámetro , se realizaron pruebas con el número de documento 1147941511 que de acuerdo a la malla se debe asignar al usuario Erika Nathaly Martinez, sin embargo lo asigna a la persona que se encuentra creada en el flujo | F39: FINALIZADO | G39: 100 | H39: =IF(OR(J39="",K39="",K39<J39),0,NETWORKDAYS(J39,K39,fESTIVOS!$A$2:$A$53)) -> 0 | I39: 46003 | J39: 46006 | L39: 46007 | M39: =IF(OR(J39="",AND(L39="",TODAY()<J39),AND(L39<>"",L39<J39)),0, IF(L39="", NETWORKDAYS(J39,TODAY(),fESTIVOS!$A$2:$A$53), NETWORKDAYS(J39,L39,fESTIVOS!$A$2:$A$53) ) ) -> 2 | Q39: 12/12/2025: Fabio: Se valida y se confirma que el NIT relacionado en el Jira no está incluido en la malla de asignación. Sin embargo, al realizar varias pruebas adicionales con NIT que sí se encuentran configurados en la malla, se evidencia que la asignación no está respetando dicha configuración. Actualmente, todos los casos están siendo asignados únicamente al usuario definido en el flujo, independientemente de la malla de asignación. 15/12/2025: Jesus iniciara validación de la incidencia reportada. 16/12/2025: Durante el análisis se identificó que, si bien la tipología se encontraba parametrizada en la asignación por malla, esta tenía activa la asignación por flujo, lo cual generaba que el sistema priorizara dicha asignación sobre la asignación por célula, provocando que los casos se direccionaran al flujo “Neli Bonet” y no al usuario definido en la malla | R39: TRUE
A40: JESUS | B40: GD772-116_3 | C40: Adicion de columnas informe medicamentos fase2 | D40: Se requiere tener informes de la operación con el que se pueda medir la prestación efectiva de cada proveedor el informe debe seguir la siguiente estructura: En este primer informe se debe poder visualizar un status actual de la operación y contendrá la siguiente estructura: | F40: FINALIZADO | G40: 100 | H40: =IF(OR(J40="",K40="",K40<J40),0,NETWORKDAYS(J40,K40,fESTIVOS!$A$2:$A$53)) -> 0 | I40: 45918 | J40: 45929 | L40: 45930 | M40: =IF(OR(J40="",AND(L40="",TODAY()<J40),AND(L40<>"",L40<J40)),0, IF(L40="", NETWORKDAYS(J40,TODAY(),fESTIVOS!$A$2:$A$53), NETWORKDAYS(J40,L40,fESTIVOS!$A$2:$A$53) ) ) -> 2 | O40: 45930 | P40: 46009 | Q40: 29/09/2025: Se Inicia con la adición de Columnas el informe de medicamentos 01/10/2025: “El informe de medicamentos se encuentra prácticamente finalizado; únicamente está pendiente una aclaración con el equipo solicitante respecto a la inclusión de la columna ‘Número de autorización’, con el fin de proceder con su cierre. 08/10/2025: Tras sesion aclaratoria con el ciente el 7 de octubre se da claridad a las columnas que finalmente se deben adicionar en el informe. El infrome es entregado para iniciar pruebas en test. 20/10/2025:Finalizan las pruebas del informe y se le informa al cliente para que realice las pruebas y autorice el paso a producción. 12/12/2025: Pendiente confirmación de paso a producción. 16/12/2025: Cliente confirma paso a producción del informe 18/12/2025: Tras solucion de la conexion a la estacia de test, se realizara paso a producción. | R40: TRUE | V40: hotfix/informeInefectivos
A41: JAIRO | B41: INTERNO-JA003 | C41: Validación Informes de cuentas medicas y colas de procesamiento | F41: FINALIZADO | G41: 100 | H41: =IF(OR(J41="",K41="",K41<J41),0,NETWORKDAYS(J41,K41,fESTIVOS!$A$2:$A$53)) -> 0 | I41: 45806 | J41: 45806 | L41: 45835 | M41: =IF(OR(J41="",AND(L41="",TODAY()<J41),AND(L41<>"",L41<J41)),0, IF(L41="", NETWORKDAYS(J41,TODAY(),fESTIVOS!$A$2:$A$53), NETWORKDAYS(J41,L41,fESTIVOS!$A$2:$A$53) ) ) -> 20 | R41: TRUE | AJ41: Aunque este informe no es problemático en tiempo de generación (menos de un minuto), su ejecución simultánea con otros puede saturar la cola. Se mantiene bajo observación para priorizar según criticidad. | AK41: A pesar de intentos de optimización con Python, los tiempos de generación siguen siendo similares No se identificaron mejoras sustanciales hasta ahora; se reconoce que el problema persiste | AL41: Se encuentra en validacion de opciones de mejora. | AM41: Debe continuar valición de los denas informes | AN41: Sin avances recientes. Se expusieron avances al jefe (Hernán), pero falta validación funcional. | AO41: Se continuará investigando otras alternativas para optimizar el proceso | AS41: 25/06/2025: Se planea optimizar tiempos de carga, actualmente afectados por el incremento de volumen de datos mes a mes. | AU41: Se finalizo la mejora del informe mas pesado, el query y se mejoro descarga de inormes en 10 seg
A42: JESUS | B42: GD772-69_4 | C42: Hacer contrato api incapacidades | F42: FINALIZADO | G42: 100 | H42: =IF(OR(J42="",K42="",K42<J42),0,NETWORKDAYS(J42,K42,fESTIVOS!$A$2:$A$53)) -> 0 | I42: 45834 | J42: 45834 | L42: 45834 | M42: =IF(OR(J42="",AND(L42="",TODAY()<J42),AND(L42<>"",L42<J42)),0, IF(L42="", NETWORKDAYS(J42,TODAY(),fESTIVOS!$A$2:$A$53), NETWORKDAYS(J42,L42,fESTIVOS!$A$2:$A$53) ) ) -> 1 | R42: TRUE
A43: JESUS | B43: INTERNO-JE005 | C43: Validaciòn CASO 31016845, no pasa de estado radicaciòn (Incapacidades) | F43: FINALIZADO | G43: 100 | H43: =IF(OR(J43="",K43="",K43<J43),0,NETWORKDAYS(J43,K43,fESTIVOS!$A$2:$A$53)) -> 0 | I43: 45846 | J43: 45848 | L43: 45848 | M43: =IF(OR(J43="",AND(L43="",TODAY()<J43),AND(L43<>"",L43<J43)),0, IF(L43="", NETWORKDAYS(J43,TODAY(),fESTIVOS!$A$2:$A$53), NETWORKDAYS(J43,L43,fESTIVOS!$A$2:$A$53) ) ) -> 1 | R43: TRUE | BB43: 10/07/2025: Se realiza apertura del flujo para continuar su gestion.
A44: DANILO | B44: GD772-69 | C44: TEST Extraccion de Imagenes ( API) (Incapacidades firmadas por apache desde el disco EFS) | F44: FINALIZADO | G44: 100 | H44: =IF(OR(J44="",K44="",K44<J44),0,NETWORKDAYS(J44,K44,fESTIVOS!$A$2:$A$53)) -> 0 | I44: 45835 | J44: 45840 | L44: 45915 | M44: =IF(OR(J44="",AND(L44="",TODAY()<J44),AND(L44<>"",L44<J44)),0, IF(L44="", NETWORKDAYS(J44,TODAY(),fESTIVOS!$A$2:$A$53), NETWORKDAYS(J44,L44,fESTIVOS!$A$2:$A$53) ) ) -> 52 | O44: 45916 | P44: 45929 | Q44: 16/09/2025: Desde el 15 de septiembre se encuentra disponible para pruebas el API de incapacidades firmadas por Apache desde el disco Amazon EFS en el ambiente TEST 24/09/2025: Se envio link con imagenes de incapacidades al cliente. 29/09/2025: Cliente confirma paso a producción y se procede con el paso. | R44: TRUE | AT44: 26/06/2025:Se escala jira MDSB-836893 con la solicitud de creación del DNS en el ambiente de TEST, Pruebas con el cliente 27 de Junio. | AW44: 02/07/2025 : Pendiente desplegar en test para validar permisos de IP y dominio. Se coordinarán pruebas desde cada estación de trabajo. | AY44: 07/07/2025: Se deben realizar validaciones sobre los tiempos de respuesta, ya que se ha evidenciado que las consultas presentan demoras en el ambiente de test, a diferencia del comportamiento observado en el ambiente DEV. 07/07/2025: Se optimizó el código y se modificó la forma de consultar y generar el recurso en S3.Anteriormente, el proceso se realizaba a través de un subproceso; ahora se utiliza una función propia de S3, lo que permitió agilizar la consulta en un 85% | AZ44: 08/07/2025: Se realiza entrega al cliente para pruebas. | BD44: 14/07/2025: El cliente ha dado el visto bueno para realizar el paso a producción; sin embargo, este se ejecutará únicamente una vez se haya completado el paso correspondiente al S3. 14/07/2025: se realiza solicitud de creaciòn del DNS en produccion MDSB-846727 | BE44: 15/07/2025: Confirman creacion del subdominio solicitado en MDSB-846727 | BF44: 16/07/2025:Se realizara hoy a las 3pm el paso a producción, pero sin habilitar consumo hasta que S3 esté listo en produccion. | BH44: 18/07/2025: Pendiente paso a produccion por falta de comunicación DNS, se escala jitar MDSB-848376 reportando incidencia. Se planea revisar hoy luego de finalizar pruebas del S3. | BK44: 22/07/2025: El 22 de julio dan respuest al jira MDSB-848376 indicando que el ajuste fue aplicado y ya permite usar el DNS.
A45: JESUS | B45: GD772-69_2 | C45: DEV Extraccion de Imagenes ( API) (Incapacidades) | F45: FINALIZADO | G45: 100 | H45: =IF(OR(J45="",K45="",K45<J45),0,NETWORKDAYS(J45,K45,fESTIVOS!$A$2:$A$53)) -> 1 | I45: 45811 | J45: 45817 | K45: 45817 | L45: 45834 | M45: =IF(OR(J45="",AND(L45="",TODAY()<J45),AND(L45<>"",L45<J45)),0, IF(L45="", NETWORKDAYS(J45,TODAY(),fESTIVOS!$A$2:$A$53), NETWORKDAYS(J45,L45,fESTIVOS!$A$2:$A$53) ) ) -> 13 | R45: TRUE | AK45: Se pausa para trabajara en Sistematización con IA (Segunda vista de incapacidades en portal) | AL45: Contunuara con el desarrollo del metodo de incapacidades despues de culminar Sistematización con IA (Segunda vista de incapacidades en portal), se estimada de entrega 9 de junio | AM45: Se iniciará hoy con el desarrollo del primer método del modelo de incapacidades, debido a que el 6 de junio dedico el dia al Sistematización con IA (Segunda vista de incapacidades en portal) | AN45: Ya se encuentran los metodos de incapacidades y medicamentos, Hoy desarrollará el servicio y completará la URL pública para pruebas desde Postman u otros medios. | AO45: El 12 de junio finalizó la lógica de firma y reestructuración del código. El API está lista, solo falta habilitar el endpoint para completar las pruebas | AP45: El metodo de incapacidades ya está listo en ambiente de desarrollo (DEV). Se creó un servicio provisional mientras se habilita la URL oficial para pruebas. | AQ45: El dominio ya está creado en DEV, pero la base de datos de imágenes no está funcionando correctamente, se acordó garantizar pruebas en DEV antes de migrar a TEST. Se cargarán imágenes de prueba. | AR45: Danilo escala jira MDSB-833779 a infraestructura debido a que se tiene acceso interno al dominio, pero externamente se recibe un error. | AS45: 25/06/2025:Actualmente solo funciona la URL secundaria (opcional) en DEV La URL principal sigue pendiente por tema de permisos. El gira MDSB-833779 aún no ha sido atendido, bloqueando la validación completa. | AT45: 26/06/2025: Jira MDSB-833779 fuen resulto con exito, se tiene funcionalidad en ambiente de dev, se escala jira Pruebas con el cliente 27 de Junio. | AU45: 27/06/2025:Fue cancelada la sesion de Pruebas por el cliente.
A46: JAIRO | B46: MDSB-707440/GD772-74_1 | C46: Generación de plantillas de cartas (glosa total, glosa parcial, devolución) Para Reembolsos ARL | F46: FINALIZADO | G46: 100 | H46: =IF(OR(J46="",K46="",K46<J46),0,NETWORKDAYS(J46,K46,fESTIVOS!$A$2:$A$53)) -> 0 | I46: 45845 | J46: 45845 | L46: 45849 | M46: =IF(OR(J46="",AND(L46="",TODAY()<J46),AND(L46<>"",L46<J46)),0, IF(L46="", NETWORKDAYS(J46,TODAY(),fESTIVOS!$A$2:$A$53), NETWORKDAYS(J46,L46,fESTIVOS!$A$2:$A$53) ) ) -> 5 | O46: 45849 | R46: TRUE | AY46: 07/07/2025 : Inicia con la generación de plantillas de cartas de respuesta (glosa total, glosa parcial, devolución), Con estas cartas finaliza el desarrolle del Portal reembolsos ARL (FLUJO YII) | BA46: 09/07/2025: Retomara desarrollo tras finalizar el Levantamiento nueva máquina virtual. | BC46: 11/07/2025: Las Plantillas ya estan listas, con inserciones preparadas, se realizara despliegue a test para realizar pruebas . | BD46: 14/07/2025: Se Realizan pruebas, pero fallaron, se estima entregar hoy antes de mediodía. | BF46: 16/07/2025: El 15 de julio el portal fue entregado al cliente para pruebas, se entregaron tanto las cartas como la funcionalidad del flujo completo.
A47: JAIRO | B47: GD772-136 | C47: Cruce automatico Autorizado Vs Cobrado | D47: Descripción Se requiere realizar el cruce automatico de lo autorizado, ya sea cargado de forma manual o por API con el lago vs lo cobrado en las facturas por el proveedor. Una vez realizada esta comparacion, los registro en los que el valor cobrado, sea igual o menor al valor autorizado, se deben asignar al usuario definido para pago masivo, Asi mismo debe permitir seleccionar todos o algunos casos, para realizar la notificacion y el cierre de caso masivo. Los caso cuyo valor cobrado es mayor al valor autorizado, deben pasar segun las reglas de asignación a los diferentes perfiles, en caso de que exista tarifa pactada, el usuario debe poder visualizar la tarifa pactada, autorizada y cobrada para su evaluacion. | F47: FINALIZADO | G47: 100 | H47: =IF(OR(J47="",K47="",K47<J47),0,NETWORKDAYS(J47,K47,fESTIVOS!$A$2:$A$53)) -> 0 | I47: 45902 | J47: 45946 | L47: 45967 | M47: =IF(OR(J47="",AND(L47="",TODAY()<J47),AND(L47<>"",L47<J47)),0, IF(L47="", NETWORKDAYS(J47,TODAY(),fESTIVOS!$A$2:$A$53), NETWORKDAYS(J47,L47,fESTIVOS!$A$2:$A$53) ) ) -> 15 | O47: 45967 | P47: 46003 | Q47: 10/09/2025: Revisión preliminar realizada. 22/10/2025: Se solicita control de cambios en test MDSB-915793 28/10/2025: Control de cambios ejecutado con éxito 21/11/2025. Se escala control de cambios a test MDSB-934083 para la creación de la tabla cm_actualizacion_facturas_sisalud y modificación de las tablas cm_pagos_masivos_generados y ctas_proveedores Control de cambios MDSB-934083 ejecutado. 26/11/2025: Se avanzó en la implementación del cruce y la construcción de las bandejas de resultado. Falta validar el comportamiento del cruce asociado a proveedores y solicitar la creación de la tabla en producción. Continúan ajustes menores previos a las pruebas finales. 27/11/2025: Se escala control de cambios en producción MDSB-937531 01/12/2025: Control de cambios aun se encuentra pendiente por QA del cliente 03/12/2025: Control de cambios programado hoy para aprobación por comité. 04/12/2025: Control de cambios ejecutado con exito el 3 de diciembre. 10/12/2025: A un esta pendientes de pruebas para realizar paso a produncción. 12/12/2025: Se encuentra pendiente la ejecución del paso a producción y la realización de las pruebas en caliente una vez se despliegue el ajuste. 15/12/2025: El desarrollo principal ya se encuentra en producción, incluyendo la tabla y el código. Sin embargo, el proceso aún no se ha ejecutado de forma completa, ya que el cruce consulta facturas antiguas una a una contra el API. Se acordó no ejecutarlo aún y, por recomendación funcional, crear bandejas adicionales para gestionar los casos no cruzados o glosados, antes de activar el proceso masivo. 17/12/2025: Se avanzó en la construcción de bandejas de gestión necesarias cuando el cruce en producción presenta fallos. Dichas bandejas están casi finalizadas e incluyen la lógica para gestión manual de casos (por ejemplo, cambios de estado en Salud). 19/12/2025: Se avanzó en la construcción de la bandeja para el cruce de facturas versus estado de pago, especialmente para facturas asociadas a un solo usuario. La funcionalidad se encuentra estable y en proceso de validación, aunque persisten definiciones pendientes sobre el manejo de casos especiales (valores elevados o inconsistencias). El desarrollo continúa en evolución. 22/12/2025: El requerimiento 136 ya se encuentra en producción en su lógica principal. Sin embargo, continúa en construcción la bandeja para gestionar los casos no cruzados o con inconsistencias históricas (glosas antiguas, facturas anuladas o sin información). El avance se mantiene en estado “Paso a produccion” debido a que aún no existe definición funcional clara sobre el tratamiento final de estos casos. Se requiere validación con el área funcional para cerrar este punto. 02/01/2026: Se cuenta con bandejas para los casos que no cruzan automáticamente. Está pendiente realizar una socialización funcional con negocio (Jenry) para validar ajustes finales antes de una entrega formal. 14/01/2026: Se tienen pendientes algunos ajustes solicitados por el cliente en el módulo de Cruce de Facturas, el cual ya se encuentra en producción. Dado que se trata de mejoras adicionales posteriores a la entrega, se definió programar estos cambios para la próxima semana. | R47: TRUE | T47: MDSB-915793 / MDSB-934083 | U47: MDSB-937531
A48: FABIO | B48: GD772-136_1 | C48: Documentación tecnica. Reporte glosas para la Superfinanciera (Cruce automatico Autorizado Vs Cobrado) | F48: FINALIZADO | G48: 100 | H48: =IF(OR(J48="",K48="",K48<J48),0,NETWORKDAYS(J48,K48,fESTIVOS!$A$2:$A$53)) -> 0 | I48: 46006 | J48: 46009 | L48: 46021 | M48: =IF(OR(J48="",AND(L48="",TODAY()<J48),AND(L48<>"",L48<J48)),0, IF(L48="", NETWORKDAYS(J48,TODAY(),fESTIVOS!$A$2:$A$53), NETWORKDAYS(J48,L48,fESTIVOS!$A$2:$A$53) ) ) -> 8 | Q48: 18/12/2025: Jairo engtrega documentación en .md. se realizara ajuste de formato y estilos 30/12/2025: Se realizaron ajustes de estilos y formato del documento, y se realizó su incorporación al directorio de la biblioteca documental técnica para su consulta y control. | R48: TRUE
A49: JAIRO | B49: INTERNO-JA005 | C49: Mejoras informe total producto Salud | F49: FINALIZADO | G49: 100 | H49: =IF(OR(J49="",K49="",K49<J49),0,NETWORKDAYS(J49,K49,fESTIVOS!$A$2:$A$53)) -> 0 | I49: 45841 | J49: 45853 | L49: 45859 | M49: =IF(OR(J49="",AND(L49="",TODAY()<J49),AND(L49<>"",L49<J49)),0, IF(L49="", NETWORKDAYS(J49,TODAY(),fESTIVOS!$A$2:$A$53), NETWORKDAYS(J49,L49,fESTIVOS!$A$2:$A$53) ) ) -> 5 | R49: TRUE | AY49: 07/07/2025 : Se estima iniciar con la validacion de este informe tan pronto finalice la Generación de plantillas de cartas (glosa total, glosa parcial, devolución) Para Reembolsos ARL | BA49: 09/07/2025: Iniciara mejoras tras finalizar la Generación de plantillas de cartas (glosa total, glosa parcial, devolución) Para Reembolsos ARL | BF49: 16/07/2025: Se inicio el 15 de julio con la mejora del informe con revisión del query para optimización. Actualmente en un 5% de avance. | BH49: 18/07/2025: Se aplicaron mejoras al query del informe y se inició la validación de rendimiento respecto a la versión anterior. Se estima un 80% de avance manteniendo los mismos modelos usados en informes anteriores, con ajustes en operaciones específicas. | BI49: 21/07/2025: El viernes 18 de julio se realizaron pruebas sobre el informe para validar que los datos coincidieran entre ambos lados. Aunque inicialmente se evidenció una diferencia en la cantidad de registros, se confirmó que los datos eran correctos. Se avanzó en el ajuste para que solo se muestre el valor de la factura y la cédula en la primera línea, como requiere la estructura del informe, posiblemente por una macro de validación en Excel. Actualmente se continúan realizando correcciones para que el formato final sea consistente. | BJ49: 23/07/2025: Se realiza paso a produccion el 21 de julio de los ajustes del informe total de salud.
A50: JAIRO | B50: INTERNO-JA006 | C50: Mejoras informes por radicado producto Salud | F50: FINALIZADO | G50: 100 | H50: =IF(OR(J50="",K50="",K50<J50),0,NETWORKDAYS(J50,K50,fESTIVOS!$A$2:$A$53)) -> 0 | I50: 45836 | J50: 45836 | L50: 45841 | M50: =IF(OR(J50="",AND(L50="",TODAY()<J50),AND(L50<>"",L50<J50)),0, IF(L50="", NETWORKDAYS(J50,TODAY(),fESTIVOS!$A$2:$A$53), NETWORKDAYS(J50,L50,fESTIVOS!$A$2:$A$53) ) ) -> 3 | R50: TRUE | AW50: 02/07/2025: Se avanzó en un 70% con el desarrollo del informe por radicado específico para el área de Salud. Se separó la lógica del informe de los casos ARL y EPS para facilitar su mantenimiento, y se optimizó la consulta SQL mejorando el rendimiento. Actualmente se están realizando pruebas de validación con datos reales, y se espera replicar mejoras de tiempo similares a las obtenidas en el informe de ARL. Pendiente validación final en ambiente de producción. | AX50: 04/07/2025.Se avanzó con pruebas en producción del informe. El query ya está construido y se están realizando validaciones con datos reales. | AY50: 07/07/2025: El nuevo informe por radicado fue desplegado a producción el 4 de julio, reduciendo el tiempo de ejecución de 40 a 2 minutos.
A51: JAIRO | B51: GD772-60 | C51: Descarga automatica de informes | E51: PENDIENTE | F51: FINALIZADO | G51: 100 | H51: =IF(OR(J51="",K51="",K51<J51),0,NETWORKDAYS(J51,K51,fESTIVOS!$A$2:$A$53)) -> 0 | I51: 45814 | J51: 45819 | L51: 45833 | M51: =IF(OR(J51="",AND(L51="",TODAY()<J51),AND(L51<>"",L51<J51)),0, IF(L51="", NETWORKDAYS(J51,TODAY(),fESTIVOS!$A$2:$A$53), NETWORKDAYS(J51,L51,fESTIVOS!$A$2:$A$53) ) ) -> 10 | O51: 45827 | P51: 45841 | R51: TRUE | T51: MDSB-833556 | U51: MDSB-837144 | AL51: Se requiere mplementar la descarga automática diaria de informes relacionados con Salud, ARL, EPS y Vida, incluyendo inconsistencias, desde el 1 de enero del año vigente hasta la fecha actual, y generarlos por radicado para tres usuarios específicos. | AM51: Se estima tiempo inicial de desarrollo: 1.5 días | AN51: Se debe crear una tabla que relacione informes con usuarios destino, para replicar informes automáticamente a múltiples usuarios, a un no se confirma fecha de inicio del desarrollo. | AO51: El 11 de junio inicia en la creación de una tabla que permita asignar informes automáticos a múltiples usuarios. Falta desarrollar el panel administrativo y completar los ajustes en la estructura de CMS. hoy se estimae se solicitara control de cambios en test | AP51: Pendiente envio del script para realizar solicitud de control de cambios para test. | AR51: 19 de junio se escala control de cambios MDSB-833556 para test, se ejecuta con exito y se pasa a test e iniciar pruebas por el cliente. A la espera de aprobación de negocio para paso a producción | AS51: 25/06/2025:El informe está listo en test, pero pendiente de aprobación por parte del negocio para proceder con el control de cambios para paso a produccion | AT51: 26/06/2025: Se recibe aprobacion para paso a producción, se escala control de cambios MDSB-837144 | AU51: 27/06/2025:Pendiente aprobación de control de cambios de parte del cliente. | AW51: 02/07/2025: El 1 de julio se realizaron todas las aprobaciones pendientes. Actualmente, el cambio se encuentra en proceso de validación por parte del líder de Cambios Digitales, y se estima que sea incluido en el Comité de Cambios Digitales programado para el día de hoy. 02/07/2025: Control de cambios aprobado, se ejecutara 3 de Julio 4pm. | AX51: 03/07/2025:Se Realiza paso a producciòn con exito, La funcionalidad de copia automática de informes quedó establecida correctamente corrigiendo un error de totales en Glosas.
A52: DANILO | B52: INTERNO-D006 | C52: Monitoreo de carga y alertas del servidor | F52: FINALIZADO | G52: 100 | H52: =IF(OR(J52="",K52="",K52<J52),0,NETWORKDAYS(J52,K52,fESTIVOS!$A$2:$A$53)) -> 0 | I52: 45818 | J52: 45818 | L52: 45820 | M52: =IF(OR(J52="",AND(L52="",TODAY()<J52),AND(L52<>"",L52<J52)),0, IF(L52="", NETWORKDAYS(J52,TODAY(),fESTIVOS!$A$2:$A$53), NETWORKDAYS(J52,L52,fESTIVOS!$A$2:$A$53) ) ) -> 3 | Q52: 11/06/2025: El 10 de junio se implementó lógica para enviar correos cuando el load average y el uso del procesador superan umbrales definidos. Se toman snapshots para detectar procesos que generan cuellos de botella. Continúan ajustes y pruebas en esta funcionalidad. 13/06/2025: el 11 de junio se finalizó la implementación del monitoreo de carga, RAM y procesadores, con toma de snapshots cada minuto ante sobrecarga. El envío de alertas por correo quedó pendiente de implementar mediante Exchange para evitar abrir puertos. Se acordó dejarlo “en proceso” para retomarlo más adelante si es necesario. | R52: TRUE | AN52: Se implementó lógica para enviar correos cuando el load average y el uso del procesador superan umbrales definidos. Se toman snapshots para detectar procesos que generan cuellos de botella. Continúan ajustes y pruebas en esta funcionalidad. | AO52: Se finalizó la implementación del monitoreo de carga, RAM y procesadores, con toma de snapshots cada minuto ante sobrecarga. El envío de alertas por correo quedó pendiente de implementar mediante Exchange para evitar abrir puertos. Se acordó dejarlo “en proceso” para retomarlo más adelante si es necesario. | AU52: 27/06/2025:Sigue pendiente confirgura el envio de correo de la notificación de caida del servidor.
A53: DANILO | B53: CNTI-271 | C53: Vulnerabilidad, CVE-2016-4055 – DoS por expresiones regulares ineficientes en Moment.js (< v2.11.2) | F53: FINALIZADO | G53: 100 | H53: =IF(OR(J53="",K53="",K53<J53),0,NETWORKDAYS(J53,K53,fESTIVOS!$A$2:$A$53)) -> 10 | I53: 45818 | J53: 45821 | K53: 45835 | L53: 45832 | M53: =IF(OR(J53="",AND(L53="",TODAY()<J53),AND(L53<>"",L53<J53)),0, IF(L53="", NETWORKDAYS(J53,TODAY(),fESTIVOS!$A$2:$A$53), NETWORKDAYS(J53,L53,fESTIVOS!$A$2:$A$53) ) ) -> 7 | R53: TRUE | AN53: Vulnerabilidad que permite ataques de denegación de servicio mediante uso excesivo de CPU al procesar duraciones con expresiones regulares mal optimizadas. | AO53: Se actualizó a la versión 2.29.4 para corregir la vulnerabilidad, se deben realizar pruebas en test para comprobar funcionamiento. | AP53: Queda disponible el 13 de Junio para pruebas por Imagine en ambientes de test | AR53: El 19 de junio Fabio realiza pruebas en ambiente de test, no se evidenció un comportamiento anómalo ante entradas no válidas, se considera viable proceder con la implementación en ambiente de producción. Se propone despliegue a produccion hasta completar migración S3, para evitar confusión en trazabilidad de errores. | AS53: 24/06/2025: Se realiza implementación de la correccion de la vulnerabilidad en produccion.
A54: DANILO | B54: GD772-69_1 | C54: Error de acceso en test con TLS y certificados ( Api incapacidades) | F54: FINALIZADO | G54: 100 | H54: =IF(OR(J54="",K54="",K54<J54),0,NETWORKDAYS(J54,K54,fESTIVOS!$A$2:$A$53)) -> 0 | I54: 45839 | J54: 45839 | L54: 45840 | M54: =IF(OR(J54="",AND(L54="",TODAY()<J54),AND(L54<>"",L54<J54)),0, IF(L54="", NETWORKDAYS(J54,TODAY(),fESTIVOS!$A$2:$A$53), NETWORKDAYS(J54,L54,fESTIVOS!$A$2:$A$53) ) ) -> 2 | R54: TRUE | AW54: 02/07/2025: Se prioriza identificar si el fallo es por cifrado propio o por certificados del proveedor 02/07/2025: No fue posible solucionar el error, entonces se agregó el comentario al ticket MDSB-837736 solicitando añadir imaginex-test-documentos.segurosbolivar.com a Alternate Domain Names (CNAMEs) del CloudFront. | AX54: 04/07/2025:El problema de acceso en el ambiente de pruebas fue resuelto el 2 de julio; el API ya se encuentra funcional con el DNS y TLS configurados. Actualmente se identifican problemas de lentitud en las consultas, posiblemente por la firma o consulta de imágenes. Se recomienda evaluar el rendimiento para optimizar el tiempo de respuesta.
A55: DANILO | B55: CNTI-195 | C55: Vulnerabilidad, Implementación insegura de la integridad de los recursos secundarios (SRI) / imaginex | F55: FINALIZADO | G55: 100 | H55: =IF(OR(J55="",K55="",K55<J55),0,NETWORKDAYS(J55,K55,fESTIVOS!$A$2:$A$53)) -> 24 | I55: 45818 | J55: 45825 | K55: 45860 | L55: 45847 | M55: =IF(OR(J55="",AND(L55="",TODAY()<J55),AND(L55<>"",L55<J55)),0, IF(L55="", NETWORKDAYS(J55,TODAY(),fESTIVOS!$A$2:$A$53), NETWORKDAYS(J55,L55,fESTIVOS!$A$2:$A$53) ) ) -> 15 | O55: 45847 | R55: TRUE | AN55: No usar SRI permite que recursos externos como scripts o estilos sean manipulados sin ser detectados, exponiendo al sitio a posibles ataques si el servidor externo es comprometido | AQ55: Inicio ayerSe inició el trabajo sobre la vulnerabilidad el 17 de Junio. | AR55: Se trabaja en una vulnerabilidad compleja relacionada con scripts ya, se requiere intervención manual en múltiples páginas. | AS55: 25/06/2025: Se avanza al 15% en la mitigación de esta vulnerabilidad. | AU55: 27/06/2025:Continua en desarrollo | AW55: 02/07/2025: No se reportan avances, se planea continuar hoy despues de solucionar el "Error de acceso en test con TLS y certificados ( Api incapacidades)" | AX55: 04/07/2025:El avance de la remediación de la vulnerabilidad llega al 70%. Se trabajó con dedicación el día anterior y se proyecta su cierre completo en el transcurso del día si se mantiene el ritmo. | AY55: 07/07/2025 : Se avanzó un 10% en la revisión y atención de la vulnerabilidad, Se planea continuar hoy con la solución. | BA55: 09/07/2025: Se avanzó en la implementación en todas las aplicaciones requeridas (nativo, autorizaciones, portales, portal de incapacidades) pero no se pudo desplegar en ambiente TES por errores de carga de estilos. Se sospecha que puede deberse a conflictos con el recaptcha o pasos omitidos, contunuara la validaciòn. | BC55: 09/07/2025: El SRI fue implementado y desplegado en ambiente test, con dificultades superadas el 9 de julio. | BD55: 14/07/2025: Se requieren pruebas generales para validar su correcto funcionamiento en todas las aplicaciones involucradas | BE55: 15/07/2025: Se realizara el paso a producción el día 16 de Julio a las 5pm | BF55: despliegue hoy | BH55: 18/07/2025: El 16 de julio se completó el despliegue de SRI a producciòn.
A56: DANILO | B56: GD772-69_3 | C56: Documentacion APi incapacidades (Seguridad) | F56: FINALIZADO | G56: 100 | H56: =IF(OR(J56="",K56="",K56<J56),0,NETWORKDAYS(J56,K56,fESTIVOS!$A$2:$A$53)) -> 0 | I56: 45864 | J56: 45864 | K56: 45839 | L56: 45865 | M56: =IF(OR(J56="",AND(L56="",TODAY()<J56),AND(L56<>"",L56<J56)),0, IF(L56="", NETWORKDAYS(J56,TODAY(),fESTIVOS!$A$2:$A$53), NETWORKDAYS(J56,L56,fESTIVOS!$A$2:$A$53) ) ) -> 0 | R56: TRUE | AU56: 27/07/2025: entrega doucmentación de seguridad
A57: DANILO | B57: CNTI-96 | C57: Vulnerabilidad,La política de seguridad de los contenidos contiene la directiva “unsafe” / imaginex | F57: FINALIZADO | G57: 100 | H57: =IF(OR(J57="",K57="",K57<J57),0,NETWORKDAYS(J57,K57,fESTIVOS!$A$2:$A$53)) -> 15 | I57: 45818 | J57: 45821 | K57: 45845 | L57: 45867 | M57: =IF(OR(J57="",AND(L57="",TODAY()<J57),AND(L57<>"",L57<J57)),0, IF(L57="", NETWORKDAYS(J57,TODAY(),fESTIVOS!$A$2:$A$53), NETWORKDAYS(J57,L57,fESTIVOS!$A$2:$A$53) ) ) -> 31 | P57: 45868 | R57: TRUE | AN57: Una configuración débil de la Política de Seguridad de Contenido (CSP) permite ejecutar scripts en línea o evaluar código dinámico, lo que incrementa el riesgo de ataques XSS. | AP57: Actualmente se trabaja en la vulnerabilidad relacionada con la política de seguridad de contenido (CSP) y el uso de unsafe-inline, necesario para integraciones con Google reCAPTCHA y Clarity, se plantea justificar su permanencia y demostrar que el nivel de seguridad general sigue siendo aceptable (B+ cercano a A). | AQ57: Se resolvió la vulnerabilidad relacionada con la política de seguridad de contenidos (CSP), aunque su implementación en producción está limitada por la versión de Apache (actualmente en 2.4.57, mientras que se requiere mínimo 2.4.58). | AU57: 27/06/2025: Se pasa a produccion en primera semana de Julio despues del paso a produccion del S3. | AY57: 07/07/2025 : iniciara preparaciòn para paso a produccion ya que la solución implica la actualización del servicio Apache, es necesario realizar un respaldo completo de los archivos de configuración, virtual hosts y demás elementos asociados, con el fin de prevenir cualquier incidente y permitir una restauración rápida en caso de ser necesario. | AZ57: 08/07/2025: Se debe validar con el cliente, ya que la implementación en producción generará una indisponibilidad aproximada de 30 minutos en el servicio. | BC57: 11/07/2025: Está pendiente una ventana de mantenimiento para desplegar los cambios en producción, ya que requiere actualización del servicio Apache y afecta servicios críticos. Se sugirió solicitar la ventana para el martes 15 o jueves 17 | BD57: 14/07/2025: Se prevé realizar la actualización del servidor Apache para permitir configuraciones de seguridad modernas, pero aún está pendiente confirmación de ventana de mantenimiento para el 15 de julio 10 pm. | BF57: 16/07/2025: El paso a producción se pospone para la semana del 21 de julio, debido a que se debe evaluar una alternativa para mitigar la vulnerabilidad identificada. Actualizar Apache implicaría también la actualización del sistema operativo, por lo cual se analizarán otras opciones antes de proceder. | BM57: 30/07/2025:Se realizó la mitigación de la vulnerabilidad prioritaria sin necesidad de actualizar Apache, mediante la implementación de encabezados de seguridad. La solución fue probada exitosamente en ambiente de pruebas y se realiza paso a produccion 30 de julio en la mañana sin afectación al servicio.
A58: WILSON | B58: INTERNO-W001 | C58: Sistema automatizado de clasificación de correos médicos con IA | D58: 1. Integración sistemas médicos 2. Aprendizaje automático 3. Más categorías **Implementación:** • Despliegue paso a paso • Monitoreo constante • Validación periódica **Mejoras por realizar:** • Integrar estándares médicos • Diccionarios especializados • Validación cruzada términos **Mantenimiento:** • Updates periódicos • Reentrenamiento programado • Control de métricas **CONCLUSIÓN** Sistema robusto y eficiente para clasificación automática de correos médicos. Resultados perfectos en pruebas iniciales. Combina múltiples modelos de IA con procesamiento especializado médico. **LOGROS CLAVE** • 100% precisión • Validación perfecta • Procesamiento rápido • Especializado en medición | F58: FINALIZADO | G58: 100 | H58: =IF(OR(J58="",K58="",K58<J58),0,NETWORKDAYS(J58,K58,fESTIVOS!$A$2:$A$53)) -> 10 | I58: 45813 | J58: 45813 | K58: 45826 | L58: 45895 | M58: =IF(OR(J58="",AND(L58="",TODAY()<J58),AND(L58<>"",L58<J58)),0, IF(L58="", NETWORKDAYS(J58,TODAY(),fESTIVOS!$A$2:$A$53), NETWORKDAYS(J58,L58,fESTIVOS!$A$2:$A$53) ) ) -> 55 | Q58: 16/06/2025: Se detecto un problema en los análisis, se trabajo en una posible solución para ello, y es overfitting, que no es otra cosa que corregir estimaciones posiblemente equivocadas. Corregido por medio de scripts de testing y aquí el reporte de los resultados 18/06/2025: Se encuentra realizando cambios en mejoras de diccionario de datos y modelos enfocados a conceptos médicos en español. 25/06/2025: Actualmente se están ejecutando pruebas de ajuste fino (fine-tuning) sobre los modelos de clasificación mediante combinaciones de parámetros de entrenamiento. Esta etapa es crítica para mejorar el rendimiento del modelo sin modificar los datos base. El proceso es intensivo en tiempo y recursos, ya que cada entrenamiento toma varias horas. Se continúa enfocado en esta optimización. 02/07/2025: El desarrollo presenta un avance del 85%. Se han realizado pruebas unitarias y automatizadas con PyTest, orientadas a implementar integración y despliegue continuo (CI/CD). Se trabaja en el ajuste fino de los modelos (fine-tuning) y se analiza la calidad y relevancia de los datos para optimizar el entrenamiento. Se cuenta con el apoyo de usuarios funcionales para identificar las tipologías clave, asegurando una clasificación más precisa de los correos médicos. Pendiente iniciar la integración con el sistema de correos y montar el entorno de desarrollo en el equipo de Bolívar. 09/07/2025:Se encuentra modificando el servicio para realizar la implenetaciòn. 14/07/2025: Se va a utilizar el ambiente duplicado existente para lanzar entrenamientos del modelo sin afectar producción. Se creará una vista que concentre los datos requeridos para el entrenamiento y así evitar la dispersión sobre múltiples tablas. El objetivo es iniciar esta semana pruebas con DigiVet y observar el comportamiento del modelo. De los resultados dependerá su implementación definitiva. 27/08/2025: Requerimiento finalizado agosto 26. | R58: TRUE | AP58: Se detecto un problema en los análisis, se trabajo en una posible solución para ello, y es overfitting, que no es otra cosa que corregir estimaciones posiblemente equivocadas. Corregido por medio de scripts de testing y aquí el reporte de los resultados | AQ58: Se encuentra realizando cambios en mejoras de diccionario de datos y modelos enfocados a conceptos médicos en español | AS58: 25/06/2025: Actualmente se están ejecutando pruebas de ajuste fino (fine-tuning) sobre los modelos de clasificación mediante combinaciones de parámetros de entrenamiento. Esta etapa es crítica para mejorar el rendimiento del modelo sin modificar los datos base. El proceso es intensivo en tiempo y recursos, ya que cada entrenamiento toma varias horas. Se continúa enfocado en esta optimización. | AW58: 02/07/2025:El desarrollo presenta un avance del 85%. Se han realizado pruebas unitarias y automatizadas con PyTest, orientadas a implementar integración y despliegue continuo (CI/CD). Se trabaja en el ajuste fino de los modelos (fine-tuning) y se analiza la calidad y relevancia de los datos para optimizar el entrenamiento. Se cuenta con el apoyo de usuarios funcionales para identificar las tipologías clave, asegurando una clasificación más precisa de los correos médicos. Pendiente iniciar la integración con el sistema de correos y montar el entorno de desarrollo en el equipo de Bolívar. | BD58: 14/07/2025: Se va a utilizar el ambiente duplicado existente para lanzar entrenamientos del modelo sin afectar producción. Se creará una vista que concentre los datos requeridos para el entrenamiento y así evitar la dispersión sobre múltiples tablas. El objetivo es iniciar esta semana pruebas con DigiVet y observar el comportamiento del modelo. De los resultados dependerá su implementación definitiva.
A59: JAIRO | B59: GD772-114 | C59: ADICIONAR INFORMACIÓN DE TENGO DUDAS DE MIS REEMBOLSOS AL INFORME CONSOLIDADO | D59: ADICIONAR INFORMACIÓN DE TENGO DUDAS DE MIS REEMBOLSOS AL INFORME CONSOLIDADO | F59: FINALIZADO | G59: 100 | H59: =IF(OR(J59="",K59="",K59<J59),0,NETWORKDAYS(J59,K59,fESTIVOS!$A$2:$A$53)) -> 0 | I59: 45825 | J59: 45832 | L59: 45833 | M59: =IF(OR(J59="",AND(L59="",TODAY()<J59),AND(L59<>"",L59<J59)),0, IF(L59="", NETWORKDAYS(J59,TODAY(),fESTIVOS!$A$2:$A$53), NETWORKDAYS(J59,L59,fESTIVOS!$A$2:$A$53) ) ) -> 2 | Q59: 24/06/2025: Se inicia ajuste 25/06/2025: Se realiza paso a producción | R59: TRUE | AQ59: Requerimiento asignado 17 de junio, en cola de trabajo. | AR59: 20/06/2025:Validara requerimiento y estimara tiempo de desarrollo. | AS59: 25/06/2025:Este informe ya fue desplegado exitosamente a producción el 24 de junio. Fue integrado a la pestaña Digitación y se unificó el manejo de dudas y pendientes por digitar, mejorando la centralización de datos.
A60: FABIO | B60: INTERNO-F3 | C60: Crear cuenta en GitHub con correo corporativo | F60: FINALIZADO | G60: 100 | H60: =IF(OR(J60="",K60="",K60<J60),0,NETWORKDAYS(J60,K60,fESTIVOS!$A$2:$A$53)) -> 0 | I60: 45826 | J60: 45888 | L60: 45888 | M60: =IF(OR(J60="",AND(L60="",TODAY()<J60),AND(L60<>"",L60<J60)),0, IF(L60="", NETWORKDAYS(J60,TODAY(),fESTIVOS!$A$2:$A$53), NETWORKDAYS(J60,L60,fESTIVOS!$A$2:$A$53) ) ) -> 1 | Q60: 19/08/2025: Se crea cuenta " PruebasImagine" | R60: TRUE | AQ60: Se propuso integrarlo al GitHub de la organización Imaging SAS para que pueda crear issues directamente relacionados con los desarrollos
A61: FABIO | B61: MDSB-833556 | C61: CDC-T, req GD772-60 Descarga automatica de informes | F61: FINALIZADO | G61: 100 | H61: =IF(OR(J61="",K61="",K61<J61),0,NETWORKDAYS(J61,K61,fESTIVOS!$A$2:$A$53)) -> 0 | I61: 45827 | J61: 45827 | L61: 45827 | M61: =IF(OR(J61="",AND(L61="",TODAY()<J61),AND(L61<>"",L61<J61)),0, IF(L61="", NETWORKDAYS(J61,TODAY(),fESTIVOS!$A$2:$A$53), NETWORKDAYS(J61,L61,fESTIVOS!$A$2:$A$53) ) ) -> 1 | R61: TRUE | AR61: !9 de junio Se escala control de cambios en test para alterar una tabla y se crea otra. Control de cambios ejecutado correctamente.
A62: FABIO | B62: CNTI-271_1 | C62: Pruebas,Vulnerabilidad, CVE-2016-4055 – DoS por expresiones regulares ineficientes en Moment.js (< v2.11.2) | F62: FINALIZADO | G62: 100 | H62: =IF(OR(J62="",K62="",K62<J62),0,NETWORKDAYS(J62,K62,fESTIVOS!$A$2:$A$53)) -> 0 | I62: 45821 | J62: 45827 | L62: 45827 | M62: =IF(OR(J62="",AND(L62="",TODAY()<J62),AND(L62<>"",L62<J62)),0, IF(L62="", NETWORKDAYS(J62,TODAY(),fESTIVOS!$A$2:$A$53), NETWORKDAYS(J62,L62,fESTIVOS!$A$2:$A$53) ) ) -> 1 | R62: TRUE | AR62: 19/06/2025: El 19 de junio se realizan pruebas en ambiente de test, no se evidenció un comportamiento anómalo ante entradas no válidas, se considera viable proceder con la implementación en ambiente de producción.
A63: FABIO | B63: INTERNO-F001 | C63: Desarrollo de informe interactivo de requerimientos | D63: Se requiere que el informe interactivo implementado para el seguimiento de requerimientos de Imagine, actualmente publicado en un repositorio personal de GitHub, sea migrado y publicado en el repositorio oficial de Imaginesas, garantizando su disponibilidad y gestión centralizada. | F63: FINALIZADO | G63: 100 | H63: =IF(OR(J63="",K63="",K63<J63),0,NETWORKDAYS(J63,K63,fESTIVOS!$A$2:$A$53)) -> 0 | I63: 45820 | J63: 45820 | L63: 45933 | M63: =IF(OR(J63="",AND(L63="",TODAY()<J63),AND(L63<>"",L63<J63)),0, IF(L63="", NETWORKDAYS(J63,TODAY(),fESTIVOS!$A$2:$A$53), NETWORKDAYS(J63,L63,fESTIVOS!$A$2:$A$53) ) ) -> 78 | Q63: 03/10/2025: Hoy se realizó una sesión con Jhon, Jennifer y Jenry, en la cual se presentó el proceso para actualizar el informe en el repositorio de Imaginesas. Como primer paso, se iniciara con la actualización del código del informe para que la información se muestre de la misma forma en que actualmente se publica. 03/10/2025: El reporte queda actualizado y publicado desde el repositorio de Imaginesas. 05/01/2026: Se implementa la opción “Última actualización por Unidad”, que permite visualizar la fecha de la última actualización realizada por cada unidad y generar un informe descargable en formato CSV. | R63: TRUE | AR63: 20/06/2025: Se esta trabajando en la actualizacion de req en el informe y en la adicion del campo "Detalle de req" | AS63: 25/06/2025: Ya se encuentra el campo detalle req, se esta trabajando en la forma de alimentar este campo y el ingreso del historico de las observaciones de cada req. | AV63: 01/07/2025: Se realiza actualización de estado de Req y cambio de Nombres de las Unidades | BA63: 09/07/2025: Se está actualizando el informe con los detalles de los requerimientos y la trazabilidad de la gestión realizada. Adicionalmente, se ha venido desarrollando un módulo que permitirá a cualquier usuario con acceso al informe ingresar observaciones relacionadas con el contenido o el avance de los requerimientos.
A64: FABIO | B64: INTERNO-F008 | C64: Inclusion de campos (fecha de compromiso con el cliente, estimado de desarrollo ..etc) informe interactivo de requerimientos | D64: Fabio muchas gracias por el informe y por tener la información actualizada, para Bolívar debemos incluir los jiras de la reunión del día hoy con ARL. Tengo algunas observaciones de mejora para el informe, incluir fecha de compromiso con el cliente, nivel de dificultad del requerimiento en el encabezado de cada descripción de requerimiento. El acceso está super fácil y llega correctamente el código de acceso. | F64: FINALIZADO | G64: 100 | H64: =IF(OR(J64="",K64="",K64<J64),0,NETWORKDAYS(J64,K64,fESTIVOS!$A$2:$A$53)) -> 0 | I64: 45953 | J64: 46048 | L64: 46050 | M64: =IF(OR(J64="",AND(L64="",TODAY()<J64),AND(L64<>"",L64<J64)),0, IF(L64="", NETWORKDAYS(J64,TODAY(),fESTIVOS!$A$2:$A$53), NETWORKDAYS(J64,L64,fESTIVOS!$A$2:$A$53) ) ) -> 3 | Q64: 26/01/2026: Se realiza ajuste del codigo que genera el json que alimenta el reporte para que lea los nuevos campos. 28/01/2026: Los campos ya se encuentran implementados en el tablero; queda pendiente el ajuste de los Drive de las diferentes unidades para habilitar la generación de la información. | R64: TRUE
A65: FABIO | B65: INTERNO-F002 | C65: Pruebas listas blancas para factor de doble autenticación | E65: EN PROCESO | F65: FINALIZADO | G65: 100 | H65: =IF(OR(J65="",K65="",K65<J65),0,NETWORKDAYS(J65,K65,fESTIVOS!$A$2:$A$53)) -> 0 | I65: 45828 | J65: 45832 | L65: 45832 | M65: =IF(OR(J65="",AND(L65="",TODAY()<J65),AND(L65<>"",L65<J65)),0, IF(L65="", NETWORKDAYS(J65,TODAY(),fESTIVOS!$A$2:$A$53), NETWORKDAYS(J65,L65,fESTIVOS!$A$2:$A$53) ) ) -> 1 | R65: TRUE | AS65: 24/06/2025: Se realizan pruebas al ingresar a un usuario en listas blancas y se deja activo al ingresar a laravel y Yii no solicita codigo de autenticación, se identifica que Nativo no esta solicitando codigo de autenticación a ningun usuario se escala a Jesus para su ajuste. 24/06/2025: Jesus entrega ajuste, se realiza validación y se confirma funcionalidad y se le informa al cliente.
A66: FABIO | B66: INTERNO-F003 | C66: Solicitud accesos ambiente Dev y Test (Jenry) | F66: FINALIZADO | G66: 100 | H66: =IF(OR(J66="",K66="",K66<J66),0,NETWORKDAYS(J66,K66,fESTIVOS!$A$2:$A$53)) -> 0 | I66: 45832 | J66: 45832 | L66: 45833 | M66: =IF(OR(J66="",AND(L66="",TODAY()<J66),AND(L66<>"",L66<J66)),0, IF(L66="", NETWORKDAYS(J66,TODAY(),fESTIVOS!$A$2:$A$53), NETWORKDAYS(J66,L66,fESTIVOS!$A$2:$A$53) ) ) -> 2 | R66: TRUE | AS66: 24/06/2025: Se escalan los siguientes solicitud de accesos Dev = MDSB-835240 test= MDSB-835246 25/06/2025: Se asignan permisos solicitados y se confirma acceso a dev y test correctamente.
A67: JESUS | B67: MDSB-835580 | C67: Jira dia a dia ajustar actividades caso 31012936 incapacidades | F67: FINALIZADO | G67: 100 | H67: =IF(OR(J67="",K67="",K67<J67),0,NETWORKDAYS(J67,K67,fESTIVOS!$A$2:$A$53)) -> 0 | I67: 45833 | J67: 45833 | L67: 45833 | M67: =IF(OR(J67="",AND(L67="",TODAY()<J67),AND(L67<>"",L67<J67)),0, IF(L67="", NETWORKDAYS(J67,TODAY(),fESTIVOS!$A$2:$A$53), NETWORKDAYS(J67,L67,fESTIVOS!$A$2:$A$53) ) ) -> 1 | R67: TRUE | AS67: 25/06/2025: Se presento un error en la asignación de la actividad del caso, se corrige asignandolo a la a ctividada correcta "Analista de Liquidación".
A68: JESUS | B68: INTERNO-JE006 | C68: Apertura de flujo de 4 casos de Preautorizaciones poliza salud - delegacion analistas creados con una sola actividad | F68: FINALIZADO | G68: 100 | H68: =IF(OR(J68="",K68="",K68<J68),0,NETWORKDAYS(J68,K68,fESTIVOS!$A$2:$A$53)) -> 0 | I68: 45833 | J68: 45833 | L68: 45833 | M68: =IF(OR(J68="",AND(L68="",TODAY()<J68),AND(L68<>"",L68<J68)),0, IF(L68="", NETWORKDAYS(J68,TODAY(),fESTIVOS!$A$2:$A$53), NETWORKDAYS(J68,L68,fESTIVOS!$A$2:$A$53) ) ) -> 1 | R68: TRUE | AS68: 25/06/2025: Flujos aperturados correctamente
A69: FABIO | B69: GD772-168_1 | C69: Elaboración HU 2do sprint - nuevo proceso de incapacidades ARL | F69: FINALIZADO | G69: 100 | H69: =IF(OR(J69="",K69="",K69<J69),0,NETWORKDAYS(J69,K69,fESTIVOS!$A$2:$A$53)) -> 2 | I69: 46036 | J69: 46037 | K69: 46038 | L69: 46038 | M69: =IF(OR(J69="",AND(L69="",TODAY()<J69),AND(L69<>"",L69<J69)),0, IF(L69="", NETWORKDAYS(J69,TODAY(),fESTIVOS!$A$2:$A$53), NETWORKDAYS(J69,L69,fESTIVOS!$A$2:$A$53) ) ) -> 2 | Q69: 16/01/2026: Se a avanzado significativa mente en la elaboración de las HU, se solicito a Jenry aclaracion de los consumos de Vlidacion liquidacion,Liquidar y autorizacion, Hoy se continua con las HU de la nueva bandeja y reasignación. Se envian HU para validaciòn y aprobacion por Jenry y Liyibet 19/01/2026: Se realizan ajustes indicados por Jenry y se incluye HU10 Notificación de pago al flujo automático de incapacidades. 20/01/2026: Jenry confirma que el documento cumple lo requerido | R69: TRUE
A70: FABIO | B70: GD772-146_5 | C70: DOCUMENTACIÓN TÉCNICA- IMPLEMENTACIÓN DE DOBLE FACTOR | F70: FINALIZADO | G70: 100 | H70: =IF(OR(J70="",K70="",K70<J70),0,NETWORKDAYS(J70,K70,fESTIVOS!$A$2:$A$53)) -> 0 | I70: 46063 | J70: 46063 | L70: 46063 | M70: =IF(OR(J70="",AND(L70="",TODAY()<J70),AND(L70<>"",L70<J70)),0, IF(L70="", NETWORKDAYS(J70,TODAY(),fESTIVOS!$A$2:$A$53), NETWORKDAYS(J70,L70,fESTIVOS!$A$2:$A$53) ) ) -> 1 | Q70: 10/02/2026: Se realiza documentación tecnica contemplando arquitectura, componentes, flujo de autenticación, controles de seguridad e interacción entre scripts PHP, controladores y vistas. | R70: TRUE
A71: FABIO | B71: INTERNO-F016 | C71: Implementación dashboard de cumplimiento en tablero de requerimientos | F71: PAUSADO | G71: 30 | H71: =IF(OR(J71="",K71="",K71<J71),0,NETWORKDAYS(J71,K71,fESTIVOS!$A$2:$A$53)) -> 0 | I71: 46070 | J71: 46070 | M71: =IF(OR(J71="",AND(L71="",TODAY()<J71),AND(L71<>"",L71<J71)),0, IF(L71="", NETWORKDAYS(J71,TODAY(),fESTIVOS!$A$2:$A$53), NETWORKDAYS(J71,L71,fESTIVOS!$A$2:$A$53) ) ) -> 79 | Q71: 17/02/2026: Se realizó revisión de la información disponible, definición de métricas de cumplimiento, análisis de viabilidad técnica y evaluación de funcionalidades necesarias (indicadores, alertas y reportes) con el fin de estructurar la propuesta del dashboard. 18/02/2026; Se reestructuró la arquitectura del informe para integrar el nuevo Dashboard de Cumplimiento mediante un sistema de navegación modular (iFrame), logrando la coexistencia de ambos reportes sin conflictos; asimismo, se depuraron errores de ejecución en los botones de control 24/02/2026: Se realiza validació: Se realiza validacion en local de la informacion que esta extrayendo el dashboard y no coincide despues de varias validaciones se identifica que no esta mostrando informacion de 38 requerimeintos finalizados los cuales estan pendientes por identificar. | R71: True
A72: FABIO | B72: MDSB-837144 | C72: CDC-P, req GD772-60 Descarga automatica de informes | F72: FINALIZADO | G72: 100 | H72: =IF(OR(J72="",K72="",K72<J72),0,NETWORKDAYS(J72,K72,fESTIVOS!$A$2:$A$53)) -> 0 | I72: 45834 | J72: 45834 | L72: 45841 | M72: =IF(OR(J72="",AND(L72="",TODAY()<J72),AND(L72<>"",L72<J72)),0, IF(L72="", NETWORKDAYS(J72,TODAY(),fESTIVOS!$A$2:$A$53), NETWORKDAYS(J72,L72,fESTIVOS!$A$2:$A$53) ) ) -> 5 | R72: TRUE | AT72: 26/06/2025: Se escala control de cambios para produccion, Pendiente que el cliente pase el req GD772-60 a estado PAP para continuar con el proceso. | AV72: 01/07/2025: Control de cambios avanza al siguiente estado (Validación), se estima sea incluido en el comite de cambios digitales el 2 de Julio. | AW72: 02/07/2025: El 1 de julio se realizaron todas las aprobaciones pendientes. Actualmente, el cambio se encuentra en proceso de validación por parte del líder de Cambios Digitales, y se estima que sea incluido en el Comité de Cambios Digitales programado para el día de hoy. 02/07/2025: Control de cambios aprobado, se ejecutara 3 de Julio 4pm. | AX72: 03/07/2025: Control de cambios ejecutado con exito.
A73: JESUS | B73: MDSB-838905 | C73: Jiras dia dia Inhabilitar 3 tipologias a 3 usuarios | F73: FINALIZADO | G73: 100 | H73: =IF(OR(J73="",K73="",K73<J73),0,NETWORKDAYS(J73,K73,fESTIVOS!$A$2:$A$53)) -> 0 | I73: 45841 | J73: 45841 | L73: 45841 | M73: =IF(OR(J73="",AND(L73="",TODAY()<J73),AND(L73<>"",L73<J73)),0, IF(L73="", NETWORKDAYS(J73,TODAY(),fESTIVOS!$A$2:$A$53), NETWORKDAYS(J73,L73,fESTIVOS!$A$2:$A$53) ) ) -> 1 | R73: TRUE | AX73: 03/07/2025: se realiza inactivaciòn de los usuarios en las tiplogias (1031) Traslado de Polizas,(10493)Mesa de Conciliacion Presencial y (10494)Mesa de conciliación Virtual
A74: JESUS | B74: MDSB-842592 | C74: jira dia a dia, Cambiar planilla de ingresos en oficina virtual ARL | F74: FINALIZADO | G74: 100 | H74: =IF(OR(J74="",K74="",K74<J74),0,NETWORKDAYS(J74,K74,fESTIVOS!$A$2:$A$53)) -> 0 | I74: 45845 | J74: 45845 | L74: 45845 | M74: =IF(OR(J74="",AND(L74="",TODAY()<J74),AND(L74<>"",L74<J74)),0, IF(L74="", NETWORKDAYS(J74,TODAY(),fESTIVOS!$A$2:$A$53), NETWORKDAYS(J74,L74,fESTIVOS!$A$2:$A$53) ) ) -> 1 | R74: TRUE | AY74: 07/07/2025 : Se realiza cambio de planilla
A75: JESUS | B75: MDSB-835432 | C75: Jira dia a dia Error en cargue de anexos de casos | F75: FINALIZADO | G75: 100 | H75: =IF(OR(J75="",K75="",K75<J75),0,NETWORKDAYS(J75,K75,fESTIVOS!$A$2:$A$53)) -> 0 | I75: 45842 | J75: 45842 | L75: 45845 | M75: =IF(OR(J75="",AND(L75="",TODAY()<J75),AND(L75<>"",L75<J75)),0, IF(L75="", NETWORKDAYS(J75,TODAY(),fESTIVOS!$A$2:$A$53), NETWORKDAYS(J75,L75,fESTIVOS!$A$2:$A$53) ) ) -> 2 | R75: TRUE | AY75: 07/07/2025: El viernes 4 de julio se implementó solución para prevenir la visualización incorrecta de archivos cargados simultáneamente por usuarios. Falta realizar pruebas en test para validar y solicitar paso a producción. 07/07/2025: La causa del comportamiento fue la ausencia de control para manejar cargas concurrentes. Como solución, el equipo de desarrollo implementó un ajuste en el sistema que permite que, en adelante, los documentos se guarden uno a uno y en el orden en que se reciben, evitando así cualquier sobrescritura o cruce de archivos entre casos.
A76: JAIRO | B76: INTERNO-JA007 | C76: Levantamiento nueva máquina virtual, | F76: FINALIZADO | G76: 100 | H76: =IF(OR(J76="",K76="",K76<J76),0,NETWORKDAYS(J76,K76,fESTIVOS!$A$2:$A$53)) -> 0 | I76: 45846 | J76: 45846 | L76: 45847 | M76: =IF(OR(J76="",AND(L76="",TODAY()<J76),AND(L76<>"",L76<J76)),0, IF(L76="", NETWORKDAYS(J76,TODAY(),fESTIVOS!$A$2:$A$53), NETWORKDAYS(J76,L76,fESTIVOS!$A$2:$A$53) ) ) -> 2 | R76: TRUE | BA76: 09/07/2025:Ayer 8 de Julio se inició el levantamiento de una nueva máquina virtual para dar continuidad a los desarrollos, debido a fallas presentadas en los discos de la máquina física (RAID dañada), lo que obligó a migrar el entorno. Actualmente, la nueva máquina virtual se encuentra casi lista, lo que permitirá retomar próximamente los desarrollos pendientes. | BC76: 11/07/2025: Fue completado el levantamiento de la máquina virtual necesaria para continuar el desarrollo. Se configuró con una base de datos y entorno de trabajo básico. Esto desbloquea tareas de desarrollo local.
A77: JAIRO | B77: INTERNO-JA008 | C77: Devolver a Seguimiento para firmeza el radicado 30949303 | F77: FINALIZADO | G77: 100 | H77: =IF(OR(J77="",K77="",K77<J77),0,NETWORKDAYS(J77,K77,fESTIVOS!$A$2:$A$53)) -> 0 | I77: 45845 | J77: 45846 | L77: 45846 | M77: =IF(OR(J77="",AND(L77="",TODAY()<J77),AND(L77<>"",L77<J77)),0, IF(L77="", NETWORKDAYS(J77,TODAY(),fESTIVOS!$A$2:$A$53), NETWORKDAYS(J77,L77,fESTIVOS!$A$2:$A$53) ) ) -> 1 | R77: TRUE | BA77: 09/07/2025: Se le elimino la linea de cierre caso y se dejó en seguimiento firmeza.
A78: JAIRO | B78: INTERNO-JA009 | C78: Corregir CC a los casos 31010548 - 31010549 en pensiones | F78: FINALIZADO | G78: 100 | H78: =IF(OR(J78="",K78="",K78<J78),0,NETWORKDAYS(J78,K78,fESTIVOS!$A$2:$A$53)) -> 0 | I78: 45845 | J78: 45846 | L78: 45846 | M78: =IF(OR(J78="",AND(L78="",TODAY()<J78),AND(L78<>"",L78<J78)),0, IF(L78="", NETWORKDAYS(J78,TODAY(),fESTIVOS!$A$2:$A$53), NETWORKDAYS(J78,L78,fESTIVOS!$A$2:$A$53) ) ) -> 1 | R78: TRUE | BA78: 09/07/2025: El 8 de junio se realiza correciòn de la CC en los casos solicitados.
A79: JAIRO | B79: INTERNO-JA004_1 | C79: Mejoras de Performance y Validaciones | F79: FINALIZADO | G79: 100 | H79: =IF(OR(J79="",K79="",K79<J79),0,NETWORKDAYS(J79,K79,fESTIVOS!$A$2:$A$53)) -> 0 | I79: 45975 | J79: 45975 | L79: 45975 | M79: =IF(OR(J79="",AND(L79="",TODAY()<J79),AND(L79<>"",L79<J79)),0, IF(L79="", NETWORKDAYS(J79,TODAY(),fESTIVOS!$A$2:$A$53), NETWORKDAYS(J79,L79,fESTIVOS!$A$2:$A$53) ) ) -> 1 | Q79: 18/11/2025: El viernes 14 de noviembre se realizaron mejoras de performance y validaciones, incluyendo la optimización de consultas y la depuración de datos. Entre los ajustes implementados se encuentran la eliminación de validaciones redundantes en resumenValidacionesGlobal, la mejora del resumen de procesamiento con conteos de validación, la validación de inconsistencias de ciudad en el procesamiento de facturas y la exclusión de registros con estado “10” en las consultas de distribución | R79: TRUE
A80: JAIRO | B80: INTERNO-JA004_2 | C80: Ajustes en Confirmación de Entrega de Lote | D80: Finalizar los ajustes pendientes en el sistema de confirmación de lotes procesados | F80: FINALIZADO | G80: 100 | H80: =IF(OR(J80="",K80="",K80<J80),0,NETWORKDAYS(J80,K80,fESTIVOS!$A$2:$A$53)) -> 0 | I80: 45975 | J80: 45975 | L80: 45985 | M80: =IF(OR(J80="",AND(L80="",TODAY()<J80),AND(L80<>"",L80<J80)),0, IF(L80="", NETWORKDAYS(J80,TODAY(),fESTIVOS!$A$2:$A$53), NETWORKDAYS(J80,L80,fESTIVOS!$A$2:$A$53) ) ) -> 6 | Q80: 18/11/2025: Hoy se continuará con los ajustes del sistema de confirmación de entrega de lote, enfocando las actividades en completar las validaciones adicionales del proceso entregar_lote, mejorar la interfaz de confirmación y ejecutar las pruebas de integración end-to-end para validar el flujo completo, manteniendo el avance estimado en un 80%. 24/11/2025: Se continua con las pruebas para la entrega del lote. Se ajustó lógica de ciudades y probabilidades. Actualmente entregando lote tanto a almacenamiento como a auditoría; pruebas en curso. 26/11/2025: Los ajustes funcionales ya fueron aplicados y verificados. Falta ejecutar el ciclo completo de pruebas para validar el comportamiento en todos los escenarios del flujo | R80: TRUE
A81: JAIRO | B81: GD772-159_2 | C81: Ajuste en descargar volúmenes grandes (Valores de factura vs valores pendientes (validaciones del masivo) Gasto medico) | D81: Se identificaron problemas en la lógica cuando los usuarios intentan descargar volúmenes grandes (más de 500 registros). Aunque se aplicó un ajuste rápido para permitir continuidad en pruebas, el componente aún falla en cargas altas. Se revisará la lógica para corregir errores en descargas masivas y depurar la validación de autorizaciones y estados | F81: FINALIZADO | G81: 100 | H81: =IF(OR(J81="",K81="",K81<J81),0,NETWORKDAYS(J81,K81,fESTIVOS!$A$2:$A$53)) -> 0 | I81: 46000 | J81: 46000 | L81: 45972 | M81: =IF(OR(J81="",AND(L81="",TODAY()<J81),AND(L81<>"",L81<J81)),0, IF(L81="", NETWORKDAYS(J81,TODAY(),fESTIVOS!$A$2:$A$53), NETWORKDAYS(J81,L81,fESTIVOS!$A$2:$A$53) ) ) -> 0 | P81: 45972 | Q81: 10/12/2025: Se identificaron problemas en la lógica cuando los usuarios intentan descargar volúmenes grandes (más de 500 registros). Aunque se aplicó un ajuste rápido para permitir continuidad en pruebas, el componente aún falla en cargas altas. Se revisará la lógica para corregir errores en descargas masivas y depurar la validación de autorizaciones y estados 12/12/2025: El 11 de diciembre se trabajó en el ajuste del tiempo de respuesta al momento de descargar el RPA, incrementándolo ligeramente para garantizar la correcta generación y disponibilidad del archivo.
A82: FABIO | B82: GD772-116_1 | C82: Pruebas gestión Medicamentos fase 2 - Sprint 2 | F82: FINALIZADO | G82: 100 | H82: =IF(OR(J82="",K82="",K82<J82),0,NETWORKDAYS(J82,K82,fESTIVOS!$A$2:$A$53)) -> 0 | I82: 45849 | J82: 45849 | L82: 45855 | M82: =IF(OR(J82="",AND(L82="",TODAY()<J82),AND(L82<>"",L82<J82)),0, IF(L82="", NETWORKDAYS(J82,TODAY(),fESTIVOS!$A$2:$A$53), NETWORKDAYS(J82,L82,fESTIVOS!$A$2:$A$53) ) ) -> 5 | R82: TRUE | BC82: 11/07/2025: Se inician pruebas del modulo de consulta en oficina virtual | BF82: 16/07/2025:Se evidencian mejoras orientadas a la experiencia de usuario. Se ha probado la marcación efectiva en la consulta del portal. Aún se encuentra pendiente la validación del módulo de gestión y la prueba de las cartas de respuesta | BH82: 18/07/2025: Se finalizan las pruebas y los ajustes por parte de Jesús sobre los hallazgos identificados.
A83: DANILO | B83: INTERNO-D007 | C83: Validaciòn del CRONTAB / Tareas duplicadas | F83: FINALIZADO | G83: 100 | H83: =IF(OR(J83="",K83="",K83<J83),0,NETWORKDAYS(J83,K83,fESTIVOS!$A$2:$A$53)) -> 0 | I83: 45852 | J83: 45852 | L83: 45852 | M83: =IF(OR(J83="",AND(L83="",TODAY()<J83),AND(L83<>"",L83<J83)),0, IF(L83="", NETWORKDAYS(J83,TODAY(),fESTIVOS!$A$2:$A$53), NETWORKDAYS(J83,L83,fESTIVOS!$A$2:$A$53) ) ) -> 1 | R83: TRUE | BD83: 14/07/2025: Se tomarán medidas de mitigación: inhabilitar el servicio CRONTAB, eliminar archivos de configuración y evitar reinicios automáticos que reactiven el proceso. | BF83: 16/07/2025. El incidente de duplicidad en tareas por CRONTAB se resolvió, era causado por una instancia duplicada.
A84: DANILO | B84: INTERNO-D008 | C84: Vlidaciòn de herramientas IA (Google Cloud / Bolivar) | F84: CANCELADO | G84: 15 | H84: =IF(OR(J84="",K84="",K84<J84),0,NETWORKDAYS(J84,K84,fESTIVOS!$A$2:$A$53)) -> 0 | I84: 45852 | J84: 45856 | M84: =IF(OR(J84="",AND(L84="",TODAY()<J84),AND(L84<>"",L84<J84)),0, IF(L84="", NETWORKDAYS(J84,TODAY(),fESTIVOS!$A$2:$A$53), NETWORKDAYS(J84,L84,fESTIVOS!$A$2:$A$53) ) ) -> 222 | Q84: 03/09/2025: La revisión aún no ha sido iniciada. Se requiere programación de espacio de tiempo para ejecutar esta validación. 07/11/2025: No se continúa utilizando herramientas alternas, el requerimiento se da por cancelado. | R84: FALSE | BD84: Se propuso investigar si es posible aprovechar herramientas de IA ofrecidas por Google, dado el contrato que Bolívar mantiene con ellos. Danilo asumirá esta tarea, con posible apoyo de Wilson para identificar contacto y canal apropiado. | BI84: 21/07/2025:Se Inicio validaciòn de las herrramientas leer documentaciòn... | BJ84: 23/07/2025: Se exploraron herramientas de Google con el fin de evaluar su integración en los flujos actuales. Si bien se identificó que podrían ser útiles para la gestión de procesos, aún no se ha logrado una funcionalidad concreta. Se requiere dedicar más tiempo a pruebas detalladas para validar su viabilidad.
A85: JAIRO | B85: GD772-119 | C85: Hablador ficha de solicitudes médicas | F85: FINALIZADO | G85: 100 | H85: =IF(OR(J85="",K85="",K85<J85),0,NETWORKDAYS(J85,K85,fESTIVOS!$A$2:$A$53)) -> 0 | I85: 45853 | J85: 45859 | L85: 45859 | M85: =IF(OR(J85="",AND(L85="",TODAY()<J85),AND(L85<>"",L85<J85)),0, IF(L85="", NETWORKDAYS(J85,TODAY(),fESTIVOS!$A$2:$A$53), NETWORKDAYS(J85,L85,fESTIVOS!$A$2:$A$53) ) ) -> 1 | O85: 45859 | P85: 45860 | R85: TRUE | BF85: Se requiere implementar un hablador en la ficha de solicitudes médicas | BI85: 21/07/2025:Se realiza implementación del hablador solicitado, A la espera del visto bueno del cliente para la implementación en produccion. | BJ85: 21/07/2025: El día de ayer se realizó el paso a producción del hablador en el módulo de Solicitudes Médicas, cumpliendo con los ajustes planificados.
A86: JAIRO | B86: GD772-120 | C86: Bloqueo de facturas radicadas con información sensible y de manejo confidencialº | F86: FINALIZADO | G86: 100 | H86: =IF(OR(J86="",K86="",K86<J86),0,NETWORKDAYS(J86,K86,fESTIVOS!$A$2:$A$53)) -> 3 | I86: 45855 | J86: 45868 | K86: 45870 | L86: 45877 | M86: =IF(OR(J86="",AND(L86="",TODAY()<J86),AND(L86<>"",L86<J86)),0, IF(L86="", NETWORKDAYS(J86,TODAY(),fESTIVOS!$A$2:$A$53), NETWORKDAYS(J86,L86,fESTIVOS!$A$2:$A$53) ) ) -> 7 | O86: 45877 | P86: 45953 | Q86: Se implementó una restricción inicial para que ciertas facturas solo sean visibles por usuarios autorizados; se requiere un módulo administrativo para gestionar esta configuración. 30/07/2025: Se tiene previsto iniciar el desarrollo el día de hoy 01/08/2025: Se encuentra en desarrollo un administrador para gestionar el bloqueo de facturas. Se ha implementado la lógica, pero falta probar la interfaz administrable. El avance fue estimado en un 60% 04/08/2025:Se escaló el control de cambios MDSB-858377 al ambiente de pruebas (test) y fue ejecutado correctamente. A continuación, se procederá con las pruebas en dicho entorno. 06/08/2025: Desarrollo en el ambiente de pruebas desde 4 de agosto. 11/08/2025: Pendiente implementación de otro control para asignar permisos solo a usuarios autorizados; se espera completarlo para pasar a pruebas en TEST. 12/08/2025: Se escala a test el control de cambios MDSB-862990, el cual se encontraba pendiente. Control de cambios ejecutado con exito. 13/08/2025: Se realizó un cambio en el bloqueo de facturas y se tiene pendiente subir un ajuste de código adicional antes de enviarlo a pruebas 20/08/2025: Se encuentra en fase de pruebas. Se ajustó la validación para permitir el ingreso de múltiples usuarios asociados a una factura. Se evalúa la mejor forma de almacenar esta relación (tabla relacional o arreglo). 22/08/2025: Pendiente modificación de query para permitir múltiples usuarios por factura (actualmente solo admite uno). 25/08/2025: Se identificó la necesidad de crear una tabla de relación muchos-a-uno para habilitar acceso de múltiples usuarios a una factura. El avance depende de la radicación de un ticket en JIRA. 27/08/2025: Pendiente solicitud de control de cambios a test. 01/09/2025: Queda pendiente formalizar el Jira de control de cambios en test (Cambio Faltante). 01/09/2025: Se escala control de cambios MDSB-874296 para crear una nueva tabla llamada cm_factura_confidencial_usuario., Confirman que el control de cambios fue ejecutado correctamente. 05/09/2025: Se escala control de cambios MDSB-878302 en test para la creacion de la tabla ctas_medicas.cm_factura_confidencial_usuario. 08/09/2025: Se escala control MDSB-879140 reemplazando el MDSB-878302 ya que presento error en el script. 12/09/2025: El desarrollo ya se encuentra desplegado en ambiente de pruebas (test) y está listo para realizar las validaciones correspondientes. Se requiere coordinar las pruebas con el equipo funcional para poder solicitar el control de cambios y pasarlo a producción. 18/09/2025: Se escala control de cambios a producción MDSB-893288 25/09/2025: El control de cambios aún se encuentra pendiente de aprobación por parte del QA del cliente. 01/10/2025: El Jira MDSB-893288 control de cambios (radicado el 18 de septiembre) continúa pendiente de aprobación por parte de Ricardo Roa QA. Dado que la autorización es un requisito para avanzar 21/10/2025: Control de cambios completa aprobaciones y pasara a validaciòn de comite de cambios digitales. 22/10/2025: Control de cambios aplicado correctamente. 23/10/2025: Paso a producción con exito. | R86: TRUE | T86: MDSB-858377 / MDSB-862990/ MDSB-874296/ MDSB-878302 / MDSB-879140 | U86: MDSB-893288 | BM86: Iniciara hoy
A87: FABIO | B87: GD772-120_1 | C87: Documentación técnica GD772-120 (Bloqueo de facturas radicadas con información sensible y de manejo confidencial) | F87: FINALIZADO | G87: 100 | H87: =IF(OR(J87="",K87="",K87<J87),0,NETWORKDAYS(J87,K87,fESTIVOS!$A$2:$A$53)) -> 0 | I87: 45952 | J87: 45917 | L87: 45917 | M87: =IF(OR(J87="",AND(L87="",TODAY()<J87),AND(L87<>"",L87<J87)),0, IF(L87="", NETWORKDAYS(J87,TODAY(),fESTIVOS!$A$2:$A$53), NETWORKDAYS(J87,L87,fESTIVOS!$A$2:$A$53) ) ) -> 1 | Q87: 17/09/2025: Ducumentación tecnica entregada por Jairo 18/11/2025: Se ajusta documentación en el formato indicado y se adiciona al directorio designado, | R87: TRUE
A88: JAIRO | B88: INTERNO-JA021 | C88: Documento tecnico GD772-120 Bloqueo de facturas radicadas con información sensible y de manejo confidencial | F88: FINALIZADO | G88: 100 | H88: =IF(OR(J88="",K88="",K88<J88),0,NETWORKDAYS(J88,K88,fESTIVOS!$A$2:$A$53)) -> 0 | I88: 45877 | J88: 45917 | L88: 45917 | M88: =IF(OR(J88="",AND(L88="",TODAY()<J88),AND(L88<>"",L88<J88)),0, IF(L88="", NETWORKDAYS(J88,TODAY(),fESTIVOS!$A$2:$A$53), NETWORKDAYS(J88,L88,fESTIVOS!$A$2:$A$53) ) ) -> 1 | Q88: 18/09/2025: Documento tecnico del desarrollo fue entregado el 17 de septiembre a pruebas. | R88: TRUE
A89: JAIRO | B89: GD772-117 | C89: Reporte glosas para la Superfinanciera (migración a lago de datos de los 2 informes de glosas (arl y salud) | D89: Entrega al cliente: 4/11/2025 Solicitamos disponer del reporte de glosa en el ambiente que pueda ser migrado al lago de datos de Seguros Bolívar, por cuanto es una de las fuentes principales para el reporte que se debe transmitir cada mes a la Superfinanciera. Es importante que debe de traer todo el histórico de transacciones realizadas en Imagine. | F89: FINALIZADO | G89: 100 | H89: =IF(OR(J89="",K89="",K89<J89),0,NETWORKDAYS(J89,K89,fESTIVOS!$A$2:$A$53)) -> 0 | I89: 45953 | J89: 45958 | L89: 45965 | M89: =IF(OR(J89="",AND(L89="",TODAY()<J89),AND(L89<>"",L89<J89)),0, IF(L89="", NETWORKDAYS(J89,TODAY(),fESTIVOS!$A$2:$A$53), NETWORKDAYS(J89,L89,fESTIVOS!$A$2:$A$53) ) ) -> 5 | O89: 45965 | Q89: 29/10/2025: Se escala control de cambios MDSB-920698 a test. 30/10/2025: Control de cambios ejecutado pendiente validación de desarrollo la creacion de las tablas solicitdas 31/10/2025: El informe total de ARL fue mejorado para evitar duplicidad de valores; solo resta ajustar la lógica de repetición en los campos numéricos. Los otros cuatro informes (RIPS, Glosas, Detallado L y Detallado Salud) ya cuentan con SQL listos y sin complejidad técnica. Pendiente: Crear las tablas faltantes (una de ellas para el informe de detalle) y subir todos los informes a ambiente de test. 31/10/2025: Se escala nuevo control de cambios en test MDSB-921949 para la creación de las tablas informe_detallado_arl y informe_detallado_salud 04/11/2025: Control de cambios ejecutado con exito. 05/10/2025: Se confirmó que el 4 de noviembre quedaron todos los informes del Lago de Datos (Glosas, Detallado ARL, Detallado Salud y RIPS) ya se encuentran desplegados en ambiente de test Se entrega informe de Glosas para sus pruebas. Pendiente preparar y cuadrar el control de cambios para paso a producción, sujeto a aprobación del cliente. 19/11/2025 : Se escala control de cambios a producción MDSB-932138 y MDSB-932173. 24/11/2025: Los controles fueron aprobados por comite y ejecutados en la tarde como resultado exitoso para el MDSB-932173 y se presento error en el script del control MDSB-932138 para lo cual se debera escalar un nuevo control. 25/11/2025: Se escala nuevo control de cambios MDSB-935841 01/12/2025: Control de cambios pendiente por aprobación de QA cliente. 03/12/2025: Control de cambios ejecutado con exito el 01 de diciembre 04/12/2025: Control de cambios ejecutado con exito el 3 de diciembre. 05/12/2025: El requerimiento fue pasado a producción pero presenta un problema puntual con una fecha mal formateada en la data. Se corregirá un ajuste menor en el código. El resto del módulo asociado a largos de datos ya se encuentra en funcionamiento. 12/12/2025: El 8 de diciembre se ejecutaron y se corrigieron los errores presentados. | R89: TRUE | T89: MDSB-920698 / MDSB-921949 | U89: MDSB-932138 y MDSB-932173, MDSB-935841
A90: JAIRO | B90: GD772-117_1 | C90: Documentación tecnica. Reporte glosas para la Superfinanciera (migración a lago de datos de los 2 informes de glosas (arl y salud) | F90: FINALIZADO | G90: 100 | H90: =IF(OR(J90="",K90="",K90<J90),0,NETWORKDAYS(J90,K90,fESTIVOS!$A$2:$A$53)) -> 0 | I90: 45973 | J90: 46003 | L90: 46009 | M90: =IF(OR(J90="",AND(L90="",TODAY()<J90),AND(L90<>"",L90<J90)),0, IF(L90="", NETWORKDAYS(J90,TODAY(),fESTIVOS!$A$2:$A$53), NETWORKDAYS(J90,L90,fESTIVOS!$A$2:$A$53) ) ) -> 5 | Q90: 12/12/2025: Se solicita docuemntación a Jairo 19/12/2025: Jairo confirma que la documentacion para este requerimiento es una sola, va con la generada para el requerimiento GD772-163_1 EXPORTAR RIPS PRESTADORES y GD772-136_1 . Reporte glosas para la Superfinanciera | R90: faLSE
A91: DANILO | B91: INTERNO-D009 | C91: Script para uso de aplicaciones | F91: FINALIZADO | G91: 100 | H91: =IF(OR(J91="",K91="",K91<J91),0,NETWORKDAYS(J91,K91,fESTIVOS!$A$2:$A$53)) -> 0 | I91: 45856 | J91: 45862 | L91: 45862 | M91: =IF(OR(J91="",AND(L91="",TODAY()<J91),AND(L91<>"",L91<J91)),0, IF(L91="", NETWORKDAYS(J91,TODAY(),fESTIVOS!$A$2:$A$53), NETWORKDAYS(J91,L91,fESTIVOS!$A$2:$A$53) ) ) -> 1 | Q91: Se reallizar un script para analizar el uso de las aplicaciones por sitio. 21/07/2025: Se revisar el contexto del script y confirmar con Alejandro si ya está implementado correctamente en proteccion. 30/07/2025: Script implementado en produccion el 24 de julio | R91: TRUE | BI91: Se reallizar un script para analizar el uso de las aplicaciones por sitio. 21/07/2025: Se revisar el contexto del script y confirmar con Alejandro si ya está implementado correctamente en proteccion. | BM91: 30/07/2025: Script implementado en produccion el 24 de julio
A92: DANILO | B92: INTERNO-D010 | C92: Carga excesiva en servidor de portales | F92: FINALIZADO | G92: 100 | H92: =IF(OR(J92="",K92="",K92<J92),0,NETWORKDAYS(J92,K92,fESTIVOS!$A$2:$A$53)) -> 0 | I92: 45860 | J92: 45860 | L92: 45861 | M92: =IF(OR(J92="",AND(L92="",TODAY()<J92),AND(L92<>"",L92<J92)),0, IF(L92="", NETWORKDAYS(J92,TODAY(),fESTIVOS!$A$2:$A$53), NETWORKDAYS(J92,L92,fESTIVOS!$A$2:$A$53) ) ) -> 2 | Q92: 23/07/2025: Se ha detectado una saturación de recursos en el servidor durante la ejecución de procesos masivos, particularmente durante el cargue de incapacidades. Este es un problema de comportamiento intermitente, asociado al procesamiento en tiempo real que realiza la aplicación. Actualmente, se está evaluando la posibilidad de enviar estos procesos a colas asíncronas como alternativa para reducir el impacto en los recursos del sistema. Sin embargo, esta solución podría afectar negativamente la experiencia del usuario final al introducir demoras perceptibles. Como medida prioritaria, se recomienda solicitar una ampliación de los recursos de infraestructura (memoria RAM y CPU), lo cual se considera la solución más adecuada para mantener la eficiencia del sistema sin comprometer la experiencia del usuario. 30/07/2025: El alto consumo de recursos en el portal ya fue analizado y explicado. No se requiere intervención adicional, por lo que este punto se considera cerrado. | R92: TRUE | BL92: 28/07/2025: Se analizará la justificación para ampliar recursos del servidor (actualmente con 3 GB RAM y 2 CPU) con el fin de mitigar alertamientos por alta carga.
A93: JAIRO | B93: INTERNO-JA011 | C93: Mejoras informe EPS | F93: FINALIZADO | G93: 100 | H93: =IF(OR(J93="",K93="",K93<J93),0,NETWORKDAYS(J93,K93,fESTIVOS!$A$2:$A$53)) -> 0 | I93: 45860 | J93: 45860 | L93: 45863 | M93: =IF(OR(J93="",AND(L93="",TODAY()<J93),AND(L93<>"",L93<J93)),0, IF(L93="", NETWORKDAYS(J93,TODAY(),fESTIVOS!$A$2:$A$53), NETWORKDAYS(J93,L93,fESTIVOS!$A$2:$A$53) ) ) -> 4 | P93: 45867 | Q93: 23/07/2025: Se inició la validación del query asociado al informe EPS, con el objetivo de optimizar las consultas SQL involucradas. Esta optimización busca reducir el consumo de recursos y mejorar los tiempos de respuesta, manteniendo al mismo tiempo una estructura común y reutilizable para todos los informes. Como parte del plan de trabajo, se espera que el informe EPS esté ajustado y en producción antes del viernes. 25/07/2025: Se completó el query principal del informe EPS y se encuentra en fase de pruebas, con un avance estimado del 50%. 28/07/2025: Query principal terminado, se espera subirlo a producción para pruebas con datos reales hoy antes del mediodía. 30/09/2025: El informe fue desplegado en producción con formato de prueba. Se corrigieron errores detectados durante la validación (especialmente en el formato de horas). Actualmente se encuentra en fase final de pruebas para habilitar completamente su funcionamiento. | R93: TRUE | BM93: Se paso a produccion 29 de julio
A94: JESUS | B94: INTERNO-JE008 | C94: Inconsistencia en cargue de proveedores Yii | F94: FINALIZADO | G94: 100 | H94: =IF(OR(J94="",K94="",K94<J94),0,NETWORKDAYS(J94,K94,fESTIVOS!$A$2:$A$53)) -> 0 | I94: 45861 | J94: 45861 | L94: 45862 | M94: =IF(OR(J94="",AND(L94="",TODAY()<J94),AND(L94<>"",L94<J94)),0, IF(L94="", NETWORKDAYS(J94,TODAY(),fESTIVOS!$A$2:$A$53), NETWORKDAYS(J94,L94,fESTIVOS!$A$2:$A$53) ) ) -> 2 | Q94: Al cargar un archivo que contiene varias filas con la misma cédula de ciudadanía (CC), solo se conserva o registra la última fila, y las anteriores se pierden del sistema. 25/07/2025:El día 24 de julio se realizaron los ajustes correspondientes a las validaciones, quedando el proceso de cargue completamente funcional en test | R94: TRUE
A95: JESUS | B95: MDSB-851497 | C95: Jiras dia dia Validar tipologia Gestion Tercero Sin Poliza" no Genera informe por tipologia. | F95: FINALIZADO | G95: 100 | H95: =IF(OR(J95="",K95="",K95<J95),0,NETWORKDAYS(J95,K95,fESTIVOS!$A$2:$A$53)) -> 0 | I95: 45861 | J95: 45861 | L95: 45861 | M95: =IF(OR(J95="",AND(L95="",TODAY()<J95),AND(L95<>"",L95<J95)),0, IF(L95="", NETWORKDAYS(J95,TODAY(),fESTIVOS!$A$2:$A$53), NETWORKDAYS(J95,L95,fESTIVOS!$A$2:$A$53) ) ) -> 1 | Q95: 25/07/2025: El 23 de julio se realizó la validación correspondiente y se identificó que el módulo no muestra información disponible para descarga, debido a que la tipología "Gestión Tercero Sin Póliza" no incluye en su flujo la actividad de generación de respuesta. Esta actividad es una condición necesaria para que una tipología sea considerada dentro del informe de tipologías | R95: TRUE
A96: JESUS | B96: INTERNO-JE029 | C96: centralizar la ejecución de jobs en el servidor Laravel | D96: Se acordó centralizar la ejecución de jobs en el servidor Laravel (servidor público) y no en el servidor privado de portales, con el fin de evitar saturación, duplicidad de procesos y problemas de mantenimiento | F96: FINALIZADO | G96: 100 | H96: =IF(OR(J96="",K96="",K96<J96),0,NETWORKDAYS(J96,K96,fESTIVOS!$A$2:$A$53)) -> 0 | I96: 46009 | J96: 46010 | L96: 46010 | M96: =IF(OR(J96="",AND(L96="",TODAY()<J96),AND(L96<>"",L96<J96)),0, IF(L96="", NETWORKDAYS(J96,TODAY(),fESTIVOS!$A$2:$A$53), NETWORKDAYS(J96,L96,fESTIVOS!$A$2:$A$53) ) ) -> 1 | O96: 46010 | P96: 46020 | Q96: 22/12/2025: El Viernes 19 de diciembre se realizó la migración de dos colas desde Portales hacia Bolívar para centralizar la ejecución de procesos y evitar saturación. En ambiente local las pruebas fueron exitosas; en Test quedan pendientes validaciones adicionales. Una vez validado, en producción solo será necesario apagar la cola de Portales y realizar el cargue de prueba correspondiente 29/12/2025: La semana anterior se realizó la migración de una cola que estaba en portales hacia el servidor antiguo de Bolívar para evitar conflictos de despliegue. Se creó una nueva cola y se actualizó la configuración correspondiente. El pendiente es el despliegue en producción de dos ramas (Portales y Bolívar) y la recarga del archivo de configuración, actividad prevista para el día de hoy Se realiza paso a producción con pruebas exitosas de parte de Danilo y Jesus. | R96: TRUE | V96: https://github.com/Imaginesas/bolivar/compare/master...hotfix/copiarJobsPortales https://github.com/Imaginesas/portales/compare/master...hotfix/quitarJobPortales
A97: JAIRO | B97: GD772-162 | C97: Ajuste servicio de Olimpia - Registraduria API | D97: Fecha de entrega al cliente: 16 de Enero de 2026 Implementar la integración con el servicio externo Olimpia para la validación de identidad ciudadana (registraduría). El sistema deberá recibir, almacenar y gestionar los tokens de autenticación que provee Olimpia, garantizando seguridad y trazabilidad en los procesos de validación. Se busca unificar el manejo de tokens utilizados en los diferentes módulos en una sola tabla centralizada, evitando duplicidad de estructuras | F97: FINALIZADO | G97: 100 | H97: =IF(OR(J97="",K97="",K97<J97),0,NETWORKDAYS(J97,K97,fESTIVOS!$A$2:$A$53)) -> 0 | I97: 46010 | J97: 46010 | L97: 46013 | M97: =IF(OR(J97="",AND(L97="",TODAY()<J97),AND(L97<>"",L97<J97)),0, IF(L97="", NETWORKDAYS(J97,TODAY(),fESTIVOS!$A$2:$A$53), NETWORKDAYS(J97,L97,fESTIVOS!$A$2:$A$53) ) ) -> 2 | O97: 46013 | P97: 46044 | Q97: 22/10/2025: Se Iniciara tan pronto finalice el desarrollo del req GD772-159 (Jira). 24/10/2025: El requerimiento será abordado por Wilson, quien reutilizará estructuras y rutas ya desarrolladas. Se debe crear una nueva tabla para almacenar tokens y marcar los asociados al servicio de Olimpia. Se coordinó con Jairo para brindar contexto técnico durante la implementación. 26/11/2025: Este requerimeinto es reasignado a Jesus . 19/12/2025: El requerimiento continuara a carga de Jairo, se solicita control de cambios en test MDSB-950030 22/12/2025: Se finalizó la descarga y ajuste de información relacionada con la registraduría, incluyendo los centros de costo adicionales solicitados. Se encuentra lista para avanzar a la siguiente etapa, quedando pendiente únicamente el GIRA correspondiente para su paso formal. El control de cambios MDSB-950030 se cnfirma ha quedado ejecutado en test. 23/12/2025: El 22 de diciembre se realiza justes en la integración con el servicio de consulta de la Registraduría se agregaron cambios para la autenticacion con olimpia y posterior manejo de respuesta. 16/01/2026: Se realiza la entrega al cliente para pruebas y aprobación. Una vez validado, se solicita la gestión del control de cambios correspondiente para el ambiente productivo (PRD), con el fin de realizar el paso a producción. 19/01/2026: Cliente confirma aprobación de paso a producción, se procedera a escalar control de cambios 20/01/2026: Se escala control de cambios a producción MDSB-963871. 21/01/2026: Control de cambios ejecutado correctamente, se realizara paso a producción. 22/01/2026: Se realiza paso a producciòn | R97: TRUE | S97: 2 | T97: MDSB-950030 | U97: MDSB-963871
A98: FABIO | B98: GD772-162_1 | C98: Documentación tecnica_Ajuste servicio de Olimpia - Registraduria API | F98: PENDIENTE | H98: =IF(OR(J98="",K98="",K98<J98),0,NETWORKDAYS(J98,K98,fESTIVOS!$A$2:$A$53)) -> 0 | I98: 46042 | M98: =IF(OR(J98="",AND(L98="",TODAY()<J98),AND(L98<>"",L98<J98)),0, IF(L98="", NETWORKDAYS(J98,TODAY(),fESTIVOS!$A$2:$A$53), NETWORKDAYS(J98,L98,fESTIVOS!$A$2:$A$53) ) ) -> 0 | Q98: 20/01/2026: Tan pronto se pase el requerimiento a producción se soicitaran los script a Jairo para elaborar la documentación tecnica. 09/02/2026: Se solicita a los scripts para realizar la documentación 11/02/2026: Se solicita a los scripts para realizar la documentación. | R98: false
A99: JESUS | B99: GD772-146 | C99: Doble factor de autentticación (Correo) | D99: Fecha de entrega al cliente: 14/11/2025 Doble factor de autenticación 1. DESCRIPCIÓN DEL REQUERIMIENTO Se requiere crear un doble factor de autenticación como control de seguridad en ambientes de test y producción para todos los aplicativos (nativo, YII, laravel) 1.2 OBJETIVO Crear un doble factor de autenticación por correo electrónico 1.3 EQUIPO DE TRABAJO Nombre Área Leidy Mayorga Administrativo 2. REQUERIMIENTOS FUNCIONALES 2.1 Creación de un doble factor de autenticación Se requiere que al momento de loguearse los aplicativos nativo, YII y laravel soliciten un doble factor de autenticación, el cual deberá ser remitido al correo electrónico registrado, teniendo en cuenta: 1. Si el usuario únicamente está en nativo deberá tomar el correo electrónico registrado 2. Si el usuario está en nativo y otro aplicativo (YII y laravel), deberá tomar el correo electrónico registrado en nativo y homologarlo en todos los aplicativo; garantizando que en todos los aplicativos tenga el mismo correo electrónico. 3. Cuando se actualice un correo electrónico automáticamente se debe actualizar para el doble factor de autenticación. Una vez llegue el código del doble factor al correo electrónico, el usuario deberá registrarlo en el aplicativo para el acceso. El doble factor debe salir por Exchange. SEGUROS BOLÍVAR S.A. OFICINA DE PROYECTOS (PMO) FORMATO ESPECIFICACIÓN DETALLADA DEL REQUERIMIENTO DE USUARIO FORMATO ESPECIFICACIÓN DETALLADA DEL REQUERIMIENTO _ Versión Septiembre 2012 Este documento es propiedad intelectual de Seguros Bolívar S.A. Prohibido el uso, reproducción y/o distribución sin autorización de la compañía. 2 2.2 Omisión en listas blancas por usuario Se requiere que al momento de loguearse no solicite el doble factor de autenticación para los usuarios o IP que registran en las listas blancas, la omisión deberá aplicar para nativo, YII y laravel. Se debe poder incluir y eliminar IP y usuarios de la lista. Esto con el propósito de mantener los RPA actuales. 2.3 Consulta listas blancas Se requiere que las restricciones de listas blancas sean identificadas, por lo cual es necesario que en el módulo de consulta registre: IP o usuario Fecha en la cual se registro Usuario que registró Estado (activo o inactivo de la lista blanca) Esto con el objetivo de conocer el estado de los usuarios e IP omitidas sin necesidad de consultar el usuario puntual , si no que muestre las existentes. | F99: FINALIZADO | G99: 100 | H99: =IF(OR(J99="",K99="",K99<J99),0,NETWORKDAYS(J99,K99,fESTIVOS!$A$2:$A$53)) -> 0 | I99: 45954 | J99: 45957 | L99: 45982 | M99: =IF(OR(J99="",AND(L99="",TODAY()<J99),AND(L99<>"",L99<J99)),0, IF(L99="", NETWORKDAYS(J99,TODAY(),fESTIVOS!$A$2:$A$53), NETWORKDAYS(J99,L99,fESTIVOS!$A$2:$A$53) ) ) -> 18 | O99: 45982 | P99: 46055 | Q99: 27/10/2025: Iniciara con la configuración de los sitios en local 31/10/2025: Se avanza en la implementación del segundo factor de autenticación con validaciones de usuario y contraseña operativas en Laravel. Pendiente: Ajustar el control del flujo de autenticación para evitar logueo sin validación. Integrar el flujo de listas blancas (usuarios exentos del doble factor). Definir tiempo de expiración del token según políticas de seguridad (30 minutos actuales deben revisarse). Se escala Control de cambios MDSB-921839 a test. Control de cambios genero error por lo cual se genero el MDSB-922162 04/11/2025: Control de cambios ejecutado con exito 05/11/2025: Se continúa con el ajuste final del desarrollo en Laravel, una vez concluya las pruebas locales, procederá a migrar el desarrollo a los demás sitios uno a uno y dejarlo en ambiente de test, para posteriormente definir quién realizará el despliegue a producción. 07/11/2025: El 28 de octubre se envian HU al cliente para su aprobación,Pendiente confirmación de tiempos de vigencia del token y unificación del proceso de autenticación. Enviada solicitud a Seguridad para definir tiempos de expiración 07/11/2025: Ciente confirma que el tiempo del token debe ser de 1 minuto y no autorizan la unificación del proceso de autenticación. 20/11/2025: Se realiza sesión con Wilson y Jesús para la entrega de los avances desarrollados por Wilson a Jesús. Jesús continuará con la implementación de la autenticación por correo en los aplicativos Yii y Nativo, así como con la incorporación de las listas blancas correspondientes. 24/11/2025: Se integró el trabajo previo con la lógica del Authenticator ajustando tablas y unificando la validación para las tres aplicaciones. Queda pendiente aplicar estilos al correo del código de verificación. Funcionalidad general opera correctamente 25/11/2025: El 24 de noviembre se entrega desarrollo al cliente para sus pruebas y aprobación de paso a producción 26/11/2025: El cliente esta realizando pruebas ayer y hoy. La funcionalidad está estable; pendiente acompañamiento para resolver cualquier incidencia que se presente durante su validación. 07/01/2026: El cliente envía la relación de correos electrónicos actualizados para su respectiva validación y uso en el proceso. 08/01/2026: Cliente da visto bueno para realizar paso a producción, se solicitar control de cambios a producción. 09/01/2026: Se escala control de cambios a produccion MDSB-958656 16/01/2026: El cliente adjunta al requerimiento las pruebas realizadas en test, el control de cambios avanza hacia las aprobaciones de QA / PO / Jefatura. 20/01/2026: Control de cambios se encuentra pendiente por aprobación de Jefatura 21/01/2026: Control de cambios ejecutado con exito, se programa paso a producción para el 22 de enero. 22/01/2026: No es posible realizar el despliegue a producción ya que hay una regla de seguridad que no permitió abrir la URL por ser muy larga, 26/01/2026: Se solucionó el problema generado por la longitud de la URL. Se implementó un esquema basado en ID temporal encriptado, almacenando la información en tabla y transmitiendo únicamente el identificador. La solución ya funciona en Laravel y hoy se implementara la soluciona en Yii y Nativo. 28/01/2026: El 27 de enero se completaron las pruebas del nuevo esquema de doble factor, reemplazando el envío de datos en la URL por un ID temporal encriptado almacenado en base de datos. El cambio ya fue validado en Nativo, Yii y Bolívar y se encuentra listo para pasar a producción, pendiente únicamente de nuevas pruebas por parte del cliente. 29/01/2026: Durante el seguimiento, el cliente informa que las pruebas fueron exitosas; sin embargo, surgió un error en la creación de un usuario, ya que en Nativo se registró con un correo y en Yii con otro. Indican que realizarán nuevamente la prueba y nos confirmarán la descripción del proceso y el error. 30/01/2026: Cliente informa que realiza pruebas y el error no volvio a salir, aprueba pasa a producción. 02/02/2026: Se confirmó la autorización para pasar a producción. El despliegue quedó programado para realizarse hoy a las 5 pm. 03/02/2026: El 2 de febrero se realiza paso a produccion con exito, | R99: TRUE | T99: MDSB-921839 /MDSB-922162 | U99: MDSB-958656 | V99: https://github.com/Imaginesas/bolivar/compare/master...feature/despliegue-login
A100: JESUS | B100: MDSB-962452 | C100: GD772-146 Doble factor – Actualización y unificación de correos en PRD | D100: Se recibió el visto bueno del cliente y el listado definitivo de correos a actualizar, conservar o inactivar. Se definió que la información válida será la contenida en la tabla principal (Yii/nativo. El ajuste se realizará mediante query de base de datos garantizando la unificación de correos sin afectar la integridad de la información. | F100: FINALIZADO | G100: 100 | H100: =IF(OR(J100="",K100="",K100<J100),0,NETWORKDAYS(J100,K100,fESTIVOS!$A$2:$A$53)) -> 0 | I100: 46038 | J100: 46038 | L100: 46038 | M100: =IF(OR(J100="",AND(L100="",TODAY()<J100),AND(L100<>"",L100<J100)),0, IF(L100="", NETWORKDAYS(J100,TODAY(),fESTIVOS!$A$2:$A$53), NETWORKDAYS(J100,L100,fESTIVOS!$A$2:$A$53) ) ) -> 1 | P100: 46038 | Q100: 16/01/2026: Querys ejecutados, correos iguales en las 4 db y usuarios inactivados en las 3 db porque en la de laravel habria que eliminarlos porque no tiene campo de inactivar | R100: True
...

Sheet EN PROCESO (Alfa)
A1: Asignado a | B1: # REQ | C1: Requerimiento | D1: Detalle del requerimiento | E1: Proceso | F1: ESTADO | G1: % | H1: Dias estimados desarrollo | I1: F.Asignado | J1: Fecha inicio | K1: Fecha estimada de entrega | L1: Finalizado | M1: Dias total desarrollo | N1: Fecha compromiso cliente | O1: TEST | P1: PRODUCCION | Q1: OBSERVACIONES | R1: Visible | S1: OBSERVACIONES ALFA
A2: MAURICIO | B2: PRV_2025_001_1 | C2: REVISIÓN DE LIQUIDACIÓN PARA PAGO, | E2: Previsional | F2: FINALIZADO | G2: 100 | H2: =IF(OR(J2="",K2="",K2<J2),0,NETWORKDAYS(J2,K2,fESTIVOS!$A$2:$A$53)) -> 90 | J2: 45691 | K2: 45821 | L2: 45824 | M2: =IF(OR(J2="",AND(L2="",TODAY()<J2),AND(L2<>"",L2<J2)),0, IF(L2="", NETWORKDAYS(J2,TODAY(),fESTIVOS!$A$2:$A$53), NETWORKDAYS(J2,L2,fESTIVOS!$A$2:$A$53) ) ) -> 91 | P2: 45843 | Q2: Se notifica por par parte del jefe de unidad inconsistencias en Vistas de las fuentes de información entregadas. Carecen de data necesaria, 09/06/2025 :El requerimirneo fue pausado 12 mayo de 2025 10/06/2025: Hoy se definira si se contunua con el desarrollo o continua pausado. 11/06/2025: Ya se cuenta con los permisos y el query para la vista. Se sincronizan las reclamaciones de Cifren, pero falta integrar las de Plus (montadas en AWS) y ajustar la identificación del origen de cada reclamación. Se estima que este requerimiento adicional tomará un día de trabajo Iniciando el 12 de Junio 13/06/2025: Se obtuvo respuesta positiva sobre permisos para acceder a la vista de Plus. Sin embargo, falta que la vista tenga datos reales para completar la sincronización. 16/06/2025 : Se completó la primera fase de validación y hoy se trabaja en la parte de gestión de pagos, cliente realizara pruebas hoy 17/06/2025: Se realizan en ajustes en la mañana de hallasgoz reportados por el cliente tras las pruebas, y se entregaran al cliente para sus pruebas. 18/06/2025: Se adaptó el grid y los reportes a los distintos roles/permisos. También se incorporaron nuevos campos a solicitud del cliente; pendiente Pruebas por el cliente. 19/06/2025; supero pruebas del cliente y se aprueba paso a produccion para el dia sabado 21 de Junio.. 24/06/2025; Alfa aplazó el paso a produccion para el 5 de julio, debido a que tenían actualizaciones pendientes. Además, dependemos de la disponibilidad de ciertas vistas en el ambiente de producción para continuar con el proceso. 07/07/2025: Se realiza paso a produccion el 5 de julio. | R2: TRUE
A3: MAURICIO | B3: PRV_2025_001_2 | C3: VALIDACIÓN DE LOTE PARA PAGO, NOTIFICACIÓN DE PAGO | E3: Previsional | F3: FINALIZADO | G3: 100 | H3: =IF(OR(J3="",K3="",K3<J3),0,NETWORKDAYS(J3,K3,fESTIVOS!$A$2:$A$53)) -> 3 | I3: 45824 | J3: 45824 | K3: 45826 | L3: 45827 | M3: =IF(OR(J3="",AND(L3="",TODAY()<J3),AND(L3<>"",L3<J3)),0, IF(L3="", NETWORKDAYS(J3,TODAY(),fESTIVOS!$A$2:$A$53), NETWORKDAYS(J3,L3,fESTIVOS!$A$2:$A$53) ) ) -> 4 | P3: 45843 | Q3: El 16 de junio se inicia desarrollo confecha estimada de finalizacion 18 de junio. 18/06/2025: El 17 de junio se desarrollan dos informes adicionales: tesorería y porvenir, con definición de estructura en curso. 19/06/2025: Entrega al cliente para pruebas 19 de junio, Cliente solicita ajuste de vistas y campos necesarios para el proceso. 24/06/2025; Alfa aplazó el paso a produccion para el 5 de julio, debido a que tenían actualizaciones pendientes 07/07/2025: Se realiza paso a produccion el 5 de julio. | R3: TRUE
A4: MAURICIO | B4: PRV_2025_004 | C4: AUXILIOS FUNERARIOS PAGO AUX. FUNERARIOS | E4: Previsional | F4: FINALIZADO | G4: 100 | H4: =IF(OR(J4="",K4="",K4<J4),0,NETWORKDAYS(J4,K4,fESTIVOS!$A$2:$A$53)) -> 4 | J4: 45827 | K4: 45833 | L4: 45841 | M4: =IF(OR(J4="",AND(L4="",TODAY()<J4),AND(L4<>"",L4<J4)),0, IF(L4="", NETWORKDAYS(J4,TODAY(),fESTIVOS!$A$2:$A$53), NETWORKDAYS(J4,L4,fESTIVOS!$A$2:$A$53) ) ) -> 9 | P4: 45843 | Q4: Cargue de formatos de formalización y consolidado 100% Opción de edición y opción de histórico del flujo 100% Se notifica por par parte del jefe de unidad inconsistencias en Vistas de las fuentes de información entregadas. Carecen de data necesaria 09/06/2025 :El requerimirneo fue pausado el 6 de junio de 2025. 16/06/2025: Se comenzarán el jueves 19 de junio. Ya se están creando las vistas necesarias para ese flujo 19/06/2025: Inicio del desarrollo. 20/06/2025:No se pudo avanzar ayer 19 de junio por ajustes requeridos por el cliente para PRV_2025_001 VALIDACIÓN DE LOTE PARA PAGO,NOTIFICACIÓN DE PAGO, Se retomara desarrollo 24 de junio. 24/06/2025; Se encuentra sincronizando data, se estiman 2 dias para finalizar. 25/06/2025:Se ajustó la lógica del requerimiento tras diferenciarlo claramente del flujo de pagos. Se avanzó en la creación de vistas y en la sincronización inicial de datos. Se espera tener el desarrollo listo para pruebas el jueves 26. Se planea agregar botones para sincronización (Pago,auxilio y exportar) diferenciada según permisos,crear tabla de auxilios x año, ajustar campos (encabezados)de la vista de gestion y ajustar modulo de consulta. 26/06/2025: Se avanzó satisfactoriamente en la creación de la tabla de auxilios por año, el ajuste de encabezados en la vista de gestión y la incorporación de los botones de sincronización según permisos. PENDIENTE, Está pendiente la solución del error en la sincronización masiva, lo cual impide avanzar con la exportación y cargue de información. También sigue sin ajustes el módulo de consulta para auxilios. 27/06/2025: pendiente: 1. asignar opcion de pendientes 2. Ver consolidado pagos. (se envia masivamente y aprueba por el flujo para pasar a pagos). 3. Generar informe radicacion pagos plus. Se estima toda la entrega para hoy 01/07/2025: Se ha avanzado en un 75% del desarrollo, incluyendo funcionalidades principales. El cierre del tema está previsto para hoy, Faltan por implementar la generación de informes, la edición de fecha de siniestro y valor, así como la opción de marcar como pendiente. 02/07/2025:El desarrollo del módulo de auxilios funerarios presenta un avance estimado del 90%. Ya se encuentra implementada la funcionalidad principal, incluyendo la creación de vistas, funciones de sincronización y flujo de radicación hasta aprobación. Se están finalizando los ajustes a los reportes en Excel, Se programó una sesión de revisión hoy a las 2:00 p.m. para validación funcional y ajuste de pendientes. 04/07/2025: Se resolvió un error en la validación de pagos, el módulo ya está funcional. Se finalizó el desarrollo y se ajustaron validaciones necesarias para la gestión masiva y manual. Solo queda pendiente la validación del cliente, ya que la sesión programada fue cancelada. 07/07/2025: Se Pasado a producción el 5 de julio sin habilitar el menú. Faltan validaciones finales por el cliiente. 16/07/2025: Las pruebas no se han culminado por un error en el sistema del cliente al cargar unos registros. Sin estos registros no puedo ver la data que necesitamos en Imagine. 29/07/2025: Se proyecta acompañar al àrea para realizar pruebas con los recursos existentes para ya dejar cerrado el requerimiento 01/08/2025: Hoy se retoma el módulo con el cliente, para validar que se tiene hasta el momento, funcionalidad y posibles desviaciones, para dar gestion y cierre del requerimiento 04/08/2025: Se continùa validaciones y ajustes correspondientes para proyectar paso a producciòn el viernes 08 de agosto 12/08/2025: Debido a incidencia presentada en la conexión Plus + UAT , no fue posible el paso a producciòn el viernes 08 de agosto, por tanto se proyecta el despliegue para el viernes 15 de agosto 20/08/2025: Despliegue a produccion realizado en 15 de Agosto. | R4: TRUE | S4: 15/07/2025 Ya se encuenra en produccion
A5: MAURICIO | B5: PRV_2025_009 | C5: DESARROLLO PREVISIONALES INCAPACIDADES | E5: Previsional | F5: FINALIZADO | G5: 100 | H5: =IF(OR(J5="",K5="",K5<J5),0,NETWORKDAYS(J5,K5,fESTIVOS!$A$2:$A$53)) -> 3 | I5: 45817 | J5: 45817 | K5: 45819 | L5: 45820 | M5: =IF(OR(J5="",AND(L5="",TODAY()<J5),AND(L5<>"",L5<J5)),0, IF(L5="", NETWORKDAYS(J5,TODAY(),fESTIVOS!$A$2:$A$53), NETWORKDAYS(J5,L5,fESTIVOS!$A$2:$A$53) ) ) -> 4 | P5: 45843 | Q5: 09/06/2025: El Objetivo Automatizar el cálculo de incapacidades en el sistema Imagine, replicando el proceso manual actual utilizado por los liquidadores y presentando los resultados en un formato claro y compatible con Excel.\niniciara con el desarrollo. 11/06/2025: Mauricio completó la función de cálculo y está terminando el formulario de consulta. Planea entregar el requerimiento completo hoy para subir a pruebas el jueves. 13/06/2025: Ya fue entregado en ambiente de pruebas para validación del cliente. Está funcionando correctamente y aplicando los cálculos según lo solicitado. 9/06/2025: Paso a produccion para el 21 de junio. 24/06/2025: Fala aplazó el paso a produccion para el 5 de julio, debido a que tenían actualizaciones pendientes. 07/07/2025: Igual que Auxilios se paso a producciòn el 5 de julio sin habilitar el menu. Se requiere validación del cliente para habilitar. 16/07/2025: Requerimiento funcional en produccion con el menu habiitado. | R5: TRUE | S5: 15/07/2025 Ya se encuenra en produccion
A6: MAURICIO | B6: PRV_2025_007 | C6: CALCULO IBL | E6: Previsional | F6: FINALIZADO | G6: 100 | H6: =IF(OR(J6="",K6="",K6<J6),0,NETWORKDAYS(J6,K6,fESTIVOS!$A$2:$A$53)) -> 2 | I6: 45817 | J6: 45841 | K6: 45842 | L6: 45842 | M6: =IF(OR(J6="",AND(L6="",TODAY()<J6),AND(L6<>"",L6<J6)),0, IF(L6="", NETWORKDAYS(J6,TODAY(),fESTIVOS!$A$2:$A$53), NETWORKDAYS(J6,L6,fESTIVOS!$A$2:$A$53) ) ) -> 2 | P6: 45852 | Q6: 11/06/2025: Continuara con el desarrollo tras finalizar req PRV_2025_001 REVISIÓN DE LIQUIDACIÓN PARA PAGO 13/06/2025:Se programó su inicio para hoy. Mauricio confirmara la estimación del tiempo de desarrollo. 16/06/2025: Se requiere una sesion con Carlos, Jenry, Mauricio y Fabio para entender el detalle de validaciones. Aún no se tiene fecha ni estimación. 04/07/2015:Se inicia desarrollo con un avance del 20%. Se ajustaron funciones en Postgres para cálculos correctos según las vistas generadas. El siguiente paso es crear la funcionalidad de consulta por cédula o siniestro y desplegar cálculos de acuerdo a la fecha indicada. Se estima finalizar req hoy para realizar paso a produccion el 5 de julio. 07/07/2025: Se realizo paso a producciòn el 5 de Julio sin habiitar el menu, Faltan pruebas formales del cliente para habilitación final. 11/07/2025: El 10 de julio se realizó un ajuste para excluir los casos con auxilios funerarios. Ahora, el sistema valida que el origen del caso sea únicamente incapacidad o supervivencia; en caso contrario, se lanza una alerta. 16/07/2025: Se realiza paso a producción el 14 de julio en la noche. | R6: TRUE | S6: 10/07/2025 Posterior a pruebas se solicito ajuste a Mauricio para que no mostrara informacion diferentes a cod_origen 1,2 15/07/2025 Ya se encuenra en produccion
