Workbook

Sheet EN PROCESO (Colmedica)
A1: Asignado a | B1: ID REQ | C1: Requerimiento | D1: Descripcion req | E1: Actividad | F1: ESTADO | G1: % AVANCE | H1: Dias estimados de desarrollo | I1: F.Asignado | J1: Fecha inicio | K1: F. estimada de entrega | L1: Finalizado | M1: Dias | N1: Fecha compromiso cliente | O1: FECHA PASO A TEST | P1: FECHA PASO A PRODUCCION | Q1: DESCRIPCION DEL AVANCE | R1: visible
A2: JHON | B2: 309 | C2: Cuentas Medicas UMD - Lectura OCR - Datos Digitación | D2: De la Lectura de Texto u OCR tomar información para el proceso de captura de información y validación de los documentos Facturas - Cuentas de Cobrro, y Captura de PILA, una vez tipificadas, tomar la información necesaria para el proceso de digitación segun preguntas para validar para traer información, o marca para saber que si cumple Factura - Fecha radicación - fecha expedicion ▪ "CUENTA CON NIT Y RAZON SOCIAL CORRECTA DE UMD" ( 830001007 - UNIDAD MEDICA Y DE DIAGNOSTICO S.A) ▪ "CUENTA CON FECHA DE EXPEDICIÓN" ▪ "PRESTADOR RADICA DOCUMENTO FACTURA DE VENTA" ▪ "LA FACTURA DE VENTA PRESENTA RESOLUCION DIAN VIGENTE" ▪ "ID Y NOMBBRE PRESTADOR COINCIDE CON FIRMA DE LA CUENTA" ▪ "CUENTA CON FIRMA" ▪ "CUENTA CON DETALLE BIEN TOTALIZADO" ▪ "VALOR DE LETRAS COINCIDE CON VALOR TOTAL EN NUMEROS DE CUENTA" Pila para la captura de la información necesaria o Nro Planilla o IBC o Fecha de pago - (20250609) o Periodo - (202506) o EPS – Valor o Fondo Pensiones – Valor o Arl – Valor o Caja de Compensación – Valor | F2: FINALIZADO | G2: 100 | H2: =IF(OR(J2="",K2="",K2<J2),0,NETWORKDAYS(J2,K2,Hoja2!$A$2:$A$53)) -> 14 | I2: 45835 | J2: 45841 | K2: 45860 | L2: 45860 | M2: =IF(OR(J2="",AND(L2="",TODAY()<J2),AND(L2<>"",L2<J2)),0, IF(L2="", NETWORKDAYS(J2,TODAY(),Hoja2!$A$2:$A$53), NETWORKDAYS(J2,L2,Hoja2!$A$2:$A$53) ) ) -> 14 | O2: 45861 | P2: 45861 | Q2: 27/06/2025 Nuevo - Imagine 03/07/2025 Se recupera información para cuentas de cobro 11/07/2025 Se recupera información de encabezado de pila (planilla, fecha de pago y periodo de pago) 17/07/2025 Se recupera información de valores($) por tipo de servicio (Salud, riesgos laborales, pensiones y caja de compensación) 21/07/2025 Los datos recuperados son guardados en la base de datos para su posterior validación 23/07/2025 Despliegue y validación en pruebas, luego de lavidación despliegue en producción | R2: True
A3: JHON | B3: 310 | C3: Afiliaciones PRE - Validación Cancelaciones Apolo (Lectura TXT) | D3: como debe quedar como tarea programada el sistema debe tomar la información de la ruta \imagine\CarguesPRE\Reporte_Cancelacion_Exclusion.txt y una vez se tome el archivo y se almacene la información en la tabla, renombrarlo Reporte_Cancelacion_Exclusion_yyyymmdd_HH_ss.txt y moverlo a la carpeta del año actual \imagine\CarguesPRE\añoactual Se debe crear tabla para almacenar la información del archivo txt ejemplos \imagine\CarguesPRE Reporte_Cancelacion_Exclusion20250601_20250615.txt Reporte_Cancelacion_Exclusion20250501_20250531.txt Solo almacenar en la tabla los registros que Usuario sean estos MRUBIANO, ALICETHR, WilliamB y que la Causal no sea esta (SIN CERTIFICACION EPS) la estructura de la tabla es la información del archvio y adicionar estos campos que se modificaran de acuerdo a la revision realizada, fechainsert defecto, estado defecto 0, solicitud texto defecto 0, usuariogestion, fechahoragestion, observacion estado 0 pendiente 1 cargada 2 validada 1. proceso tarea programada que tome el archivo de una ruta para insertar en la tabla y luego hacer el barrido de lo que esté en la tabla estado 0 solicitud 0 con la siguiente consulta select f01 from bkencpre as p, bkdetpre as d where p.sr = d.sr and f28 = 43559206 and d.fechainsert=20250502 group by f01 (variables del query son estos campos Numero de Id,Fecha de ejecucion) si encuentra solicitudes guardar los números del f01 en la tabla separados por (,) en el campo nuevo solicitud, dejar el estado en 1, usuariogestion = Sistema | F3: FINALIZADO | G3: 100 | H3: =IF(OR(J3="",K3="",K3<J3),0,NETWORKDAYS(J3,K3,Hoja2!$A$2:$A$53)) -> 3 | I3: 45835 | J3: 45839 | K3: 45841 | L3: 45841 | M3: =IF(OR(J3="",AND(L3="",TODAY()<J3),AND(L3<>"",L3<J3)),0, IF(L3="", NETWORKDAYS(J3,TODAY(),Hoja2!$A$2:$A$53), NETWORKDAYS(J3,L3,Hoja2!$A$2:$A$53) ) ) -> 3 | O3: 45849 | P3: 45870 | Q3: 27/06/2025 Nuevo - Imagine/Cliente 01/07/2025 Se Inicia el desarrollo 3/07/2025 se termina el desarrollo ... 11/07/2025 se dispone en el servidor de pruebas para ser revisado por Jennifer | R3: True
A4: JHON | B4: 310_1 | C4: Afiliaciones PRE - Validación Cancelaciones Apolo (UI) | D4: 2. Bandeja de trabajo (definir sitio) donde se listen los registros que quedaron con estado 0 solicitud 0, permitiendo obtener la observación del análisis que haga la persona, y registrar observacion, usuariogestion usuario de sesión, fechahoragestion la de la revisión, y actualizar el estado en 2 | F4: FINALIZADO | G4: 100 | H4: =IF(OR(J4="",K4="",K4<J4),0,NETWORKDAYS(J4,K4,Hoja2!$A$2:$A$53)) -> 0 | I4: 45835 | J4: 45870 | K4: 45853 | L4: 45870 | M4: =IF(OR(J4="",AND(L4="",TODAY()<J4),AND(L4<>"",L4<J4)),0, IF(L4="", NETWORKDAYS(J4,TODAY(),Hoja2!$A$2:$A$53), NETWORKDAYS(J4,L4,Hoja2!$A$2:$A$53) ) ) -> 1 | O4: 45870 | P4: 45870 | Q4: 27/06/2025 Nuevo - Imagine/Cliente 01/08/2025 se realiza primera entrega UI de test 01/08/2025 se realiza ajustes solicitados en primera entrega y se pasa a pruebas y producción | R4: True
A5: JHON | B5: 306 | C5: Lectura XML PBS - Afiliaciones POS | D5: La información de las afiliaciones de PBS ahora se recibirá en XML, desarrollar la opción para interpretar el XML y posterior ajuste a la plataforma, para relacionarla con las tabla actuales del proceso | F5: FINALIZADO | G5: 100 | H5: =IF(OR(J5="",K5="",K5<J5),0,NETWORKDAYS(J5,K5,Hoja2!$A$2:$A$53)) -> 3 | I5: 45804 | J5: 45877 | K5: 45881 | L5: 45881 | M5: =IF(OR(J5="",AND(L5="",TODAY()<J5),AND(L5<>"",L5<J5)),0, IF(L5="", NETWORKDAYS(J5,TODAY(),Hoja2!$A$2:$A$53), NETWORKDAYS(J5,L5,Hoja2!$A$2:$A$53) ) ) -> 3 | O5: 45881 | P5: 45968 | Q5: 27/05/2025 Nuevo - Cliente 18/06/2025 Entregan un nuevo ejemplo del XML 22/06/2025 Revision y Punteo de información del XML, frente a Formulario, para confirmar que se estuviera recibiendo la información y cómo se iba a recibir 24/06/2025 Reunión con el cliente para contextualización de la revisión del XML 27/06/2025 Entregan tablas paramétricas que se usan para unificar conceptos, e Imagine queda a la espera de un nuevo ejemplo y definicion final de cómo llegaría el XML 08/08/2025 Se comienza a realizar desarrollo 11/08/2025 El auto guardado la creación de tablas y columnas queda correcta en un 80% XML 12/08/2025 Se realiza ajuste para que el auto guardado del XML se realice de manera correcta en su totalidad 22/09/2025 Se revisan XML recibidos de pruebas, encontrando hallazgos en inconsistencias de etiquetas y almacenamiento de información de beneficiarios. Jennifer por correo electrónico solicita más ejemplos de afiliaciones. Se pide confirmacion de cómo será el proceso de consumo de imágenes, y aclaracion de una información entregada en el XML. 22/09/2025 Se realiza ajuste para desglose de cada una de las etiquetas XM para que se creen las tablas y las columnas correspondientes 23/09/2025 Se ajustan errores de guardado se hace rollback si se envia algun exception 7/11/2025 se publica en poducción que es la fecha en la que Colmédica empieza a enviar estas afiliaciones | R5: True
A6: JHON | B6: 302 | C6: Modulo Tutelas - Recobros | D6: Revisar que todas las opciones de registro y almacenamientos queden con el usuario de sesión | F6: FINALIZADO | G6: 100 | H6: =IF(OR(J6="",K6="",K6<J6),0,NETWORKDAYS(J6,K6,Hoja2!$A$2:$A$53)) -> 1 | I6: 45798 | J6: 45898 | K6: 45898 | L6: 45898 | M6: =IF(OR(J6="",AND(L6="",TODAY()<J6),AND(L6<>"",L6<J6)),0, IF(L6="", NETWORKDAYS(J6,TODAY(),Hoja2!$A$2:$A$53), NETWORKDAYS(J6,L6,Hoja2!$A$2:$A$53) ) ) -> 1 | O6: 45898 | P6: 45898 | Q6: 21/05/2025 Ajuste - Mejora Imagine 29/08/2025 Se realiza ajsutes en paginas para que el usuario se envie de manera correcta | R6: True
A7: JENNIFER | B7: 293 | C7: Base Caida Mes - Acreditacion | D7: Base de Usuarios de las vigencias del mes inmediatamente anterior con corte al primero del mes, actualmente se hace manual, crear opción para que se pueda programar tarea automática un correo con el excel generado, las fechas del query corresponden a las vigencias del mes inmediatamente anterior select nombrevigencia,* from tbl_afiliados_informe where nombrevigencia in (20250201,20250215) and fuentelegalizado is null and causaexclusiactual in (0,64) order by nombrevigencia debe generar un excel con los siquientes campos vigencia,contrato,numben ,tipoid,identificacion,primerapellido,segundoapellido,nombre,plan,vigini,vigfin,tipodecontrato,nit colectivo | F7: FINALIZADO | G7: 100 | H7: =IF(OR(J7="",K7="",K7<J7),0,NETWORKDAYS(J7,K7,Hoja2!$A$2:$A$53)) -> 26 | I7: 45925 | J7: 45931 | K7: 45968 | L7: 45937 | M7: =IF(OR(J7="",AND(L7="",TODAY()<J7),AND(L7<>"",L7<J7)),0, IF(L7="", NETWORKDAYS(J7,TODAY(),Hoja2!$A$2:$A$53), NETWORKDAYS(J7,L7,Hoja2!$A$2:$A$53) ) ) -> 5 | O7: 45937 | P7: 45937 | Q7: 1/10/2025 se prepara el query con el que se debe entregar la información al cliente, y crear una opción por el navegador que permita descargar dicha data 3/10/2025 ya disponible la opción nueva y asignar los permisos al rol necesario y inicio gestion para descargar la información 7/10/2025 ya se genera el excel con la informacion y la estructura que se maneja con el cliente | R7: True
A8: JHON | B8: 305 | C8: WebService Afiliacion PBS - Afiliaciones POS | D8: Crear servicio para que Colmedica entregue a Imagine el XML y el numero de solicitud, y se almacene al interior para luego hacer la lectura segun req 306 | F8: FINALIZADO | G8: 100 | H8: =IF(OR(J8="",K8="",K8<J8),0,NETWORKDAYS(J8,K8,Hoja2!$A$2:$A$53)) -> 1 | I8: 45832 | J8: 45876 | K8: 45877 | L8: 45877 | M8: =IF(OR(J8="",AND(L8="",TODAY()<J8),AND(L8<>"",L8<J8)),0, IF(L8="", NETWORKDAYS(J8,TODAY(),Hoja2!$A$2:$A$53), NETWORKDAYS(J8,L8,Hoja2!$A$2:$A$53) ) ) -> 1 | O8: 45877 | Q8: 24/06/2025 Nuevo - Cliente 07/08/2025 Se define parámetros de entrada más estructura de tabla en base de datos 08/08/2025 Se comienza a crear WS con REST de tipo POST 08/08/2025 Se realiza ajustes adicionales para el guardado de XML y el guardado de la información en base de datos 14/08/2025 Jennifer envía correo al cliente para que se haga la prueba respectiva de conexión, entregando documentación y url en servidor de pruebas 19/08/2025 El cliente informa de una inconsistencia, en la que el consumo le devuelve el error {"response":false,"message":"Error al guardar el archivo XML"} 21/08/2025 Se realiza la correccion, en Pruebas hizo falta el permiso a una carpeta 26/08/2025 Jennifer informa al Cliente por correo electrónico del error corregido, y que pueden continuar haciendo pruebas 27/08/2025 se recibe xml de prueba 19/09/2025 se recibe xml de prueba | R8: True
A9: JHON | B9: 304 | C9: verificacion cuentas contables - Cuentas Medicas UMD (valor cuentas contables) | D9: Mostrar en la pantalla de información de la cuentas, los valores capturados y agrupados según cuenta contable | F9: FINALIZADO | G9: 100 | H9: =IF(OR(J9="",K9="",K9<J9),0,NETWORKDAYS(J9,K9,Hoja2!$A$2:$A$53)) -> 2 | I9: 45804 | J9: 45804 | K9: 45805 | L9: 45805 | M9: =IF(OR(J9="",AND(L9="",TODAY()<J9),AND(L9<>"",L9<J9)),0, IF(L9="", NETWORKDAYS(J9,TODAY(),Hoja2!$A$2:$A$53), NETWORKDAYS(J9,L9,Hoja2!$A$2:$A$53) ) ) -> 2 | P9: 45805 | Q9: 27/05/2025 Ajuste - Mejora Cliente 28/05/2025 Se realiza ajuste para mostrar los valores de las cuentas contables de digitacion | R9: True
A10: JHON | B10: 304_1 | C10: verificacion cuentas contables -Cuentas Medicas UMD (Modificacion valores cuentas contables) | D10: Permitir la modificación por registro principa de los valores capturados a cada cuenta contable | F10: FINALIZADO | G10: 100 | H10: =IF(OR(J10="",K10="",K10<J10),0,NETWORKDAYS(J10,K10,Hoja2!$A$2:$A$53)) -> 9 | I10: 45804 | J10: 45873 | K10: 45884 | L10: 45884 | M10: =IF(OR(J10="",AND(L10="",TODAY()<J10),AND(L10<>"",L10<J10)),0, IF(L10="", NETWORKDAYS(J10,TODAY(),Hoja2!$A$2:$A$53), NETWORKDAYS(J10,L10,Hoja2!$A$2:$A$53) ) ) -> 9 | O10: 45884 | P10: 45890 | Q10: 27/05/2025 Ajuste - Mejora Imagine 14/08/2025 Se ajusta el DOM para imprimir inputs si se desea actualizar los valores 15/08/2025 Creación del BackEnd para la validación y actualización de valores | R10: True
A11: JHON | B11: OPT_2 | C11: Afiliaciones POS - Estados de Salud (Lectura PDF- OCR | D11: Optimizar proceso para que por medio de Lectura de PDF al momento del revisar el estado de salud de una solicitud si este tiene respuestas positivas ya le salgan marcadas en el formulario para almacenarlas | F11: FINALIZADO | G11: 100 | H11: =IF(OR(J11="",K11="",K11<J11),0,NETWORKDAYS(J11,K11,Hoja2!$A$2:$A$53)) -> 4 | I11: 45800 | J11: 45800 | K11: 45805 | L11: 45805 | M11: =IF(OR(J11="",AND(L11="",TODAY()<J11),AND(L11<>"",L11<J11)),0, IF(L11="", NETWORKDAYS(J11,TODAY(),Hoja2!$A$2:$A$53), NETWORKDAYS(J11,L11,Hoja2!$A$2:$A$53) ) ) -> 4 | O11: 45805 | P11: 45807 | Q11: 23/05/2025 Nuevo - Imagine/Cliente | R11: True
A12: JENNIFER | B12: OPT_2_1 | C12: Afiliaciones POS - Estados de Salud (identificar casos sin Respuestas Positivas) | D12: Optimizar proceso para que por medio de Lectura de PDF se pueda marcar la solicitud con Respuestas Negativas. utilizando Python | F12: FINALIZADO | G12: 100 | H12: =IF(OR(J12="",K12="",K12<J12),0,NETWORKDAYS(J12,K12,Hoja2!$A$2:$A$53)) -> 5 | I12: 45826 | J12: 45826 | K12: 45833 | L12: 45833 | M12: =IF(OR(J12="",AND(L12="",TODAY()<J12),AND(L12<>"",L12<J12)),0, IF(L12="", NETWORKDAYS(J12,TODAY(),Hoja2!$A$2:$A$53), NETWORKDAYS(J12,L12,Hoja2!$A$2:$A$53) ) ) -> 5 | O12: 45833 | P12: 45835 | Q12: 18/06/2025 - Ajuste - Mejora Imagine 25/06/2025 Se dispone en ambien de pruebas para revisar el proceso de identificación de estados de salud sin respuestas positivas 27/06/2025 se dispone en ambiente productivo, y se ejecuta de manera manual para hacer seguimiento | R12: True
A13: JENNIFER | B13: OPT_2_3 | C13: Afiliaciones POS - Estados de Salud (Identificar casos con Respuestas Positivas) | D13: Optimizar proceso para que por medio de Lectura de PDF se pueda marcar la solicitud con Respuestas Positivas almacernar para cada usuario la respuesta positiva que corresponda. utilizando Python | F13: FINALIZADO | G13: 100 | H13: =IF(OR(J13="",K13="",K13<J13),0,NETWORKDAYS(J13,K13,Hoja2!$A$2:$A$53)) -> 2 | I13: 45835 | J13: 45845 | K13: 45846 | L13: 45846 | M13: =IF(OR(J13="",AND(L13="",TODAY()<J13),AND(L13<>"",L13<J13)),0, IF(L13="", NETWORKDAYS(J13,TODAY(),Hoja2!$A$2:$A$53), NETWORKDAYS(J13,L13,Hoja2!$A$2:$A$53) ) ) -> 2 | O13: 45847 | P13: 45849 | Q13: 27/06/2025 Ajuste - Mejora Imagine 7/07/2025 se empiezan a didentificar las respuestas positivas a que preguntas corresponden 8/07/2025 se cruzan dependiendo de la cantidad de usuarios digitados se realicionan con los casos según el array de las respuestas positivas, para hacer el almacenamiento en base de datos de dichas respuestas, y la marcación de que la solicitud fue revisada y marcada con respuestas poisitivas 9/07/2025 se dispone en el servidor de pruebas lo correspondiente a estados de salud de PBS, y se hacen las pruebas de funcionamiento del modulo 11/07/2025 se dispone en el servidor de producción lo correspondiente a estados de salud de PBS, y se hace una prueba controlada para confirmar que todo el flujo, tanto de respuestas positivas, como negativas quede funcionando correctamente. 14/07/2025 Se ejecuta de manera manual el proceso haciendo seguimiento 15/07/2025 Se empieza el desarrollo para dejarlo por tarea programada la ejecución de esta revisión 21/07/2025 Se deja la tarea programada y log de salida para hacer seguimiento | R13: True
A14: JENNIFER | B14: OPT_3 | C14: Afiliaciones PRE - Estados de Salud | D14: Optimizar el proceso de Estados de Salud PRE, para registrar de manera automática utilizando Python los casos de solicitudes donde no tienen respuestas positivas | F14: FINALIZADO | G14: 100 | H14: =IF(OR(J14="",K14="",K14<J14),0,NETWORKDAYS(J14,K14,Hoja2!$A$2:$A$53)) -> 5 | I14: 45847 | J14: 45852 | K14: 45856 | L14: 45856 | M14: =IF(OR(J14="",AND(L14="",TODAY()<J14),AND(L14<>"",L14<J14)),0, IF(L14="", NETWORKDAYS(J14,TODAY(),Hoja2!$A$2:$A$53), NETWORKDAYS(J14,L14,Hoja2!$A$2:$A$53) ) ) -> 5 | O14: 45856 | P14: 45859 | Q14: 14/07/2025 Ajuste - Mejora Imagine 14/07/2025 Se inicia el desarrollo con python para la lecturas de los documentos de estados de Salud producto PRE 15/07/2025 Identificando los diferentes formatos de estados de salud para las solicitudes de pre, y que se puedan tomar los casos con respuestas negativas 17/07/2025 Se completa proceso para que se tomen de la base de datos las solicitudes pendientes de validación de los estados de salud con respuestas negativas 18/07/2025 se dispone en ambiente de pruebas y se revisan casos puntuales para ver el proceso 21/07/2025 se pasa a producción y se hace prueba controlada, dejando la tarea programada y log de salida para hacer seguimiento | R14: True
A15: JHON | B15: OPT_1 | C15: Cuentas Medicas UMD - Lectura OCR - PDF (Clasificación Documental) | D15: Realizar proceso de clasificacion de los documentos cargados Principal Factura o Cuenta de Cobro - Pila - Anexos. De acuerdo a la información precargada por parte del cliente, se deben ligar los documentos ya clasificados a un correlativo, teniendo en cuenta valor, centro de costo. | F15: FINALIZADO | G15: 100 | H15: =IF(OR(J15="",K15="",K15<J15),0,NETWORKDAYS(J15,K15,Hoja2!$A$2:$A$53)) -> 10 | I15: 45814 | J15: 45814 | K15: 45827 | L15: 45821 | M15: =IF(OR(J15="",AND(L15="",TODAY()<J15),AND(L15<>"",L15<J15)),0, IF(L15="", NETWORKDAYS(J15,TODAY(),Hoja2!$A$2:$A$53), NETWORKDAYS(J15,L15,Hoja2!$A$2:$A$53) ) ) -> 6 | O15: 45821 | P15: 45827 | Q15: 19/06/2025 Se dispone en producción el boton que permite ejecutar el proceso de clasificacion documental 20/06/2025 Se pasa a producción opcion para dividir casos en los que no se puedan clasificar los documentos por que en 1 sola imagen vienen varios tipos de doc, ya sí poder hacer la clasificación manual | R15: True
A16: JHON | B16: OPT_1_1 | C16: Cuentas Medicas UMD - Lectura OCR - PDF (Radicación Automática) | D16: Una vez los documentos han sido plenamente identificados, se debe proceder a automatizar el proceso de radicación, para los paquetes que cumplieron con plena clasificación documental, asignación del correlativo y la cantidad de archivos del paquete está entre 2 y 5 imágenes. el resto quedaán para validación puntual. | F16: FINALIZADO | G16: 100 | H16: =IF(OR(J16="",K16="",K16<J16),0,NETWORKDAYS(J16,K16,Hoja2!$A$2:$A$53)) -> 15 | I16: 45814 | J16: 45814 | K16: 45835 | L16: 45835 | M16: =IF(OR(J16="",AND(L16="",TODAY()<J16),AND(L16<>"",L16<J16)),0, IF(L16="", NETWORKDAYS(J16,TODAY(),Hoja2!$A$2:$A$53), NETWORKDAYS(J16,L16,Hoja2!$A$2:$A$53) ) ) -> 15 | O16: 45835 | P16: 45847 | Q16: 27/06/2025 Se dipuso el proceso de radicación automática una vez se hubiera identificado plenemente el paquete de imagenes en el servidor de pruebas 7/07/2025 William Barajas realiza la prueba de subir varias imagenes y correr el proceso de clasificación, denrto de las pruebas se identifican unos casos que teniana varias cuentas contables que se debian puntear al momento de la radicación y solo estaba quedando una, se escala a Jhon para que sea revisado. 7/07/2025 Se corrige el inconveniente con el punteo de las cuentas contables, ajustando un ciclo para que a marcación quede de manera correcta, y se dispone nuevamente en ambiente de pruebas 8/07/2025 William Barajas realiza nuevamente la revisión con casos nuevos de imagenes que se subieron en pruebas y ejecuta nuevamente el proceso de radicación correctamente entre lo plenamente identificado y que el paquete tenga entre 2 y 5 imagenes 9/07/2025 Se pasa a produción el proceso de radicación automática, y William queda encargado de hacerle seguimiento y reportar de alguna anomalía ya en producción o que se pueda presentar en la digitación. | R16: True
A17: JHON | B17: OPT_4 | C17: Afiliaciones POS - Consulta automática de empresas en el RUES | D17: Se requiere un opción automática para la consulta de NIT's en el sistema RUES | F17: FINALIZADO | G17: 100 | H17: =IF(OR(J17="",K17="",K17<J17),0,NETWORKDAYS(J17,K17,Hoja2!$A$2:$A$53)) -> 2 | I17: 45881 | J17: 45881 | K17: 45882 | L17: 45882 | M17: =IF(OR(J17="",AND(L17="",TODAY()<J17),AND(L17<>"",L17<J17)),0, IF(L17="", NETWORKDAYS(J17,TODAY(),Hoja2!$A$2:$A$53), NETWORKDAYS(J17,L17,Hoja2!$A$2:$A$53) ) ) -> 2 | O17: 45882 | P17: 45896 | Q17: 12/08/2025 Se realiza desarrollo de consulta a REUS 13/08/2025 Se implementa desarrollo dentro del flujo de trabajo de afiliciones PBS 26/08/2025 Se realiza un servicio con Fast API 26/08/2025 Se realiza ajustes nuevo para encriptar la información del cuerpo de la solicitud | R17: True
A18: JHON | B18: 311 | C18: Comercial - Reasignación Solicitudes | D18: por Directores - Administracion Comercial , crear en la lista la opcion de Reasignar Solicitudes listar gestores activos dependiendo del seleccionado, debe listar las solicitudes que tiene para tramitar devolución SELECT count(nosolicitud) as cantidad,estado from reldiariaproduccion as r where r.nosolicitud in (select solicitud from devvarias where corregido = 0) and gestor_asignacion = .$usses. and estado IN (DEVUELTA,REVISION MEDICA,REINGRESO RECH,RECHAZADA,REINGRESO,FOSYGA,CONSULTA SARLAFT) group by estado order by cantidad desc permitir seleccionar de la lista las solicitudes que se desean reasignar cargar otro combo con los gestores activos a los que les puedo reasignar(quitando el seleccionado en el primer combo) boton de reasignación, pedir confirmación del proceso y ejecutar los siguiesntes querys por solicitud resignada update reldiariaproduccion set gestor_asignacion = .$usernuevo.,gestor_asignacion_original = .$usernuevo. where nosolicitud = .$data_re[nosolicitud]. insert into gestionafiliaciones (nosolicitud,gestion,userinsert,estado) values (.$data_re[nosolicitud].,Reasignacion Manual para solucionar inconsistencia con la solicitud a .$usernuevo..,$usuariosesion,.$data_re[estado].) | F18: FINALIZADO | G18: 100 | H18: =IF(OR(J18="",K18="",K18<J18),0,NETWORKDAYS(J18,K18,Hoja2!$A$2:$A$53)) -> 3 | I18: 45870 | J18: 45874 | K18: 45877 | L18: 45877 | M18: =IF(OR(J18="",AND(L18="",TODAY()<J18),AND(L18<>"",L18<J18)),0, IF(L18="", NETWORKDAYS(J18,TODAY(),Hoja2!$A$2:$A$53), NETWORKDAYS(J18,L18,Hoja2!$A$2:$A$53) ) ) -> 3 | O18: 45877 | P18: 45881 | Q18: 8/08/2025 reunión Jennifer con Comercial para mostrar el módulo en Pruebas y recibir observaciones y comentarios por parte del área, quienes dan el aval para pasar a produccion. 12/08/2025 Jhon pasa a producción el desarrollo y Jennifer envía correo al área informando del paso a producción para que ya pueda ser utilizado por ellos. | R18: True
A19: JHON | B19: 312 | C19: Lectura OCR - Datos Digitación - Pila | D19: Según requerimiento 309 Lectura OCR – Datos Digitación, para almacenar información de pila - Es necesario que, si se adjuntan pila después, se debe ejecutar OCR para la captura de la información - Debe haber un botón en la pagina de detalles de cuentas que permita ejecutar esta tarea automática | F19: FINALIZADO | G19: 100 | H19: =IF(OR(J19="",K19="",K19<J19),0,NETWORKDAYS(J19,K19,Hoja2!$A$2:$A$53)) -> 2 | I19: 45882 | J19: 45891 | K19: 45894 | L19: 45895 | M19: =IF(OR(J19="",AND(L19="",TODAY()<J19),AND(L19<>"",L19<J19)),0, IF(L19="", NETWORKDAYS(J19,TODAY(),Hoja2!$A$2:$A$53), NETWORKDAYS(J19,L19,Hoja2!$A$2:$A$53) ) ) -> 3 | O19: 45895 | P19: 45895 | R19: True
A20: JENNIFER | B20: OPT_5 | C20: Acreditación - Generacion Bases Vigencias | D20: Permitir que el cargue de la vigencia no dependa de que la persona suba unos archivos para que la información quede publicada para empezar a trabajar, sino que por tarea automática el sistema haga la creación y la deje disponible para la revisión, los días 10 y 25 de cada mes | F20: FINALIZADO | G20: 100 | H20: =IF(OR(J20="",K20="",K20<J20),0,NETWORKDAYS(J20,K20,Hoja2!$A$2:$A$53)) -> 3 | I20: 45891 | J20: 45891 | K20: 45895 | L20: 45895 | M20: =IF(OR(J20="",AND(L20="",TODAY()<J20),AND(L20<>"",L20<J20)),0, IF(L20="", NETWORKDAYS(J20,TODAY(),Hoja2!$A$2:$A$53), NETWORKDAYS(J20,L20,Hoja2!$A$2:$A$53) ) ) -> 3 | O20: 45895 | P20: 45898 | Q20: 22/08/2025 Se inicia el desarrollo para generar las bases, ya no se crearan tablas individuales, sino se almacenara directamente en la tabla destino. validación de la estrucutura de tablas para ajustar los insert into. 25/08/2025 adicionando las validaciones que hacia el sistema al simular el cargue de los archivos de vigencia, para actualizar algunos usuarios que se pueden acreditar por el cruce con la base de Apolo 26/08/2025 se publica en pruebas para revisar el proceso 29/08/2025 Se publica en producción y se hará seguiemiento para el proximo proceso que se ejecutará el 10/09 | R20: True
A21: JENNIFER | B21: OPT_6 | C21: Afiliaciones PRE - Generacion de Kits | D21: Cambiar la plataforma del Access - Crear archivos planos enviados al proveedor que hace el envío de los Kits a los clientes de medicina prepagada, a partir del correo que ya se envía de confirmación del cargue de las preexistencias. Si todo esta Cargado, generar archivos planos, conectarse a la ruta y dejar los archivos, enviar correo notificando de la generación. En caso de que las preexistencias no esten todas cargadas, no se genera nada autmático, sin embargo se dispondrá una opción desde el Sitio Web de Imagine para que se generen dihos archivos. | F21: PRUEBAS CLIENTE | G21: 95 | H21: =IF(OR(J21="",K21="",K21<J21),0,NETWORKDAYS(J21,K21,Hoja2!$A$2:$A$53)) -> 8 | I21: 45891 | J21: 46078 | K21: 46087 | M21: =IF(OR(J21="",AND(L21="",TODAY()<J21),AND(L21<>"",L21<J21)),0, IF(L21="", NETWORKDAYS(J21,TODAY(),Hoja2!$A$2:$A$53), NETWORKDAYS(J21,L21,Hoja2!$A$2:$A$53) ) ) -> 79 | O21: 46090 | P21: 46092 | Q21: 9/09/2025 Se inicia con el levantamiento de información para iniciar con el desarrollo 11/09/2025 Creación de schema-tabla principal - el resto se revisarán si son necesarias o como se ajusta seguramente se puedan omitir 12/09/2025 Se inicia el desarrollo para traer la información (Pagina principal - página de funciones) 16/09/2025 Avance en los tipos de proceso que se ejectutan Normal,Chevron,Puntual 19/09/2025 Lectura del encabezado para ir sacando el registro tipo 1 (Encabezado) 25/02/2026 se retoma, el desarrollo dandole un vuelco para unificar el código y dejarlo de manera virtual 26/02/2026 ajustes a la pagina a conexiones de bases de datos dependiendo de la base donde se encuentre la tabla 27/02/2026 Ajuste de ciclos y querys según las funciones y/o clases defindas en la conexión ya existente. Ya no genera error el código, pero se le está haciendo seguimiento a los querys y ejecución para obtener el resultado de los respectivos archivos 6/03/2026 se terminaron de ajustar los errores de la pagina en la generación de afiliaciones nuevas 9/03/2026 se empiezan a validar inconsistencias para la generación de Inclusiones. y como ya se generan archivos, pues se debe realizar la comparación de estructura y data con la generada actualmente por el access. 10/03/2026 se hicieron ajsutes por homologación para los nombres de los archivos de inclusiones 11/03/2026 se pasa a producción la pagina, para empezar a hacer pruebas controladas comparando ambos sistemas 12/03/2026 pruebas con los archivos en produccion, como no todos los días se generan la misma cantidad y los mismos archivos se identifacn unos no generados con la nomenclatura correcta, pero se generan en otro archivo, 13/03/2026 pruebas con los archivos en produccion, como no todos los días se generan la misma cantidad y los mismos archivos se identifacn unos no generados con la nomenclatura correcta, perose generan en otro archivo, 17/03/2026 se envía correo a operaciones para entregar una muestra de los archivos al otro proveedor, para que no se vayan haber afectados con el cambio | R21: True
A22: JENNIFER | B22: OPT_7 | C22: Afiliaciones POS - PRE - Estados de Salud (Muestra Militar) | D22: Ya con los estados de salud capturados, 1. Crear tarea programada para identificar las solicitudes a diario de la muestra militar del del 15%.de lo validado en el día por el proceso automático. 2. Se debe crear una opción como bandeja de trabajo donde se liste la muestra militar , para que una persona realice a revisión control de calidad | F22: FINALIZADO | G22: 100 | H22: =IF(OR(J22="",K22="",K22<J22),0,NETWORKDAYS(J22,K22,Hoja2!$A$2:$A$53)) -> 6 | I22: 45897 | J22: 45897 | K22: 45904 | L22: 45904 | M22: =IF(OR(J22="",AND(L22="",TODAY()<J22),AND(L22<>"",L22<J22)),0, IF(L22="", NETWORKDAYS(J22,TODAY(),Hoja2!$A$2:$A$53), NETWORKDAYS(J22,L22,Hoja2!$A$2:$A$53) ) ) -> 6 | O22: 45905 | P22: 45908 | Q22: 28/08/2025 Se inicia con el desarrollo, pagina con la que se debe sacar la muestra militar del 20% y dejar en una tabla marcadas para revisar 1/09/2025 pagina de tarea programada terminada, para sacar la muestra e insertar en tabla destino 2/09/2025 se genera documentacion tecnica de la pagina de la muestra, y se inicia con el desarrollo de la bandeja de trabajo para revisar las solicitudes de la muestra 3/09/2025 Se adelantó la bandeja de trabajo, ya se listan las solicitudes de la muestra, mostrando la información para realizar la validación. 4/09/2025 se termina el desarrollo 5/09/2025 se pasa a pruebas, tanto paginas nuevas, como las modificadas por funciones, y creacion de tablas 8/09/2025 se pasa a aproduccion, tanto paginas nuevas, como las modificadas por funciones, y creacion de tablas. se deja la tarea programada para la extracción de la muestra 15/09/2025 se corre histórico desde el 1/08/2025 de muestra a la fecha 14/09, desde el 15/09 queda habilitada la tarea programada 8/09. Se genera documentación Técnica | R22: True
A23: JHON | B23: OPT_8 | C23: Lectura Emails UMD | D23: Se requiere realizar una lectura automática de correos para la recuperación de la información y de los anexos para consiguiente guardar la información en base de datos y los anexos sen una ruta determinada | F23: PAUSADO | G23: 60 | H23: =IF(OR(J23="",K23="",K23<J23),0,NETWORKDAYS(J23,K23,Hoja2!$A$2:$A$53)) -> 0 | I23: 45898 | J23: 45898 | M23: =IF(OR(J23="",AND(L23="",TODAY()<J23),AND(L23<>"",L23<J23)),0, IF(L23="", NETWORKDAYS(J23,TODAY(),Hoja2!$A$2:$A$53), NETWORKDAYS(J23,L23,Hoja2!$A$2:$A$53) ) ) -> 200 | Q23: 29/08/2025 Se incia desarrollo, paso de funcinalidades de php a python 01/09/2025 Creación de servicio para lectura de correo 02/09/2025 Consulta a base de datos para recuperar prestador 03/09/2025 Creación completa del servicio REST para guardar las imagnes y la data 5/09/2025 Jennifer-Seguimiento con la persona Cliente para concertar reunión y revisar permisos sobre el buzon 9/09/2025 Jennifer-Seguimiento con la persona Cliente para concertar reunión y revisar permisos sobre el buzon 10/09/2025 Jennifer-Seguimiento con la persona Cliente para concertar reunión y revisar permisos sobre el buzon 11/09/2025 Jennifer-Seguimiento con la persona Cliente para concertar reunión y revisar permisos sobre el buzon | R23: False
A24: JHON | B24: OPT_9 | C24: Reestablecer contraseña convenios | D24: Se requiere actualizar estado y contraseñas del usuario, por el perfil que ya existe para Mesa de Ayuda, la opción de Reestablecer contraseña debe permitir desbloquear el usuario, no solo reestablecer la contraseña. y así como se busca por Usuario debe permitir buscar por identificación | F24: FINALIZADO | G24: 100 | H24: =IF(OR(J24="",K24="",K24<J24),0,NETWORKDAYS(J24,K24,Hoja2!$A$2:$A$53)) -> 1 | I24: 45905 | J24: 45908 | K24: 45908 | L24: 45909 | M24: =IF(OR(J24="",AND(L24="",TODAY()<J24),AND(L24<>"",L24<J24)),0, IF(L24="", NETWORKDAYS(J24,TODAY(),Hoja2!$A$2:$A$53), NETWORKDAYS(J24,L24,Hoja2!$A$2:$A$53) ) ) -> 2 | O24: 45909 | P24: 45909 | Q24: Ajuste 08/09/2025 Se realiza ajuste en backend y frontend para reestabecer la contraseña | R24: True
A25: JHON | B25: OPT_10 | C25: Afiliaciones PBS - Separar Marcacion de Soportes - Digitación | D25: Opción para marcación de soportes de las afiliaciones PBS, ya algunas se pueden pre-marcar dado la entrega de la data, y otras que si requerirán de validación del usuario y alguna captura adicional para la completa identificación. | F25: PENDIENTE | H25: =IF(OR(J25="",K25="",K25<J25),0,NETWORKDAYS(J25,K25,Hoja2!$A$2:$A$53)) -> 0 | I25: 45905 | M25: =IF(OR(J25="",AND(L25="",TODAY()<J25),AND(L25<>"",L25<J25)),0, IF(L25="", NETWORKDAYS(J25,TODAY(),Hoja2!$A$2:$A$53), NETWORKDAYS(J25,L25,Hoja2!$A$2:$A$53) ) ) -> 0 | Q25: 5/09/2025 Posible mejora detectada por Imagine -Jennifer | R25: False
A26: JHON | B26: OPT_11 | C26: Novedades - Correo automático falta de imágenes | D26: valide en la carpeta /archivosimagine/huella/ la fecha del día, si no hay se debe enviar un correo electrónico informando que no existe carpeta con las imágenes de novedades Agradezco su revisión porque se valida el repositorio de imágenes de novedades tiff, y se encuentran faltantes las imágenes correspondientes a : fechadia. adicionar en página /var/www/html/procesos/novedadespdf.php | F26: FINALIZADO | G26: 100 | H26: =IF(OR(J26="",K26="",K26<J26),0,NETWORKDAYS(J26,K26,Hoja2!$A$2:$A$53)) -> 1 | I26: 45911 | J26: 45912 | K26: 45912 | L26: 45912 | M26: =IF(OR(J26="",AND(L26="",TODAY()<J26),AND(L26<>"",L26<J26)),0, IF(L26="", NETWORKDAYS(J26,TODAY(),Hoja2!$A$2:$A$53), NETWORKDAYS(J26,L26,Hoja2!$A$2:$A$53) ) ) -> 1 | O26: 45912 | P26: 45912 | Q26: 12/09/2025 Se agrega la opción para validar carpeta y se agrega la opción para enviar correo 12/09/2025 Se agrega la opción de administrar correo al menu de procesos imgine | R26: True
A27: JHON | B27: 315 | C27: Afiliaciones PRE - Reporte de Sarlaf Solicitudes en Lista | D27: Proceso automático para crear a diario lo que quede devuelto por listas tabla devvarias 200-Falta Documento 166 -Soporte Sarlaft Titular reportado en listas donde fecha insert se el dia actual. con el numero de solicitud y buscarlo en consulta_sarlaft para sacar información que se debe colocar en un excel que se debe enviar por correo electronico | F27: FINALIZADO | G27: 100 | H27: =IF(OR(J27="",K27="",K27<J27),0,NETWORKDAYS(J27,K27,Hoja2!$A$2:$A$53)) -> 3 | I27: 11/09/0205 | J27: 45923 | K27: 45925 | L27: 45925 | M27: =IF(OR(J27="",AND(L27="",TODAY()<J27),AND(L27<>"",L27<J27)),0, IF(L27="", NETWORKDAYS(J27,TODAY(),Hoja2!$A$2:$A$53), NETWORKDAYS(J27,L27,Hoja2!$A$2:$A$53) ) ) -> 3 | O27: 45925 | P27: 45925 | Q27: 24/09/2024 Se realiza validacion de tablas base de datos y creacion del archivo .xlsx 25/09/2024 S e realiza ajuste para el envio de correos | R27: True
A28: JHON | B28: 314 | C28: Afiliaciones PRE - No devolver la solicitud Listas Sarlaft | D28: En la opción 6 \var\www\html\modulo_imagine\core\imagine\indexaprocesosafiliaciones.php donde se va a insertar la devolución por listas se debe adicionar la validación si el titular tiene otra solicitud dentro de los ultimos 3 meses en estado CARGADA, no se debe hacer la devolución, de lo contrario si hacerla. y continua el proceso | F28: FINALIZADO | G28: 100 | H28: =IF(OR(J28="",K28="",K28<J28),0,NETWORKDAYS(J28,K28,Hoja2!$A$2:$A$53)) -> 2 | I28: 11/09/0205 | J28: 45917 | K28: 45918 | L28: 45918 | M28: =IF(OR(J28="",AND(L28="",TODAY()<J28),AND(L28<>"",L28<J28)),0, IF(L28="", NETWORKDAYS(J28,TODAY(),Hoja2!$A$2:$A$53), NETWORKDAYS(J28,L28,Hoja2!$A$2:$A$53) ) ) -> 2 | O28: 45918 | P28: 45918 | Q28: 17/09/2025 Se realiza analisis y paso a pruebas la validación de devoluciones | R28: True
A29: JHON | B29: 313 | C29: Afiliaciones PRE - Lectura del PDF respuesta Sarlaft | D29: Cargue de Archivos Perfil de riesgo Al momento de cargar los PDF de la respuesta de las consulta de SArlaft, se debe agregar la lectura del PDF para saber si esta en listas o no, y si lo está almacenar las escalas encontradas (Crear campo nuevo para almacenar la escala(s) en la tabla consulta_sarlaft), si tiene el aviso "No se obtuvieron resultados para la búsqueda realizada." debe ser NO en listas, y si trae Escalas el campo listas debe quedar en SI. adicinar en esta pagina la actualización mencionada \var\www\html\salud\cargadearchivos\renombrarArchivosSarlaft.php, dejando el update sobre la tabla update consulta_sarlaft set listas =,escala where afiliacion='$plani' and estado = 1 . Adicional una vez almacenada esta información se debe cerrar el registro, invocando pag \var\www\html\modulo_imagine\core\imagine\indexaprocesosafiliaciones.php opcion 6, la cual deja el registro tramitado | F29: FINALIZADO | G29: 100 | H29: =IF(OR(J29="",K29="",K29<J29),0,NETWORKDAYS(J29,K29,Hoja2!$A$2:$A$53)) -> 5 | I29: 11/09/0205 | J29: 45912 | K29: 45918 | L29: 45917 | M29: =IF(OR(J29="",AND(L29="",TODAY()<J29),AND(L29<>"",L29<J29)),0, IF(L29="", NETWORKDAYS(J29,TODAY(),Hoja2!$A$2:$A$53), NETWORKDAYS(J29,L29,Hoja2!$A$2:$A$53) ) ) -> 4 | O29: 45917 | P29: 45916 | Q29: 15/09/2025 Se realiza lectura ocr para recuperar estacals del archivo PDF 16/09/2025 Relizar el servicio para la lectura del PDF y guardado en la base de datos 23/09/2025 se encuentran hallazgos sobre el proceso automático de renombre CC dumplcadas en la consulta y control al finalizar el proceso de que todo quede bien. | R29: True
A30: JENNIFER | B30: OPT_12 | C30: Consolidados Procesos Pendientes Afiliaciones PRE-Afiliaciones POS-Llamadas Acreditación | D30: Crear graficas de la produccion diaria pendiente que no sea mediante un correo electronico, y se visuelice al ingresar en el sitio web de Imagine para los usuarios de Imagine, y puedan identificar de manera más oportuna lo pendiente | F30: FINALIZADO | G30: 100 | H30: =IF(OR(J30="",K30="",K30<J30),0,NETWORKDAYS(J30,K30,Hoja2!$A$2:$A$53)) -> 3 | I30: 45917 | J30: 45917 | K30: 45919 | L30: 45919 | M30: =IF(OR(J30="",AND(L30="",TODAY()<J30),AND(L30<>"",L30<J30)),0, IF(L30="", NETWORKDAYS(J30,TODAY(),Hoja2!$A$2:$A$53), NETWORKDAYS(J30,L30,Hoja2!$A$2:$A$53) ) ) -> 3 | O30: 45919 | P30: 45923 | Q30: 17/09/2025 se empieza con la informacion recibida en el correo de produccion pendiente para optimizar su análisis y la organización para el trabajo, identificando que se necesita mostrar en grafica para una mejor visualiación 18/09/2025 Se crea pagina para la creacion de las graficas para evidenciar los pendientes de afiliaciones de PRE y POS, y la cantidad de contratos pendientes por llamadas, y se incluye dentro de la principal de la web de Imagine una vez se loguean 19/09/2025 Se pasa pruebas, se comprueba el funcionamiento de visualización, 23/09/2025 Se explica a William el funcionamiento de la visualización, para que ver que lo usen, y se contextualice con la gente | R30: True
A31: JENNIFER | B31: OPT_13 | C31: Consolidados Pendientes Proceso - Estados UMD | D31: Crear graficas de la produccion del proceso actual, para mostrar estados, valores | F31: FINALIZADO | G31: 100 | H31: =IF(OR(J31="",K31="",K31<J31),0,NETWORKDAYS(J31,K31,Hoja2!$A$2:$A$53)) -> 3 | I31: 45923 | J31: 45923 | K31: 45925 | L31: 45925 | M31: =IF(OR(J31="",AND(L31="",TODAY()<J31),AND(L31<>"",L31<J31)),0, IF(L31="", NETWORKDAYS(J31,TODAY(),Hoja2!$A$2:$A$53), NETWORKDAYS(J31,L31,Hoja2!$A$2:$A$53) ) ) -> 3 | O31: 45925 | P31: 45926 | Q31: 23/09/2025 Se inicia con la identificación de lo que se desea mostrar, primera imagens seguimiento del periodo en curso con estados, valores y cantidades 25/09/2025 se termina de ajustar la grafica para mostrar proceso actual, estados y los valores correspondientes. Se dispone en ambiente de pruebas para revisar que funciona de manera correcta. 26/09/2025 se pasa a produccion las páginas realizadas y se deja disponible para la visualizacion tanto del área operativa como del cliente | R31: True
A32: JHON | B32: OPT_14 | C32: Afiliaciones Pre - Sarlaft derivado del REQ-313 | D32: validar cantidades del excel vs los pdf, cambiar el renombre de los archivos tomando como base el excel e ir a buscar la cc en el nombre del archivo y así asignarle la solicitud, al final imprima mensaje indicando si algo quedó en estado 1 o estado 2 "Quedaron solicitudes en estado pendiente" - "Todo procesado correctamente" | F32: FINALIZADO | G32: 100 | H32: =IF(OR(J32="",K32="",K32<J32),0,NETWORKDAYS(J32,K32,Hoja2!$A$2:$A$53)) -> 1 | I32: 45924 | J32: 45925 | K32: 45925 | L32: 45925 | M32: =IF(OR(J32="",AND(L32="",TODAY()<J32),AND(L32<>"",L32<J32)),0, IF(L32="", NETWORKDAYS(J32,TODAY(),Hoja2!$A$2:$A$53), NETWORKDAYS(J32,L32,Hoja2!$A$2:$A$53) ) ) -> 1 | O32: 45925 | P32: 45925 | Q32: 25/09/2025 Se valida el funcionamiento del script encargado y su proceso corresponde a la descripcion del req | R32: True
A33: JHON | B33: 316 | C33: Acreditación - Consulta Puntual en BDEX | D33: Consulta de usuarios en régimen especial los pendinetes por acreditar de las vigencias activas para revisar, de manera automática en página del Adres. se necesita homologar logueo con usuario y contraseña, y al momento de la consulta de cada identificación revisar el captchap que se muestra. generar consultas en intervalo de tiempos para no generar algun tipo de laerta, dado que se usan logueos del cliente. Dejar usuarios y contraseñas administrables (POS-PRE). Si la fecha de nacimiento del usuario es mayor a 20000131 y en la base esta como CC y la respuesta no devuelve nada, se puede consultar como TI o RC y en la base esta como TI y la respuesta no devuelve nada, se puede consultar como CC o RC y en la base esta como RC y la respuesta no devuelve nada, se puede consultar como CC o TI Si la respuesta de la consulta es que si se encuentra en Regimen especial, se debe guardar un pdf con el nombre xxxxxxxx_REG010.pdf donde xxxxxx es el número de identificación y el REG010 la EPS, el cual se toma de una tla según el nombre que entrega la consulta del adres, y guardar en la ruta del servidor Se debe crear archivo de 7 columnas, para dejar resgitros de la consulta puntual del régimen especial 7 columnas:, Nombre Vigencia, Contrato, Tipo ID contratante, Número ID contratante, Tipo ID beneficiario, Número ID beneficiario, Código Gestion (44 - Consulta Puntual RES) y que se pueda ejecutar por debajo la función de la opción Acreditación - Gestion - Registrar Gestión Búsqueda Puntual | F33: PAUSADO | G33: 30 | H33: =IF(OR(J33="",K33="",K33<J33),0,NETWORKDAYS(J33,K33,Hoja2!$A$2:$A$53)) -> 15 | I33: 45929 | J33: 45933 | K33: 45954 | M33: =IF(OR(J33="",AND(L33="",TODAY()<J33),AND(L33<>"",L33<J33)),0, IF(L33="", NETWORKDAYS(J33,TODAY(),Hoja2!$A$2:$A$53), NETWORKDAYS(J33,L33,Hoja2!$A$2:$A$53) ) ) -> 175 | Q33: 29/09/2025 Jennifer - se contextualiza a Jhon lo que se require 30/09/2025 Jennifer - Radicación requerimiento en la plataforma 07/10/2025 Jhon - Se finaliza test con Modelo OCR para lectura e identificación del CAPTCHA 08/10/2025 Jhon - Se completa formulario de incio de sesión 20/10/2025 Jhon - Completoelincio de sesión mas recuperacion de lainformcion a cosultar | R33: False
A34: JENNIFER | B34: OPT_15 | C34: Acreditación - Usuarios Aliansalud subsidiado | D34: Al cargar la respuesta del adres de la consulta, si se recibe un usuario en Aliansalud - sbsidiado, se debe identificar en la tabla de afiliados pos como subsidiado - fecha de última consulta. En el proceso diario y de carga de las consultas se debe ajustar que no se puedan acreditas usuarios de Aliansalud que en la base de afiliados pos tengan la marca de subsidiado | F34: FINALIZADO | G34: 100 | H34: =IF(OR(J34="",K34="",K34<J34),0,NETWORKDAYS(J34,K34,Hoja2!$A$2:$A$53)) -> 7 | I34: 45925 | J34: 45932 | K34: 45940 | L34: 45938 | M34: =IF(OR(J34="",AND(L34="",TODAY()<J34),AND(L34<>"",L34<J34)),0, IF(L34="", NETWORKDAYS(J34,TODAY(),Hoja2!$A$2:$A$53), NETWORKDAYS(J34,L34,Hoja2!$A$2:$A$53) ) ) -> 5 | O34: 45938 | P34: 45940 | Q34: 30/09/2025 Se inicia con el desarrollo, creando campo nuevo que permite la identificación de si el usuario está en contributivo o subsidiado, según resultado de consulta Adres. 2/10/2025 se ubica la pagina en la que se lee el archivo de la respuesta del adres, para hacer el ajuste y que cuando se suba dicha data se identifiquen que usuarios estan en subsidiado-activo-aliansalud y poner la marca en la tabla de afiliados pos 6/10/2025 validar las páginas que ejecutan procedo de acreditación sobre la tabla de afiliadospos para que solo tome los que estan en contributivo y fecha fin 20251231 8/10/2025 se pasa a pruebas las opciones de subida de los archivos y las de validación para la acreditacipn, junto con la creacion del campo nuevo en la tabla de afiliadospos 10/10/2025 se pasa a produccion las opciones de subida de los archivos y las de validación para la acreditacipn, junto con la creacion del campo nuevo en la tabla de afiliadospos | R34: True
A35: JENNIFER | B35: OPT_16 | C35: Afiliaciones Pos - Menores Duplicados - RC-CN | D35: Control de menores Recien Nacido - Registro Civil duplicados, identificación dentro de contratos diferentes por misma fecha de nacimiento, primer apellido CN es igual al segunto apellido del RC, crear reporte semanal para poder validarlos | F35: FINALIZADO | G35: 100 | H35: =IF(OR(J35="",K35="",K35<J35),0,NETWORKDAYS(J35,K35,Hoja2!$A$2:$A$53)) -> 6 | I35: 45954 | J35: 45968 | K35: 45975 | L35: 45975 | M35: =IF(OR(J35="",AND(L35="",TODAY()<J35),AND(L35<>"",L35<J35)),0, IF(L35="", NETWORKDAYS(J35,TODAY(),Hoja2!$A$2:$A$53), NETWORKDAYS(J35,L35,Hoja2!$A$2:$A$53) ) ) -> 6 | O35: 45975 | P35: 45975 | Q35: 7/11/2025 Se inica el desarrollo, definiendo el query base con el que se hará la comparación y busqueda de posibles duplicados | R35: True
A36: JENNIFER | B36: OPT_17 | C36: Afiliaciones Pre - Base datos Inclusiones diarias Cargue | D36: sea remitir una base diaria de las solicitudes de inclusiones con los datos de residencia y correspondencia del contratante, para poder actualizarlos en Apolo. | F36: FINALIZADO | G36: 100 | H36: =IF(OR(J36="",K36="",K36<J36),0,NETWORKDAYS(J36,K36,Hoja2!$A$2:$A$53)) -> 6 | I36: 45960 | J36: 45961 | K36: 45971 | L36: 45971 | M36: =IF(OR(J36="",AND(L36="",TODAY()<J36),AND(L36<>"",L36<J36)),0, IF(L36="", NETWORKDAYS(J36,TODAY(),Hoja2!$A$2:$A$53), NETWORKDAYS(J36,L36,Hoja2!$A$2:$A$53) ) ) -> 6 | O36: 45971 | P36: 45971 | Q36: 31/10/2025 Se inicia creando el query para extraer la información que se necesita reportar, y se envía muestra al cliente para que confirme si así estaria bien la entrega y continuar con el desarrollo 4/11/2025 el cliente ya a prueba la estructura, y confirma que se debe hacer el reporte a Diario 7/11/2025 se crea la pagina que se ejecutará a Diario, y se empieza el desarrollo para la exportación de la data y el envío del correo electrónico 10/11/2025 Se termina el desarrollo, se publica la página en pruebas y producción. Se programa tarea para el envío de la información a diario. | R36: True
A37: JENNIFER | B37: OPT_18 | C37: Clasificacion Tributaria | D37: Captura de información o datos básico de documento Perfil tributario desde la radicación desde el módulo de convenios médicos, y que alimente lo de clasificacion tributaria | F37: PENDIENTE | G37: 0 | H37: =IF(OR(J37="",K37="",K37<J37),0,NETWORKDAYS(J37,K37,Hoja2!$A$2:$A$53)) -> 0 | I37: 45957 | M37: =IF(OR(J37="",AND(L37="",TODAY()<J37),AND(L37<>"",L37<J37)),0, IF(L37="", NETWORKDAYS(J37,TODAY(),Hoja2!$A$2:$A$53), NETWORKDAYS(J37,L37,Hoja2!$A$2:$A$53) ) ) -> 0 | Q37: 6/11/2025 se hace reunión con el área de convenios para identificar el proceso de radicación del documento de Perfil Tributario, que sería el que se tomará para el proceso de clasificación tributaria, u saber que información podemos tomar de alli, y optimizar la captura de los datos necesarios para el área de impuestos | R37: False
A38: JENNIFER | B38: OPT_19 | C38: Reporte Correos Colectivos Masivos - Acreditacion | D38: Una vez se cargue la base de correos de los colectivos enviados, se debe enviar dicha base de manera automática al equipo de manteniemento de colectivos del área de Fidelización | F38: FINALIZADO | G38: 100 | H38: =IF(OR(J38="",K38="",K38<J38),0,NETWORKDAYS(J38,K38,Hoja2!$A$2:$A$53)) -> 2 | I38: 46092 | J38: 46093 | K38: 46094 | M38: =IF(OR(J38="",AND(L38="",TODAY()<J38),AND(L38<>"",L38<J38)),0, IF(L38="", NETWORKDAYS(J38,TODAY(),Hoja2!$A$2:$A$53), NETWORKDAYS(J38,L38,Hoja2!$A$2:$A$53) ) ) -> 68 | O38: 46097 | P38: 46098 | Q38: 5/11/2025 Posible mejora detectada por Imagine -Jennifer 12/03/2026 se inicia con el desarrollo para el envío del correo a las 3 personas de mantenimiento de colectivos, se adiciona la función del envío del archivo que se sube, por correo electronico 16/03/2026 se adicionan cuentas para el envío de correos, por la adminitracion del envio de correos, y se debio adicionar un campo nuevo en el cargue, dado que dentro del cuerpo del correo salia un datos que no se pedía en el excel - se pasa a pruebas, para ser validado por el usuario 17/03/2026 se pasa a producción y en el siguiente proceso se le hará seguimiento, para confirmar el envío a las cuentas de mantenimiento colectivo | R38: True
A39: JENNIFER | B39: OPT_20 | C39: Afiliaciones Pre - Base datos usuarios menores sin datos de ubicación | D39: envío de una base con la información “si en la solicitud de ingreso los menores de edad vienen con los campos vacíos o en cero en dirección de residencia, teléfono residencia, ciudad, email y celular, se replique la información del contratante y se carguen con los mismos datos. Esto solo para menores de edad y solo si los campos no vienen diligenciados o vienen con dato cero “0”.” De manera semanal , todos los lunes | F39: FINALIZADO | G39: 100 | H39: =IF(OR(J39="",K39="",K39<J39),0,NETWORKDAYS(J39,K39,Hoja2!$A$2:$A$53)) -> 6 | I39: 45968 | J39: 45968 | K39: 45975 | L39: 45981 | M39: =IF(OR(J39="",AND(L39="",TODAY()<J39),AND(L39<>"",L39<J39)),0, IF(L39="", NETWORKDAYS(J39,TODAY(),Hoja2!$A$2:$A$53), NETWORKDAYS(J39,L39,Hoja2!$A$2:$A$53) ) ) -> 9 | O39: 45981 | P39: 45981 | Q39: 20/11/2025 se envía correo al cliente confirmando el el asunto del correo Menores sin datos en Afiliaciones Prepagadas cargadas y que el envío de la informacion corresponderá a lo cargado la semana inmediatamente anterior lunes a domingo. y se enviará de manera automática todos los lunes | R39: True
A40: JENNIFER | B40: OPT_21 | C40: Afiliaciones Pre - Base datos usuarios mayores que traen los mismos datos de ubicacion del titular | D40: envío de una base con la información “sobre los casos en los que los datos de afiliación de los beneficiarios mayores de edad presenten coincidencias en el correo electrónico y el número de teléfono. Este reporte tiene como objetivo identificar y analizar a los beneficiarios cuya información de contacto sea la misma.”. De manera mensual | F40: FINALIZADO | G40: 100 | H40: =IF(OR(J40="",K40="",K40<J40),0,NETWORKDAYS(J40,K40,Hoja2!$A$2:$A$53)) -> 6 | I40: 45968 | J40: 45968 | K40: 45975 | L40: 45981 | M40: =IF(OR(J40="",AND(L40="",TODAY()<J40),AND(L40<>"",L40<J40)),0, IF(L40="", NETWORKDAYS(J40,TODAY(),Hoja2!$A$2:$A$53), NETWORKDAYS(J40,L40,Hoja2!$A$2:$A$53) ) ) -> 9 | O40: 45981 | P40: 45981 | Q40: 20/11/2025 se envía correo al cliente confirmando el el asunto del correo Mayores con datos igual al Titular en Afiliaciones Prepagadas cargadas y que el envío de la informacion corresponderá a lo cargado el mes inmediatamente anterior, se vniará de manera automática el primer día del mes. | R40: True
A41: JENNIFER | B41: OPT_23 | C41: Afiliaciones Pos - Consulta Afilicion PBS Nuevas | D41: Afiliaciones nuevas de PBS WEB cambio la numeración y en la consulta se tiene restringido el largo | F41: FINALIZADO | G41: 100 | H41: =IF(OR(J41="",K41="",K41<J41),0,NETWORKDAYS(J41,K41,Hoja2!$A$2:$A$53)) -> 1 | I41: 45973 | J41: 45981 | K41: 45981 | L41: 45981 | M41: =IF(OR(J41="",AND(L41="",TODAY()<J41),AND(L41<>"",L41<J41)),0, IF(L41="", NETWORKDAYS(J41,TODAY(),Hoja2!$A$2:$A$53), NETWORKDAYS(J41,L41,Hoja2!$A$2:$A$53) ) ) -> 1 | O41: 45981 | P41: 45981 | Q41: 20/11/2025 se ajusta en la página de consulta para seguimiento de las solicitudes de PBS el largo de la numeración, dado los cambios de las nuevas afiliaciones PBS WEB | R41: True
A42: JENNIFER | B42: OPT_24 | C42: Afiliaciones Pos - Proceso nuevas afiliaciones | D42: inconsistencia en la generación de los lotes por imágenes de más y que son informativas, Adicionar al proceso la eliminación de estos archivos para que el sistema no las tenga en cuenta al momento del loteo | F42: FINALIZADO | G42: 100 | H42: =IF(OR(J42="",K42="",K42<J42),0,NETWORKDAYS(J42,K42,Hoja2!$A$2:$A$53)) -> 1 | I42: 45973 | J42: 45973 | K42: 45973 | L42: 45973 | M42: =IF(OR(J42="",AND(L42="",TODAY()<J42),AND(L42<>"",L42<J42)),0, IF(L42="", NETWORKDAYS(J42,TODAY(),Hoja2!$A$2:$A$53), NETWORKDAYS(J42,L42,Hoja2!$A$2:$A$53) ) ) -> 1 | O42: 45973 | P42: 45973 | Q42: 12/11/2025 se adiciona en la revisión de las imágenes la eliminación de los documentos que son informativos, e iguales para todos los usuarios y no son necesarios queden adjuntos a la afiliacion | R42: True
A43: JENNIFER | B43: OPT_25 | C43: Afiliaciones Pre - Parentescos XML | D43: Ajustar un parentesco que no se estaba cargando desde el xml por cambio en su escritura | F43: FINALIZADO | G43: 100 | H43: =IF(OR(J43="",K43="",K43<J43),0,NETWORKDAYS(J43,K43,Hoja2!$A$2:$A$53)) -> 1 | I43: 45973 | J43: 45973 | K43: 45973 | L43: 45973 | M43: =IF(OR(J43="",AND(L43="",TODAY()<J43),AND(L43<>"",L43<J43)),0, IF(L43="", NETWORKDAYS(J43,TODAY(),Hoja2!$A$2:$A$53), NETWORKDAYS(J43,L43,Hoja2!$A$2:$A$53) ) ) -> 1 | O43: 45973 | P43: 45973 | Q43: 12/11/2025 se adicionan los parentescos nuevos creados para hacer la respectiva hologación al tramitar la afiliación | R43: True
A44: JENNIFER | B44: OPT_26 | C44: Afiliaciones Pos - Documentos con extension errada | D44: Seguimiento nuevas afiliaciones en la marcación de soportes hay imágenes que no se pueden visualizar, y se detecta que llegan con una extensión que no corresponde al tipo de archivo real | F44: FINALIZADO | G44: 100 | H44: =IF(OR(J44="",K44="",K44<J44),0,NETWORKDAYS(J44,K44,Hoja2!$A$2:$A$53)) -> 3 | I44: 45974 | J44: 45974 | K44: 45979 | L44: 45979 | M44: =IF(OR(J44="",AND(L44="",TODAY()<J44),AND(L44<>"",L44<J44)),0, IF(L44="", NETWORKDAYS(J44,TODAY(),Hoja2!$A$2:$A$53), NETWORKDAYS(J44,L44,Hoja2!$A$2:$A$53) ) ) -> 3 | O44: 45979 | P44: 45985 | Q44: 13/11/2025 se detecta que las imagenes no se pueden visualizar y es por un error de la extensión, asi que se hace desarrollo para que el sistema identifique si llega jpg y es pdf, le cambia la extención y se hace seguimiento del cambio 14/11/2025 Reporte de la inconsistencia para que corrigan desde el origen(otro proveedor) 18/11/2025 - 21/11/2025 ajuste de los lotes ya armados corrigiendo mediante página la extensión de los archivos 24/11/2025 Adicionar al proceso de organización de imágenes para el loteo, la validación del tipo de imagen para que se corrija antes de la generación de lotes | R44: True
A45: JENNIFER | B45: OPT_27 | C45: Cuentas Umd - Cambio cargue de archivo precuentas | D45: Se crearan nuevas cuentas contables y se necesita modificar la estructura para el cargue respectivo según el archivo arrojado por el sistema de UMD | F45: FINALIZADO | G45: 100 | H45: =IF(OR(J45="",K45="",K45<J45),0,NETWORKDAYS(J45,K45,Hoja2!$A$2:$A$53)) -> 6 | I45: 45988 | J45: 46009 | K45: 46017 | L45: 46028 | M45: =IF(OR(J45="",AND(L45="",TODAY()<J45),AND(L45<>"",L45<J45)),0, IF(L45="", NETWORKDAYS(J45,TODAY(),Hoja2!$A$2:$A$53), NETWORKDAYS(J45,L45,Hoja2!$A$2:$A$53) ) ) -> 12 | O45: 46017 | P45: 46027 | Q45: 27/11/2025 Según reunión, necesitan hacer un ajuste a la estructura para cargar nuevas cuentas contables 9/11/2025 se carga el archivo con la estructura actual, y el valor de la cuenta contable nueva, lo cargan en una ya existente y desde Imagine se hace el ajuste a la nueva cuenta contable. se recibe la estructura nueva para poder iniciar el desarrollo 19/12/2025 Se inicia con la revisión y contraste de la posición de las columnas y cuentas contables del cargue actual y la nueva estructura entregada, y se ajustan las columnas, para el cargue 22/12/2025 prueba de cargue con el archivo enviado en desarrollo,y ajuste de las validaciones a 27 columnas, ajuste a 26/12/2025 se pasa a pruebas y se prueba la estructura 5/01/2025 se pasa a producción para el cargue del archivo por parte del cliente, y se confirma el cargue satisfactorio | R45: True
A46: JENNIFER | B46: OPT_28 | C46: Recobros - Opcion para ejecucion del proceso documental | D46: Crear boton, para que puedan ejecutar el proceso, cuando lo necesite la parte operativa y nose dependa de Imagine | F46: FINALIZADO | G46: 100 | H46: =IF(OR(J46="",K46="",K46<J46),0,NETWORKDAYS(J46,K46,Hoja2!$A$2:$A$53)) -> 6 | I46: 45989 | J46: 45989 | K46: 45996 | L46: 45996 | M46: =IF(OR(J46="",AND(L46="",TODAY()<J46),AND(L46<>"",L46<J46)),0, IF(L46="", NETWORKDAYS(J46,TODAY(),Hoja2!$A$2:$A$53), NETWORKDAYS(J46,L46,Hoja2!$A$2:$A$53) ) ) -> 6 | O46: 46003 | P46: 46003 | Q46: 28/11/2025 Creacion de opcion por Administración que permita la ajecución del proceso de busqueda documental 05/12/2025 se colocan las paginas que hacen la validación documental 12/12/2025 se pasa a pruebas y produccion | R46: True
A47: JENNIFER | B47: OPT_29 | C47: Afiliaciones PBS - Consumo de Imagenes | D47: Crear página que realice el consumo para poder traernos las imágenes de PBS, y evitar que Colmédica las deje de manera manual en un repositorio | F47: FINALIZADO | G47: 100 | H47: =IF(OR(J47="",K47="",K47<J47),0,NETWORKDAYS(J47,K47,Hoja2!$A$2:$A$53)) -> 5 | I47: 46001 | J47: 46021 | K47: 46028 | L47: 46027 | M47: =IF(OR(J47="",AND(L47="",TODAY()<J47),AND(L47<>"",L47<J47)),0, IF(L47="", NETWORKDAYS(J47,TODAY(),Hoja2!$A$2:$A$53), NETWORKDAYS(J47,L47,Hoja2!$A$2:$A$53) ) ) -> 4 | O47: 46027 | P47: 46028 | Q47: 10/12/2025 Entrega de web service por parte de Colmedica url de pruebas y documentacion 12/12/2025 pruebas de consumo manualmente, el web service no da respuesta de imágenes 15/12/2025 reunión contextualizacion incosistencia, y se evidencia que los id no son correctos para hacer los consumos, el proveedor debe hacer ajustes en el XML y el otro proveedor crear documentos de PBS 17/12/2025 entregan el ajuste de los documentos, se hace nuevamente la prueba manual del consumo y ya se recibe el base64, sin embargo solo se pudieron consumir los documentos principales, ninguno de los adjuntos llega con id para el consumo, se reporta de nuevo al proveedor para que revisen 23/12/2025 Informa, que ya hicieron los ajustes en el XML para poder consumor los soportes adjuntos, se realizan las pruebas en Ambiente de pruebas, y se pudo hacer el consumo e los documentos. 29/12/2025 Se ajusta la pagina para el consumo por parte de nosotros, de manera puntual indicando los numeros de solicitudes, y validar el consumos de las solicitudes pendientes 30/12/2025 ya se consumen en produccion las imágenes de las solicitudes y se crea la página que invocará el proceso de radicación, para que se vayan trayendo las imágenes a medida que se van radicando en el sistema 5/01/2026 se hace hace la implementación en pruebas y consume sin problema las imágenes 6/01/2026 se implementa en producción y se le hace seguimiento al proceso | R47: True
A48: JENNIFER | B48: OPT_30 | C48: Comercial - Modulo de Normalización | D48: Mejoras al módulo para agilizar la auditoria y revisión de inconsistencias por parte de las Gestoras, ver inforción importante, eliminar datos innecesarios, mejorar ventana para visualización de información | F48: FINALIZADO | G48: 100 | H48: =IF(OR(J48="",K48="",K48<J48),0,NETWORKDAYS(J48,K48,Hoja2!$A$2:$A$53)) -> 15 | I48: 46029 | J48: 46058 | K48: 46078 | L48: 46078 | M48: =IF(OR(J48="",AND(L48="",TODAY()<J48),AND(L48<>"",L48<J48)),0, IF(L48="", NETWORKDAYS(J48,TODAY(),Hoja2!$A$2:$A$53), NETWORKDAYS(J48,L48,Hoja2!$A$2:$A$53) ) ) -> 15 | O48: 46080 | P48: 46091 | Q48: 7/01/2026 se hace reunión con el área comercial, para ver mejoras del módulode normalización, y mejorar la revisión de las solicitudes 5/02/2026 Se revisa documento enviado por el área comercial, para validar los ajustes solicitados para la plataforma de Normalización de Afiliaciones, Se renombfran columnas y eliminan las solicitadas 6/02/2026 se inicia con la adición de columnas y la modificación en query para obtener el datos 9/02/2026 modificación en las vistas de modales con la información de devolucions y auditoria médica 11/02/2026 Se validan los filtros solicitados sobre los campos para consultas puntuales 27/02/2026 se confirman, cambios, y se informa al cliente para la revisión 3/03/2026 se hace reunión con el átrea para hacer retroalimentación, y piden unos ajustes de forma para poder pasar a producción 4/03/2026 se empiezan a hacer los ajustes solicitados en la reunión anterioir 10/03/2026 se hace reunión para mostrar los ajustes según la última reunión, y se aprueban por parte del área para paso a producción | R48: True
A49: JENNIFER | B49: OPT_31 | C49: Afiliaciones Pre - Validación 7 campos | D49: En la validación de los 7 campos importantes que se toman del soporte de identificación, si ya existe en la base de afiliados se completará la información con dicha data para que en la operación no la capturen pero si la validen | F49: FINALIZADO | G49: 100 | H49: =IF(OR(J49="",K49="",K49<J49),0,NETWORKDAYS(J49,K49,Hoja2!$A$2:$A$53)) -> 1 | I49: 46035 | J49: 46035 | K49: 46035 | L49: 46035 | M49: =IF(OR(J49="",AND(L49="",TODAY()<J49),AND(L49<>"",L49<J49)),0, IF(L49="", NETWORKDAYS(J49,TODAY(),Hoja2!$A$2:$A$53), NETWORKDAYS(J49,L49,Hoja2!$A$2:$A$53) ) ) -> 1 | O49: 46035 | P49: 46035 | Q49: 13/01/2026 en la opción de selección de lote que llena la tabla con la info del lote a validar con las identificaciones de titular y beneficiarios, se adiciona query para traer datos de la base de afiliados pre y si no está de afiliados pos | R49: True
A50: JENNIFER | B50: OPT_32 | C50: Afiliaciones Pos - Validación 7 campos | D50: En la validación de los 7 campos importantes que se toman del soporte de identificación, si ya existe en la base de afiliados se completará la información con dicha data para que en la operación no la capturen pero si la validen | F50: FINALIZADO | G50: 100 | H50: =IF(OR(J50="",K50="",K50<J50),0,NETWORKDAYS(J50,K50,Hoja2!$A$2:$A$53)) -> 1 | I50: 46036 | J50: 46036 | K50: 46036 | L50: 46036 | M50: =IF(OR(J50="",AND(L50="",TODAY()<J50),AND(L50<>"",L50<J50)),0, IF(L50="", NETWORKDAYS(J50,TODAY(),Hoja2!$A$2:$A$53), NETWORKDAYS(J50,L50,Hoja2!$A$2:$A$53) ) ) -> 1 | O50: 46036 | P50: 46036 | Q50: 14/01/2026 en la opción de selección de lote que llena la tabla con la info del lote a validar con las identificaciones de cotizante y beneficiarios, se adiciona query para traer datos de la base de afiliados pre y si no está de afiliados pos | R50: True
... A55: JENNIFER | B55: OPT_36 | C55: Afiliaciones PRE - Consulta Sarlaft | D55: Se debe hacer la consulta por el titular y los usuarios que vengan en el formulario mayores de edad, incluir en base de datos y se debe modificar el cargue de respuesta de infolat, por que ya se cargaran varios soportes a la misma solicitud | F55: FINALIZADO | G55: 100 | H55: =IF(OR(J55="",K55="",K55<J55),0,NETWORKDAYS(J55,K55,Hoja2!$A$2:$A$53)) -> 8 | I55: 46073 | J55: 46078 | K55: 46087 | L55: 46086 | M55: =IF(OR(J55="",AND(L55="",TODAY()<J55),AND(L55<>"",L55<J55)),0, IF(L55="", NETWORKDAYS(J55,TODAY(),Hoja2!$A$2:$A$53), NETWORKDAYS(J55,L55,Hoja2!$A$2:$A$53) ) ) -> 7 | O55: 46086 | P55: 46087 | Q55: 25/02/2026 Se crea campo nuevo para diferenciar el titular del beneficiario.,se Realiza revisión del momento en el que se coloca la información en la tabla de consulta sarlaft para que se empiecen a almacenar los usuarios que sean mayores a 18 años 26/02/2026 en el proceso de consulta, de captura y verificación del sarlaft, se ajusta para omitir los registros que corresponden a beneficiarios, dado que por ellos no se recibirá documento, sino solo el del titular, más sin embargo si se llegase a devolver por alguna inconsistencia, los registros de los beneficiarios, tambien deben quedar devueltos, o de lo contrario enviarse para la consulta 3/03/2026 se inician los ajustes para la carga de los soportes y que no se renombren los soportes con solo el numero de solicitud, sino que queden solicitud y cc de la consulta. Se confirma el proceso que hace la lectura del PDF para guardar si viene reportado en listas y ajustar tambien que lea el pdf afiliacion_identificacion 5/03/2026 confirmacion de la última parte del proceso, donde despues se valida el resultado de la lectura del pdf, para saber si la solicitud queda devuelta o continua el proceso normal, y se adjunta la imagen a cada afiliación. se dispone en pruebas y valida 6/03/2026 Se pasa a produccion y se hacen 2 pruebas controladas para revisar el proceso completo | R55: True
A56: JENNIFER | B56: OPT_37 | C56: Convenios Medicos - Ajuste cuerpo del correo campaña | D56: Ajuste al cuerpo del correo por cambio en las páginas de Colmedica - Aliansalud para los prestadores, links de redireccionamiento se deben retirar, y ajustes a texto, dependiendo de la compañia y/o tipo de prestador | F56: FINALIZADO | G56: 100 | H56: =IF(OR(J56="",K56="",K56<J56),0,NETWORKDAYS(J56,K56,Hoja2!$A$2:$A$53)) -> 2 | I56: 46080 | J56: 46098 | K56: 46099 | M56: =IF(OR(J56="",AND(L56="",TODAY()<J56),AND(L56<>"",L56<J56)),0, IF(L56="", NETWORKDAYS(J56,TODAY(),Hoja2!$A$2:$A$53), NETWORKDAYS(J56,L56,Hoja2!$A$2:$A$53) ) ) -> 65 | O56: 46099 | P56: 46105 | Q56: 27/02/2026 solicitan ejemplo de correos de los diferentes prestadores, para jacer modificaciones al cuerpo del correo de la campaña 2/03/2026 se envía correo ejemplos por cada tipo de prestador solicitado. 16/03/2026 alcance al correo para hacer seguimiento, no se han recibido los cambios que mencionaron, se recibe finalizando la tarde el correo con los ajustes respectivos 17/03/2026 se validan los cambios, y se procede a relaizarlos 18/03/2026 se pasa al ambiente de pruebas 19/03/2026 se envían correos de pruebas con los cambios, para Aliansalud IPS - Colmedica IPS y Medicos Colmédica 20/03/2026 se hace una pequeña sesión donde piden unos ajustes de forma, los cuales se realizan y se envían nuevas muestras de los correos para aprobación 24/03/2026 se pasa a producción ya autorización del cliente y visto bueno de los cambios en el cuerpo del correo. se enviaron unas pruebas controladas en producción y se dispara la campaña | R56: True
A57: JENNIFER | B57: OPT_38 | C57: Comercial - Ajuste archivo de reporte general de Normalización | D57: Piden se cambie de nombre unas columnas y se adicione otra columna con dato de asignación | F57: FINALIZADO | G57: 100 | H57: =IF(OR(J57="",K57="",K57<J57),0,NETWORKDAYS(J57,K57,Hoja2!$A$2:$A$53)) -> 1 | I57: 46094 | J57: 46099 | K57: 46099 | M57: =IF(OR(J57="",AND(L57="",TODAY()<J57),AND(L57<>"",L57<J57)),0, IF(L57="", NETWORKDAYS(J57,TODAY(),Hoja2!$A$2:$A$53), NETWORKDAYS(J57,L57,Hoja2!$A$2:$A$53) ) ) -> 64 | O57: 46099 | P57: 46099 | Q57: 17/03/2026 se validan los cambios solicitados para la modificación del excel que se genera 18/03/2026 se pasa a pruebas, y se envía ejemplo de cómo quedaría la nueva versión de dicho excel, es aprobado por el responsable y se pasa a producción | R57: True
A58: JENNIFER | B58: OPT_39 | C58: Afiliaciones PRE - Campos nuevos que se recibiran en el XML | D58: campos nuevos que se recibiran en el XML, se debe garantizar su almacenamiento en todas las tablas del proceso | F58: FINALIZADO | G58: 100 | H58: =IF(OR(J58="",K58="",K58<J58),0,NETWORKDAYS(J58,K58,Hoja2!$A$2:$A$53)) -> 7 | I58: 46101 | J58: 46132 | K58: 46140 | M58: =IF(OR(J58="",AND(L58="",TODAY()<J58),AND(L58<>"",L58<J58)),0, IF(L58="", NETWORKDAYS(J58,TODAY(),Hoja2!$A$2:$A$53), NETWORKDAYS(J58,L58,Hoja2!$A$2:$A$53) ) ) -> 44 | O58: 46141 | P58: 46146 | Q58: 20/03/2026 se pide aclaración sobre los campos nuevos que se recibiran en el formulario de Medicina prepagada, si apliacarán tanto para titular como beneficiario, y si se van a migrar a Apolo 24/03/2026 aclaración por parte del cliente de lo que se recibirá, y por ahora se mantendrá en Imagine, a la espera de recibir xml de prueba para saber como llegaran las etiquetas y los datos en este y así poder definir como se almacenaran en la base de imagine. a la espera de definir si migrarán a Apolo y como será la homologación 6/04/2026 sesión para confirmar lo de las pruebas de los xml que se recibira, según el otro proveedor el miercoles 8/04 8/04/2026 se reciben muestras de XMl, y se piden ajustes, por que no llega toda la informacion completa 10/04/2026 se reciben nuevas pruebas de XML para poder validar los campos nuevos, y se piden ajustes por inconsistencias 16/04/2026 se reciben de nuevo pruebas con la información de xml, asi que se empieza a revisar las diferentes tablas en imgine para la ceración de los campos nuevos 20/04/2026 se valida que la informacion que llega en el xml se almacene de manera correcta en la shema del ipad 22/04/2026 se empezaron a crear los campos nuevos en las tablas afectadas del proceso de Medicina prepagada, por las que se mueven mientras esten en proces, devueltas, en área médica, anuladas, para cargue y ya cargadas. 24/04/2026 se empieza a justar el proceso de distribución de la información que llega en el xml en los campos nuevos de las tablas básicas y en todas las distribuciones en las diferentes tablas, para que dentro de ningun paso se omitan 4/05/2026 se pasa a producción las páginas del ajuste de los nuevos campos, y la creación de campos en las tablas de producción | R58: True
A59: JENNIFER | B59: OPT_40 | C59: Acreditación - Envio de correos a los colectivos | D59: Envío de corrreos sobre los usuarios pendientes por acreditar, directamente a la empresa y dejar trazabilidad del mismo dentro de la gestión de cada contrato. | F59: EN PROCESO | G59: 60 | H59: =IF(OR(J59="",K59="",K59<J59),0,NETWORKDAYS(J59,K59,Hoja2!$A$2:$A$53)) -> 0 | I59: 46106 | J59: 46108 | M59: =IF(OR(J59="",AND(L59="",TODAY()<J59),AND(L59<>"",L59<J59)),0, IF(L59="", NETWORKDAYS(J59,TODAY(),Hoja2!$A$2:$A$53), NETWORKDAYS(J59,L59,Hoja2!$A$2:$A$53) ) ) -> 58 | Q59: 27/03/2026 revisar el proceso actual de generación de correos, para identificar el proceso de colectivos, y su respectivo armado 30/03/2026 se ajusta para que el correo salga directamente a la cuenta del colectivo 6/04/2026 se empieza a hacer el ajsute para que se vaya dejando trazabilidad del envío del correo por contrato del colectivo | R59: True
A60: JENNIFER | B60: OPT_41 | C60: Afiliaciones PRE - Lectura XML Estados Salud | D60: Revisar inconsistencia no todas las solicitudes con respuesta positiva están quedando marcadas con la causal médica para que la respectiva área las revise | F60: FINALIZADO | G60: 100 | H60: =IF(OR(J60="",K60="",K60<J60),0,NETWORKDAYS(J60,K60,Hoja2!$A$2:$A$53)) -> 1 | I60: 46127 | J60: 46127 | K60: 46127 | L60: 46127 | M60: =IF(OR(J60="",AND(L60="",TODAY()<J60),AND(L60<>"",L60<J60)),0, IF(L60="", NETWORKDAYS(J60,TODAY(),Hoja2!$A$2:$A$53), NETWORKDAYS(J60,L60,Hoja2!$A$2:$A$53) ) ) -> 1 | O60: 46127 | P60: 46127 | Q60: 15/04/2026 se realiza la revisión del proceso de lectura del XL de Ipad, para poder identificar los casos que vienen con respuestas positivas y no quedan con la causal respectiva para que pase al área médica, y de identifica que un array que se llena con los nombres de las columnas de de las tablas de los estados de salud, si bien en la mayoria los nombres de los campos son los mismos, en otra no lo son, y como el array no se estaba definiendo, pues generó la inconsistena | R60: True
A61: JENNIFER | B61: OPT_42 | C61: Afiliaciones Pre - Revisión Médica | D61: Inconsistencia en la visualización de ciertas imágenes que el visor actual no esta permitiendo ver | F61: FINALIZADO | G61: 100 | H61: =IF(OR(J61="",K61="",K61<J61),0,NETWORKDAYS(J61,K61,Hoja2!$A$2:$A$53)) -> 1 | I61: 46132 | J61: 46133 | K61: 46133 | L61: 46133 | M61: =IF(OR(J61="",AND(L61="",TODAY()<J61),AND(L61<>"",L61<J61)),0, IF(L61="", NETWORKDAYS(J61,TODAY(),Hoja2!$A$2:$A$53), NETWORKDAYS(J61,L61,Hoja2!$A$2:$A$53) ) ) -> 1 | O61: 46134 | P61: 46134 | Q61: 20/04/2026 se realiza reunión para evidenciar que en algunos casos las impágenes soporte de ciertas afiliaciones no las pueden visualizar de manera correcta por la plataforma de Riesgo médico 21/04/2026 se recibieron varios casos de ejemplo en el que no se podian sivualisar, y el error es con las imágenes jpg que el viso no ls esta mostrando, se retira la opción que no permitia visualizar de manera correcta los jpg 22/04/2026 se pasa a test y producción entregando al cliente | R61: True
A62: JENNIFER | B62: OPT_43 | C62: Afiliaciones Pre - Revisión Médica | D62: Ajustar la visualización sobre si las solicitudes durante la revisión médica le generaron Formato para envío a Salesforce, | F62: FINALIZADO | G62: 100 | H62: =IF(OR(J62="",K62="",K62<J62),0,NETWORKDAYS(J62,K62,Hoja2!$A$2:$A$53)) -> 1 | I62: 46136 | J62: 46136 | K62: 46136 | L62: 46136 | M62: =IF(OR(J62="",AND(L62="",TODAY()<J62),AND(L62<>"",L62<J62)),0, IF(L62="", NETWORKDAYS(J62,TODAY(),Hoja2!$A$2:$A$53), NETWORKDAYS(J62,L62,Hoja2!$A$2:$A$53) ) ) -> 1 | O62: 46136 | P62: 46139 | Q62: 24/04/2026 Se ajusta la visualización para que sea más claro si el área médica le generó formato y si este fue o no enviado a Salesforce para seguimiento médico 27/04/2026 se publica en producción el ajuste y se informa al área encargada para su revisión | R62: True
A63: JENNIFER | B63: OPT_44 | C63: Afiliaciones Pre - Comercial | D63: Ajustar la visualización sobre si las solicitudes durante la revisión médica le generaron Formato para envío a Salesforce, | F63: FINALIZADO | G63: 100 | H63: =IF(OR(J63="",K63="",K63<J63),0,NETWORKDAYS(J63,K63,Hoja2!$A$2:$A$53)) -> 4 | I63: 46139 | J63: 46140 | K63: 46146 | L63: 46142 | M63: =IF(OR(J63="",AND(L63="",TODAY()<J63),AND(L63<>"",L63<J63)),0, IF(L63="", NETWORKDAYS(J63,TODAY(),Hoja2!$A$2:$A$53), NETWORKDAYS(J63,L63,Hoja2!$A$2:$A$53) ) ) -> 3 | O63: 46142 | P63: 46146 | Q63: 28/04/2026 se inicia con el ajuste en la vista de los datos de revisión médica en el módulo de Normalización para que se identifique si el área médica le generó formato y si este fue o no enviado a Salesforce para seguimiento médico 30/04/2026 se ajusta la vista de la información del área médica por la consulta general de la solicitud, para que se pueda visualizar si tiene o no formato, y si fueron enviados a salesforce 4/05/2026 se pasa a producción los cambios de las 2 vistas | R63: True
A64: JENNIFER | B64: OPT_45 | C64: Convenios Medicos - Adicionar 2 documentos para cargue de documentos de manera masiva | D64: Adicionar al cargue Masivo los documentos de Afiliación ARL y Certificaciones de Titulo, y en producto adicionar CEM | F64: FINALIZADO | G64: 100 | H64: =IF(OR(J64="",K64="",K64<J64),0,NETWORKDAYS(J64,K64,Hoja2!$A$2:$A$53)) -> 2 | I64: 46136 | J64: 46139 | K64: 46140 | L64: 46140 | M64: =IF(OR(J64="",AND(L64="",TODAY()<J64),AND(L64<>"",L64<J64)),0, IF(L64="", NETWORKDAYS(J64,TODAY(),Hoja2!$A$2:$A$53), NETWORKDAYS(J64,L64,Hoja2!$A$2:$A$53) ) ) -> 2 | O64: 46140 | P64: 46148 | Q64: 27/04/2026 se validan los documentos y se habilitan para que puedan ser seleccionados desde la pagina del cargue, y se comparan con los campos utilizados de otros documentos del cargue masivo 28/04/2026 se hacen los ajustes en las paginas que se involucran en el cargue adicionando las validaciones respectivas de cada documento, y se adicionan los códigos y querys necesarios según el documento. 6/05/2026 confirman las pruebas y se pasaa producción los cambios para los cargues nuevos | R64: True
A65: JENNIFER | B65: OPT_46 | C65: Afiliaciones PRE - Ajuste validación tarifa asociativos | D65: En la entrega de la validación de los 7 campos, al entregar el lote se debe ajustar paraq eu los contrato | F65: FINALIZADO | G65: 100 | H65: =IF(OR(J65="",K65="",K65<J65),0,NETWORKDAYS(J65,K65,Hoja2!$A$2:$A$53)) -> 1 | I65: 46168 | J65: 46168 | K65: 46168 | M65: =IF(OR(J65="",AND(L65="",TODAY()<J65),AND(L65<>"",L65<J65)),0, IF(L65="", NETWORKDAYS(J65,TODAY(),Hoja2!$A$2:$A$53), NETWORKDAYS(J65,L65,Hoja2!$A$2:$A$53) ) ) -> 20 | O65: 46168 | P65: 46168 | Q65: 26/05/2026 se ajusta la pagina para que en caso de las afiliaciones que son asociativos y no se encuentra la tarifa definida como familiar, puede estar definida solo como colectivo | R65: True
A66: JENNIFER | B66: OPT_47 | C66: Afiliaciones PRE - Reporte diario solicitudes cargue matrices puntuales | D66: enviar por correo electrónico a operaciones la base de afiliaciones de matriz específica de cargue masivo que estan listas para cargue, proceso automático | F66: FINALIZADO | G66: 100 | H66: =IF(OR(J66="",K66="",K66<J66),0,NETWORKDAYS(J66,K66,Hoja2!$A$2:$A$53)) -> 2 | I66: 46168 | J66: 46169 | K66: 46170 | M66: =IF(OR(J66="",AND(L66="",TODAY()<J66),AND(L66<>"",L66<J66)),0, IF(L66="", NETWORKDAYS(J66,TODAY(),Hoja2!$A$2:$A$53), NETWORKDAYS(J66,L66,Hoja2!$A$2:$A$53) ) ) -> 19 | O66: 46170 | P66: 46170 | Q66: 27/05/2026 creación de registro para el envió del correo, y se empieza con el desarrollo de la página 28/05/2026 se pasa la pagina a pruebas y se crea eel registro en la administracion de correos automáticos. se pasa la pagina a produccióny se crea eel registro en la administracion de correos automáticos. se crea la tarea automática de envió del correo para que sea sobre las 4:40pm | R66: True
A67: JENNIFER | B67: OPT_48 | C67: Acreditación - Entrega base para mensajes personalizados | D67: Entrega de base de usuarios pendientes por acreditación para envío de mensajes de texto al celular, datos del contrato, titular id y nombre completo y cantidad de usuarios dentro del contrato pendientes por acreditar | F67: PENDIENTE | G67: 0 | H67: =IF(OR(J67="",K67="",K67<J67),0,NETWORKDAYS(J67,K67,Hoja2!$A$2:$A$53)) -> 0 | M67: =IF(OR(J67="",AND(L67="",TODAY()<J67),AND(L67<>"",L67<J67)),0, IF(L67="", NETWORKDAYS(J67,TODAY(),Hoja2!$A$2:$A$53), NETWORKDAYS(J67,L67,Hoja2!$A$2:$A$53) ) ) -> 0 | Q67: 25/05/2026 en reunión se trata el tema de entregar periódicamente una base con los afiliados pendientes por acreditar, quedamos atentos a definición de con que periodicidad y fomarlizar la solicitud por parte del área 3/06/2026 seguimos a la espera, segun reunión de seguimiento no han definido los tiempos para la entrega de la base | R67: False
A68: JENNIFER | B68: OPT_49 | C68: Gestion Humana - Indexador | D68: Realizar el indexador de hojas de vida y dejar de usar el access de indexación actual y el de importación, se escanerarn las guias de las hojas de vida por paquete documental y se debe crear opción donde se consulte la guia y se adjunten los soportes, para que queden publicados en la carpeta del funcionario | F68: EN PROCESO | G68: 80 | H68: =IF(OR(J68="",K68="",K68<J68),0,NETWORKDAYS(J68,K68,Hoja2!$A$2:$A$53)) -> 0 | I68: 46167 | J68: 46170 | M68: =IF(OR(J68="",AND(L68="",TODAY()<J68),AND(L68<>"",L68<J68)),0, IF(L68="", NETWORKDAYS(J68,TODAY(),Hoja2!$A$2:$A$53), NETWORKDAYS(J68,L68,Hoja2!$A$2:$A$53) ) ) -> 18 | Q68: 25/05/2026 Se entrega documento con el requerimiento a Don HErnán y el crea la opción 26/05/2026 Se piden ajustes sobre la información pintada en pantalla y y se realizan primeras pruebas de subir soportes 27/05/2026 se solicita una adición de validación a la cantidad de folios, y se pide nuevamente ajustes a la pantalla principal que muestra información innecesaria y satura la vista 28/05/2026 Se confirma que puede ser entregado el proyecto para ponerlo en desarrollo y empezar a hacer los ajsutes relacionados a conexión base de datos 23/06/2026 Se explica a Jhon, para ajuste de url destino de las imágenes adecuadas al servidor, y que no cargeu pagina de logueo, sino que se incoque el usuario del logueo incial y se lleve a ese link | R68: True
A69: JENNIFER | B69: OPT_50 | C69: Comercial - Cambios plataforma de Normalización | D69: Cambios en la bandeja de trabajo, como alertas por vigencia color por rango de fecha, opción de ordenamiento, permitir filtros por ciertas columnas. mensaje de confirmación de vigencia al registrar el reingreso | F69: EN PROCESO | G69: 10 | H69: =IF(OR(J69="",K69="",K69<J69),0,NETWORKDAYS(J69,K69,Hoja2!$A$2:$A$53)) -> 0 | I69: 46174 | J69: 46176 | M69: =IF(OR(J69="",AND(L69="",TODAY()<J69),AND(L69<>"",L69<J69)),0, IF(L69="", NETWORKDAYS(J69,TODAY(),Hoja2!$A$2:$A$53), NETWORKDAYS(J69,L69,Hoja2!$A$2:$A$53) ) ) -> 14 | Q69: 3/06/2026 se inicia con la modificación en la plantilla para adicionar las columnas nuevas, se adicióno semaforización para las afiliaciones segun fecha de inicio de vigencia | R69: True
A70: JENNIFER | B70: OPT_51 | C70: Acreditación - Base con corte al 1 de cada mes | D70: Cambios en la bandeja de trabajo, como alertas por vigencia color por rango de fecha, opción de ordenamiento, permitir filtros por ciertas columnas. mensaje de confirmación de vigencia al registrar el reingreso | F70: PENDIENTE | G70: 0 | H70: =IF(OR(J70="",K70="",K70<J70),0,NETWORKDAYS(J70,K70,Hoja2!$A$2:$A$53)) -> 0 | I70: 46182 | M70: =IF(OR(J70="",AND(L70="",TODAY()<J70),AND(L70<>"",L70<J70)),0, IF(L70="", NETWORKDAYS(J70,TODAY(),Hoja2!$A$2:$A$53), NETWORKDAYS(J70,L70,Hoja2!$A$2:$A$53) ) ) -> 0 | R70: False
A71: JENNIFER | B71: OPT_52 | C71: Acreditación - Informes - Gestion Acreditacion - Tipos Acreditacion | D71: Informe soporte para la Facturacion, Registros de Gestión durante el mes y registros de causales de acreditación durante el mes | F71: PENDIENTE | G71: 0 | H71: =IF(OR(J71="",K71="",K71<J71),0,NETWORKDAYS(J71,K71,Hoja2!$A$2:$A$53)) -> 0 | I71: 46182 | M71: =IF(OR(J71="",AND(L71="",TODAY()<J71),AND(L71<>"",L71<J71)),0, IF(L71="", NETWORKDAYS(J71,TODAY(),Hoja2!$A$2:$A$53), NETWORKDAYS(J71,L71,Hoja2!$A$2:$A$53) ) ) -> 0 | R71: False
A72: JENNIFER | B72: OPT_53 | C72: Tutelas - Ajuste de Visor Imagenes | D72: Ajustar el visor para ver imágenes tiff,pdf,jpg,png | F72: PRUEBAS CLIENTE | G72: 100 | H72: =IF(OR(J72="",K72="",K72<J72),0,NETWORKDAYS(J72,K72,Hoja2!$A$2:$A$53)) -> 2 | I72: 46190 | J72: 46191 | K72: 46192 | M72: =IF(OR(J72="",AND(L72="",TODAY()<J72),AND(L72<>"",L72<J72)),0, IF(L72="", NETWORKDAYS(J72,TODAY(),Hoja2!$A$2:$A$53), NETWORKDAYS(J72,L72,Hoja2!$A$2:$A$53) ) ) -> 5 | O72: 46192 | Q72: 18/06/2026 se evalua y revisa el visor actual de las archivos que se suben de tutelas y se inicia el ajuste según visro actual de afiliaciones 19/06/2026 se pasa a pruebas y se informa al cliente para que revisen la visualización | R72: False
A73: JENNIFER | C73: Afiliaciones POS - Completar descarga de cartas Derechos y Deberes | F73: PENDIENTE | G73: 0 | H73: =IF(OR(J73="",K73="",K73<J73),0,NETWORKDAYS(J73,K73,Hoja2!$A$2:$A$53)) -> 0 | M73: =IF(OR(J73="",AND(L73="",TODAY()<J73),AND(L73<>"",L73<J73)),0, IF(L73="", NETWORKDAYS(J73,TODAY(),Hoja2!$A$2:$A$53), NETWORKDAYS(J73,L73,Hoja2!$A$2:$A$53) ) ) -> 0 | Q73: 19/11/2025 Posible mejora detectada por Imagine -Jennifer | R73: False
A74: JENNIFER | C74: Afiliaciones Pre - Llegan casos con imágenes repetidas en el xml, generando imágenes incompletas en el proceso | D74: Opción para eliminar imágenes duplicadas dentro de la ya actual de reproceso de Afiliaciones Pre | F74: PENDIENTE | G74: 0 | H74: =IF(OR(J74="",K74="",K74<J74),0,NETWORKDAYS(J74,K74,Hoja2!$A$2:$A$53)) -> 0 | M74: =IF(OR(J74="",AND(L74="",TODAY()<J74),AND(L74<>"",L74<J74)),0, IF(L74="", NETWORKDAYS(J74,TODAY(),Hoja2!$A$2:$A$53), NETWORKDAYS(J74,L74,Hoja2!$A$2:$A$53) ) ) -> 0 | R74: False
C75: Afiliaciones POS - Consumo Puntual de las afiliaciones | F75: PENDIENTE | G75: 0 | H75: =IF(OR(J75="",K75="",K75<J75),0,NETWORKDAYS(J75,K75,Hoja2!$A$2:$A$53)) -> 0 | M75: =IF(OR(J75="",AND(L75="",TODAY()<J75),AND(L75<>"",L75<J75)),0, IF(L75="", NETWORKDAYS(J75,TODAY(),Hoja2!$A$2:$A$53), NETWORKDAYS(J75,L75,Hoja2!$A$2:$A$53) ) ) -> 0 | R75: False
C76: Acreditación - Validación de casos para saber su ultima acreditacion Desarrollo | F76: PENDIENTE | G76: 0 | H76: =IF(OR(J76="",K76="",K76<J76),0,NETWORKDAYS(J76,K76,Hoja2!$A$2:$A$53)) -> 0 | M76: =IF(OR(J76="",AND(L76="",TODAY()<J76),AND(L76<>"",L76<J76)),0, IF(L76="", NETWORKDAYS(J76,TODAY(),Hoja2!$A$2:$A$53), NETWORKDAYS(J76,L76,Hoja2!$A$2:$A$53) ) ) -> 0 | Q76: 19/11/2025 Posible mejora detectada por Imagine -Jennifer | R76: False
C77: Afiliaciones Pre - Llegan casos con imágenes repetidas en el xml, generando imágenes incompletas en el proceso | D77: Opción para eliminar imágenes duplicadas dentro de la ya actual de reproceso de Afiliaciones Pre | F77: PENDIENTE | G77: 0 | H77: =IF(OR(J77="",K77="",K77<J77),0,NETWORKDAYS(J77,K77,Hoja2!$A$2:$A$53)) -> 0 | M77: =IF(OR(J77="",AND(L77="",TODAY()<J77),AND(L77<>"",L77<J77)),0, IF(L77="", NETWORKDAYS(J77,TODAY(),Hoja2!$A$2:$A$53), NETWORKDAYS(J77,L77,Hoja2!$A$2:$A$53) ) ) -> 0 | R77: False
C78: Afiliaciones POS - Consumo Puntual de las afiliaciones | F78: PENDIENTE | G78: 0 | H78: =IF(OR(J78="",K78="",K78<J78),0,NETWORKDAYS(J78,K78,Hoja2!$A$2:$A$53)) -> 0 | M78: =IF(OR(J78="",AND(L78="",TODAY()<J78),AND(L78<>"",L78<J78)),0, IF(L78="", NETWORKDAYS(J78,TODAY(),Hoja2!$A$2:$A$53), NETWORKDAYS(J78,L78,Hoja2!$A$2:$A$53) ) ) -> 0 | Q78: 01/2026 Posible mejora detectada por Imagine -Jennifer | R78: False
A79: JENNIFER | C79: Convenios Medicos - Cargue Masivo de Planes a Nits | D79: Cargue de excel para relacionar de manera masiva los planes creados nuevos por Colmédica a los diferentes prestadores | F79: PENDIENTE | G79: 0 | H79: =IF(OR(J79="",K79="",K79<J79),0,NETWORKDAYS(J79,K79,Hoja2!$A$2:$A$53)) -> 0 | M79: =IF(OR(J79="",AND(L79="",TODAY()<J79),AND(L79<>"",L79<J79)),0, IF(L79="", NETWORKDAYS(J79,TODAY(),Hoja2!$A$2:$A$53), NETWORKDAYS(J79,L79,Hoja2!$A$2:$A$53) ) ) -> 0 | Q79: 01/2026 Posible mejora detectada por Imagine -Jennifer | R79: False
A80: JENNIFER | C80: Afiliaciones POS - Cargue de SAT | D80: Completar el proceso del cargue via web, el cliente ya carga el excel por el sitio web de imagine, Y se quiere migrar lo que hace el access que corresponde a la radicación y distribucion en las tablas definitas de encabezado y detalle | F80: PENDIENTE | G80: 0 | H80: =IF(OR(J80="",K80="",K80<J80),0,NETWORKDAYS(J80,K80,Hoja2!$A$2:$A$53)) -> 0 | M80: =IF(OR(J80="",AND(L80="",TODAY()<J80),AND(L80<>"",L80<J80)),0, IF(L80="", NETWORKDAYS(J80,TODAY(),Hoja2!$A$2:$A$53), NETWORKDAYS(J80,L80,Hoja2!$A$2:$A$53) ) ) -> 0 | R80: False

Sheet Hoja2
A1: 45292 | B1: Año Nuevo
A2: 45299 | B2: Día de los Reyes Magos
A3: 45376 | B3: Día de San José
A4: 45379 | B4: Jueves Santo (Semana Santa)
A5: 45380 | B5: Viernes Santo (Semana Santa)
A6: 45413 | B6: Día del Trabajo
A7: 45425 | B7: Día de la Ascensión
A8: 45446 | B8: Corpus Christi
A9: 45453 | B9: Sagrado Corazón
A10: 45474 | B10: San Pedro y San Pablo
A11: 45493 | B11: Día de la Independencia
A12: 45511 | B12: Batalla de Boyacá
... A53: 46381 | B53: Navidad

Sheet ASISTENCIA
A1: ASISTENCIA DAYLI
A3: INTEGRANTE | B3: 45596 | C3: 45597 | D3: 45601 | E3: 45602 | F3: 45603 | G3: 45604 | H3: 45608 | I3: 45609 | J3: 45610 | K3: 45611 | L3: 45614 | M3: 45615 | N3: 45616 | O3: 45617 | P3: 45618 | Q3: 45621 | R3: 45622 | S3: 45623 | T3: 45624 | U3: 45625 | V3: 45628 | W3: 45629 | X3: 45630 | Y3: 45631 | Z3: 45632 | AA3: 45635 | AB3: 45636 | AC3: 45637 | AD3: 45638 | AE3: 45639 | AF3: 45642 | AG3: 45643 | AH3: 45644 | AI3: 45645 | AJ3: 45646 | AK3: 45649 | AL3: 45650 | AM3: 45652 | AN3: 45653 | AO3: 45656 | AP3: 45656 | AQ3: 45664 | AR3: 45665 | AS3: 45666 | AT3: 45667 | AU3: 45670 | AV3: 45671 | AW3: 45672 | AX3: 45673 | AY3: 45674 | AZ3: 45677 | BA3: 45678 | BB3: 45679 | BC3: 45680 | BD3: 45681 | BE3: 45684 | BF3: 45685 | BG3: 45686 | BH3: 45687 | BI3: 45688 | BJ3: 45691 | BK3: 45692 | BL3: 45693 | BM3: 45694 | BN3: 45695 | BO3: 45698 | BP3: 45699 | BQ3: 45700 | BR3: 45701 | BS3: 45702 | BT3: 45705 | BU3: 45706 | BV3: 45707 | BW3: 45708 | BX3: 45709 | BY3: 45712 | BZ3: 45713 | CA3: 45714 | CB3: 45715 | CC3: 45716 | CD3: 45719 | CE3: 45720 | CF3: 45721 | CG3: 45722 | CH3: 45723 | CI3: 45726 | CJ3: 45727 | CK3: 45728 | CL3: 45729 | CM3: 45730 | CN3: 45733 | CO3: 45734 | CP3: 45735 | CQ3: 45736 | CR3: 45737 | CS3: 45741
A4: DANILO RAMIREZ | B4: SI | C4: no (Dia de la familia) | D4: SI | E4: SI | F4: SI | G4: SI | H4: SI | I4: SI | J4: SI | K4: SI | L4: SI | M4: SI | N4: SI | O4: No hubo sesion | P4: SI | Q4: SI | R4: SI | S4: SI | T4: SI | U4: NO | V4: SI | W4: SI | X4: SI | Y4: SI | Z4: SI | AA4: SI | AB4: SI | AC4: SI | AD4: SI | AE4: No hubo sesión | AF4: SI | AG4: SI | AH4: SI | AI4: SI | AJ4: SI | AK4: SI | AL4: NO HUBO SESION | AM4: NO | AN4: NO | AO4: SI | AP4: NO HAY SESION | AQ4: SI | AR4: SI | AS4: NO HAY SESION | AT4: SI | AU4: SI | AV4: SI | AW4: SI | AX4: SI | AY4: NO HAY SESION | AZ4: SI | BA4: SI | BB4: SI | BC4: SI | BD4: SI | BE4: SI | BF4: SI | BG4: SI | BH4: SI | BI4: SI | BJ4: NO HAY SESION | BK4: Vacaciones | BL4: Vacaciones | BM4: Vacaciones | BN4: Vacaciones | BO4: Vacaciones | BP4: Vacaciones | BQ4: Vacaciones | BR4: SI | BS4: SI | BT4: SI | BU4: SI | BV4: SI | BW4: SI | BX4: SI | BY4: SI | BZ4: SI | CA4: SI | CB4: SI | CC4: SI | CD4: SI | CE4: SI | CF4: SI | CI4: No hobo sesion por caida de los sitios. | CS4: SI
A5: JAIRO NIÑO | B5: SI | C5: SI | D5: SI | E5: SI | F5: SI | G5: SI | H5: SI | I5: SI | J5: SI | K5: SI | L5: Vacaciones | M5: Vacaciones | N5: Vacaciones | O5: Vacaciones | P5: Vacaciones | Q5: SI | R5: SI | S5: SI | T5: SI | U5: SI | V5: SI | W5: SI | X5: SI | Y5: SI | Z5: SI | AA5: SI | AB5: SI | AC5: SI | AD5: SI | AF5: SI | AG5: SI | AH5: SI | AI5: SI | AJ5: SI | AK5: SI | AM5: SI | AN5: SI | AO5: SI | AQ5: Vacaciones | AR5: Vacaciones | AT5: Vacaciones | AU5: Vacaciones | AV5: Vacaciones | AW5: Vacaciones | AX5: Vacaciones | AZ5: Vacaciones | BA5: SI | BB5: SI | BC5: SI | BD5: SI | BE5: SI | BF5: SI | BG5: SI | BH5: SI | BI5: SI | BK5: SI | BL5: SI | BM5: SI | BN5: SI | BO5: SI | BP5: SI | BQ5: SI | BR5: SI | BS5: SI | BT5: SI | BU5: SI | BV5: SI | BW5: SI | BX5: SI | BY5: SI | BZ5: SI | CA5: SI | CB5: SI | CC5: SI | CD5: SI | CE5: SI | CF5: SI | CS5: SI
A6: JESUS PEÑA | B6: SI | C6: SI | D6: SI | E6: SI | F6: SI | G6: SI | H6: SI | I6: SI | J6: SI | K6: Dia de la familia | L6: SI | M6: SI | N6: SI | O6: No hubo sesion | P6: SI | Q6: SI | R6: SI | S6: SI | T6: SI | U6: SI | V6: SI | W6: SI | X6: SI | Y6: SI | Z6: SI | AA6: SI | AB6: SI | AC6: SI | AD6: SI | AF6: SI | AG6: SI | AH6: SI | AI6: SI | AJ6: SI | AK6: SI | AM6: SI | AN6: SI | AO6: SI | AQ6: SI | AR6: SI | AT6: SI | AU6: SI | AV6: SI | AW6: SI | AX6: SI | AZ6: SI | BA6: SI | BB6: SI | BC6: SI | BD6: SI | BE6: SI | BF6: SI | BG6: SI | BH6: SI | BI6: SI | BK6: SI | BL6: SI | BM6: Falla electrica | BN6: SI | BO6: SI | BP6: SI | BQ6: SI | BR6: SI | BS6: SI | BT6: SI | BU6: SI | BV6: SI | BW6: SI | BX6: SI | BY6: SI | BZ6: SI | CA6: SI | CB6: SI | CC6: SI | CD6: SI | CE6: SI | CF6: SI | CS6: SI
A7: LUIS BEDOYA | B7: SI | C7: SI | D7: SI | E7: SI | F7: SI | G7: SI | H7: SI | I7: SI | J7: SI | K7: SI | L7: Dia de la familia | M7: SI | N7: SI | O7: No hubo sesion | P7: SI | Q7: SI | R7: SI | S7: SI | T7: SI | U7: SIN INTERNET | V7: SI | W7: SI | X7: SI | Y7: SI | Z7: NO | AA7: SI | AB7: SI | AC7: SI | AD7: SI | AF7: SI | AG7: SI | AH7: SI | AI7: SI | AJ7: SI | AK7: SI | AM7: SI | AN7: SI | AO7: SI | AQ7: SI | AR7: SI | AT7: SI | AU7: NO | AV7: SI | AW7: SI | AX7: SI | AZ7: SI | BA7: SI | BB7: SI | BC7: SI | BD7: SI | BE7: SI | BF7: SI | BG7: SI | BH7: SI | BI7: SI | BK7: SI | BL7: SI | BM7: SI | BN7: SI | BO7: NO | BU7: SI | BV7: SI | BW7: SI | BX7: SI
A8: JOHAN QUICENO | B8: SI | C8: SI | D8: SI | E8: SI | F8: SI | G8: SI | H8: SI | I8: SI | J8: SI | K8: SI | L8: NO | M8: SI | N8: SI | O8: No hubo sesion | P8: SI | Q8: SI | R8: SI | S8: SI | T8: SI | U8: SI | V8: SI | W8: Permiso | X8: SI | Y8: SI | Z8: SI | AA8: SI | AB8: NO | AC8: SI | AD8: SI | AF8: SI | AG8: SI | AH8: SI | AI8: SI | AJ8: SI | AK8: SI | AM8: SI | AN8: NO | AO8: SI | AQ8: SI | AR8: SI | AT8: SI | AU8: SI | AV8: SI | AW8: SI | AX8: SI | AZ8: SI | BA8: SI | BB8: SI | BC8: SI | BD8: SI | BE8: SI | BF8: SI | BG8: sin internet | BH8: SI | BI8: SI | BK8: SI | BL8: SI | BM8: SI | BN8: SI | BO8: SI | BP8: SI | BQ8: SI | BR8: SI | BS8: SI | BT8: SI | BU8: SI | BV8: SI | BW8: SI | BX8: TRABAJO HASTA HOY
A9: FABIO FORERO | B9: SI | C9: SI | D9: SI | E9: SI | F9: SI | G9: SI | H9: SI | I9: SI | J9: SI | K9: SI | L9: SI | M9: SI | N9: SI | O9: Dia de la familia | P9: SI | Q9: SI | R9: SI | S9: SI | T9: SI | U9: SI | V9: SI | W9: SI | X9: SI | Y9: SI | Z9: SI | AA9: SI | AB9: SI | AC9: SI | AD9: SI | AF9: SI | AG9: SI | AH9: SI | AI9: SI | AJ9: SI | AK9: SI | AM9: SI | AN9: SI | AO9: SI | AQ9: SI | AR9: SI | AT9: SI | AU9: SI | AV9: SI | AW9: SI | AX9: SI | AZ9: SI | BA9: SI | BB9: SI | BC9: SI | BD9: SI | BE9: SI | BF9: SI | BG9: SI | BH9: SI | BI9: SI | BK9: SI | BL9: SI | BM9: SI | BN9: SI | BO9: SI | BP9: SI | BQ9: SI | BR9: SI | BS9: SI | BT9: SI | BU9: SI | BV9: SI | BW9: SI | BX9: SI | BY9: SI | BZ9: SI | CA9: SI | CB9: SI | CC9: SI | CD9: SI | CE9: SI | CF9: SI | CS9: SI
A10: JENRY HENAO | B10: SI | C10: SI | D10: SI | E10: SI | F10: SI | G10: SI | H10: SI | I10: NO | J10: SI | K10: NO | L10: SI | M10: SI | N10: NO | O10: No hubo sesion | P10: NO | Q10: NO | R10: SI | S10: SI | T10: SI | U10: NO | V10: SI | W10: SI | X10: SI | Y10: SI | Z10: SI | AA10: SI | AB10: SI | AC10: SI | AD10: SI | AF10: SI | AG10: SI | AH10: SI | AI10: SI | AJ10: SI | AK10: NO | AM10: NO | AN10: SI | AO10: SI | AQ10: SI | AR10: SI | AT10: SI | AU10: SI | AV10: SI | AW10: SI | AX10: SI | AZ10: SI | BA10: NO | BB10: NO | BC10: NO | BD10: NO | BE10: NO | BF10: SI | BG10: SI | BH10: SI | BI10: SI | BK10: SI | BL10: SI | BM10: SI | BN10: SI | BO10: SI | BP10: SI | BQ10: SI | BR10: SI | BS10: SI | BT10: SI | BU10: SI | BV10: SI | BW10: NO | BX10: SI | BY10: SI | BZ10: SI | CA10: SI | CB10: SI | CC10: SI | CD10: SI | CE10: SI | CF10: SI | CS10: SI
A11: LIYIBET PEREZ | B11: SI | C11: SI | D11: SI | E11: SI | F11: SI | G11: SI | H11: SI | I11: SI | J11: nomina | K11: NO | L11: SI | M11: NO | N11: SI | O11: No hubo sesion | P11: SI | Q11: SI | R11: SI | S11: NO | T11: NO | U11: NO | V11: SI | W11: SI | X11: SI | Y11: SI | Z11: SI | AA11: SI | AB11: SI | AC11: SI | AD11: NO | AF11: SI | AG11: SI | AH11: SI | AI11: SI | AJ11: SI | AK11: SI | AM11: SI | AN11: SI | AO11: SI | AQ11: SI | AR11: SI | AT11: SI | AU11: NO | AV11: NO | AW11: SI | AX11: SI | AZ11: NO | BA11: SI | BB11: SI | BC11: SI | BD11: SI | BE11: NO | BF11: NO | BG11: NO | BH11: SI | BI11: SI | BK11: SI | BL11: SI | BM11: SI | BN11: SI | BO11: NO | BP11: SI | BQ11: SI | BR11: NOMINA | BS11: SI | BT11: SI | BU11: SI | BV11: SI | BW11: SI | BX11: SI | BY11: SI | BZ11: SI | CA11: SI | CB11: NO | CC11: NO | CD11: SI | CE11: SI | CF11: SI | CS11: SI
A12: WILSON APONTE | B12: SI | C12: NO | D12: SI | E12: SI | F12: NO | G12: NO | H12: SI | I12: NO | J12: SI | K12: NO | L12: SI | M12: NO | N12: NO | O12: No hubo sesion | P12: SI | Q12: NO | R12: NO | S12: NO | T12: NO | U12: NO | V12: NO | W12: SI | X12: NO | Y12: NO | Z12: SI | AA12: NO | AB12: NO | AC12: SI | AD12: NO | AF12: NO | AG12: NO | AH12: NO | AI12: NO | AJ12: SI | AK12: SI | AM12: NO | AN12: NO | AO12: NO | AQ12: NO | AR12: NO | AT12: NO | AU12: NO | AV12: SI | AW12: SI | AX12: NO | AZ12: NO | BA12: NO | BB12: NO | BC12: SI | BD12: NO | BE12: SI | BF12: NO | BG12: NO | BH12: SI | BI12: NO | BK12: NO | BL12: NO | BM12: SI | BN12: NO | BO12: NO | BP12: NO | BQ12: NO | BR12: SI | BS12: NO | BT12: NO | BU12: SI | BV12: SI | BW12: NO | BX12: NO | BY12: SI | BZ12: NO | CA12: NO | CB12: SI | CC12: NO | CD12: NO | CE12: SI | CF12: NO | CS12: NO
A13: JOHN ROLON | B13: SI | C13: NO | D13: NO | E13: NO | F13: NO | G13: NO | H13: NO | I13: NO | J13: SI | K13: NO | L13: NO | M13: SI | N13: NO | O13: No hubo sesion | P13: NO | Q13: NO | R13: NO | S13: NO | T13: NO | U13: NO | V13: SI | W13: NO | X13: NO | Y13: NO | Z13: NO | AA13: NO | AB13: NO | AC13: SI | AD13: NO | AF13: NO | AG13: NO | AH13: NO | AI13: SI | AJ13: NO | AK13: NO | AM13: NO | AN13: NO | AO13: NO | AQ13: NO | AR13: NO | AT13: NO | AU13: NO | AV13: NO | AW13: NO | AX13: NO | AZ13: NO | BA13: NO | BB13: NO | BC13: NO | BD13: NO | BE13: NO | BF13: NO | BG13: NO | BH13: NO | BI13: NO | BK13: NO | BL13: NO | BM13: NO | BN13: NO | BO13: NO | BP13: NO | BQ13: NO | BR13: NOMINA | BS13: NO | BT13: NO | BU13: NO | BV13: NO | BW13: NO | BX13: NO | BY13: NO | BZ13: NO | CA13: NO | CB13: NO | CC13: NO | CD13: SI | CE13: SI | CF13: SI | CS13: NO

Sheet pruebas i
A1: Asignado | B1: Requerimiento | C1: Actividad | D1: ESTADO | E1: F.Asignado | F1: Fecha inicio | G1: F. estimada de entrega | H1: Finalizado | I1: Dias | J1: TEST | K1: PRODUCCION | L1: Observacion
A2: LUIS BAYONA | B2: Encolar informe de efectividad de salud | D2: FINALIZADO | E2: 45567 | F2: 45567 | G2: 45568 | H2: 45569 | I2: =IF(ISBLANK(H2), NETWORKDAYS(F2, TODAY(),Hoja2!$A$1:$A$18), NETWORKDAYS(F2, H2, Hoja2!$A$1:$A$18)) -> 3 | J2: 45572 | L2: *02/10/2024 inicia gestion. *03/10/2024 Finalizar la consulta y realizar pruebas * 07/10/2024 desarrollo en test para pruebas
A3: FABIO FORERO | B3: VULNERABILIDADES BAJAS | C3: Web Server Allows Password Auto-Completion | D3: PENDIENTE | E3: 45575 | H3: 0 | I3: =IF(ISBLANK(H3), NETWORKDAYS(F3, TODAY(),Hoja2!$A$1:$A$18), NETWORKDAYS(F3, H3, Hoja2!$A$1:$A$18)) -> 0 | J3: 45569 | L3: *04/10/2024 pruebas * 07/10/2024 se entrega a Danilo para pruebas y posterior despliegue a producción * 09/10/2024 Confirmar entrega de rama a Danilo * 10/10/2024 Etregadas a Danilo 9 de octubre,
A4: FABIO FORERO | C4: Autocomplete Enabled (15 Y 18) | D4: PENDIENTE | E4: 45575 | H4: 0 | I4: =IF(ISBLANK(H4), NETWORKDAYS(F4, TODAY(),Hoja2!$A$1:$A$18), NETWORKDAYS(F4, H4, Hoja2!$A$1:$A$18)) -> 0 | J4: 45569 | L4: *04/10/2024 pruebas * 07/10/2024 se entrega a Danilo para pruebas y posterior despliegue a producción * 09/10/2024 Confirmar entrega de rama a Danilo * 10/10/2024 Etregadas a Danilo 9 de octubre
A5: FABIO FORERO | B5: VULNERABILIDADES MEDIAS | C5: Internal Server Error | D5: PENDIENTE | E5: 45575 | H5: 0 | I5: =IF(ISBLANK(H5), NETWORKDAYS(F5, TODAY(),Hoja2!$A$1:$A$18), NETWORKDAYS(F5, H5, Hoja2!$A$1:$A$18)) -> 0 | J5: 45569 | L5: *04/10/2024 pruebas * 07/10/2024 se entrega a Danilo para pruebas y posterior despliegue a producción * 09/10/2024 Confirmar entrega de rama a Danilo * 10/10/2024 Etregadas a Danilo 9 de octubre
