Workbook

Sheet EN PROCESO (Proteccíon)
A1: Asignado a | B1: ID REQ | C1: Requerimiento | D1: Descripcion req | E1: Actividad | F1: ESTADO | G1: % AVANCE | H1: Dias estimados de desarrollo | I1: F.Asignado | J1: Fecha inicio | K1: F. estimada de entrega | L1: Finalizado | M1: Dias total desarrollo | N1: Fecha compromiso cliente | O1: FECHA PASO A TEST | P1: FECHA PASO A PRODUCCION | Q1: OBSERVACIONES | R1: Visible
A2: Alejandro | B2: REQ-1-1 | C2: Tratamiento especial al radicar trámites de vejez (Revision de flujo y código) | D2: Se está a la espera de la solicitud formal por parte del cliente | F2: FINALIZADO | G2: 100 | H2: =IF(OR(J2="",K2="",K2<J2),0,NETWORKDAYS(J2,K2,Hoja2!$A$2:$A$53)) -> 1 | I2: 45826 | J2: 45827 | K2: 45827 | L2: 45827 | M2: =IF(OR(J2="",AND(L2="",TODAY()<J2),AND(L2<>"",L2<J2)),0, IF(L2="", NETWORKDAYS(J2,TODAY(),Hoja2!$A$2:$A$53), NETWORKDAYS(J2,L2,Hoja2!$A$2:$A$53) ) ) -> 1 | Q2: 19/06/2025 Se identifico el código a intervenir y con el que trabajar en el requerimiento | R2: true
A3: Alejandro | B3: REQ-1-2 | C3: Tratamiento especial al radicar trámites de vejez (Reunión con las partes interesadas para identificar los inputs de trabajo) | D3: Se está a la espera de la solicitud formal por parte del cliente | F3: FINALIZADO | G3: 100 | H3: =IF(OR(J3="",K3="",K3<J3),0,NETWORKDAYS(J3,K3,Hoja2!$A$2:$A$53)) -> 1 | I3: 45827 | J3: 45832 | K3: 45832 | L3: 45832 | M3: =IF(OR(J3="",AND(L3="",TODAY()<J3),AND(L3<>"",L3<J3)),0, IF(L3="", NETWORKDAYS(J3,TODAY(),Hoja2!$A$2:$A$53), NETWORKDAYS(J3,L3,Hoja2!$A$2:$A$53) ) ) -> 1 | Q3: 24/06/2025: Se reune con las partes interesadas, se identifican los requisitos, necesidades y material de trabajo, pero se suspende el requerimiento hasta nuevo aviso | R3: true
A4: Alejandro | B4: REQ-2-1 | C4: Creación de reporte de AUF para identificación de pagos, creación de opción de cargue masivo para cambio de bandejas y creación de opción de consulta de pagos (Creación de script para generar reporte de pagos de auxilios funerarios y la vista para su consumo) | D4: Creación de Herramientas adicionales para el tratamiento de información y flujo en el módulo de auxilios funerarios | F4: FINALIZADO | G4: 100 | H4: =IF(OR(J4="",K4="",K4<J4),0,NETWORKDAYS(J4,K4,Hoja2!$A$2:$A$53)) -> 0 | I4: 45832 | J4: 45839 | K4: 45833 | L4: 45839 | M4: =IF(OR(J4="",AND(L4="",TODAY()<J4),AND(L4<>"",L4<J4)),0, IF(L4="", NETWORKDAYS(J4,TODAY(),Hoja2!$A$2:$A$53), NETWORKDAYS(J4,L4,Hoja2!$A$2:$A$53) ) ) -> 1 | O4: 45839 | P4: 45853 | Q4: 24/06/2025: Se realiza reunión para la identificación de nuevos requisitos 01/07/2025: Se realiza vista para el consumo y parte de la lóigica para la creación del reporte 01/07/2025: Se está a la espera de validar la información del reporte debido a que se nos envía 2 reportes con estructuras distintas 09/07/2025: Se realiza reunión con las partes interesadas y se acuerda en agregar información obtenida de distintas fuentes al formulario 15/07/2025: Se realizaron aún más cambios propuestos por el usuario y correcciones de fallas en el funcionamiento 15/07/2025: Se pasa a producción | R4: true
A5: Alejandro | B5: REQ-2-2 | C5: Creación de reporte de AUF para identificación de pagos, creación de opción de cargue masivo para cambio de bandejas y creación de opción de consulta de pagos (Creación de script para generar opción de consulta de pagos) | D5: Creación de Herramientas adicionales para el tratamiento de información y flujo en el módulo de auxilios funerarios | F5: FINALIZADO | G5: 100 | H5: =IF(OR(J5="",K5="",K5<J5),0,NETWORKDAYS(J5,K5,Hoja2!$A$2:$A$53)) -> 2 | I5: 45839 | J5: 45839 | K5: 45840 | L5: 45848 | M5: =IF(OR(J5="",AND(L5="",TODAY()<J5),AND(L5<>"",L5<J5)),0, IF(L5="", NETWORKDAYS(J5,TODAY(),Hoja2!$A$2:$A$53), NETWORKDAYS(J5,L5,Hoja2!$A$2:$A$53) ) ) -> 8 | O5: 45848 | P5: 45853 | Q5: 09/07/2025: Se Había pospuesto la creación del código y se retoma el día 8 10/07/2025: Se termina el desarrollo y las pruebas e 10 con las modificaciones indicadas en la reunión 15/07/2025: Se realizaron aún más cambios propuestos por el usuario y correcciones de fallas en el funcionamiento 15/07/2025: Se pasa a producción | R5: true
A6: Alejandro | B6: REQ-2-3 | C6: Creación de reporte de AUF para identificación de pagos, creación de opción de cargue masivo para cambio de bandejas y creación de opción de consulta de pagos (Creación de script para generar opción en el de cargue y procesado de datos ) | D6: Creación de Herramientas adicionales para el tratamiento de información y flujo en el módulo de auxilios funerarios | F6: FINALIZADO | G6: 100 | H6: =IF(OR(J6="",K6="",K6<J6),0,NETWORKDAYS(J6,K6,Hoja2!$A$2:$A$53)) -> 1 | I6: 45839 | J6: 45840 | K6: 45840 | L6: 45840 | M6: =IF(OR(J6="",AND(L6="",TODAY()<J6),AND(L6<>"",L6<J6)),0, IF(L6="", NETWORKDAYS(J6,TODAY(),Hoja2!$A$2:$A$53), NETWORKDAYS(J6,L6,Hoja2!$A$2:$A$53) ) ) -> 1 | O6: 45840 | P6: 45853 | Q6: 01/07/2025: Se realiza reunión para la identificación de nuevos requisitos 02/07/2025: Se Crea vista y lógica para el cargue de documentos y procesamiento de datos 02/07/2025: Se realizan pruebas de funcionamiento y se esta a la espera de que el cliente realice pruebas 15/07/2025: Se realizaron aún más cambios propuestos por el usuario y correcciones de fallas en el funcionamiento 15/07/2025: Se pasa a producción | R6: true
A7: Alejandro | B7: REQ-2-4 | C7: Creación de reporte de AUF para identificación de pagos, creación de opción de cargue masivo para cambio de bandejas y creación de opción de consulta de pagos (Modificación de script para generar reporte de pagos de auxilios funerarios agregando distinta información y lógica para su construcción) | D7: Creación de Herramientas adicionales para el tratamiento de información y flujo en el módulo de auxilios funerarios | F7: FINALIZADO | G7: 100 | H7: =IF(OR(J7="",K7="",K7<J7),0,NETWORKDAYS(J7,K7,Hoja2!$A$2:$A$53)) -> 2 | I7: 45847 | J7: 45847 | K7: 45848 | L7: 45848 | M7: =IF(OR(J7="",AND(L7="",TODAY()<J7),AND(L7<>"",L7<J7)),0, IF(L7="", NETWORKDAYS(J7,TODAY(),Hoja2!$A$2:$A$53), NETWORKDAYS(J7,L7,Hoja2!$A$2:$A$53) ) ) -> 2 | O7: 45848 | P7: 45853 | Q7: 10/07/2025: Se termina el desarrollo y las pruebas. Se está en espera del visto bueno para pasar a producción 14/07/2025: Se identifican a través de las pruebas de usuarios modificaciones y añadidos por hacer. Se realizan los debidos cambios y se entrega al cliente resultados para su validación 15/07/2025: Se realizaron aún más cambios propuestos por el usuario y correcciones de fallas en el funcionamiento 15/07/2025: Se pasa a producción | R7: true
A8: Alejandro | B8: REQ-3-1 | C8: Cambios técnicos en aplicativo imagine para proceso de mesa de control documental solicitud de pensión (Reunión con las partes interesadas para identificación de requerimientos) | D8: desarrollo de la mesa de validación documental con inteligencia artificial en Filenet que implica las siguientees actividades: Se debe retirar la bandeja de imagine Validación Mesa de Control Unificada ya que la validación de documentos se realizará a través de filenet. Dado que se requiere conservar otras funciones adicionales a la bandeja de validación en el software de imagine que depende de la validación documental, se les notificara a través del siguiente web service cada vez que una solicitud documental (Paquete de documentos relacionado a los diferentes riesgos) haya finalizado el proceso de validación: | F8: FINALIZADO | G8: 100 | H8: =IF(OR(J8="",K8="",K8<J8),0,NETWORKDAYS(J8,K8,Hoja2!$A$2:$A$53)) -> 1 | I8: 45832 | J8: 45832 | K8: 45832 | L8: 45832 | M8: =IF(OR(J8="",AND(L8="",TODAY()<J8),AND(L8<>"",L8<J8)),0, IF(L8="", NETWORKDAYS(J8,TODAY(),Hoja2!$A$2:$A$53), NETWORKDAYS(J8,L8,Hoja2!$A$2:$A$53) ) ) -> 1 | Q8: 24/06/2025: Se realiza reunión para realización de pruebas e identificación de requerimientos | R8: true
A9: Alejandro | B9: REQ-4-1 | C9: Migración de registros para tipos documentales gabinete 2 (Identificación y failitación al cliente de los tipos documnetales) | F9: FINALIZADO | G9: 100 | H9: =IF(OR(J9="",K9="",K9<J9),0,NETWORKDAYS(J9,K9,Hoja2!$A$2:$A$53)) -> 1 | I9: 45847 | J9: 45847 | K9: 45847 | L9: 45847 | M9: =IF(OR(J9="",AND(L9="",TODAY()<J9),AND(L9<>"",L9<J9)),0, IF(L9="", NETWORKDAYS(J9,TODAY(),Hoja2!$A$2:$A$53), NETWORKDAYS(J9,L9,Hoja2!$A$2:$A$53) ) ) -> 1 | O9: 45847 | Q9: 09/07/2025: Se indica al cliente los distintos tipos de documentación del gabinete 2 | R9: true
A10: Alejandro | B10: REQ-5-1 | C10: Proyecto relacionado con las inconsistencias norma 2381 (Identificación de método de consumo y generación de informe de resultados) | F10: FINALIZADO | G10: 100 | H10: =IF(OR(J10="",K10="",K10<J10),0,NETWORKDAYS(J10,K10,Hoja2!$A$2:$A$53)) -> 1 | I10: 45849 | J10: 45849 | K10: 45849 | L10: 45849 | M10: =IF(OR(J10="",AND(L10="",TODAY()<J10),AND(L10<>"",L10<J10)),0, IF(L10="", NETWORKDAYS(J10,TODAY(),Hoja2!$A$2:$A$53), NETWORKDAYS(J10,L10,Hoja2!$A$2:$A$53) ) ) -> 1 | Q10: 09/07/2025: Se identifica los métodos de consumo posibles, su funcionamiento y se plasma junto con las respuestas a las dudas del cliente en un informe | R10: true
A11: Alejandro | B11: REQ-3-3 | C11: Cambios técnicos en aplicativo imagine para proceso de mesa de control documental solicitud de pensión (Creación de otro método para consumo necesario para tratamiento de trámites de pruebas de protección) | D11: desarrollo de la mesa de validación documental con inteligencia artificial en Filenet que implica las siguientees actividades: Se debe retirar la bandeja de imagine Validación Mesa de Control Unificada ya que la validación de documentos se realizará a través de filenet. Dado que se requiere conservar otras funciones adicionales a la bandeja de validación en el software de imagine que depende de la validación documental, se les notificara a través del siguiente web service cada vez que una solicitud documental (Paquete de documentos relacionado a los diferentes riesgos) haya finalizado el proceso de validación: | F11: FINALIZADO | G11: 100 | H11: =IF(OR(J11="",K11="",K11<J11),0,NETWORKDAYS(J11,K11,Hoja2!$A$2:$A$53)) -> 1 | I11: 45854 | J11: 45854 | K11: 45854 | L11: 45854 | M11: =IF(OR(J11="",AND(L11="",TODAY()<J11),AND(L11<>"",L11<J11)),0, IF(L11="", NETWORKDAYS(J11,TODAY(),Hoja2!$A$2:$A$53), NETWORKDAYS(J11,L11,Hoja2!$A$2:$A$53) ) ) -> 1 | O11: 45854 | Q11: 16/07/2025 Se realiza nuevo método de consumo para cerrar trámites con procesos documentales abiertos y asi, protección pueda ser pruebas de cierre de mesa unificada documental sin necesidad de tener procesos abiertos y con documentos | R11: true
A12: Alejandro | B12: REQ-6-1 | C12: Análisis y corrección de procesos de cargue e identificación de pagos de tipo de riesgo AUX (Análisis de la situación en Imagine) | D12: Se identificaron errores de procesos de cargue que no están identificando correctamente el estado de un trámite en la bandeja de AUX. | F12: FINALIZADO | G12: 100 | H12: =IF(OR(J12="",K12="",K12<J12),0,NETWORKDAYS(J12,K12,Hoja2!$A$2:$A$53)) -> 5 | I12: 45855 | J12: 45856 | K12: 45862 | L12: 45861 | M12: =IF(OR(J12="",AND(L12="",TODAY()<J12),AND(L12<>"",L12<J12)),0, IF(L12="", NETWORKDAYS(J12,TODAY(),Hoja2!$A$2:$A$53), NETWORKDAYS(J12,L12,Hoja2!$A$2:$A$53) ) ) -> 4 | O12: 45861 | Q12: 17/07/2025 Se realiza reunión para identificar las inconsistencias. Se está a la espera de datos de prueba y de análisis de los procesos para la verificación de los mismos 21/07/2025 Se Identificaron lógicas erroneas en el código que se corrigieron y otras lógicas de negocio que no, debido a que primero se deben de socializar los resultados antes de poder pensar en una solución 23/07/2025 Se genera informe de la situación, recomendaciones y procesos a seguir para brindar solución 23/07/2025 Se pasa los cambios que corregian errores a producción | R12: true
A13: Alejandro | B13: REQ-7-1 | C13: Mejoras en los modulos de Imagine (Reunión con las partes interesadas e identificación de requerimientos) | D13: Solicitud de protección para mejoras IMAGINE en el módulo de Auxilios funerarios | F13: FINALIZADO | G13: 100 | H13: =IF(OR(J13="",K13="",K13<J13),0,NETWORKDAYS(J13,K13,Hoja2!$A$2:$A$53)) -> 1 | I13: 45860 | J13: 45860 | K13: 45860 | L13: 45860 | M13: =IF(OR(J13="",AND(L13="",TODAY()<J13),AND(L13<>"",L13<J13)),0, IF(L13="", NETWORKDAYS(J13,TODAY(),Hoja2!$A$2:$A$53), NETWORKDAYS(J13,L13,Hoja2!$A$2:$A$53) ) ) -> 1 | Q13: 22/07/2025 Se realiza reunión para la identificación de requerimientos y necesidades del cliente 23/07/2025 Se comparte archivo de la solicitud | R13: true
A14: Alejandro | B14: Interno-H8 | C14: Automatización y migración de lógica a python ( Ejecuci[on y correcci[on de script y descarga de recursos necesarios para el entrenamiento del modelo de clasificaci[on) | F14: FINALIZADO | G14: 100 | H14: =IF(OR(J14="",K14="",K14<J14),0,NETWORKDAYS(J14,K14,Hoja2!$A$2:$A$53)) -> 2 | I14: 45863 | J14: 45863 | K14: 45866 | L14: 45866 | M14: =IF(OR(J14="",AND(L14="",TODAY()<J14),AND(L14<>"",L14<J14)),0, IF(L14="", NETWORKDAYS(J14,TODAY(),Hoja2!$A$2:$A$53), NETWORKDAYS(J14,L14,Hoja2!$A$2:$A$53) ) ) -> 2 | Q14: 25/07/2025 Se realiza la descarga de 80000 archivos no sin antes reestructurar el script y acoplarlo para no sobrecargar los procesos y que funcionara 25/07/2025 Se empieza proceso de carga en local, todo esto debido a que no se puede generar el modelo de entrenamiento en el servidor por capacidad 25/07/2025 Se termina el proceso de carga en local | R14: true
A15: Alejandro | B15: Interno-H1 | C15: Automatización y migración de lógica a python (Migración de código en donde se importa el lote tanto física como en bases de datos) | F15: FINALIZADO | G15: 100 | H15: =IF(OR(J15="",K15="",K15<J15),0,NETWORKDAYS(J15,K15,Hoja2!$A$2:$A$53)) -> 2 | I15: 45824 | J15: 45825 | K15: 45826 | L15: 45827 | M15: =IF(OR(J15="",AND(L15="",TODAY()<J15),AND(L15<>"",L15<J15)),0, IF(L15="", NETWORKDAYS(J15,TODAY(),Hoja2!$A$2:$A$53), NETWORKDAYS(J15,L15,Hoja2!$A$2:$A$53) ) ) -> 3 | O15: 45826 | Q15: 19/06/2025 Se produjeron ciertos errores en la fase de pruebas y se realizaron todas las correcciones para que el nuevo funcionamiento responda y se acople bien | R15: true
A16: Alejandro | B16: Interno-H2 | C16: Automatización y migración de lógica a python (Migración de código en donde se trata toda la lógica y activación de tareas de la indexación del lote) | F16: FINALIZADO | G16: 100 | H16: =IF(OR(J16="",K16="",K16<J16),0,NETWORKDAYS(J16,K16,Hoja2!$A$2:$A$53)) -> 2 | I16: 45826 | J16: 45828 | K16: 45832 | L16: 45833 | M16: =IF(OR(J16="",AND(L16="",TODAY()<J16),AND(L16<>"",L16<J16)),0, IF(L16="", NETWORKDAYS(J16,TODAY(),Hoja2!$A$2:$A$53), NETWORKDAYS(J16,L16,Hoja2!$A$2:$A$53) ) ) -> 3 | O16: 45833 | Q16: 20/06/2025: Identificación y paso del flujo para la funcionalidad de indexación de lotes de PHP a python 24/06/2025: Se tiene identificado el código necesario para la migración y se avanza en ella. Se han tenido muchos requerimientos adicionales actualmente por lo que se retrasa un poco en su construcción 25/06/2025: Se termina la migracion a python para el flujo de la funcionalidad de indexar lote y se realizaron pruebas de funcionalidad | R16: true
A17: Alejandro | B17: Interno-H3 | C17: Automatización y migración de lógica a python (Acoplar lógica faltante en la migración de código) | F17: FINALIZADO | G17: 100 | H17: =IF(OR(J17="",K17="",K17<J17),0,NETWORKDAYS(J17,K17,Hoja2!$A$2:$A$53)) -> 0 | I17: 45826 | J17: 45869 | K17: 45834 | L17: 45870 | M17: =IF(OR(J17="",AND(L17="",TODAY()<J17),AND(L17<>"",L17<J17)),0, IF(L17="", NETWORKDAYS(J17,TODAY(),Hoja2!$A$2:$A$53), NETWORKDAYS(J17,L17,Hoja2!$A$2:$A$53) ) ) -> 2 | O17: 45870 | Q17: 31/07/2025 Se inicializa el trabajo de acoplamiento de la lógica del módulo con el proceso de clasificación después de tener un modelo entrenado para la tarea | R17: true
A18: Alejandro | B18: Interno-H4 | C18: Automatización y migración de lógica a python (Migración de código para la funcionalidad en donde se consume un web service para la asignación de casos a HRUA) | F18: FINALIZADO | G18: 100 | H18: =IF(OR(J18="",K18="",K18<J18),0,NETWORKDAYS(J18,K18,Hoja2!$A$2:$A$53)) -> 0 | I18: 45833 | J18: 45841 | K18: 45839 | L18: 45845 | M18: =IF(OR(J18="",AND(L18="",TODAY()<J18),AND(L18<>"",L18<J18)),0, IF(L18="", NETWORKDAYS(J18,TODAY(),Hoja2!$A$2:$A$53), NETWORKDAYS(J18,L18,Hoja2!$A$2:$A$53) ) ) -> 3 | O18: 45845 | Q18: 03/07/2025: Se construye los modelos relacionados, el agente y se le asigna el trabajo que corresponde a la funcionalidad en PHP, faltan migrar características y realizar modificaciones 07/07/2025: Se migra la lógica faltante y se realiza una prueba básica de flujo debido a que se conecta y consume un servicio web que en el ambiente local no se puede probar, por lo que esta a la espera de pasarlo al ambiente de QA(Pruebas) para probar definitivamente todas las características | R18: true
A19: Alejandro | B19: Interno-H5 | C19: Automatización y migración de lógica a python (Migración de lógica para el cruce de datos existentes ya en las distintas tablas de pre radicación) | F19: FINALIZADO | G19: 100 | H19: =IF(OR(J19="",K19="",K19<J19),0,NETWORKDAYS(J19,K19,Hoja2!$A$2:$A$53)) -> 1 | I19: 45845 | J19: 45845 | K19: 45845 | L19: 45845 | M19: =IF(OR(J19="",AND(L19="",TODAY()<J19),AND(L19<>"",L19<J19)),0, IF(L19="", NETWORKDAYS(J19,TODAY(),Hoja2!$A$2:$A$53), NETWORKDAYS(J19,L19,Hoja2!$A$2:$A$53) ) ) -> 1 | O19: 45845 | Q19: 07/07/2025: Se migra toda la lógica de la funcionalidad y se realizan pruebas | R19: true
A20: Alejandro | B20: Interno-H6 | C20: Automatización y migración de lógica a python | F20: FINALIZADO | G20: 100 | H20: =IF(OR(J20="",K20="",K20<J20),0,NETWORKDAYS(J20,K20,Hoja2!$A$2:$A$53)) -> 3 | I20: 45854 | J20: 45854 | K20: 45858 | M20: =IF(OR(J20="",AND(L20="",TODAY()<J20),AND(L20<>"",L20<J20)),0, IF(L20="", NETWORKDAYS(J20,TODAY(),Hoja2!$A$2:$A$53), NETWORKDAYS(J20,L20,Hoja2!$A$2:$A$53) ) ) -> 230 | Q20: 16/07/2025 Se identifican los docuemntos a clasificar. Se empieza con la actividad de elección y la forma en que se le dará tratamiento a los documentos 17/07/2025 Se crean queries y scripts necesarios para la descarga y conversión a pdf desde el repositorio S3 de los archivos necesarios para el entrenamiento del modelo | R20: true
A21: Alejandro | B21: REQ-1-3 | C21: Tratamiento especial al radicar trámites de vejez (Fase de desarrollo para la creacion de código para la implementación del requerimiento) | D21: Se está a la espera de la solicitud formal por parte del cliente | F21: CANCELADO | H21: =IF(OR(J21="",K21="",K21<J21),0,NETWORKDAYS(J21,K21,Hoja2!$A$2:$A$53)) -> 0 | M21: =IF(OR(J21="",AND(L21="",TODAY()<J21),AND(L21<>"",L21<J21)),0, IF(L21="", NETWORKDAYS(J21,TODAY(),Hoja2!$A$2:$A$53), NETWORKDAYS(J21,L21,Hoja2!$A$2:$A$53) ) ) -> 0 | Q21: 24/06/2025: El requerimiento esta en pauisa hasta que se identifique la viabilidad de la reforma pensional 06/03/2026 Hasta el momento no se ha obtenido respuesta del parte del cliente | R21: False
A22: Alejandro | B22: REQ-3-2 | C22: Cambios técnicos en aplicativo imagine para proceso de mesa de control documental solicitud de pensión (Creación de método para el cpnsumo como servicio e identificación de código a modificar y procesos que clausurar) | D22: desarrollo de la mesa de validación documental con inteligencia artificial en Filenet que implica las siguientees actividades: Se debe retirar la bandeja de imagine Validación Mesa de Control Unificada ya que la validación de documentos se realizará a través de filenet. Dado que se requiere conservar otras funciones adicionales a la bandeja de validación en el software de imagine que depende de la validación documental, se les notificara a través del siguiente web service cada vez que una solicitud documental (Paquete de documentos relacionado a los diferentes riesgos) haya finalizado el proceso de validación: | F22: FINALIZADO | G22: 100 | H22: =IF(OR(J22="",K22="",K22<J22),0,NETWORKDAYS(J22,K22,Hoja2!$A$2:$A$53)) -> 3 | I22: 45834 | J22: 45834 | K22: 45839 | L22: 45840 | M22: =IF(OR(J22="",AND(L22="",TODAY()<J22),AND(L22<>"",L22<J22)),0, IF(L22="", NETWORKDAYS(J22,TODAY(),Hoja2!$A$2:$A$53), NETWORKDAYS(J22,L22,Hoja2!$A$2:$A$53) ) ) -> 4 | O22: 45840 | Q22: 26/06/2025: Se construye nuevo método de consumo y la lógica para tratamiento de trámites para cerrar mesa unificada 26/06/2025: Se cierra bandeja de mesa unificada 26/06/2025: Se realizan preubas de consumo al nuevo método del servicio 02/07/2025: Se añade código para realizar tratamientos de envío de eventos de normalización si el trámite lo permite 02/07/2025: Se inicia la fase de pruebas con una aún no satisfactoria 03/07/2025: Se realiza correcciones en el flujo y se realiza prueba con resultado satisfactorio, Se está a la espera de realizar pruebas junto con el cliente 29/07/2025 El requerimiento había estado parado debido a la falta de pruebas por parte de protección. Se encuentra la neesidad de realizar ciertas modificaciones 30/07/2025 Se realizan las modificaciones identificadas yse informa nuevamente para la realización de pruebas 31/07/2025 Se crea y comparte documentación técnica del proceso 01/08/2025 Se realizan pruebas satisfactorias y se esta a la espera del cliente para pasar a producción | R22: true
A23: Alejandro | B23: REQ-4-2 | C23: Migracion de servidor y actualizaciones de tecnologías (Acompañamiento de pruebas y validaciones con el cliente) | D23: Migración de servicios y tecnologías para cumplir con requerimientos de seguridad y calidad | F23: FINALIZADO | G23: 100 | H23: =IF(OR(J23="",K23="",K23<J23),0,NETWORKDAYS(J23,K23,Hoja2!$A$2:$A$53)) -> 46 | I23: 45833 | J23: 45833 | K23: 45901 | L23: 45901 | M23: =IF(OR(J23="",AND(L23="",TODAY()<J23),AND(L23<>"",L23<J23)),0, IF(L23="", NETWORKDAYS(J23,TODAY(),Hoja2!$A$2:$A$53), NETWORKDAYS(J23,L23,Hoja2!$A$2:$A$53) ) ) -> 46 | O23: 45901 | Q23: 25/06/2025: Se realizan validaciones para pruebas de servicios generados desde protección 26/06/2025: Se realizan validaciones para pruebas de servicios generados desde protección 01/07/2025: Se realizan validaciones para pruebas de servicios generados desde protección 09/07/2025: Se realizan validaciones para pruebas de servicios generados desde protección 01/09/2025: Setermianron las pruebas por parte del cliente y se gestiona nueva tarea en el que IMAGINE es el encargado | R23: true
A24: Alejandro | B24: Interno-H7 | C24: Automatización y migración de lógica a python ( Creación de script para entrenamiento del modelo de clasificación) | F24: FINALIZADO | G24: 100 | H24: =IF(OR(J24="",K24="",K24<J24),0,NETWORKDAYS(J24,K24,Hoja2!$A$2:$A$53)) -> 5 | I24: 45855 | J24: 45855 | K24: 45861 | L24: 45870 | M24: =IF(OR(J24="",AND(L24="",TODAY()<J24),AND(L24<>"",L24<J24)),0, IF(L24="", NETWORKDAYS(J24,TODAY(),Hoja2!$A$2:$A$53), NETWORKDAYS(J24,L24,Hoja2!$A$2:$A$53) ) ) -> 12 | O24: 45870 | Q24: 17/07/2025 Se realiza reunión con Danilo para identificar enfoque de manejo de dependencias y entre otros temas 18/07/2025 Se construye con ayuda de la IA varios scripts que se usaran como modelo e inferencia del proyecto. No se han probado ni tampoco se han acoplado al sistema de agentes 28/07/2025 Se había detenido la actividad hasta tener todos los recursos al menos en el sistema local para trabajar el modelo de entrenamiento, en este caso faltaba los archivos 28/07/2025 Se realizan correcciones, pruebas y generación de los primeros 5 recorridos completos por todo el dataset de entrenamiento y se obtiene un modelo con 84% de fiabilidad. Cada recorrido tarda alrededor de 2 horas y genera un esfuerzo moderado al PC, por lo que las demás actividades se ven un poco afectadas, se espera conseguir un modelo de mas de 90% de fiabilidad y por lo que serán necesario más entrenamiento, análisis y recorridos por toda la data 29/07/2025 Se siguen ejecutando el entrenamiento para la búsqueda de un modelo más fiable 01/08/2025 Se modifica el script de entrenamiento añadiendo fine-tune y transformaciones con la esperanza de construír un modelo más fiable, pero después de 48 horas de entrenamiento, el modelo se estanca en validación y con los archivos actuales no puede aumentar su aprendizaje, esto es debido a que en algunos tipos documentales no existen suficientes muestras | R24: true
A25: Alejandro | B25: Interno-2-1 | C25: Requerimiento de infraestructura para habilitar monitoreo y encapsulamiento a través de contenedores de aplicaciones ( Informe de requerimientos al área encargada, instalación y prueba de funcionamiento de librerías de monitoreo y de contenedores) | D25: Instalación de dependencias, scripts y demas para dos procesos, uno de auditoria de accesos y otro de encapsulación de aplicaciones a través de contenedores docker | F25: FINALIZADO | G25: 100 | H25: =IF(OR(J25="",K25="",K25<J25),0,NETWORKDAYS(J25,K25,Hoja2!$A$2:$A$53)) -> 5 | I25: 45862 | J25: 45862 | K25: 45868 | L25: 45894 | M25: =IF(OR(J25="",AND(L25="",TODAY()<J25),AND(L25<>"",L25<J25)),0, IF(L25="", NETWORKDAYS(J25,TODAY(),Hoja2!$A$2:$A$53), NETWORKDAYS(J25,L25,Hoja2!$A$2:$A$53) ) ) -> 21 | O25: 45894 | P25: 45894 | Q25: 24/07/2025 Se genera informe para la instalación de dependencias al área encargada, incluyendo información técnica y necesidades en las siguientes solicitudes de protección: SR1267449 SR1267909 SR1267937 25/08/2025 Se habia detenido el proceso debido a la falta de instalación por parte del cliente de las librerias. Se trabajo en la configuración de los dos ambientes el 22 y 25 de agosto, día en el que se completo el requerimiento | R25: true
A26: Alejandro | B26: REQ-8-1 | C26: Definición y cambio de flujo en la activación agente - investigación (Análisis de requerimientos, código y modificación de módulo para cumplirnecesidades) | D26: Modificación del flujo, cargue y almacenamiento de datos de la fase de investigación. Además, de envió de esa información a filenet | F26: FINALIZADO | G26: 100 | H26: =IF(OR(J26="",K26="",K26<J26),0,NETWORKDAYS(J26,K26,Hoja2!$A$2:$A$53)) -> 4 | I26: 45868 | J26: 45868 | K26: 45873 | L26: 45870 | M26: =IF(OR(J26="",AND(L26="",TODAY()<J26),AND(L26<>"",L26<J26)),0, IF(L26="", NETWORKDAYS(J26,TODAY(),Hoja2!$A$2:$A$53), NETWORKDAYS(J26,L26,Hoja2!$A$2:$A$53) ) ) -> 3 | Q26: 30/07/2025 Se inicia el proceso de análisis para la parte de modificación de cargue y se informa de lo encontrado 01/08/2025 Se realiza el análisis del proceso y de los posibles cambios. Se comparte la situación y se está a la espera de una respuesta por parte del cliente para empezar a cambiar el proceso | R26: true
A27: Alejandro | B27: REQ-8-2 | C27: Definición y cambio de flujo en la activación agente - investigación (Cambio del proceso y desarrollo del requerimiento) | D27: Modificación del flujo, cargue y almacenamiento de datos de la fase de investigación. Además, de envió de esa información a filenet | E27: Cambio del proceso y desarrollo del requerimiento | F27: CANCELADO | H27: =IF(OR(J27="",K27="",K27<J27),0,NETWORKDAYS(J27,K27,Hoja2!$A$2:$A$53)) -> 0 | M27: =IF(OR(J27="",AND(L27="",TODAY()<J27),AND(L27<>"",L27<J27)),0, IF(L27="", NETWORKDAYS(J27,TODAY(),Hoja2!$A$2:$A$53), NETWORKDAYS(J27,L27,Hoja2!$A$2:$A$53) ) ) -> 0 | Q27: 06/03/2026 Hasta el momento no se ha obtenido respuesta del parte del cliente | R27: False
A28: Alejandro | B28: Interno-H8_1 | C28: Creación de un sistema distribuido registro - puerta de enlace - aplicacion, todo dockerizado que sirva como estructura base a las aplicaciones por venir y la que se esta trabajando actualmente de sistema de agentes inteligentes | F28: FINALIZADO | G28: 100 | H28: =IF(OR(J28="",K28="",K28<J28),0,NETWORKDAYS(J28,K28,Hoja2!$A$2:$A$53)) -> 3 | I28: 45894 | J28: 45894 | K28: 45896 | L28: 45896 | M28: =IF(OR(J28="",AND(L28="",TODAY()<J28),AND(L28<>"",L28<J28)),0, IF(L28="", NETWORKDAYS(J28,TODAY(),Hoja2!$A$2:$A$53), NETWORKDAYS(J28,L28,Hoja2!$A$2:$A$53) ) ) -> 3 | O28: 45896 | Q28: 01/08/2025 Se habían tenido muchas dificultades debido a las configuraciones del servidor y del mismo docker, pero ya se tiene la plataforma base y se realizarán pruebas con otros contenedores para identificar no solo su funcionamiento, sino también la forma correcta de identificar volumenes de memoria ajenos a la máquina dockerizada, ta les como el local del servidor y los repositorios externos | R28: true
A29: Alejandro | B29: REQ-9-1 | C29: AJUSTES EN CAMPOS DE GESTION DE CASOS INGESTA MANUAL DE FECHA CORRESPONDIENTE AL PAGO DEL PREVISIONAL DE AUXILIOS FUNERARIOS VISUALIZACION DE LA FECHA PAGO PREVISIONAL EN LA PESTAÑA FLUJOS PREVISIONALES ALERTA TRAMITE INVALIDEZ | D29: SOLICITUD MEJORAS IMAGINE PORCESO AUXILIOS FUNERARIOS | F29: FINALIZADO | G29: 100 | H29: =IF(OR(J29="",K29="",K29<J29),0,NETWORKDAYS(J29,K29,Hoja2!$A$2:$A$53)) -> 5 | I29: 45866 | J29: 45866 | K29: 45870 | L29: 45870 | M29: =IF(OR(J29="",AND(L29="",TODAY()<J29),AND(L29<>"",L29<J29)),0, IF(L29="", NETWORKDAYS(J29,TODAY(),Hoja2!$A$2:$A$53), NETWORKDAYS(J29,L29,Hoja2!$A$2:$A$53) ) ) -> 5 | O29: 45870 | R29: true
A30: Alejandro | B30: Interno-H9 | C30: Creación de un sistema distribuido registro - puerta de enlace - aplicacion, todo dockerizado que sirva como estructura base a las aplicaciones por venir y la que se esta trabajando actualmente de sistema de agentes inteligentes | F30: FINALIZADO | G30: 100 | H30: =IF(OR(J30="",K30="",K30<J30),0,NETWORKDAYS(J30,K30,Hoja2!$A$2:$A$53)) -> 5 | I30: 45896 | J30: 45896 | K30: 45902 | L30: 45902 | M30: =IF(OR(J30="",AND(L30="",TODAY()<J30),AND(L30<>"",L30<J30)),0, IF(L30="", NETWORKDAYS(J30,TODAY(),Hoja2!$A$2:$A$53), NETWORKDAYS(J30,L30,Hoja2!$A$2:$A$53) ) ) -> 5 | O30: 45902 | R30: true
A31: Alejandro | B31: Interno-H10 | C31: Desacople de agente de clasificación y su lógica y acople del mismo dento del sistema distribuido. Adicionalmente, acople de la plataforma de agentes y todas las otras aplicaciones del sistema | F31: FINALIZADO | G31: 100 | H31: =IF(OR(J31="",K31="",K31<J31),0,NETWORKDAYS(J31,K31,Hoja2!$A$2:$A$53)) -> 3 | I31: 45902 | J31: 45902 | K31: 45904 | L31: 45903 | M31: =IF(OR(J31="",AND(L31="",TODAY()<J31),AND(L31<>"",L31<J31)),0, IF(L31="", NETWORKDAYS(J31,TODAY(),Hoja2!$A$2:$A$53), NETWORKDAYS(J31,L31,Hoja2!$A$2:$A$53) ) ) -> 2 | O31: 45903 | R31: true
A32: Alejandro | B32: Interno-H12 | C32: Generación de ambiente local a través de lo generado en el ambiente de pruebas, para facilitar la construcción de otros servicios | F32: FINALIZADO | G32: 100 | H32: =IF(OR(J32="",K32="",K32<J32),0,NETWORKDAYS(J32,K32,Hoja2!$A$2:$A$53)) -> 2 | I32: 45904 | J32: 45908 | K32: 45909 | L32: 45908 | M32: =IF(OR(J32="",AND(L32="",TODAY()<J32),AND(L32<>"",L32<J32)),0, IF(L32="", NETWORKDAYS(J32,TODAY(),Hoja2!$A$2:$A$53), NETWORKDAYS(J32,L32,Hoja2!$A$2:$A$53) ) ) -> 1 | R32: true
A33: Alejandro | B33: Interno-H11 | C33: Generación de servicio para el tratamiento de datos usando agentes | F33: FINALIZADO | G33: 100 | H33: =IF(OR(J33="",K33="",K33<J33),0,NETWORKDAYS(J33,K33,Hoja2!$A$2:$A$53)) -> 4 | I33: 45904 | J33: 45909 | K33: 45912 | L33: 45918 | M33: =IF(OR(J33="",AND(L33="",TODAY()<J33),AND(L33<>"",L33<J33)),0, IF(L33="", NETWORKDAYS(J33,TODAY(),Hoja2!$A$2:$A$53), NETWORKDAYS(J33,L33,Hoja2!$A$2:$A$53) ) ) -> 8 | O33: 45918 | Q33: 12/09/2025 Desde el día Mierrcoles 10 de sep no se avanza debido a que se debía de trabajar en requerimientos de mayor impórtancia para el cliente 19/09/2025 Se volvio a retomar el días 15 en la tarde, cuando se termina los pendientes de mayor importancia, terminando sus pruebas el 18 | R33: true
A34: Alejandro | B34: Interno2-1 | C34: Se identificaron, a través de un informe recién creado que había un hueco en la información. | D34: Corrección de datos guardados en BD | F34: FINALIZADO | G34: 100 | H34: =IF(OR(J34="",K34="",K34<J34),0,NETWORKDAYS(J34,K34,Hoja2!$A$2:$A$53)) -> 2 | I34: 45909 | J34: 45910 | K34: 45911 | L34: 45911 | M34: =IF(OR(J34="",AND(L34="",TODAY()<J34),AND(L34<>"",L34<J34)),0, IF(L34="", NETWORKDAYS(J34,TODAY(),Hoja2!$A$2:$A$53), NETWORKDAYS(J34,L34,Hoja2!$A$2:$A$53) ) ) -> 2 | O34: 45911 | Q34: 12/09/2025 Se identifica los datos, se correlacionan entre sí y se completa 3000 datos de 4000 | R34: true
A35: Alejandro | B35: Interno2-2 | C35: Se identificaron, a través de un informe recién creado que había un hueco en la información que debe ser corregido. | D35: Corrección de datos guardados en BD | F35: FINALIZADO | G35: 100 | H35: =IF(OR(J35="",K35="",K35<J35),0,NETWORKDAYS(J35,K35,Hoja2!$A$2:$A$53)) -> 2 | I35: 45909 | J35: 45910 | K35: 45911 | L35: 45911 | M35: =IF(OR(J35="",AND(L35="",TODAY()<J35),AND(L35<>"",L35<J35)),0, IF(L35="", NETWORKDAYS(J35,TODAY(),Hoja2!$A$2:$A$53), NETWORKDAYS(J35,L35,Hoja2!$A$2:$A$53) ) ) -> 2 | O35: 45911 | Q35: 12/09/2025 Se identifica los datos, se correlacionan entre sí y se completa 3000 datos de 4000 | R35: true
A36: Alejandro | B36: REQ-10-1 | C36: Se necesita la descarga de imagenes según varios filtros y necesidades del usuario | D36: Descarga de archivos relacionados a un cargue de datos, que identifican tipo de documento, año y a quien pertenece | F36: FINALIZADO | G36: 100 | H36: =IF(OR(J36="",K36="",K36<J36),0,NETWORKDAYS(J36,K36,Hoja2!$A$2:$A$53)) -> 4 | I36: 45909 | J36: 45910 | K36: 45915 | L36: 45915 | M36: =IF(OR(J36="",AND(L36="",TODAY()<J36),AND(L36<>"",L36<J36)),0, IF(L36="", NETWORKDAYS(J36,TODAY(),Hoja2!$A$2:$A$53), NETWORKDAYS(J36,L36,Hoja2!$A$2:$A$53) ) ) -> 4 | O36: 45915 | Q36: 12/09/2025 Se realiza la descarga y se esta en la espera de habilitación del punto de carga. Además, se indica que se debe de hacer un proceso de descarga adicional 19/09/2025 Se han realizado reuniones a lo largo de la semana para la habilitación de un punto de cargue por parte del cliente | R36: true
A37: Alejandro | B37: Interno-H13 | C37: Generación de servicio para el procesamiento de documentos y generación de un documento general | D37: Automatización de tarea para el proceso de cambios de fondos de cesantías | F37: FINALIZADO | G37: 100 | H37: =IF(OR(J37="",K37="",K37<J37),0,NETWORKDAYS(J37,K37,Hoja2!$A$2:$A$53)) -> 6 | I37: 45918 | J37: 45919 | K37: 45926 | L37: 45926 | M37: =IF(OR(J37="",AND(L37="",TODAY()<J37),AND(L37<>"",L37<J37)),0, IF(L37="", NETWORKDAYS(J37,TODAY(),Hoja2!$A$2:$A$53), NETWORKDAYS(J37,L37,Hoja2!$A$2:$A$53) ) ) -> 6 | O37: 45926 | Q37: 22/09/2025 Este día solo se trabajo en la migración 23/09/2025 Se retomo el trabajo nuevamente 28/10/2025 Se entrega todo el proyeecto incluyendo este modulo de generación de archivo | R37: true
A38: Alejandro | B38: REQ-11-1 | C38: Se necesita organizar una instancia de AWS, de tal modo que su ambiente quedé diospuesto para funcionar en producción | D38: Ambientación de instancia AWS para migración | F38: CANCELADO | G38: 85 | H38: =IF(OR(J38="",K38="",K38<J38),0,NETWORKDAYS(J38,K38,Hoja2!$A$2:$A$53)) -> 8 | I38: 45910 | J38: 45922 | K38: 45931 | M38: =IF(OR(J38="",AND(L38="",TODAY()<J38),AND(L38<>"",L38<J38)),0, IF(L38="", NETWORKDAYS(J38,TODAY(),Hoja2!$A$2:$A$53), NETWORKDAYS(J38,L38,Hoja2!$A$2:$A$53) ) ) -> 184 | Q38: 21/09/2025 Se habilitan todos los accesos para el trabajo en el servidor 23/09/2025 Se paro la ejecución debido a tareas con mayor prioridad 07/10/2025 Se empieza de nuevo con la ejecucción de la migración 10/10/2025 Se encuentra problemas con la comunicación a la base de datos 15/10/2025 Se genera una nueva instancia de bases de datos que sirva de pruebas para el nuevo ambiente 05/11/2025 Debido a nueva directiva se instancia una copia del ambiente de pruebas para confugurarla y ambientarla para producción 06/03/2026 Se estaba ambientando una instancia completamente nueva para la migración, pero el proceso se cancelo y se reformulo, esto debido a que se requerían realizar la menor cantidad de pruebas posibles, por lo que se clonó el servidor de pruebas QA que serviría de base para la migración | R38: False
A39: Alejandro | B39: Interno-H14 | C39: Creación de lógica y vista para la aprobación y rechazos de documentos cargados | D39: Automatización de tarea para el proceso de cambios de fondos de cesantías | F39: FINALIZADO | G39: 100 | H39: =IF(OR(J39="",K39="",K39<J39),0,NETWORKDAYS(J39,K39,Hoja2!$A$2:$A$53)) -> 7 | I39: 45929 | J39: 45929 | K39: 45937 | L39: 45958 | M39: =IF(OR(J39="",AND(L39="",TODAY()<J39),AND(L39<>"",L39<J39)),0, IF(L39="", NETWORKDAYS(J39,TODAY(),Hoja2!$A$2:$A$53), NETWORKDAYS(J39,L39,Hoja2!$A$2:$A$53) ) ) -> 21 | O39: 45958 | Q39: 30/09/2025 Este día solo se decdico la mitad del tiempo debido a camnio de prioridades. Se trabajará en el proyecto a medida que se vaya avanzando con las demás tareas 03/10/2025 Debido a la migración, el trabajo se ve reducido a menos de 2 horas diarias para la terminación de este protyecto 03/10/2025 Se entrega avance y se identifia procesos de mejoras y de añadir operativas para guardar información para cosos de rechazo y de análisis de datos 14/10/2025 Se entrega avance enfocado en las mejoras de procesos indicadas en la entrega anterior 28/10/2025 Se entrega todo el proyeecto incluyendo este modulo y mejoras continuas para incrementarla satisfacción y la operatividad | R39: true
A40: Alejandro | B40: REQ-11-2 | C40: Se necesita la asociación de registros relacionados con pagos de AUF | D40: Relacionar pagos de auxilios no cargados en IMAGINE | F40: FINALIZADO | G40: 100 | H40: =IF(OR(J40="",K40="",K40<J40),0,NETWORKDAYS(J40,K40,Hoja2!$A$2:$A$53)) -> 3 | I40: 45930 | J40: 45930 | K40: 45932 | L40: 45932 | M40: =IF(OR(J40="",AND(L40="",TODAY()<J40),AND(L40<>"",L40<J40)),0, IF(L40="", NETWORKDAYS(J40,TODAY(),Hoja2!$A$2:$A$53), NETWORKDAYS(J40,L40,Hoja2!$A$2:$A$53) ) ) -> 3 | O40: 45932 | P40: 45932 | Q40: 2/10/2025 Se genera informe de las actividades y de gestión con los casos que se necesitaban actualizar | R40: true
A41: Alejandro | B41: REQ-12-1 | C41: Se necesita actualizar el consumo para ingreso de nuevos datos usados en distintas tareas | D41: Actualización de consumo de mesa unificada para acoplar el flujo nuevo | F41: PRUEBAS CLIENTE | G41: 90 | H41: =IF(OR(J41="",K41="",K41<J41),0,NETWORKDAYS(J41,K41,Hoja2!$A$2:$A$53)) -> 2 | I41: 45932 | J41: 45932 | K41: 45933 | L41: 45933 | M41: =IF(OR(J41="",AND(L41="",TODAY()<J41),AND(L41<>"",L41<J41)),0, IF(L41="", NETWORKDAYS(J41,TODAY(),Hoja2!$A$2:$A$53), NETWORKDAYS(J41,L41,Hoja2!$A$2:$A$53) ) ) -> 2 | O41: 45932 | Q41: 2/10/2025 Se habilita punto de consumo con las nuevas actualizaciones 3/10/2025 Se le comunica al cliente para la realización de pruebas | R41: true
A42: Alejandro | B42: REQ-9-2 | C42: Se identifica con ayuda de las pruebas realizadas por el cliente, nuevos procesos para añadir y corregir | D42: SOLICITUD MEJORAS IMAGINE PORCESO AUXILIOS FUNERARIOS | F42: FINALIZADO | G42: 100 | H42: =IF(OR(J42="",K42="",K42<J42),0,NETWORKDAYS(J42,K42,Hoja2!$A$2:$A$53)) -> 2 | I42: 45945 | J42: 45945 | K42: 45946 | L42: 45946 | M42: =IF(OR(J42="",AND(L42="",TODAY()<J42),AND(L42<>"",L42<J42)),0, IF(L42="", NETWORKDAYS(J42,TODAY(),Hoja2!$A$2:$A$53), NETWORKDAYS(J42,L42,Hoja2!$A$2:$A$53) ) ) -> 2 | O42: 45946 | P42: 45960 | Q42: 16/10/2025 Se entrega al cliente 17/10/2025 A la espera de reunión junto con el cliente para finiquitar desarrollo 30/10/2025 Se entrga todo el proyecto con todos los errores identificados y corregidos | R42: true
A43: Alejandro | B43: REQ-13-1 | C43: Se encontraron irregularidaes en validaciones y en el código que deben ser parchadas | D43: Actualización de consumos para la creación de la solicitud de pensión y para el envío de evento de activación de investigación | F43: FINALIZADO | G43: 100 | H43: =IF(OR(J43="",K43="",K43<J43),0,NETWORKDAYS(J43,K43,Hoja2!$A$2:$A$53)) -> 2 | I43: 45944 | J43: 45947 | K43: 45950 | L43: 45967 | M43: =IF(OR(J43="",AND(L43="",TODAY()<J43),AND(L43<>"",L43<J43)),0, IF(L43="", NETWORKDAYS(J43,TODAY(),Hoja2!$A$2:$A$53), NETWORKDAYS(J43,L43,Hoja2!$A$2:$A$53) ) ) -> 14 | O43: 45967 | P43: 45967 | Q43: 14/10/2025 Se informa desde operación de un caso con bloqueo desde agosto y cuya gestión era prioritaria. Se identifica la problemática y se avanza el caso. 15/10/2025 Se identifica, por medio de operación, otros problemas que junto con los del día anterior deben ser revisados y parchados 06/11/2025 Se realizaron reuniones con Integración, dueños del consumo y cuyas respuestas al servicio no eran indicadas, se corrigio varios puntos pero los que no se pudieron se modificaron en IMAGINE | R43: true
A44: Alejandro | B44: REQ-14-1 | C44: Creación de scripts para gestión de casos en AS400 para CATE y NO CATE | D44: Gestión de casos de A400 que no han podido ejecutarse debido a fallas en integración | F44: FINALIZADO | G44: 100 | H44: =IF(OR(J44="",K44="",K44<J44),0,NETWORKDAYS(J44,K44,Hoja2!$A$2:$A$53)) -> 2 | I44: 45966 | J44: 45966 | K44: 45967 | L44: 45967 | M44: =IF(OR(J44="",AND(L44="",TODAY()<J44),AND(L44<>"",L44<J44)),0, IF(L44="", NETWORKDAYS(J44,TODAY(),Hoja2!$A$2:$A$53), NETWORKDAYS(J44,L44,Hoja2!$A$2:$A$53) ) ) -> 2 | O44: 45967 | P44: 45967 | Q44: 06/11/2025 Se realiza los scripts y se actulizan estados de casos | R44: true
A45: Alejandro | B45: REQ-15-1 | C45: Creación de script para gestión de casos en pagos | D45: Gestión de pagos que no han podido actualizarse debido a fallas en integración | F45: FINALIZADO | G45: 100 | H45: =IF(OR(J45="",K45="",K45<J45),0,NETWORKDAYS(J45,K45,Hoja2!$A$2:$A$53)) -> 1 | I45: 45967 | J45: 45967 | K45: 45967 | L45: 45967 | M45: =IF(OR(J45="",AND(L45="",TODAY()<J45),AND(L45<>"",L45<J45)),0, IF(L45="", NETWORKDAYS(J45,TODAY(),Hoja2!$A$2:$A$53), NETWORKDAYS(J45,L45,Hoja2!$A$2:$A$53) ) ) -> 1 | O45: 45967 | P45: 45967 | Q45: 06/11/2025 Se realiza el script y se actulizan estados de casos | R45: true
A46: Alejandro | B46: Interno-H15 | C46: Identificación de conexiones y validación de proyecto | D46: Migración de lógica de FILENET para gestionar validaciones en IMAGINE | F46: FINALIZADO | G46: 100 | H46: =IF(OR(J46="",K46="",K46<J46),0,NETWORKDAYS(J46,K46,Hoja2!$A$2:$A$53)) -> 5 | I46: 45965 | J46: 45965 | K46: 45971 | L46: 45971 | M46: =IF(OR(J46="",AND(L46="",TODAY()<J46),AND(L46<>"",L46<J46)),0, IF(L46="", NETWORKDAYS(J46,TODAY(),Hoja2!$A$2:$A$53), NETWORKDAYS(J46,L46,Hoja2!$A$2:$A$53) ) ) -> 5 | O46: 45971 | P46: 45992 | Q46: 06/11/2025 Seidentifica la viabilidad mas se debe probar todas las opciones manejadas en FILENET para verificar que todo puede ser migrado 12/11/2025 Seidentificó la forma que realiza la conexión fileNet con el proceso de interés a cada uno de sus recursos y en principio se puede replicar | R46: true
A47: Alejandro | B47: Interno-H15-2 | C47: Creación de la base del proyecto y de la lógica para la extracción de datos para la bandeja de validación | D47: Migración de lógica de FILENET para gestionar validaciones en IMAGINE | F47: FINALIZADO | G47: 100 | H47: =IF(OR(J47="",K47="",K47<J47),0,NETWORKDAYS(J47,K47,Hoja2!$A$2:$A$53)) -> 10 | I47: 45971 | J47: 45971 | K47: 45985 | L47: 45980 | M47: =IF(OR(J47="",AND(L47="",TODAY()<J47),AND(L47<>"",L47<J47)),0, IF(L47="", NETWORKDAYS(J47,TODAY(),Hoja2!$A$2:$A$53), NETWORKDAYS(J47,L47,Hoja2!$A$2:$A$53) ) ) -> 7 | O47: 45980 | P47: 45992 | Q47: 19/11/2025 Se construye la base para la identificación de los datos para la validación. Se encontraron muchas barreras en las que fallaba la comunicación debido al contexto de ejecución y el teimpo de sesión | R47: true
A48: Alejandro | B48: Interno-H15-3 | C48: Creación del servicio que ejecuta la extracción de los datos diariamente y creación del plan de trabajo | D48: Migración de lógica de FILENET para gestionar validaciones en IMAGINE | F48: FINALIZADO | G48: 100 | H48: =IF(OR(J48="",K48="",K48<J48),0,NETWORKDAYS(J48,K48,Hoja2!$A$2:$A$53)) -> 3 | I48: 45981 | J48: 45981 | K48: 45985 | L48: 45985 | M48: =IF(OR(J48="",AND(L48="",TODAY()<J48),AND(L48<>"",L48<J48)),0, IF(L48="", NETWORKDAYS(J48,TODAY(),Hoja2!$A$2:$A$53), NETWORKDAYS(J48,L48,Hoja2!$A$2:$A$53) ) ) -> 3 | O48: 45985 | P48: 45992 | Q48: 24/11/2025 Se integra el servicio a la malla de sistema distribuido | R48: true
A49: Alejandro | B49: Interno-H15-4 | C49: Creación de la bandeja y front del proyecto de validación | D49: Migración de lógica de FILENET para gestionar validaciones en IMAGINE | F49: FINALIZADO | G49: 100 | H49: =IF(OR(J49="",K49="",K49<J49),0,NETWORKDAYS(J49,K49,Hoja2!$A$2:$A$53)) -> 3 | I49: 45985 | J49: 45985 | K49: 45987 | L49: 45987 | M49: =IF(OR(J49="",AND(L49="",TODAY()<J49),AND(L49<>"",L49<J49)),0, IF(L49="", NETWORKDAYS(J49,TODAY(),Hoja2!$A$2:$A$53), NETWORKDAYS(J49,L49,Hoja2!$A$2:$A$53) ) ) -> 3 | O49: 45987 | P49: 45992 | Q49: 24/11/2025 Se crea la estructura para la validación desde Imagine y se muestra al equipo para la retroalimentación | R49: true
A50: Alejandro | B50: Interno-H15-5 | C50: Organización y asociación del front con el back, identificación de los consumos y extracción de los documentos. Además, de migración del proyectyo de un ambiente local al de producción | D50: Migración de lógica de FILENET para gestionar validaciones en IMAGINE | F50: FINALIZADO | G50: 100 | H50: =IF(OR(J50="",K50="",K50<J50),0,NETWORKDAYS(J50,K50,Hoja2!$A$2:$A$53)) -> 4 | I50: 45987 | J50: 45987 | K50: 45992 | L50: 45992 | M50: =IF(OR(J50="",AND(L50="",TODAY()<J50),AND(L50<>"",L50<J50)),0, IF(L50="", NETWORKDAYS(J50,TODAY(),Hoja2!$A$2:$A$53), NETWORKDAYS(J50,L50,Hoja2!$A$2:$A$53) ) ) -> 4 | O50: 45992 | P50: 45992 | Q50: 24/11/2025 Se tiene la base del proyecto funcial en producción, falta la ejecución de las validaciones | R50: true
A51: Alejandro | B51: Interno-H15-6 | C51: Ejecución de validaciones, afinamiento del proyecto y entrega | D51: Migración de lógica de FILENET para gestionar validaciones en IMAGINE | F51: FINALIZADO | G51: 100 | H51: =IF(OR(J51="",K51="",K51<J51),0,NETWORKDAYS(J51,K51,Hoja2!$A$2:$A$53)) -> 7 | I51: 45992 | J51: 45992 | K51: 46001 | L51: 46001 | M51: =IF(OR(J51="",AND(L51="",TODAY()<J51),AND(L51<>"",L51<J51)),0, IF(L51="", NETWORKDAYS(J51,TODAY(),Hoja2!$A$2:$A$53), NETWORKDAYS(J51,L51,Hoja2!$A$2:$A$53) ) ) -> 7 | O51: 46000 | P51: 46000 | Q51: 24/11/2025 Se entrega todo el proyecto y se esta a la espera de retroalimentación para modificación | R51: true
A52: Alejandro | B52: Interno-H15-7 | C52: Proceso de validación, estabilidad y modificación del proyecto | D52: Migración de lógica de FILENET para gestionar validaciones en IMAGINE | F52: FINALIZADO | G52: 100 | H52: =IF(OR(J52="",K52="",K52<J52),0,NETWORKDAYS(J52,K52,Hoja2!$A$2:$A$53)) -> 10 | I52: 46000 | J52: 46000 | K52: 46013 | L52: 46010 | M52: =IF(OR(J52="",AND(L52="",TODAY()<J52),AND(L52<>"",L52<J52)),0, IF(L52="", NETWORKDAYS(J52,TODAY(),Hoja2!$A$2:$A$53), NETWORKDAYS(J52,L52,Hoja2!$A$2:$A$53) ) ) -> 9 | O52: 46010 | Q52: 16/12/2025 Se actualiza el proyecto adicionandole mejoras de visualización de documento. Una opción para abrir el visor en produccion 16/12/2025 Se realizan pruebas de funcionamiento y a excepción de una modificación todo funciona bien 19/12/2025 Se identifica viabilidad y se construye plan de requerimientos y de elementos a realizar durante el proyecto | R52: true
A53: Alejandro | B53: Interno-H16 | C53: Identificación de procesos y validación del proyecto | D53: Proyecto de validación automática de documentación de fileNet con integración en BPO e historia laboral | F53: FINALIZADO | G53: 100 | H53: =IF(OR(J53="",K53="",K53<J53),0,NETWORKDAYS(J53,K53,Hoja2!$A$2:$A$53)) -> 5 | I53: 46006 | J53: 46006 | K53: 46010 | L53: 46010 | M53: =IF(OR(J53="",AND(L53="",TODAY()<J53),AND(L53<>"",L53<J53)),0, IF(L53="", NETWORKDAYS(J53,TODAY(),Hoja2!$A$2:$A$53), NETWORKDAYS(J53,L53,Hoja2!$A$2:$A$53) ) ) -> 5 | O53: 46010 | Q53: 16/11/2025 Se Realizó reunión con Carina para identificar procesos 18/11/2025 Se Realizó reunión con Carina para aclarar pasos en las actividades realizadas en el proceso de la tarea 19/11/2025 Se identifia la viabilidad del proyecto y se cres plan de ejecución | R53: true
A54: Alejandro | B54: REQ-16 | C54: Se están identificando muchos casos en varios frentes de soporte caausados para malas prácticas , por ahora se esta identificando las causales y corrigiendo casos manualmente | D54: Identificación y corrección de servicios de consumo en Imagine | F54: FINALIZADO | G54: 100 | H54: =IF(OR(J54="",K54="",K54<J54),0,NETWORKDAYS(J54,K54,Hoja2!$A$2:$A$53)) -> 11 | I54: 46002 | J54: 46002 | K54: 46017 | L54: 46020 | M54: =IF(OR(J54="",AND(L54="",TODAY()<J54),AND(L54<>"",L54<J54)),0, IF(L54="", NETWORKDAYS(J54,TODAY(),Hoja2!$A$2:$A$53), NETWORKDAYS(J54,L54,Hoja2!$A$2:$A$53) ) ) -> 12 | O54: 46020 | Q54: 16/11/2025 Se corrigienron un gran número de casos de AUF 17/11/2025 Se analizaron manualmente una gran cantidad de casos solicitados 18/11/2025 Se realizó reunió para el analisis de casos que no abrieron notificación 22/11/2025 Se identifia razón de fallo para algunos casos de AUF 29/12/2025 Por ahora se ha identificado y corregido los casos, hasta que se identifique alguna causa que este afectando globalmente | R54: true
A55: Alejandro | B55: Interno-H16-2 | C55: Creación de la base del proyecto para la extrrasión de datos de filenet | D55: Proyecto de validación automática de documentación de fileNet con integración en BPO e historia laboral | F55: FINALIZADO | G55: 100 | H55: =IF(OR(J55="",K55="",K55<J55),0,NETWORKDAYS(J55,K55,Hoja2!$A$2:$A$53)) -> 5 | I55: 46010 | J55: 46010 | K55: 46017 | L55: 46020 | M55: =IF(OR(J55="",AND(L55="",TODAY()<J55),AND(L55<>"",L55<J55)),0, IF(L55="", NETWORKDAYS(J55,TODAY(),Hoja2!$A$2:$A$53), NETWORKDAYS(J55,L55,Hoja2!$A$2:$A$53) ) ) -> 6 | O55: 46020 | P55: 46092 | Q55: 29/12/2025 Se habia aplazado en muchos momentos durante diciembre y debido a permisos en la bandeja se dificultó el acceso 06/03/2026 Hace parte de un grupo de funcionalidades que ya están probadas y son funcionales, pero el módulo aún le hace falta y todavía nada se ha pasado a producción. Esto último se debe a que se han priorizado otras tareas incluyendo el tema de migración el cual debía realizarse antes de pasar todo el proyecto y pedir los permisos de conexión al portal de BPO 11/03/2026 Se migra la lógica y los servicios del local a producción | R55: true
A56: Alejandro | B56: Interno-H16-3 | C56: Creacion de servicio para la captura y trabajo dentro de la plataforma de bonos | D56: Proyecto de validación automática de documentación de fileNet con integración en BPO e historia laboral | F56: FINALIZADO | G56: 100 | H56: =IF(OR(J56="",K56="",K56<J56),0,NETWORKDAYS(J56,K56,Hoja2!$A$2:$A$53)) -> 8 | I56: 46021 | J56: 46021 | K56: 46031 | L56: 46035 | M56: =IF(OR(J56="",AND(L56="",TODAY()<J56),AND(L56<>"",L56<J56)),0, IF(L56="", NETWORKDAYS(J56,TODAY(),Hoja2!$A$2:$A$53), NETWORKDAYS(J56,L56,Hoja2!$A$2:$A$53) ) ) -> 9 | O56: 46035 | P56: 46092 | Q56: 05/01/2026 Se crea servicio que se comunica con la extracción de filente y que además captura el inicio de sesión de la plataforma para empezar a trabajar automatizadamente con esta 13/01/2026 se completa el servicio, se se divide la lógica en tareas ejecutables y se desarrolla la persistencia 06/03/2026 Hace parte de un grupo de funcionalidades que ya están probadas y son funcionales, pero el módulo aún le hace falta y todavía nada se ha pasado a producción. Esto último se debe a que se han priorizado otras tareas incluyendo el tema de migración el cual debía realizarse antes de pasar todo el proyecto y pedir los permisos de conexión al portal de BPO 11/03/2026 Se migra la lógica y los servicios del local a producción | R56: true
A57: Alejandro | B57: REQ-21 | C57: Identificación de documentos y modificación de necesidad | D57: Modificación de documentos abligatorios para cesantías | F57: FINALIZADO | G57: 100 | H57: =IF(OR(J57="",K57="",K57<J57),0,NETWORKDAYS(J57,K57,Hoja2!$A$2:$A$53)) -> 2 | I57: 46028 | J57: 46028 | K57: 46029 | L57: 46029 | M57: =IF(OR(J57="",AND(L57="",TODAY()<J57),AND(L57<>"",L57<J57)),0, IF(L57="", NETWORKDAYS(J57,TODAY(),Hoja2!$A$2:$A$53), NETWORKDAYS(J57,L57,Hoja2!$A$2:$A$53) ) ) -> 2 | O57: 46029 | P57: 46029 | Q57: 07/01/2026 Se termina la identificación y se modifica el proceso | R57: true
A58: Alejandro | B58: Interno-H16-4 | C58: Creacion de servicio place holder con agentes para la identificación de información capturada y análisis OCR | D58: Proyecto de validación automática de documentación de fileNet con integración en BPO e historia laboral | F58: FINALIZADO | G58: 100 | H58: =IF(OR(J58="",K58="",K58<J58),0,NETWORKDAYS(J58,K58,Hoja2!$A$2:$A$53)) -> 4 | I58: 46036 | J58: 46036 | K58: 46041 | L58: 46038 | M58: =IF(OR(J58="",AND(L58="",TODAY()<J58),AND(L58<>"",L58<J58)),0, IF(L58="", NETWORKDAYS(J58,TODAY(),Hoja2!$A$2:$A$53), NETWORKDAYS(J58,L58,Hoja2!$A$2:$A$53) ) ) -> 3 | O58: 46038 | P58: 46092 | Q58: 14/01/2026 Se crea lógica de persistencia para activar servicio 16/01/2026 Se completa la llógica del servicio, se construye la base y se da respuesta constante para luego poder realizar implementación 06/03/2026 Hace parte de un grupo de funcionalidades que ya están probadas y son funcionales, pero el módulo aún le hace falta y todavía nada se ha pasado a producción. Esto último se debe a que se han priorizado otras tareas incluyendo el tema de migración el cual debía realizarse antes de pasar todo el proyecto y pedir los permisos de conexión al portal de BPO 11/03/2026 Se migra la lógica y los servicios del local a producción | R58: true
A59: Alejandro | B59: REQ-17 | C59: Radicados con fallos en la trazabilidad se deben analizar y de corregir | D59: Modificación de trazabilidad radicados prestaciones | F59: FINALIZADO | G59: 100 | H59: =IF(OR(J59="",K59="",K59<J59),0,NETWORKDAYS(J59,K59,Hoja2!$A$2:$A$53)) -> 1 | I59: 46035 | J59: 46036 | K59: 46036 | L59: 46036 | M59: =IF(OR(J59="",AND(L59="",TODAY()<J59),AND(L59<>"",L59<J59)),0, IF(L59="", NETWORKDAYS(J59,TODAY(),Hoja2!$A$2:$A$53), NETWORKDAYS(J59,L59,Hoja2!$A$2:$A$53) ) ) -> 1 | O59: 46036 | P59: 46036 | Q59: 14/01/2026 Se analiza y se corrige la trazabilidad para mas de 100 radicados con situación de falla | R59: true
A60: Alejandro | B60: Interno-H16-5 | C60: Construcción y conexiónd del Front con la lógica generada hasta el momento | D60: Proyecto de validación automática de documentación de fileNet con integración en BPO e historia laboral | F60: FINALIZADO | G60: 100 | H60: =IF(OR(J60="",K60="",K60<J60),0,NETWORKDAYS(J60,K60,Hoja2!$A$2:$A$53)) -> 4 | I60: 46041 | J60: 46041 | K60: 46044 | L60: 46050 | M60: =IF(OR(J60="",AND(L60="",TODAY()<J60),AND(L60<>"",L60<J60)),0, IF(L60="", NETWORKDAYS(J60,TODAY(),Hoja2!$A$2:$A$53), NETWORKDAYS(J60,L60,Hoja2!$A$2:$A$53) ) ) -> 8 | O60: 46050 | P60: 46092 | Q60: 26/01/2026 Se retoma el trabajo después de identificar las correcciones y nuevos elementos por analizar en el back. Sin embargo, hace falta un escenario por parametrizar que no se pudo encontrar un ejemplo 06/03/2026 Hace parte de un grupo de funcionalidades que ya están probadas y son funcionales, pero el módulo aún le hace falta y todavía nada se ha pasado a producción. Esto último se debe a que se han priorizado otras tareas incluyendo el tema de migración el cual debía realizarse antes de pasar todo el proyecto y pedir los permisos de conexión al portal de BPO 11/03/2026 Se migra la lógica y los servicios del local a producción | R60: true
A61: Alejandro | B61: Interno-H16-6 | C61: Reunion con Carina para identificar el flujo del proceso de principio a fin para los 3 tipos documentales para rechazos y confirmaciones | D61: Proyecto de validación automática de documentación de fileNet con integración en BPO e historia laboral | F61: FINALIZADO | G61: 100 | H61: =IF(OR(J61="",K61="",K61<J61),0,NETWORKDAYS(J61,K61,Hoja2!$A$2:$A$53)) -> 1 | I61: 46042 | J61: 46042 | K61: 46042 | L61: 46042 | M61: =IF(OR(J61="",AND(L61="",TODAY()<J61),AND(L61<>"",L61<J61)),0, IF(L61="", NETWORKDAYS(J61,TODAY(),Hoja2!$A$2:$A$53), NETWORKDAYS(J61,L61,Hoja2!$A$2:$A$53) ) ) -> 1 | O61: 46042 | P61: 46042 | Q61: 20/01/2026 Se dispone de un tiempo para la validación e identificación de cada uno de los casos posibles y re modelar el trabajo hecho acoplado a las necesidades | R61: true
A62: Alejandro | B62: REQ-18 | C62: Radicados con fallos en la trazabilidad se deben analizar y de corregir | D62: Corrección de casos que no avanzan | F62: FINALIZADO | G62: 100 | H62: =IF(OR(J62="",K62="",K62<J62),0,NETWORKDAYS(J62,K62,Hoja2!$A$2:$A$53)) -> 1 | I62: 46042 | J62: 46042 | K62: 46042 | L62: 46042 | M62: =IF(OR(J62="",AND(L62="",TODAY()<J62),AND(L62<>"",L62<J62)),0, IF(L62="", NETWORKDAYS(J62,TODAY(),Hoja2!$A$2:$A$53), NETWORKDAYS(J62,L62,Hoja2!$A$2:$A$53) ) ) -> 1 | O62: 46042 | P62: 46042 | Q62: 20/01/2026 Se analiza y se corrige la trazabilidad para trámites varios | R62: true
A63: Alejandro | B63: Interno-H16-7 | C63: Corrección de datos para acoplar a las necesidades y todos los casos posibles del proceso | D63: Proyecto de validación automática de documentación de fileNet con integración en BPO e historia laboral | F63: FINALIZADO | G63: 100 | H63: =IF(OR(J63="",K63="",K63<J63),0,NETWORKDAYS(J63,K63,Hoja2!$A$2:$A$53)) -> 3 | I63: 46043 | J63: 46043 | K63: 46045 | L63: 46050 | M63: =IF(OR(J63="",AND(L63="",TODAY()<J63),AND(L63<>"",L63<J63)),0, IF(L63="", NETWORKDAYS(J63,TODAY(),Hoja2!$A$2:$A$53), NETWORKDAYS(J63,L63,Hoja2!$A$2:$A$53) ) ) -> 6 | O63: 46050 | P63: 46092 | Q63: 06/03/2026 Hace parte de un grupo de funcionalidades que ya están probadas y son funcionales, pero el módulo aún le hace falta y todavía nada se ha pasado a producción. Esto último se debe a que se han priorizado otras tareas incluyendo el tema de migración el cual debía realizarse antes de pasar todo el proyecto y pedir los permisos de conexión al portal de BPO 11/03/2026 Se migra la lógica y los servicios del local a producción | R63: true
A64: Alejandro | B64: REQ-20 | C64: Existen trámites a los que les llegan actualizaciones de estados de terceros, estas actualizaciones se analizaron y parecen que en algunos casos son enviadas una de trás de otra presentando problemas a la hora del procesamiento. Se debe de construir un sistema que ponga en encolamiento las tareas y procese el primero según el momento de llegada y añadir un log para la identificación de ese momento | D64: Creación de lóigica para el control de casos de notificación | F64: FINALIZADO | G64: 100 | H64: =IF(OR(J64="",K64="",K64<J64),0,NETWORKDAYS(J64,K64,Hoja2!$A$2:$A$53)) -> 2 | I64: 46044 | J64: 46044 | K64: 46045 | L64: 46045 | M64: =IF(OR(J64="",AND(L64="",TODAY()<J64),AND(L64<>"",L64<J64)),0, IF(L64="", NETWORKDAYS(J64,TODAY(),Hoja2!$A$2:$A$53), NETWORKDAYS(J64,L64,Hoja2!$A$2:$A$53) ) ) -> 2 | O64: 46045 | P64: 46045 | Q64: 22/01/2026 Se analiza y se cnstruye la solución 23/01/2026 Se realizan pruebas para distintos casos, se realizan correciciones y se sube a producción | R64: true
A65: Alejandro | B65: REQ-19 | C65: Añadir información procedente de tercceros para los distintos casos | D65: Modificación de módulo de validación filenet | F65: FINALIZADO | G65: 100 | H65: =IF(OR(J65="",K65="",K65<J65),0,NETWORKDAYS(J65,K65,Hoja2!$A$2:$A$53)) -> 1 | I65: 46044 | J65: 46044 | K65: 46044 | L65: 46044 | M65: =IF(OR(J65="",AND(L65="",TODAY()<J65),AND(L65<>"",L65<J65)),0, IF(L65="", NETWORKDAYS(J65,TODAY(),Hoja2!$A$2:$A$53), NETWORKDAYS(J65,L65,Hoja2!$A$2:$A$53) ) ) -> 1 | O65: 46044 | P65: 46044 | Q65: 22/01/2026 Se identifica con Carina la necesidad, se analiza y se cnstruye la solución | R65: true
A66: Alejandro | B66: Interno-H16-8 | C66: Conexión front - servicio - filenet para la visualización de archivos y gestionar aprovaciones y rechazos | D66: Proyecto de validación automática de documentación de fileNet con integración en BPO e historia laboral | F66: FINALIZADO | G66: 100 | H66: =IF(OR(J66="",K66="",K66<J66),0,NETWORKDAYS(J66,K66,Hoja2!$A$2:$A$53)) -> 6 | I66: 46045 | J66: 46045 | K66: 46052 | L66: 46050 | M66: =IF(OR(J66="",AND(L66="",TODAY()<J66),AND(L66<>"",L66<J66)),0, IF(L66="", NETWORKDAYS(J66,TODAY(),Hoja2!$A$2:$A$53), NETWORKDAYS(J66,L66,Hoja2!$A$2:$A$53) ) ) -> 4 | O66: 46050 | P66: 46092 | Q66: 28/01/2026 Se encontraron dificultades en el acomplamiento de los servicios sobre todo hacia filenet, pero se puedo implementar todo el flujo 06/03/2026 Hace parte de un grupo de funcionalidades que ya están probadas y son funcionales, pero el módulo aún le hace falta y todavía nada se ha pasado a producción. Esto último se debe a que se han priorizado otras tareas incluyendo el tema de migración el cual debía realizarse antes de pasar todo el proyecto y pedir los permisos de conexión al portal de BPO 11/03/2026 Se migra la lógica y los servicios del local a producción | R66: true
... A68: Alejandro | B68: Interno-H16-10 | C68: Creación de pestaña de consultas de radicados y cédulas tanto para procesos históricos y procesos gestionados con la herramienta | D68: Proyecto de validación automática de documentación de fileNet con integración en BPO e historia laboral | F68: FINALIZADO | G68: 100 | H68: =IF(OR(J68="",K68="",K68<J68),0,NETWORKDAYS(J68,K68,Hoja2!$A$2:$A$53)) -> 2 | I68: 46051 | J68: 46051 | K68: 46052 | L68: 46056 | M68: =IF(OR(J68="",AND(L68="",TODAY()<J68),AND(L68<>"",L68<J68)),0, IF(L68="", NETWORKDAYS(J68,TODAY(),Hoja2!$A$2:$A$53), NETWORKDAYS(J68,L68,Hoja2!$A$2:$A$53) ) ) -> 4 | O68: 46051 | P68: 46092 | Q68: 29/01/2026 Se termina la implementación y me encuentro en pruebas de funcionamiento 03/02/2026 Se pudo lograr realizar una prueba depunto a punto exitosa 06/03/2026 Hace parte de un grupo de funcionalidades que ya están probadas y son funcionales, pero el módulo aún le hace falta y todavía nada se ha pasado a producción. Esto último se debe a que se han priorizado otras tareas incluyendo el tema de migración el cual debía realizarse antes de pasar todo el proyecto y pedir los permisos de conexión al portal de BPO 11/03/2026 Se migra la lógica y los servicios del local a producción | R68: true
A69: Alejandro | B69: REQ-22 | C69: Se incluye lógica para la verificación de tiempo de ejecución en los procesos de creación de trámites | D69: Creación de lóigica para el control de casos de creación de trámite | F69: FINALIZADO | G69: 100 | H69: 1 | I69: 46045 | J69: 46048 | K69: 46048 | L69: 46048 | M69: =IF(OR(J69="",AND(L69="",TODAY()<J69),AND(L69<>"",L69<J69)),0, IF(L69="", NETWORKDAYS(J69,TODAY(),Hoja2!$A$2:$A$53), NETWORKDAYS(J69,L69,Hoja2!$A$2:$A$53) ) ) -> 1 | O69: 46048 | P69: 46048 | Q69: 26/01/2026 Se procesa prueba exitosa y se pasa a producción | R69: true
A70: Alejandro | B70: Interno-H16-11 | C70: Modificación de obtención de motivos y causas de rechazo. Se necesita crear lógica asincrona para mejorar tiempos de procedimiento | D70: Proyecto de validación automática de documentación de fileNet con integración en BPO e historia laboral | F70: FINALIZADO | G70: 100 | H70: =IF(OR(J70="",K70="",K70<J70),0,NETWORKDAYS(J70,K70,Hoja2!$A$2:$A$53)) -> 2 | I70: 46056 | J70: 46056 | K70: 46057 | L70: 46057 | M70: =IF(OR(J70="",AND(L70="",TODAY()<J70),AND(L70<>"",L70<J70)),0, IF(L70="", NETWORKDAYS(J70,TODAY(),Hoja2!$A$2:$A$53), NETWORKDAYS(J70,L70,Hoja2!$A$2:$A$53) ) ) -> 2 | O70: 46057 | P70: 46092 | Q70: 04/02/2026 Se cambia la lógica actual que estaba presentando lentitud en la gestión del operador por una asyncrona que se renueva todos los días 06/03/2026 Hace parte de un grupo de funcionalidades que ya están probadas y son funcionales, pero el módulo aún le hace falta y todavía nada se ha pasado a producción. Esto último se debe a que se han priorizado otras tareas incluyendo el tema de migración el cual debía realizarse antes de pasar todo el proyecto y pedir los permisos de conexión al portal de BPO 11/03/2026 Se migra la lógica y los servicios del local a producción | R70: true
A71: Alejandro | B71: Interno-H16-12 | C71: Procesos de mejora de rendimiento de tiempo al aprovar y rechazar un documento. Trasladando el proceso síncrono a uno asíncrono | D71: Modificación de módulo de validación filenet | F71: FINALIZADO | G71: 100 | H71: 2 | I71: 46057 | J71: 46057 | K71: 46057 | L71: 46059 | M71: =IF(OR(J71="",AND(L71="",TODAY()<J71),AND(L71<>"",L71<J71)),0, IF(L71="", NETWORKDAYS(J71,TODAY(),Hoja2!$A$2:$A$53), NETWORKDAYS(J71,L71,Hoja2!$A$2:$A$53) ) ) -> 3 | O71: 46057 | P71: 46070 | Q71: 05/02/2026 Se agrega termina de cambiar la lógica y de agregar el script que ejecute asíncronamente el envió 06/02/2026 Se esta en proceso de pruebas y cambiosdebido a que se han presentado situaciones que deben de darse mantenimiento 17/02/2026 Se habían generado pruebas pero el sistema no se estaba usando hasta hoy debido a que los problemas de la plataforma todavía se trasladaba a nuestro sistema con la carga de documentos sincrónica. Esto se cambio y ya desde el momento en que se trae la información también se trae el documento asociado | R71: true
A72: Alejandro | B72: Interno-H16-13 | C72: Adición de modulos para la asignación y filtro de información | D72: Modificación de módulo de validación filenet | F72: FINALIZADO | G72: 100 | H72: =IF(OR(J72="",K72="",K72<J72),0,NETWORKDAYS(J72,K72,Hoja2!$A$2:$A$53)) -> 1 | I72: 46057 | J72: 46057 | K72: 46057 | L72: 46058 | M72: =IF(OR(J72="",AND(L72="",TODAY()<J72),AND(L72<>"",L72<J72)),0, IF(L72="", NETWORKDAYS(J72,TODAY(),Hoja2!$A$2:$A$53), NETWORKDAYS(J72,L72,Hoja2!$A$2:$A$53) ) ) -> 2 | O72: 46058 | P72: 46058 | Q72: 05/02/2026 Se agrega los nuevos módulos, se prueban y se pasan a producción | R72: true
A73: Alejandro | B73: Interno-H16-14 | C73: Identificación de problemas con el servidor al momento de hacer cargues pesados | D73: Automatización de tarea para el proceso de cambios de fondos de cesantías | F73: FINALIZADO | G73: 100 | H73: =IF(OR(J73="",K73="",K73<J73),0,NETWORKDAYS(J73,K73,Hoja2!$A$2:$A$53)) -> 2 | I73: 46059 | J73: 46059 | K73: 46062 | L73: 46062 | M73: =IF(OR(J73="",AND(L73="",TODAY()<J73),AND(L73<>"",L73<J73)),0, IF(L73="", NETWORKDAYS(J73,TODAY(),Hoja2!$A$2:$A$53), NETWORKDAYS(J73,L73,Hoja2!$A$2:$A$53) ) ) -> 2 | O73: 46062 | P73: 46062 | Q73: 06/02/2026 Se identifica lentitud y se empieza un proceso de migración de servicios a producción que originalmente estaban en pruebas 09/02/2026 Se monta la solución en producción y se espera confirmación de funcionamiento | R73: true
A74: Alejandro | B74: Interno-H16-15 | C74: Creación de servicio que accedera a FileNet y descargará los archivos asociados a la documentación por validar y acoplamiento a los dos proyectos de fileNet | D74: Modificación para los módulo de validación filenet y creación de servicio para el acceso a archivos | F74: FINALIZADO | G74: 100 | H74: =IF(OR(J74="",K74="",K74<J74),0,NETWORKDAYS(J74,K74,Hoja2!$A$2:$A$53)) -> 3 | I74: 46062 | J74: 46063 | K74: 46065 | L74: 46070 | M74: =IF(OR(J74="",AND(L74="",TODAY()<J74),AND(L74<>"",L74<J74)),0, IF(L74="", NETWORKDAYS(J74,TODAY(),Hoja2!$A$2:$A$53), NETWORKDAYS(J74,L74,Hoja2!$A$2:$A$53) ) ) -> 6 | O74: 46070 | P74: 46070 | Q74: 05/02/2026 Se agrega los nuevos módulos, se prueban y se pasan a producción 17/02/2026 Se acopla el servicio de descarga de documentación con el sistema de validación en mesa unificada | R74: true
A75: Alejandro | B75: Interno-H16-14-2 | C75: corrección en irregularidades en el servicio de cesantías y el de PHP | D75: Automatización de tarea para el proceso de cambios de fondos de cesantías | F75: FINALIZADO | G75: 100 | H75: =IF(OR(J75="",K75="",K75<J75),0,NETWORKDAYS(J75,K75,Hoja2!$A$2:$A$53)) -> 2 | I75: 46063 | J75: 46065 | K75: 46066 | L75: 46069 | M75: =IF(OR(J75="",AND(L75="",TODAY()<J75),AND(L75<>"",L75<J75)),0, IF(L75="", NETWORKDAYS(J75,TODAY(),Hoja2!$A$2:$A$53), NETWORKDAYS(J75,L75,Hoja2!$A$2:$A$53) ) ) -> 3 | O75: 46069 | P75: 46069 | Q75: 10/02/2026 Se indican problemas de cargue y al realizar validaciones se encontraron inconsistencias en las configuraciones y versiones del servicio 16/02/2026 Se sube a producción las correcciones y se está en espera de las pruebas 06/03/2026 Al realizarse pruebas con lotes grandes se encontraron fallos que luego fueron arreglados aumentando la capacidad de carga del servicio | R75: true
A76: Alejandro | B76: REQ-23 | C76: Se debe de corregir lógica que identifica el sub estado de un trámite a la hora de rechazar documentación | D76: Creación de lóigica para la visualización de sub estados de trámites | F76: FINALIZADO | G76: 100 | H76: =IF(OR(J76="",K76="",K76<J76),0,NETWORKDAYS(J76,K76,Hoja2!$A$2:$A$53)) -> 2 | I76: 46070 | J76: 46070 | K76: 46071 | L76: 46072 | M76: =IF(OR(J76="",AND(L76="",TODAY()<J76),AND(L76<>"",L76<J76)),0, IF(L76="", NETWORKDAYS(J76,TODAY(),Hoja2!$A$2:$A$53), NETWORKDAYS(J76,L76,Hoja2!$A$2:$A$53) ) ) -> 3 | O76: 46072 | P76: 46072 | Q76: 17/02/2026 Se realiza un análisis de la lógica que genera los estados de las solicitudes 18/02/2026 Se desarrolla posible soluci+on a la necesidad 19/02/2026 Se realiza pruebas, modificaciones y se sube a producción | R76: true
A77: Alejandro | B77: Interno-H16-13-2 | C77: Adición de modulos que faciliten el proceso de la validación | D77: Modificación de módulo de validación filenet | F77: FINALIZADO | G77: 100 | H77: =IF(OR(J77="",K77="",K77<J77),0,NETWORKDAYS(J77,K77,Hoja2!$A$2:$A$53)) -> 3 | I77: 46072 | J77: 46072 | K77: 46076 | L77: 46073 | M77: =IF(OR(J77="",AND(L77="",TODAY()<J77),AND(L77<>"",L77<J77)),0, IF(L77="", NETWORKDAYS(J77,TODAY(),Hoja2!$A$2:$A$53), NETWORKDAYS(J77,L77,Hoja2!$A$2:$A$53) ) ) -> 2 | O77: 46073 | P77: 46073 | Q77: 19/02/2026 Se habla con Harol para la identificación de cambios que faciliten el trabajo del módulo 20/02/2026 Se cargan cambios para la visualización del visor en distintas ventanas, además de el formateo de información para el tipo documental 21/02/2026 Se está a la espera de las retroalimentaciones 24/02/2026 Se realizaron algunos cambios para extraer más datos pero el servicio solo carga hasta cierto punto y se debe revisar si es por alguna sobrecarga. De resto todo parece funcionar correctamente | R77: true
A78: Alejandro | B78: REQ-24 | C78: Se deben de dar respuesta a la cola de casos abiertos en la plataforma del cliente | D78: Atención al soporte en plataforma del cliente | F78: FINALIZADO | G78: 100 | H78: =IF(OR(J78="",K78="",K78<J78),0,NETWORKDAYS(J78,K78,Hoja2!$A$2:$A$53)) -> 4 | I78: 46076 | J78: 46076 | K78: 46079 | L78: 46080 | M78: =IF(OR(J78="",AND(L78="",TODAY()<J78),AND(L78<>"",L78<J78)),0, IF(L78="", NETWORKDAYS(J78,TODAY(),Hoja2!$A$2:$A$53), NETWORKDAYS(J78,L78,Hoja2!$A$2:$A$53) ) ) -> 5 | O78: 46080 | P78: 46080 | Q78: 23/02/2026 Se identifica que hay una cola de casos para soporte que se deben de gestionar. Se recibe documnetación para la atención en la plataforma 25/02/2026 Hasta el momento se han gestionado alrededor de 40 - 50 casos 27/02/2026 solo quedá a lo mucho 3 casos, pero es una tarea que será necesario trabajarle al mismo ritmo que llegan casos | R78: true
A79: Alejandro | B79: REQ-25 | C79: Resultado de una falla lógica se debe de reenviar 1800 casos para finalizar etapa de documentación. Para ello se debe de crear un script que facilite la manualidad | D79: Casos con eventos de finalización de documentación no ingresados a IMAGINE | F79: FINALIZADO | G79: 100 | H79: =IF(OR(J79="",K79="",K79<J79),0,NETWORKDAYS(J79,K79,Hoja2!$A$2:$A$53)) -> 2 | I79: 46076 | J79: 46076 | K79: 46077 | L79: 46077 | M79: =IF(OR(J79="",AND(L79="",TODAY()<J79),AND(L79<>"",L79<J79)),0, IF(L79="", NETWORKDAYS(J79,TODAY(),Hoja2!$A$2:$A$53), NETWORKDAYS(J79,L79,Hoja2!$A$2:$A$53) ) ) -> 2 | O79: 46077 | P79: 46077 | Q79: 25/02/2026 Se realiza la gestión para todos los casos asociados | R79: true
A80: Alejandro | B80: REQ-26 | C80: Se debe de cargar servicios y actualizar aplicativo para el servidor de migraciones | D80: Cargue de servicios y afinación de servidor para migración | F80: FINALIZADO | G80: 100 | H80: =IF(OR(J80="",K80="",K80<J80),0,NETWORKDAYS(J80,K80,Hoja2!$A$2:$A$53)) -> 4 | I80: 46078 | J80: 46079 | K80: 46084 | L80: 46084 | M80: =IF(OR(J80="",AND(L80="",TODAY()<J80),AND(L80<>"",L80<J80)),0, IF(L80="", NETWORKDAYS(J80,TODAY(),Hoja2!$A$2:$A$53), NETWORKDAYS(J80,L80,Hoja2!$A$2:$A$53) ) ) -> 4 | N80: 46084 | O80: 46084 | P80: 46084 | Q80: 26/02/2026 Se necesita poner en punta de nuevo el servidor que dejó de estar actualizada desde diciembre, por lo que es necesario cargar los servicios de validación fileNet 02/03/2026 Con los servicios ya cargados se cambia un proceso que no se había actualizado. Además se actualiza el repositorio para tener los datos tal cuál en producción 03/03/2026 Se termina de configurar, actualizar y cargar el repositorio. Además, se pasa el servidor de migraci´n a producción de 7 a 9 de la noche | R80: true
A81: Alejandro | B81: REQ-27 | C81: Se debe de agregar una función que permita que si se valida mesa, se debe de identificar si se marco bonos para abrir dicha tarea | D81: Corrección lógica de mesa unificada | F81: FINALIZADO | G81: 100 | H81: =IF(OR(J81="",K81="",K81<J81),0,NETWORKDAYS(J81,K81,Hoja2!$A$2:$A$53)) -> 3 | I81: 46083 | J81: 46083 | K81: 46085 | L81: 46090 | M81: =IF(OR(J81="",AND(L81="",TODAY()<J81),AND(L81<>"",L81<J81)),0, IF(L81="", NETWORKDAYS(J81,TODAY(),Hoja2!$A$2:$A$53), NETWORKDAYS(J81,L81,Hoja2!$A$2:$A$53) ) ) -> 6 | O81: 46084 | P81: 46090 | Q81: 03/03/2026 Se termina de construir la lógica para que el evento de mesa unificada ok pueda evaluar e identificar si el trámite necesita abrir bonos | R81: true
A82: Alejandro | B82: REQ-28 | C82: Identificación y mantenimiento a cada una de las dificultades presentadas en el servidor nuevo | D82: Soporte a inconsistencias en la migración | F82: FINALIZADO | G82: 100 | H82: =IF(OR(J82="",K82="",K82<J82),0,NETWORKDAYS(J82,K82,Hoja2!$A$2:$A$53)) -> 3 | I82: 46085 | J82: 46085 | K82: 46087 | L82: 46091 | M82: =IF(OR(J82="",AND(L82="",TODAY()<J82),AND(L82<>"",L82<J82)),0, IF(L82="", NETWORKDAYS(J82,TODAY(),Hoja2!$A$2:$A$53), NETWORKDAYS(J82,L82,Hoja2!$A$2:$A$53) ) ) -> 5 | O82: 46090 | P82: 46091 | Q82: 06/03/2026 Se han hecho trabajos de soporte para distintos m[odulos que incurrieron en errores en el momento de la migraci[on. IOnluyendo reporter[ia, consumos, formularios, visores, etc> no Se ha terminado el proceso de normalizaci[on del sistema y se siguen realizando correcciones | R82: true
A83: Alejandro | B83: Interno-H16-16 | C83: Pruebas y acople del desarrollo al ambiente nuevo en producción | D83: Proyecto de validación automática de documentación de fileNet con integración en BPO e historia laboral | F83: FINALIZADO | G83: 100 | H83: =IF(OR(J83="",K83="",K83<J83),0,NETWORKDAYS(J83,K83,Hoja2!$A$2:$A$53)) -> 3 | I83: 46091 | J83: 46092 | K83: 46094 | L83: 46097 | M83: =IF(OR(J83="",AND(L83="",TODAY()<J83),AND(L83<>"",L83<J83)),0, IF(L83="", NETWORKDAYS(J83,TODAY(),Hoja2!$A$2:$A$53), NETWORKDAYS(J83,L83,Hoja2!$A$2:$A$53) ) ) -> 4 | O83: 46094 | P83: 46097 | Q83: 16/03/2026 El paso a producción de todos los modulos del proyecto son exitosos y se gestiona la salida al portal OBP desde el servidor | R83: true
A84: Alejandro | B84: Interno-H16-17 | C84: Identificación y validación del código proporcionado por Don Hernan | D84: Migración de módulo de auxilios a tecnologías más modernas | F84: FINALIZADO | G84: 100 | H84: =IF(OR(J84="",K84="",K84<J84),0,NETWORKDAYS(J84,K84,Hoja2!$A$2:$A$53)) -> 3 | I84: 46091 | J84: 46091 | K84: 46093 | L84: 46093 | M84: =IF(OR(J84="",AND(L84="",TODAY()<J84),AND(L84<>"",L84<J84)),0, IF(L84="", NETWORKDAYS(J84,TODAY(),Hoja2!$A$2:$A$53), NETWORKDAYS(J84,L84,Hoja2!$A$2:$A$53) ) ) -> 3 | Q84: 12/03/2026 Se termina de realizar la validacion del código y su funcionamiento. Se encuentra que el código fuie prepadrado para otra unidada y se le indica a Don Hernan | R84: true
A85: Alejandro | B85: REQ-28-2 | C85: Identificación y mantenimiento a cada una de las dificultades presentadas en el servidor nuevo | D85: Soporte a inconsistencias en la migración | F85: FINALIZADO | G85: 100 | H85: =IF(OR(J85="",K85="",K85<J85),0,NETWORKDAYS(J85,K85,Hoja2!$A$2:$A$53)) -> 1 | I85: 46094 | J85: 46094 | K85: 46094 | L85: 46097 | M85: =IF(OR(J85="",AND(L85="",TODAY()<J85),AND(L85<>"",L85<J85)),0, IF(L85="", NETWORKDAYS(J85,TODAY(),Hoja2!$A$2:$A$53), NETWORKDAYS(J85,L85,Hoja2!$A$2:$A$53) ) ) -> 2 | O85: 46094 | P85: 46094 | Q85: 13/03/2026 Se encontraron errores en el proceso que estaba presentando problemas problemas delicacdos en el flujo, tanto para las trámites abiertos en investigación como los trámites gestionados en glosas. Se realizan todas las validaciones, cambios y verificaciones y se consigue solventar los problemas 16/03/2026 Se terminan de validar unos casos asociados al problema y se corrigen | R85: true
A86: Alejandro | B86: Interno-H16-18 | C86: Moódulo para identificación a modo de bandeja para los documentos de identidad que deben gestrionarse en el portal de historia laboral | D86: Proyecto de validación automática de documentación de fileNet con integración en BPO e historia laboral | F86: FINALIZADO | G86: 100 | H86: =IF(OR(J86="",K86="",K86<J86),0,NETWORKDAYS(J86,K86,Hoja2!$A$2:$A$53)) -> 2 | I86: 46097 | J86: 46098 | K86: 46099 | L86: 46099 | M86: =IF(OR(J86="",AND(L86="",TODAY()<J86),AND(L86<>"",L86<J86)),0, IF(L86="", NETWORKDAYS(J86,TODAY(),Hoja2!$A$2:$A$53), NETWORKDAYS(J86,L86,Hoja2!$A$2:$A$53) ) ) -> 2 | O86: 46099 | P86: 46101 | Q86: 19/03/2026 Se realiza pruebas para identificar que todo el flujo sea correcto 20/03/2026 Se pasa a producción con la lógica de cargue | R86: true
A87: Alejandro | B87: Interno-H16-19 | C87: Moódulo para cargar los mas de 1 millon de registros generados del módulo que se ha trabajado de manera manual | D87: Proyecto de validación automática de documentación de fileNet con integración en BPO e historia laboral | F87: FINALIZADO | G87: 100 | H87: =IF(OR(J87="",K87="",K87<J87),0,NETWORKDAYS(J87,K87,Hoja2!$A$2:$A$53)) -> 2 | I87: 46097 | J87: 46099 | K87: 46100 | L87: 46106 | M87: =IF(OR(J87="",AND(L87="",TODAY()<J87),AND(L87<>"",L87<J87)),0, IF(L87="", NETWORKDAYS(J87,TODAY(),Hoja2!$A$2:$A$53), NETWORKDAYS(J87,L87,Hoja2!$A$2:$A$53) ) ) -> 5 | O87: 46100 | P87: 46101 | Q87: 19/03/2026 Se esta teniendo dificultades en la ejecución del módulo debido a la cantidad de información y se estima una espera de hasta 50 horas para la carga. Se esperaba traabajar en .csv pero el archivo es tan grande que no permite la conversión, por lo que se va a esperar hasta el viernes o el sabado para ejecutar de nuevo y que se cargue durante todo el fin de semana 24/03/2026 El fin de semana se paso la mayor parte de información, pero existía en el dopcumento datos no normalizados que fueron entonces individualizados y cargados según correspondía 25/03/2026 Se realiza el cargue para los datos de la última semana | R87: true
A88: Alejandro | B88: REQ-28-3 | C88: Corrección en trámites y reporteria | D88: Soporte a inconsistencias en la migración | F88: FINALIZADO | G88: 100 | H88: =IF(OR(J88="",K88="",K88<J88),0,NETWORKDAYS(J88,K88,Hoja2!$A$2:$A$53)) -> 3 | I88: 46097 | J88: 46098 | K88: 46100 | L88: 46100 | M88: =IF(OR(J88="",AND(L88="",TODAY()<J88),AND(L88<>"",L88<J88)),0, IF(L88="", NETWORKDAYS(J88,TODAY(),Hoja2!$A$2:$A$53), NETWORKDAYS(J88,L88,Hoja2!$A$2:$A$53) ) ) -> 3 | O88: 46100 | P88: 46100 | Q88: 19/03/2026 Problemas resueltos en el flujo de trámites para mesa unificada. Se corrige todas las ionconsitencias generadas en el cambio de tecnología para el reporte de trazabilidad | R88: true
A89: Alejandro | B89: REQ-29 | C89: Creación de lógica en el consumo para registro de errores de código, corrección e identificación de lógica que puede estar causando las inconsistencias | D89: Identificación y corrección de servicios de consumo de bonos complejos en imagine | F89: FINALIZADO | G89: 100 | H89: =IF(OR(J89="",K89="",K89<J89),0,NETWORKDAYS(J89,K89,Hoja2!$A$2:$A$53)) -> 1 | I89: 46104 | J89: 46105 | K89: 46105 | L89: 46105 | M89: =IF(OR(J89="",AND(L89="",TODAY()<J89),AND(L89<>"",L89<J89)),0, IF(L89="", NETWORKDAYS(J89,TODAY(),Hoja2!$A$2:$A$53), NETWORKDAYS(J89,L89,Hoja2!$A$2:$A$53) ) ) -> 1 | O89: 46105 | P89: 46105 | Q89: 24/03/2026 Se identifican posibles probelmas para uno de lasopciones del cargue, se realizan correcciones y se le indica al usuario que hay eventos que se están consumiendo con fallas en los datos y que según la necesidad puede que se deba realizar un cambio en el código | R89: true
A90: Alejandro | B90: REQ-30 | C90: Se necesita añadir lógica a respuesta de servicio con información complementaria | D90: Complementación de respuesta de servicio con distinta información de tracking | F90: FINALIZADO | G90: 100 | H90: =IF(OR(J90="",K90="",K90<J90),0,NETWORKDAYS(J90,K90,Hoja2!$A$2:$A$53)) -> 4 | I90: 46107 | J90: 46107 | K90: 46112 | L90: 46111 | M90: =IF(OR(J90="",AND(L90="",TODAY()<J90),AND(L90<>"",L90<J90)),0, IF(L90="", NETWORKDAYS(J90,TODAY(),Hoja2!$A$2:$A$53), NETWORKDAYS(J90,L90,Hoja2!$A$2:$A$53) ) ) -> 3 | O90: 46111 | Q90: 30/03/2026 Se realizan distintas pruebas internas y se crea manual de consumo 30/03/2026 Se indica al usuario la necesidad de ejecutar pruebas 10/04/2026 El usuario había estado realizando pruebas pero no se estaba reflejando la nueva estructura en la respuesta que ellos obtienen, se hizo verificación, conversación y se llegó a la conclusión de que el servicio que ellos tienen desplegado no está capturando bien la información 14/04/2026 Se realiza reunión para verificar pruebas nuevamente, se comunica que la necesidad ya es totalmente distinta de la que necesitaban y se procede con el análisis y cambios necesarios | R90: true
A91: Alejandro | B91: REQ-31 | C91: Debido a que en integración no existe forma de reenvío se debe de efectuar el cargue manual de cambioi de tareas. | D91: corrección de trámites que fallaron al realizar el consumo de mesa unificada OK | F91: FINALIZADO | G91: 100 | H91: =IF(OR(J91="",K91="",K91<J91),0,NETWORKDAYS(J91,K91,Hoja2!$A$2:$A$53)) -> 1 | I91: 46111 | J91: 46111 | K91: 46111 | L91: 46111 | M91: =IF(OR(J91="",AND(L91="",TODAY()<J91),AND(L91<>"",L91<J91)),0, IF(L91="", NETWORKDAYS(J91,TODAY(),Hoja2!$A$2:$A$53), NETWORKDAYS(J91,L91,Hoja2!$A$2:$A$53) ) ) -> 1 | O91: 46111 | P91: 46111 | Q91: 30/03/2026 Se realiza el cargue manual y se conversa sobre la necesidad de creación de un módulo que le permita al cliente realizar esas ejecuciones manuales | R91: true
A92: Alejandro | B92: REQ-29-2 | C92: Se han evidenciado que la necesidad del cliente corresponde a una ejecución distinta dentro de IMAGINE. Se necesita validar los distintos casos de actualización de estado y si es necesario modificar la lógica actual | D92: Identificación y corrección de servicios de consumo de bonos complejos en imagine | F92: FINALIZADO | G92: 100 | H92: =IF(OR(J92="",K92="",K92<J92),0,NETWORKDAYS(J92,K92,Hoja2!$A$2:$A$53)) -> 3 | I92: 46119 | J92: 46119 | K92: 46121 | L92: 46121 | M92: =IF(OR(J92="",AND(L92="",TODAY()<J92),AND(L92<>"",L92<J92)),0, IF(L92="", NETWORKDAYS(J92,TODAY(),Hoja2!$A$2:$A$53), NETWORKDAYS(J92,L92,Hoja2!$A$2:$A$53) ) ) -> 3 | O92: 46121 | P92: 46121 | Q92: 07/04/2026 Se realiza un acercamiento y se comparte lo que se ha realizado y trabajado correspondiente al tema. Se identifica que se debe de analizar otros casos y la ejecucipon de una propiedad que no se esta efectuando | R92: true
A93: Alejandro | B93: Interno-H16-20 | C93: actualización de módulo para la extracción de todos los registros de fileNEt | D93: Proyecto de validación automática de documentación de fileNet con integración en BPO e historia laboral | F93: FINALIZADO | G93: 100 | H93: =IF(OR(J93="",K93="",K93<J93),0,NETWORKDAYS(J93,K93,Hoja2!$A$2:$A$53)) -> 2 | I93: 46112 | J93: 46112 | K93: 46113 | L93: 46113 | M93: =IF(OR(J93="",AND(L93="",TODAY()<J93),AND(L93<>"",L93<J93)),0, IF(L93="", NETWORKDAYS(J93,TODAY(),Hoja2!$A$2:$A$53), NETWORKDAYS(J93,L93,Hoja2!$A$2:$A$53) ) ) -> 2 | O93: 46113 | P93: 46113 | Q93: 31/03/2026 Se identifica la necesidad de traer todos los registros y se desarrolla la funcionalidad para recrear la paginación de filenet y traer todos kis registros | R93: true
A94: Alejandro | B94: REQ-32 | C94: Realizar corrección del sistema para permitir la carga de documentos en el módulo | D94: Corrección de opción de cargue edictos | F94: FINALIZADO | G94: 100 | H94: =IF(OR(J94="",K94="",K94<J94),0,NETWORKDAYS(J94,K94,Hoja2!$A$2:$A$53)) -> 1 | I94: 46119 | J94: 46119 | K94: 46119 | L94: 46119 | M94: =IF(OR(J94="",AND(L94="",TODAY()<J94),AND(L94<>"",L94<J94)),0, IF(L94="", NETWORKDAYS(J94,TODAY(),Hoja2!$A$2:$A$53), NETWORKDAYS(J94,L94,Hoja2!$A$2:$A$53) ) ) -> 1 | O94: 46119 | P94: 46119 | Q94: 07/04/2026 Se realiza un acercamiento y se comparte lo que se ha realizado y trabajado correspondiente al tema. Se identifica que se debe de analizar otros casos y la ejecucipon de una propiedad que no se esta efectuando | R94: true
A95: Alejandro | B95: REQ-33 | C95: Identificar la situación y si es posible crear una solución desde IMAGINE, para controlar los errores en ADVANCE. Además corregir más de los 700 casos con error | D95: Casos cuyos eventos generados desde IMAGINE no replican en ADVANCE | F95: FINALIZADO | G95: 100 | H95: =IF(OR(J95="",K95="",K95<J95),0,NETWORKDAYS(J95,K95,Hoja2!$A$2:$A$53)) -> 1 | I95: 46125 | J95: 46125 | K95: 46125 | L95: 46128 | M95: =IF(OR(J95="",AND(L95="",TODAY()<J95),AND(L95<>"",L95<J95)),0, IF(L95="", NETWORKDAYS(J95,TODAY(),Hoja2!$A$2:$A$53), NETWORKDAYS(J95,L95,Hoja2!$A$2:$A$53) ) ) -> 4 | O95: 46125 | P95: 46125 | Q95: 13/04/2026 Se realizan cambios para que el sistema reintente hasta 3 veces y que guarde en memoria los archivos que son necesarios para la construcción de la petición del endPoint 14/04/2026 Se realizan las actualizaciones de estado para los 700 casos aúin con errores. Se identifica que no se esta guardando los archivos en cache porque hay errores en el momento de la descarga, se deshabilita la opción para evitar retrasos en las peticiones. Se indica que existe todavía errores 15/04/2026 Se identifican errores en otros métodos que usan el mismo consumo y se indica la novedad, anunciando un problema de intermitencia posiblemente causado por un bloqueo 16/04/2026 Se realiza una reunión con todos los equipos implicados y se levanta el bloqueo, además s ecomparten los archivos para que desde IMAGINE se pueda construir la petición, algo que en este momento está pendiente por hacer | R95: true
A96: Alejandro | B96: REQ-34 | C96: Corrección del reporte de análisis que está construyendo registros con cantidad de campos inconsistentes | D96: Corrección de reporte | F96: FINALIZADO | G96: 100 | H96: =IF(OR(J96="",K96="",K96<J96),0,NETWORKDAYS(J96,K96,Hoja2!$A$2:$A$53)) -> 1 | I96: 46129 | J96: 46129 | K96: 46129 | L96: 46129 | M96: =IF(OR(J96="",AND(L96="",TODAY()<J96),AND(L96<>"",L96<J96)),0, IF(L96="", NETWORKDAYS(J96,TODAY(),Hoja2!$A$2:$A$53), NETWORKDAYS(J96,L96,Hoja2!$A$2:$A$53) ) ) -> 1 | O96: 46129 | P96: 46129 | R96: true
A97: Alejandro | B97: REQ-30-2 | C97: Se necesita añadir lógica a respuesta de servicio con información complementaria | D97: Complementación de respuesta de servicio con distinta información de tracking | F97: FINALIZADO | G97: 100 | H97: =IF(OR(J97="",K97="",K97<J97),0,NETWORKDAYS(J97,K97,Hoja2!$A$2:$A$53)) -> 2 | I97: 46126 | J97: 46128 | K97: 46129 | L97: 46129 | M97: =IF(OR(J97="",AND(L97="",TODAY()<J97),AND(L97<>"",L97<J97)),0, IF(L97="", NETWORKDAYS(J97,TODAY(),Hoja2!$A$2:$A$53), NETWORKDAYS(J97,L97,Hoja2!$A$2:$A$53) ) ) -> 2 | O97: 46129 | Q97: 17/04/2026 Se realiza el cambio y con diferencia a lo que se había logrado, es que la información ya no se captura de un punto sino que se debe de modificar cada uno de los llamados a la operación en distintos archivos de distintos módulos. Se indica la necesidad de realizar bastantes pruebas porque fueron muchos los cambios 19/05/2026 Termino pruebas junto con el cliente y se está a la espera de que ellos terminen su desarrollo para pasar a producción | R97: true
A98: Alejandro | B98: REQ-35 | C98: Se está bloqueando el flujo normal en la gestión de un trámite luego de cerrar una bandeja, se necesita el análisis y su corrección | D98: Análisis y corrección al momento de realziar gestión en una bandeja | F98: FINALIZADO | G98: 100 | H98: =IF(OR(J98="",K98="",K98<J98),0,NETWORKDAYS(J98,K98,Hoja2!$A$2:$A$53)) -> 2 | I98: 46125 | J98: 46127 | K98: 46128 | L98: 46128 | M98: =IF(OR(J98="",AND(L98="",TODAY()<J98),AND(L98<>"",L98<J98)),0, IF(L98="", NETWORKDAYS(J98,TODAY(),Hoja2!$A$2:$A$53), NETWORKDAYS(J98,L98,Hoja2!$A$2:$A$53) ) ) -> 2 | O98: 46128 | P98: 46128 | Q98: 15/04/2026 Se realiza reunión con personal encargado de la gestión de la bandeja para identificar el flujo. Se analiza el código y se empieza a trabajar en su corrección 16/04/2026 Se entrega la corrección y se analiza para 3 casos si el flujo volvío con normalidad 17/04/2026 Se corrigen los casos que presentaron el error | R98: true
A99: Alejandro | B99: REQ-36 | C99: Análisis y modificación de servicio para adiccionar aperturas de distintas tareas | D99: Modificación de servicio para agregar la apertura de distintas tareas | F99: FINALIZADO | G99: 100 | H99: =IF(OR(J99="",K99="",K99<J99),0,NETWORKDAYS(J99,K99,Hoja2!$A$2:$A$53)) -> 2 | I99: 46133 | J99: 46134 | K99: 46135 | L99: 46157 | M99: =IF(OR(J99="",AND(L99="",TODAY()<J99),AND(L99<>"",L99<J99)),0, IF(L99="", NETWORKDAYS(J99,TODAY(),Hoja2!$A$2:$A$53), NETWORKDAYS(J99,L99,Hoja2!$A$2:$A$53) ) ) -> 17 | O99: 46141 | P99: 46157 | Q99: 22/04/2026 Se trabajo con la información suministrada asociada al servicio, pero no se encontró lógica para la apertura de las tareas necesitadas. Se requirio nueva información asociada 27/04/2026 Se había estado parado el desarrollo pero ya se facilitó el evento para su análisis 28/04/2026 El evento que se facilitó no cuadra con la necesidad. Se debe de verificar si es otro proceso el que se hace cargo 29/04/2026 Se verifica con el usuario, quien indica más epecificamente el funcionamiento y se modifica el ambiente de pruebas para que hagan pruebas con el añadido 15/05/2026 Se recibe mensaje para el paso a producción,y se ejecuta esa tarea | R99: true
A100: Alejandro | B100: REQ-30-3 | C100: Se requiere la realización de un script que permita la creación de un archivo que cargue disntinta información necesitada por el cliente | D100: Complementación de respuesta de servicio con distinta información de tracking | F100: FINALIZADO | G100: 100 | H100: =IF(OR(J100="",K100="",K100<J100),0,NETWORKDAYS(J100,K100,Hoja2!$A$2:$A$53)) -> 3 | I100: 46133 | J100: 46134 | K100: 46136 | L100: 46139 | M100: =IF(OR(J100="",AND(L100="",TODAY()<J100),AND(L100<>"",L100<J100)),0, IF(L100="", NETWORKDAYS(J100,TODAY(),Hoja2!$A$2:$A$53), NETWORKDAYS(J100,L100,Hoja2!$A$2:$A$53) ) ) -> 4 | O100: 46139 | Q100: 22/04/2026 Se suministra la información requerida para la evaluación del desarrollo. Inofrmación asociada a los trámites y su estado, a manera de reporte base del final requerido 23/04/2026 Se me facilita todos los campos que requieren y se empieza el desarrollo 27/04/2026 Se termina el desarrollo. Se espera hasta que se terminen de hacer las primeras pruebas para la primer parte del desarrollo para seguir con estas 19/05/2026 Termino pruebas junto con el cliente y se está a la espera de que ellos terminen su desarrollo para pasar a producción | R100: true
A101: Alejandro | B101: REQ-37 | C101: Análisis de casos de envío de evento de normalización y solución general para quienes generan inconsistencias | D101: Solución de casos y creación de script para envío automático de evento | F101: FINALIZADO | G101: 100 | H101: =IF(OR(J101="",K101="",K101<J101),0,NETWORKDAYS(J101,K101,Hoja2!$A$2:$A$53)) -> 2 | I101: 46139 | J101: 46139 | K101: 46140 | L101: 46140 | M101: =IF(OR(J101="",AND(L101="",TODAY()<J101),AND(L101<>"",L101<J101)),0, IF(L101="", NETWORKDAYS(J101,TODAY(),Hoja2!$A$2:$A$53), NETWORKDAYS(J101,L101,Hoja2!$A$2:$A$53) ) ) -> 2 | O101: 46140 | P101: 46140 | Q101: 27/04/2026 Se analiza y corrigen los casos 28/04/2026 Se construye solución apartir del análisi previo para envío autoático | R101: true
...

Sheet FINALIZADOS  despues de actu, i
A1: Asignado a | B1: ID REQ | C1: Requerimiento | D1: Descripcion req | E1: Actividad | F1: ESTADO | G1: % AVANCE | H1: dias estimados | I1: F.Asignado | J1: Fecha inicio | K1: F. estimada de entrega | L1: Finalizado | M1: Dias | N1: FECHA PASO A TEST | O1: FECHA PASO A PRODUCCION | P1: OBSERVACIONES
A2: Alejandro Cardona Ocampo | B2: REQ-1-1 | C2: Tratamiento especial al radicar trámites de vejez | D2: Se está a la espera de la solicitud formal por parte del cliente | E2: Revision de flujo y código | F2: FINALIZADO | G2: 1 | H2: 1 | I2: 45826 | J2: 45827 | K2: 45827 | L2: 45827 | M2: =IF(ISBLANK(L2), NETWORKDAYS(J2, TODAY(),Hoja2!$A$1:$A$18), NETWORKDAYS(J2, L2, Hoja2!$A$1:$A$18)) -> 1 | P2: 19/06/2025 Se identifico el código a intervenir y con el que trabajar en el requerimiento
A3: Alejandro Cardona Ocampo | B3: REQ-1-2 | C3: Tratamiento especial al radicar trámites de vejez | D3: Se está a la espera de la solicitud formal por parte del cliente | E3: Reunión con las partes interesadas para identificar los inputs de trabajo | F3: FINALIZADO | G3: 1 | H3: 1 | I3: 45827 | J3: 45832 | K3: 45832 | L3: 45832 | M3: =IF(ISBLANK(L3), NETWORKDAYS(J3, TODAY(),Hoja2!$A$1:$A$18), NETWORKDAYS(J3, L3, Hoja2!$A$1:$A$18)) -> 1 | P3: 24/06/2025: Se reune con las partes interesadas, se identifican los requisitos, necesidades y material de trabajo, pero se suspende el requerimiento hasta nuevo aviso
A4: Alejandro Cardona Ocampo | B4: REQ-2-1 | C4: Creación de reporte de AUF para identificación de pagos, creación de opción de cargue masivo para cambio de bandejas y creación de opción de consulta de pagos | D4: Creación de Herramientas adicionales para el tratamiento de información y flujo en el módulo de auxilios funerarios | E4: Creación de script para generar reporte de pagos de auxilios funerarios y la vista para su consumo | F4: FINALIZADO | G4: 1 | H4: 1 | I4: 45832 | J4: 45839 | K4: 45833 | L4: 45839 | M4: =IF(ISBLANK(L4), NETWORKDAYS(J4, TODAY(),Hoja2!$A$1:$A$18), NETWORKDAYS(J4, L4, Hoja2!$A$1:$A$18)) -> 1 | N4: 45839 | O4: 45853 | P4: 24/06/2025: Se realiza reunión para la identificación de nuevos requisitos 01/07/2025: Se realiza vista para el consumo y parte de la lóigica para la creación del reporte 01/07/2025: Se está a la espera de validar la información del reporte debido a que se nos envía 2 reportes con estructuras distintas 09/07/2025: Se realiza reunión con las partes interesadas y se acuerda en agregar información obtenida de distintas fuentes al formulario 15/07/2025: Se realizaron aún más cambios propuestos por el usuario y correcciones de fallas en el funcionamiento 15/07/2025: Se pasa a producción
A5: Alejandro Cardona Ocampo | B5: REQ-2-2 | C5: Creación de reporte de AUF para identificación de pagos, creación de opción de cargue masivo para cambio de bandejas y creación de opción de consulta de pagos | D5: Creación de Herramientas adicionales para el tratamiento de información y flujo en el módulo de auxilios funerarios | E5: Creación de script para generar opción de consulta de pagos | F5: FINALIZADO | G5: 1 | H5: 2 | I5: 45839 | J5: 45839 | K5: 45840 | L5: 45848 | M5: =IF(ISBLANK(L5), NETWORKDAYS(J5, TODAY(),Hoja2!$A$1:$A$18), NETWORKDAYS(J5, L5, Hoja2!$A$1:$A$18)) -> 8 | N5: 45848 | O5: 45853 | P5: 09/07/2025: Se Había pospuesto la creación del código y se retoma el día 8 10/07/2025: Se termina el desarrollo y las pruebas e 10 con las modificaciones indicadas en la reunión 15/07/2025: Se realizaron aún más cambios propuestos por el usuario y correcciones de fallas en el funcionamiento 15/07/2025: Se pasa a producción
A6: Alejandro Cardona Ocampo | B6: REQ-2-3 | C6: Creación de reporte de AUF para identificación de pagos, creación de opción de cargue masivo para cambio de bandejas y creación de opción de consulta de pagos | D6: Creación de Herramientas adicionales para el tratamiento de información y flujo en el módulo de auxilios funerarios | E6: Creación de script para generar opción en el de cargue y procesado de datos | F6: FINALIZADO | G6: 1 | H6: 1 | I6: 45839 | J6: 45840 | K6: 45840 | L6: 45840 | M6: =IF(ISBLANK(L6), NETWORKDAYS(J6, TODAY(),Hoja2!$A$1:$A$18), NETWORKDAYS(J6, L6, Hoja2!$A$1:$A$18)) -> 1 | N6: 45840 | O6: 45853 | P6: 01/07/2025: Se realiza reunión para la identificación de nuevos requisitos 02/07/2025: Se Crea vista y lógica para el cargue de documentos y procesamiento de datos 02/07/2025: Se realizan pruebas de funcionamiento y se esta a la espera de que el cliente realice pruebas 15/07/2025: Se realizaron aún más cambios propuestos por el usuario y correcciones de fallas en el funcionamiento 15/07/2025: Se pasa a producción
A7: Alejandro Cardona Ocampo | B7: REQ-2-4 | C7: Creación de reporte de AUF para identificación de pagos, creación de opción de cargue masivo para cambio de bandejas y creación de opción de consulta de pagos | D7: Creación de Herramientas adicionales para el tratamiento de información y flujo en el módulo de auxilios funerarios | E7: Modificación de script para generar reporte de pagos de auxilios funerarios agregando distinta información y lógica para su construcción | F7: FINALIZADO | G7: 1 | H7: 1 | I7: 45847 | J7: 45847 | K7: 45848 | L7: 45848 | M7: =IF(ISBLANK(L7), NETWORKDAYS(J7, TODAY(),Hoja2!$A$1:$A$18), NETWORKDAYS(J7, L7, Hoja2!$A$1:$A$18)) -> 2 | N7: 45848 | O7: 45853 | P7: 10/07/2025: Se termina el desarrollo y las pruebas. Se está en espera del visto bueno para pasar a producción 14/07/2025: Se identifican a través de las pruebas de usuarios modificaciones y añadidos por hacer. Se realizan los debidos cambios y se entrega al cliente resultados para su validación 15/07/2025: Se realizaron aún más cambios propuestos por el usuario y correcciones de fallas en el funcionamiento 15/07/2025: Se pasa a producción
A8: Alejandro Cardona Ocampo | B8: REQ-3-1 | C8: Cambios técnicos en aplicativo imagine para proceso de mesa de control documental solicitud de pensión | D8: desarrollo de la mesa de validación documental con inteligencia artificial en Filenet que implica las siguientees actividades: Se debe retirar la bandeja de imagine Validación Mesa de Control Unificada ya que la validación de documentos se realizará a través de filenet. Dado que se requiere conservar otras funciones adicionales a la bandeja de validación en el software de imagine que depende de la validación documental, se les notificara a través del siguiente web service cada vez que una solicitud documental (Paquete de documentos relacionado a los diferentes riesgos) haya finalizado el proceso de validación: | E8: Reunión con las partes interesadas para identificación de requerimientos | F8: FINALIZADO | G8: 1 | H8: 1 | I8: 45832 | J8: 45832 | K8: 45832 | L8: 45832 | M8: =IF(ISBLANK(L8), NETWORKDAYS(J8, TODAY(),Hoja2!$A$1:$A$18), NETWORKDAYS(J8, L8, Hoja2!$A$1:$A$18)) -> 1 | P8: 24/06/2025: Se realiza reunión para realización de pruebas e identificación de requerimientos
A9: Alejandro Cardona Ocampo | B9: REQ-4-1 | C9: Migración de registros para tipos documentales gabinete 2 | E9: Identificación y failitación al cliente de los tipos documnetales | F9: FINALIZADO | G9: 1 | H9: 1 | I9: 45847 | J9: 45847 | K9: 45847 | L9: 45847 | M9: =IF(ISBLANK(L9), NETWORKDAYS(J9, TODAY(),Hoja2!$A$1:$A$18), NETWORKDAYS(J9, L9, Hoja2!$A$1:$A$18)) -> 1 | N9: 45847 | P9: 09/07/2025: Se indica al cliente los distintos tipos de documentación del gabinete 2
A10: Alejandro Cardona Ocampo | B10: REQ-5-1 | C10: Proyecto relacionado con las inconsistencias norma 2381 | E10: Identificación de método de consumo y generación de informe de resultados | F10: FINALIZADO | G10: 1 | H10: 1 | I10: 45849 | J10: 45849 | K10: 45849 | L10: 45849 | M10: =IF(ISBLANK(L10), NETWORKDAYS(J10, TODAY(),Hoja2!$A$1:$A$18), NETWORKDAYS(J10, L10, Hoja2!$A$1:$A$18)) -> 1 | P10: 09/07/2025: Se identifica los métodos de consumo posibles, su funcionamiento y se plasma junto con las respuestas a las dudas del cliente en un informe
A11: Alejandro Cardona Ocampo | B11: REQ-3-3 | C11: Cambios técnicos en aplicativo imagine para proceso de mesa de control documental solicitud de pensión | D11: desarrollo de la mesa de validación documental con inteligencia artificial en Filenet que implica las siguientees actividades: Se debe retirar la bandeja de imagine Validación Mesa de Control Unificada ya que la validación de documentos se realizará a través de filenet. Dado que se requiere conservar otras funciones adicionales a la bandeja de validación en el software de imagine que depende de la validación documental, se les notificara a través del siguiente web service cada vez que una solicitud documental (Paquete de documentos relacionado a los diferentes riesgos) haya finalizado el proceso de validación: | E11: Creación de otro método para consumo necesario para tratamiento de trámites de pruebas de protección | F11: FINALIZADO | G11: 1 | H11: 1 | I11: 45854 | J11: 45854 | K11: 45854 | L11: 45854 | M11: =IF(ISBLANK(L11), NETWORKDAYS(J11, TODAY(),Hoja2!$A$1:$A$18), NETWORKDAYS(J11, L11, Hoja2!$A$1:$A$18)) -> 1 | N11: 45854 | P11: 16/07/2025 Se realiza nuevo método de consumo para cerrar trámites con procesos documentales abiertos y asi, protección pueda ser pruebas de cierre de mesa unificada documental sin necesidad de tener procesos abiertos y con documentos
A12: Alejandro Cardona Ocampo | B12: REQ-6-1 | C12: Análisis y corrección de procesos de cargue e identificación de pagos de tipo de riesgo AUX | D12: Se identificaron errores de procesos de cargue que no están identificando correctamente el estado de un trámite en la bandeja de AUX. | E12: Análisis de la situación en Imagine | F12: FINALIZADO | G12: 1 | H12: 5 | I12: 45855 | J12: 45856 | K12: 45862 | L12: 45861 | M12: =IF(ISBLANK(K12), NETWORKDAYS(J12, TODAY(),Hoja2!$A$1:$A$18), NETWORKDAYS(J12, K12, Hoja2!$A$1:$A$18)) -> 5 | N12: 45861 | P12: 17/07/2025 Se realiza reunión para identificar las inconsistencias. Se está a la espera de datos de prueba y de análisis de los procesos para la verificación de los mismos 21/07/2025 Se Identificaron lógicas erroneas en el código que se corrigieron y otras lógicas de negocio que no, debido a que primero se deben de socializar los resultados antes de poder pensar en una solución 23/07/2025 Se genera informe de la situación, recomendaciones y procesos a seguir para brindar solución 23/07/2025 Se pasa los cambios que corregian errores a producción
A13: Alejandro Cardona Ocampo | B13: REQ-7-1 | C13: Mejoras en los modulos de Imagine | D13: Solicitud de protección para mejoras IMAGINE en el módulo de Auxilios funerarios | E13: Reunión con las partes interesadas e identificación de requerimientos | F13: FINALIZADO | G13: 1 | H13: 1 | I13: 45860 | J13: 45860 | K13: 45860 | L13: 45860 | M13: =IF(ISBLANK(L13), NETWORKDAYS(J13, TODAY(),Hoja2!$A$1:$A$18), NETWORKDAYS(J13, L13, Hoja2!$A$1:$A$18)) -> 1 | P13: 22/07/2025 Se realiza reunión para la identificación de requerimientos y necesidades del cliente 23/07/2025 Se comparte archivo de la solicitud
A14: Alejandro Cardona Ocampo | B14: Interno-H8 | C14: Automatización y migración de lógica a python | E14: Ejecuci[on y correcci[on de script y descarga de recursos necesarios para el entrenamiento del modelo de clasificaci[on | F14: FINALIZADO | G14: 1 | H14: 2 | I14: 45863 | J14: 45863 | K14: 45866 | L14: 45866 | M14: =IF(ISBLANK(L14), NETWORKDAYS(J14, TODAY(),Hoja2!$A$1:$A$18), NETWORKDAYS(J14, L14, Hoja2!$A$1:$A$18)) -> 2 | P14: 25/07/2025 Se realiza la descarga de 80000 archivos no sin antes reestructurar el script y acoplarlo para no sobrecargar los procesos y que funcionara 25/07/2025 Se empieza proceso de carga en local, todo esto debido a que no se puede generar el modelo de entrenamiento en el servidor por capacidad 25/07/2025 Se termina el proceso de carga en local

Sheet Hoja2
A1: 45292 | B1: Año Nuevo
A2: 45299 | B2: Día de los Reyes Magos
A3: 45376 | B3: Día de San José
A4: 45379 | B4: Jueves Santo (Semana Santa)
A5: 45380 | B5: Viernes Santo (Semana Santa)
A6: 45413 | B6: Día del Trabajo
A7: 45425 | B7: Día de la Ascensión
A8: 45446 | B8: Corpus Christi
A9: 45453 | B9: Sagrado Corazón
A10: 45474 | B10: San Pedro y San Pablo
A11: 45493 | B11: Día de la Independencia
A12: 45511 | B12: Batalla de Boyacá
... A53: 46381 | B53: Navidad

Sheet ASISTENCIA
A1: ASISTENCIA DAYLI
A3: INTEGRANTE | B3: 45596 | C3: 45597 | D3: 45601 | E3: 45602 | F3: 45603 | G3: 45604 | H3: 45608 | I3: 45609 | J3: 45610 | K3: 45611 | L3: 45614 | M3: 45615 | N3: 45616 | O3: 45617 | P3: 45618 | Q3: 45621 | R3: 45622 | S3: 45623 | T3: 45624 | U3: 45625 | V3: 45628 | W3: 45629 | X3: 45630 | Y3: 45631 | Z3: 45632 | AA3: 45635 | AB3: 45636 | AC3: 45637 | AD3: 45638 | AE3: 45639 | AF3: 45642 | AG3: 45643 | AH3: 45644 | AI3: 45645 | AJ3: 45646 | AK3: 45649 | AL3: 45650 | AM3: 45652 | AN3: 45653 | AO3: 45656 | AP3: 45656 | AQ3: 45664 | AR3: 45665 | AS3: 45666 | AT3: 45667 | AU3: 45670 | AV3: 45671 | AW3: 45672 | AX3: 45673 | AY3: 45674 | AZ3: 45677 | BA3: 45678 | BB3: 45679 | BC3: 45680 | BD3: 45681 | BE3: 45684 | BF3: 45685 | BG3: 45686 | BH3: 45687 | BI3: 45688 | BJ3: 45691 | BK3: 45692 | BL3: 45693 | BM3: 45694 | BN3: 45695 | BO3: 45698 | BP3: 45699 | BQ3: 45700 | BR3: 45701 | BS3: 45702 | BT3: 45705 | BU3: 45706 | BV3: 45707 | BW3: 45708 | BX3: 45709 | BY3: 45712 | BZ3: 45713 | CA3: 45714 | CB3: 45715 | CC3: 45716 | CD3: 45719 | CE3: 45720 | CF3: 45721 | CG3: 45722 | CH3: 45723 | CI3: 45726 | CJ3: 45727 | CK3: 45728 | CL3: 45729 | CM3: 45730 | CN3: 45733 | CO3: 45734 | CP3: 45735 | CQ3: 45736 | CR3: 45737 | CS3: 45741
A4: DANILO RAMIREZ | B4: SI | C4: no (Dia de la familia) | D4: SI | E4: SI | F4: SI | G4: SI | H4: SI | I4: SI | J4: SI | K4: SI | L4: SI | M4: SI | N4: SI | O4: No hubo sesion | P4: SI | Q4: SI | R4: SI | S4: SI | T4: SI | U4: NO | V4: SI | W4: SI | X4: SI | Y4: SI | Z4: SI | AA4: SI | AB4: SI | AC4: SI | AD4: SI | AE4: No hubo sesión | AF4: SI | AG4: SI | AH4: SI | AI4: SI | AJ4: SI | AK4: SI | AL4: NO HUBO SESION | AM4: NO | AN4: NO | AO4: SI | AP4: NO HAY SESION | AQ4: SI | AR4: SI | AS4: NO HAY SESION | AT4: SI | AU4: SI | AV4: SI | AW4: SI | AX4: SI | AY4: NO HAY SESION | AZ4: SI | BA4: SI | BB4: SI | BC4: SI | BD4: SI | BE4: SI | BF4: SI | BG4: SI | BH4: SI | BI4: SI | BJ4: NO HAY SESION | BK4: Vacaciones | BL4: Vacaciones | BM4: Vacaciones | BN4: Vacaciones | BO4: Vacaciones | BP4: Vacaciones | BQ4: Vacaciones | BR4: SI | BS4: SI | BT4: SI | BU4: SI | BV4: SI | BW4: SI | BX4: SI | BY4: SI | BZ4: SI | CA4: SI | CB4: SI | CC4: SI | CD4: SI | CE4: SI | CF4: SI | CI4: No hobo sesion por caida de los sitios. | CS4: SI
A5: JAIRO NIÑO | B5: SI | C5: SI | D5: SI | E5: SI | F5: SI | G5: SI | H5: SI | I5: SI | J5: SI | K5: SI | L5: Vacaciones | M5: Vacaciones | N5: Vacaciones | O5: Vacaciones | P5: Vacaciones | Q5: SI | R5: SI | S5: SI | T5: SI | U5: SI | V5: SI | W5: SI | X5: SI | Y5: SI | Z5: SI | AA5: SI | AB5: SI | AC5: SI | AD5: SI | AF5: SI | AG5: SI | AH5: SI | AI5: SI | AJ5: SI | AK5: SI | AM5: SI | AN5: SI | AO5: SI | AQ5: Vacaciones | AR5: Vacaciones | AT5: Vacaciones | AU5: Vacaciones | AV5: Vacaciones | AW5: Vacaciones | AX5: Vacaciones | AZ5: Vacaciones | BA5: SI | BB5: SI | BC5: SI | BD5: SI | BE5: SI | BF5: SI | BG5: SI | BH5: SI | BI5: SI | BK5: SI | BL5: SI | BM5: SI | BN5: SI | BO5: SI | BP5: SI | BQ5: SI | BR5: SI | BS5: SI | BT5: SI | BU5: SI | BV5: SI | BW5: SI | BX5: SI | BY5: SI | BZ5: SI | CA5: SI | CB5: SI | CC5: SI | CD5: SI | CE5: SI | CF5: SI | CS5: SI
A6: JESUS PEÑA | B6: SI | C6: SI | D6: SI | E6: SI | F6: SI | G6: SI | H6: SI | I6: SI | J6: SI | K6: Dia de la familia | L6: SI | M6: SI | N6: SI | O6: No hubo sesion | P6: SI | Q6: SI | R6: SI | S6: SI | T6: SI | U6: SI | V6: SI | W6: SI | X6: SI | Y6: SI | Z6: SI | AA6: SI | AB6: SI | AC6: SI | AD6: SI | AF6: SI | AG6: SI | AH6: SI | AI6: SI | AJ6: SI | AK6: SI | AM6: SI | AN6: SI | AO6: SI | AQ6: SI | AR6: SI | AT6: SI | AU6: SI | AV6: SI | AW6: SI | AX6: SI | AZ6: SI | BA6: SI | BB6: SI | BC6: SI | BD6: SI | BE6: SI | BF6: SI | BG6: SI | BH6: SI | BI6: SI | BK6: SI | BL6: SI | BM6: Falla electrica | BN6: SI | BO6: SI | BP6: SI | BQ6: SI | BR6: SI | BS6: SI | BT6: SI | BU6: SI | BV6: SI | BW6: SI | BX6: SI | BY6: SI | BZ6: SI | CA6: SI | CB6: SI | CC6: SI | CD6: SI | CE6: SI | CF6: SI | CS6: SI
A7: LUIS BEDOYA | B7: SI | C7: SI | D7: SI | E7: SI | F7: SI | G7: SI | H7: SI | I7: SI | J7: SI | K7: SI | L7: Dia de la familia | M7: SI | N7: SI | O7: No hubo sesion | P7: SI | Q7: SI | R7: SI | S7: SI | T7: SI | U7: SIN INTERNET | V7: SI | W7: SI | X7: SI | Y7: SI | Z7: NO | AA7: SI | AB7: SI | AC7: SI | AD7: SI | AF7: SI | AG7: SI | AH7: SI | AI7: SI | AJ7: SI | AK7: SI | AM7: SI | AN7: SI | AO7: SI | AQ7: SI | AR7: SI | AT7: SI | AU7: NO | AV7: SI | AW7: SI | AX7: SI | AZ7: SI | BA7: SI | BB7: SI | BC7: SI | BD7: SI | BE7: SI | BF7: SI | BG7: SI | BH7: SI | BI7: SI | BK7: SI | BL7: SI | BM7: SI | BN7: SI | BO7: NO | BU7: SI | BV7: SI | BW7: SI | BX7: SI
A8: JOHAN QUICENO | B8: SI | C8: SI | D8: SI | E8: SI | F8: SI | G8: SI | H8: SI | I8: SI | J8: SI | K8: SI | L8: NO | M8: SI | N8: SI | O8: No hubo sesion | P8: SI | Q8: SI | R8: SI | S8: SI | T8: SI | U8: SI | V8: SI | W8: Permiso | X8: SI | Y8: SI | Z8: SI | AA8: SI | AB8: NO | AC8: SI | AD8: SI | AF8: SI | AG8: SI | AH8: SI | AI8: SI | AJ8: SI | AK8: SI | AM8: SI | AN8: NO | AO8: SI | AQ8: SI | AR8: SI | AT8: SI | AU8: SI | AV8: SI | AW8: SI | AX8: SI | AZ8: SI | BA8: SI | BB8: SI | BC8: SI | BD8: SI | BE8: SI | BF8: SI | BG8: sin internet | BH8: SI | BI8: SI | BK8: SI | BL8: SI | BM8: SI | BN8: SI | BO8: SI | BP8: SI | BQ8: SI | BR8: SI | BS8: SI | BT8: SI | BU8: SI | BV8: SI | BW8: SI | BX8: TRABAJO HASTA HOY
A9: FABIO FORERO | B9: SI | C9: SI | D9: SI | E9: SI | F9: SI | G9: SI | H9: SI | I9: SI | J9: SI | K9: SI | L9: SI | M9: SI | N9: SI | O9: Dia de la familia | P9: SI | Q9: SI | R9: SI | S9: SI | T9: SI | U9: SI | V9: SI | W9: SI | X9: SI | Y9: SI | Z9: SI | AA9: SI | AB9: SI | AC9: SI | AD9: SI | AF9: SI | AG9: SI | AH9: SI | AI9: SI | AJ9: SI | AK9: SI | AM9: SI | AN9: SI | AO9: SI | AQ9: SI | AR9: SI | AT9: SI | AU9: SI | AV9: SI | AW9: SI | AX9: SI | AZ9: SI | BA9: SI | BB9: SI | BC9: SI | BD9: SI | BE9: SI | BF9: SI | BG9: SI | BH9: SI | BI9: SI | BK9: SI | BL9: SI | BM9: SI | BN9: SI | BO9: SI | BP9: SI | BQ9: SI | BR9: SI | BS9: SI | BT9: SI | BU9: SI | BV9: SI | BW9: SI | BX9: SI | BY9: SI | BZ9: SI | CA9: SI | CB9: SI | CC9: SI | CD9: SI | CE9: SI | CF9: SI | CS9: SI
A10: JENRY HENAO | B10: SI | C10: SI | D10: SI | E10: SI | F10: SI | G10: SI | H10: SI | I10: NO | J10: SI | K10: NO | L10: SI | M10: SI | N10: NO | O10: No hubo sesion | P10: NO | Q10: NO | R10: SI | S10: SI | T10: SI | U10: NO | V10: SI | W10: SI | X10: SI | Y10: SI | Z10: SI | AA10: SI | AB10: SI | AC10: SI | AD10: SI | AF10: SI | AG10: SI | AH10: SI | AI10: SI | AJ10: SI | AK10: NO | AM10: NO | AN10: SI | AO10: SI | AQ10: SI | AR10: SI | AT10: SI | AU10: SI | AV10: SI | AW10: SI | AX10: SI | AZ10: SI | BA10: NO | BB10: NO | BC10: NO | BD10: NO | BE10: NO | BF10: SI | BG10: SI | BH10: SI | BI10: SI | BK10: SI | BL10: SI | BM10: SI | BN10: SI | BO10: SI | BP10: SI | BQ10: SI | BR10: SI | BS10: SI | BT10: SI | BU10: SI | BV10: SI | BW10: NO | BX10: SI | BY10: SI | BZ10: SI | CA10: SI | CB10: SI | CC10: SI | CD10: SI | CE10: SI | CF10: SI | CS10: SI
A11: LIYIBET PEREZ | B11: SI | C11: SI | D11: SI | E11: SI | F11: SI | G11: SI | H11: SI | I11: SI | J11: nomina | K11: NO | L11: SI | M11: NO | N11: SI | O11: No hubo sesion | P11: SI | Q11: SI | R11: SI | S11: NO | T11: NO | U11: NO | V11: SI | W11: SI | X11: SI | Y11: SI | Z11: SI | AA11: SI | AB11: SI | AC11: SI | AD11: NO | AF11: SI | AG11: SI | AH11: SI | AI11: SI | AJ11: SI | AK11: SI | AM11: SI | AN11: SI | AO11: SI | AQ11: SI | AR11: SI | AT11: SI | AU11: NO | AV11: NO | AW11: SI | AX11: SI | AZ11: NO | BA11: SI | BB11: SI | BC11: SI | BD11: SI | BE11: NO | BF11: NO | BG11: NO | BH11: SI | BI11: SI | BK11: SI | BL11: SI | BM11: SI | BN11: SI | BO11: NO | BP11: SI | BQ11: SI | BR11: NOMINA | BS11: SI | BT11: SI | BU11: SI | BV11: SI | BW11: SI | BX11: SI | BY11: SI | BZ11: SI | CA11: SI | CB11: NO | CC11: NO | CD11: SI | CE11: SI | CF11: SI | CS11: SI
A12: WILSON APONTE | B12: SI | C12: NO | D12: SI | E12: SI | F12: NO | G12: NO | H12: SI | I12: NO | J12: SI | K12: NO | L12: SI | M12: NO | N12: NO | O12: No hubo sesion | P12: SI | Q12: NO | R12: NO | S12: NO | T12: NO | U12: NO | V12: NO | W12: SI | X12: NO | Y12: NO | Z12: SI | AA12: NO | AB12: NO | AC12: SI | AD12: NO | AF12: NO | AG12: NO | AH12: NO | AI12: NO | AJ12: SI | AK12: SI | AM12: NO | AN12: NO | AO12: NO | AQ12: NO | AR12: NO | AT12: NO | AU12: NO | AV12: SI | AW12: SI | AX12: NO | AZ12: NO | BA12: NO | BB12: NO | BC12: SI | BD12: NO | BE12: SI | BF12: NO | BG12: NO | BH12: SI | BI12: NO | BK12: NO | BL12: NO | BM12: SI | BN12: NO | BO12: NO | BP12: NO | BQ12: NO | BR12: SI | BS12: NO | BT12: NO | BU12: SI | BV12: SI | BW12: NO | BX12: NO | BY12: SI | BZ12: NO | CA12: NO | CB12: SI | CC12: NO | CD12: NO | CE12: SI | CF12: NO | CS12: NO
A13: JOHN ROLON | B13: SI | C13: NO | D13: NO | E13: NO | F13: NO | G13: NO | H13: NO | I13: NO | J13: SI | K13: NO | L13: NO | M13: SI | N13: NO | O13: No hubo sesion | P13: NO | Q13: NO | R13: NO | S13: NO | T13: NO | U13: NO | V13: SI | W13: NO | X13: NO | Y13: NO | Z13: NO | AA13: NO | AB13: NO | AC13: SI | AD13: NO | AF13: NO | AG13: NO | AH13: NO | AI13: SI | AJ13: NO | AK13: NO | AM13: NO | AN13: NO | AO13: NO | AQ13: NO | AR13: NO | AT13: NO | AU13: NO | AV13: NO | AW13: NO | AX13: NO | AZ13: NO | BA13: NO | BB13: NO | BC13: NO | BD13: NO | BE13: NO | BF13: NO | BG13: NO | BH13: NO | BI13: NO | BK13: NO | BL13: NO | BM13: NO | BN13: NO | BO13: NO | BP13: NO | BQ13: NO | BR13: NOMINA | BS13: NO | BT13: NO | BU13: NO | BV13: NO | BW13: NO | BX13: NO | BY13: NO | BZ13: NO | CA13: NO | CB13: NO | CC13: NO | CD13: SI | CE13: SI | CF13: SI | CS13: NO

Sheet pruebas i
A1: Asignado | B1: Requerimiento | C1: Actividad | D1: ESTADO | E1: F.Asignado | F1: Fecha inicio | G1: F. estimada de entrega | H1: Finalizado | I1: Dias | J1: TEST | K1: PRODUCCION | L1: Observacion
A2: LUIS BAYONA | B2: Encolar informe de efectividad de salud | D2: FINALIZADO | E2: 45567 | F2: 45567 | G2: 45568 | H2: 45569 | I2: =IF(ISBLANK(H2), NETWORKDAYS(F2, TODAY(),Hoja2!$A$1:$A$18), NETWORKDAYS(F2, H2, Hoja2!$A$1:$A$18)) -> 3 | J2: 45572 | L2: *02/10/2024 inicia gestion. *03/10/2024 Finalizar la consulta y realizar pruebas * 07/10/2024 desarrollo en test para pruebas
A3: FABIO FORERO | B3: VULNERABILIDADES BAJAS | C3: Web Server Allows Password Auto-Completion | D3: PENDIENTE | E3: 45575 | H3: 0 | I3: =IF(ISBLANK(H3), NETWORKDAYS(F3, TODAY(),Hoja2!$A$1:$A$18), NETWORKDAYS(F3, H3, Hoja2!$A$1:$A$18)) -> 0 | J3: 45569 | L3: *04/10/2024 pruebas * 07/10/2024 se entrega a Danilo para pruebas y posterior despliegue a producción * 09/10/2024 Confirmar entrega de rama a Danilo * 10/10/2024 Etregadas a Danilo 9 de octubre,
A4: FABIO FORERO | C4: Autocomplete Enabled (15 Y 18) | D4: PENDIENTE | E4: 45575 | H4: 0 | I4: =IF(ISBLANK(H4), NETWORKDAYS(F4, TODAY(),Hoja2!$A$1:$A$18), NETWORKDAYS(F4, H4, Hoja2!$A$1:$A$18)) -> 0 | J4: 45569 | L4: *04/10/2024 pruebas * 07/10/2024 se entrega a Danilo para pruebas y posterior despliegue a producción * 09/10/2024 Confirmar entrega de rama a Danilo * 10/10/2024 Etregadas a Danilo 9 de octubre
A5: FABIO FORERO | B5: VULNERABILIDADES MEDIAS | C5: Internal Server Error | D5: PENDIENTE | E5: 45575 | H5: 0 | I5: =IF(ISBLANK(H5), NETWORKDAYS(F5, TODAY(),Hoja2!$A$1:$A$18), NETWORKDAYS(F5, H5, Hoja2!$A$1:$A$18)) -> 0 | J5: 45569 | L5: *04/10/2024 pruebas * 07/10/2024 se entrega a Danilo para pruebas y posterior despliegue a producción * 09/10/2024 Confirmar entrega de rama a Danilo * 10/10/2024 Etregadas a Danilo 9 de octubre
